Workbook

Sheet Март 26
A1: 3 | B1: Вчера | C1: =DAY(TODAY()-1) -> 26 | F1: Дней в месяце | G1: 31
A2: Актуально на | B2: 46083 | M2: Оз | O2: Вб | Q2: Ям | S2: Лету | U2: ЗЯ | W2: Магнит Маркет | Y2: Сайт | AE2: план | AF2: ауты | AG2: реальный план | AI2: выручка | AJ2: отказы/возвраты | AK2: раздачи | AL2: выкупы | AM2: реальная выручка
B3: Ozon | M3: Биг–Л | N3: Смарт | O3: Биг–Л | P3: Смарт | Q3: Биг–Л | R3: Смарт | S3: Биг–Л | T3: Смарт | U3: Биг–Л | V3: Смарт | W3: Биг–Л | X3: Смарт | Y3: qeep | Z3: harly | AA3: Алтея | AC3: WB | AD3: Биг–Л | AE3: =D39 -> 2.0608031e+08 | AG3: =AE3-AF3 -> 2.0608031e+08 | AI3: =O35 -> 290489634 | AM3: =AI3-SUM(AJ3:AL3) -> 290489634
B4: Биг–Л / Март | до | D4: =TODAY()-1 -> 46107 | F4: Смарт/ Март| до | H4: =$D$4 -> 46107 | K4: 46082 | L4: =SUM(M4:AA4) -> 20051499 | M4: 2945127 | N4: 3391718 | O4: 9196294 | P4: 4172079 | Q4: 134607 | R4: 81004 | S4: 16982 | T4: 43929 | U4: 2160 | V4: 62928 | W4: 2150.16 | X4: 2520.99 | AD4: Смарт–Сэйл | AE4: =H39 -> 1.1437699e+08 | AG4: =AE4-AF4 -> 1.1437699e+08 | AI4: =P35 -> 118684688 | AM4: =AI4-SUM(AJ4:AL4) -> 118684688
A5: =IFERROR(C5/$C$15, " ") -> 0.90385015 | B5: Оплата за клик | C5: 7249209 | F5: Оплата за клик | G5: 8738826 | I5: =IFERROR(G5/$G$15, " ") -> 0.92420892 | K5: 46083 | L5: =SUM(M5:AA5) -> 19578836 | M5: 3007289 | N5: 3171863 | O5: 8671856 | P5: 4350042 | Q5: 179463 | R5: 86947 | S5: 13327 | T5: 35981 | U5: 720 | V5: 53664 | W5: 3155.5 | X5: 4528 | AC5: Ozon | AD5: Биг–Л | AE5: =D21 -> 105053826 | AG5: =AE5-AF5 -> 105053826 | AI5: =M35 -> 90218782 | AM5: =AI5-SUM(AJ5:AL5) -> 90218782
A6: =IFERROR(C6/$C$15, " ") -> 0.0031626986 | B6: Оплата за заказ | C6: 25366 | F6: Оплата за заказ | G6: 259877 | I6: =IFERROR(G6/$G$15, " ") -> 0.027484314 | K6: 46084 | L6: =SUM(M6:AA6) -> 19591015 | M6: 3568197 | N6: 3044559 | O6: 8488956 | P6: 4112286 | Q6: 163215 | R6: 80224 | S6: 12112 | T6: 52186 | U6: 0 | V6: 62968 | W6: 2884 | X6: 3428 | AD6: Смарт–Сэйл | AE6: =H21 -> 84254055 | AG6: =AE6-AF6 -> 84254055 | AI6: =N35 -> 71210163 | AM6: =AI6-SUM(AJ6:AL6) -> 71210163
A7: =IFERROR(C7/$C$15, " ") -> 0.076261607 | B7: Медийка | C7: 611646 | F7: Медийка | G7: 334224 | I7: =IFERROR(G7/$G$15, " ") -> 0.035347174 | K7: 46085 | L7: =SUM(M7:AA7) -> 18415458 | M7: 2896596 | N7: 2872328 | O7: 8033493 | P7: 4331084 | Q7: 102960 | R7: 58136 | S7: 11886 | T7: 39485 | U7: 1710 | V7: 63302 | W7: 1464.13 | X7: 3014 | AC7: ЯМаркет | AD7: Биг–Л | AE7: =D78 -> 3069853 | AG7: =AE7-AF7 -> 3069853 | AI7: =Q35 -> 4382190 | AM7: =AI7-SUM(AJ7:AL7) -> 4382190
A8: =IFERROR(C8/$C$15, " ") -> 0.00023727097 | B8: Баллы за отзывы | C8: 1903 | F8: Баллы за отзывы | I8: =IFERROR(G8/$G$15, " ") -> 0 | K8: 46086 | L8: =SUM(M8:AA8) -> 18359103 | M8: 3080360 | N8: 2861536 | O8: 7770325 | P8: 4271487 | Q8: 105469 | R8: 90888 | S8: 21717 | T8: 57184 | U8: 5123 | V8: 89257 | W8: 1502.43 | X8: 4255 | AD8: Смарт–Сэйл | AE8: =H78 -> 2257611 | AG8: =AE8-AF8 -> 2257611 | AI8: =R35 -> 1494137 | AM8: =AI8-SUM(AJ8:AL8) -> 1494137
A9: =IFERROR(C9/$C$15, " ") -> 0.01633903 | B9: Бонусы продавца | C9: 131045 | F9: Бонусы продавца | G9: 122539 | I9: =IFERROR(G9/$G$15, " ") -> 0.012959594 | K9: 46087 | L9: =SUM(M9:AA9) -> 17470815 | M9: 2960566 | N9: 2942818 | O9: 7054264 | P9: 3913988 | Q9: 299320 | R9: 58859 | S9: 27911 | T9: 76444 | U9: 9856 | V9: 119808 | W9: 1011.13 | X9: 5970 | AC9: Летуаль | AD9: Биг–Л | AE9: =S42 -> 619304 | AG9: =AE9-AF9 -> 619304 | AI9: =S35 -> 490176 | AM9: =AI9-SUM(AJ9:AL9) -> 490176
A10: =IFERROR(C10/$C$15, " ") -> 0 | B10: Рассылки | C10: 0 | F10: Рассылки | I10: =IFERROR(G10/$G$15, " ") -> 0 | K10: 46088 | L10: =SUM(M10:AA10) -> 18122854 | M10: 2966816 | N10: 2690818 | O10: 8071469 | P10: 3932225 | Q10: 101684 | R10: 61858 | S10: 24663 | T10: 90823 | U10: 18190 | V10: 158017 | W10: 1020 | X10: 5270.7 | AD10: Смарт–Сэйл | AE10: =T42 -> 1719666 | AG10: =AE10-AF10 -> 1719666 | AI10: =T35 -> 1274528 | AM10: =AI10-SUM(AJ10:AL10) -> 1274528
A11: =IFERROR(C11/$C$15, " ") -> 0 | B11: Закрепление отзыва | C11: 0 | F11: Закрепление отзыва | I11: =IFERROR(G11/$G$15, " ") -> 0 | K11: 46089 | L11: =SUM(M11:AA11) -> 17009761 | M11: 2571667 | N11: 2299783 | O11: 7749386 | P11: 3943225 | Q11: 105112 | R11: 41541 | S11: 38052 | T11: 107299 | U11: 14371 | V11: 136238 | W11: 421.28 | X11: 2666 | AC11: Золотое Яблоко | AD11: Биг–Л | AE11: =U42 -> 141359 | AG11: =AE11-AF11 -> 141359 | AI11: =U35 -> 100903 | AM11: =AI11-SUM(AJ11:AL11) -> 100903
B12: Иные электронные услуги | C12: 0 | F12: Иные электронные услуги | I12: =IFERROR(G12/$G$15, " ") -> 0 | K12: 46090 | L12: =SUM(M12:AA12) -> 24043922 | M12: 3764474 | N12: 2900168 | O12: 11849879 | P12: 4998959 | Q12: 144166 | R12: 41253 | S12: 43214 | T12: 133590 | U12: 8039 | V12: 148975 | W12: 4705.42 | X12: 6500.08 | AD12: Смарт–Сэйл | AE12: =V42 -> 1599107 | AG12: =AE12-AF12 -> 1599107 | AI12: =V35 -> 2120688 | AM12: =AI12-SUM(AJ12:AL12) -> 2120688
B13: Продвижение бренда | C13: 0 | F13: Продвижение бренда | I13: =IFERROR(G13/$G$15, " ") -> 0 | K13: 46091 | L13: =SUM(M13:AA13) -> 23853038 | M13: 3911352 | N13: 2863966 | O13: 11628689 | P13: 4953182 | Q13: 142061 | R13: 61566 | S13: 33783 | T13: 104680 | U13: 8158 | V13: 145133 | W13: 0 | X13: 467.5 | AD13: итог | AE13: =SUM(AE3:AE12) -> 5.1917208e+08 | AF13: =SUM(AF3:AF12) -> 0 | AG13: =SUM(AG3:AG12) -> 5.1917208e+08 | AI13: =SUM(AI3:AI12) -> 5.8046589e+08 | AJ13: =SUM(AJ3:AJ12) -> 0 | AK13: =SUM(AK3:AK12) -> 0 | AL13: =SUM(AL3:AL12) -> 0 | AM13: =SUM(AM3:AM12) -> 5.8046589e+08
B14: Ozon Рассрочка | C14: 1197 | F14: Ozon Рассрочка | K14: 46092 | L14: =SUM(M14:AA14) -> 22236976 | M14: 3872679 | N14: 2875709 | O14: 10344154 | P14: 4733883 | Q14: 180466 | R14: 60308 | S14: 20470 | T14: 49268 | U14: 2759 | V14: 85661 | W14: 3840.16 | X14: 7778.84
B15: Итого расходов | C15: =SUM(C5:C14) -> 8020366 | F15: Итого расходов | G15: =SUM(G5:G14) -> 9455466 | H15: =SUM(H5:H14) -> 0 | K15: 46093 | L15: =SUM(M15:AA15) -> 20520671 | M15: 3859705 | N15: 3092489 | O15: 8833371 | P15: 4394002 | Q15: 140487 | R15: 58106 | S15: 14501 | T15: 45955 | U15: 3801 | V15: 74085 | W15: 0 | X15: 4168.6
B16: Выручка | D16: =M35 -> 90218782 | F16: Выручка | H16: =N35 -> 71210163 | K16: 46094 | L16: =SUM(M16:AA16) -> 19577117 | M16: 3509459 | N16: 2865973.6 | O16: 8740909 | P16: 4134370 | Q16: 114001 | R16: 62938 | S16: 15814 | T16: 55687 | U16: 4259 | V16: 64011 | W16: 6163.92 | X16: 3531.24
B17: ДРР / Факт | D17: =C15/D16 -> 0.088899072 | F17: ДРР / Факт | H17: =G15/H16 -> 0.13278254 | K17: 46095 | L17: =SUM(M17:AA17) -> 21112873 | M17: 3452216 | N17: 3044362 | O17: 9524177 | P17: 4687344 | Q17: 195086 | R17: 45308 | S17: 19788 | T17: 53394 | U17: 3413 | V17: 80937 | W17: 2090.4 | X17: 4757.49 | AE17: Без вычетов | AI17: С вычетом всего
A18: =D17/C18 -> 0.59266048 | B18: ДРР / План | C18: 0.15 | D18: =D16*C18 -> 13532817 | F18: ДРР / План | G18: 0.13 | H18: =H16*G18 -> 9257321.2 | I18: =H17/G18 -> 1.0214041 | K18: 46096 | L18: =SUM(M18:AA18) -> 22925434 | M18: 3654183 | N18: 3106266.1 | O18: 10917100 | P18: 4802264 | Q18: 211721 | R18: 52353 | S18: 16462 | T18: 58043 | U18: 6825 | V18: 92768 | W18: 2476.52 | X18: 4972.18 | AE18: план | AF18: выручка | AG18: дельта | AI18: реальный план | AJ18: реальная выручка | AK18: дельта
B19: Перерасход в деньгах | D19: =C15-D18 -> -5512451.3 | F19: Перераход в деньгах | H19: =G15-H18 -> 198144.77 | K19: 46097 | L19: =SUM(M19:AA19) -> 20543142 | M19: 3241939 | N19: 2833187 | O19: 9344888 | P19: 4786615 | Q19: 152313 | R19: 55254 | S19: 20448 | T19: 30366 | U19: 2201 | V19: 72032 | W19: 0 | X19: 3898.89 | AC19: WB | AD19: Биг–Л | AE19: =AE3 -> 2.0608031e+08 | AF19: =AI3 -> 290489634 | AG19: =IFERROR(AF19/AE19, " ") -> 1.4095943 | AI19: =AG3 -> 2.0608031e+08 | AJ19: =AM3 -> 290489634 | AK19: =IFERROR(AJ19/AI19, " ") -> 1.4095943
K20: 46098 | L20: =SUM(M20:AA20) -> 21487958 | M20: 3023131 | N20: 2638046.5 | O20: 10218979 | P20: 5288172 | Q20: 167861 | R20: 40414 | S20: 12716 | T20: 18561 | U20: 406 | V20: 73937 | W20: 3353.51 | X20: 2381.2 | AD20: Смарт–Сэйл | AE20: =AE4 -> 1.1437699e+08 | AF20: =AI4 -> 118684688 | AG20: =IFERROR(AF20/AE20, " ") -> 1.0376623 | AI20: =AG4 -> 1.1437699e+08 | AJ20: =AM4 -> 118684688 | AK20: =IFERROR(AJ20/AI20, " ") -> 1.0376623
B21: План | D21: =M42 -> 105053826 | F21: План | H21: =N42 -> 84254055 | K21: 46099 | L21: =SUM(M21:AA21) -> 25002721 | M21: 4246087 | N21: 3407136.1 | O21: 12051770 | P21: 4943058 | Q21: 166674 | R21: 63061 | S21: 14012 | T21: 28323 | U21: 2255 | V21: 74396 | W21: 0 | X21: 5949.15 | AC21: Ozon | AD21: Биг–Л | AE21: =AE5 -> 105053826 | AF21: =AI5 -> 90218782 | AG21: =IFERROR(AF21/AE21, " ") -> 0.85878626 | AI21: =AG5 -> 105053826 | AJ21: =AM5 -> 90218782 | AK21: =IFERROR(AJ21/AI21, " ") -> 0.85878626
B22: Плато продаж | D22: =D16/$C$1 -> 3469953.2 | F22: Плато продаж | H22: =H16/$C$1 -> 2738852.4 | K22: 46100 | L22: =SUM(M22:AA22) -> 25508707 | M22: 3132743 | N22: 2281600 | O22: 15170599 | P22: 4537065 | Q22: 221414 | R22: 69428 | S22: 9416 | T22: 17682 | U22: 0 | V22: 64132 | W22: 1452.36 | X22: 3175.85 | AD22: Смарт–Сэйл | AE22: =AE6 -> 84254055 | AF22: =AI6 -> 71210163 | AG22: =IFERROR(AF22/AE22, " ") -> 0.84518381 | AI22: =AG6 -> 84254055 | AJ22: =AM6 -> 71210163 | AK22: =IFERROR(AJ22/AI22, " ") -> 0.84518381
B23: Нужно сделать на вчера | D23: =D21/$G$1*$C$1 -> 88109661 | F23: Нужно сделать на вчера | H23: =H21/$G$1*$C$1 -> 70664691 | K23: 46101 | L23: =SUM(M23:AA23) -> 22322077 | M23: 3027373 | N23: 2195710 | O23: 12387900 | P23: 4398525 | Q23: 147256 | R23: 66531 | S23: 13031 | T23: 20231 | U23: 540 | V23: 61974 | W23: 430.16 | X23: 2575.63 | AC23: ЯМаркет | AD23: Биг–Л | AE23: =AE7 -> 3069853 | AF23: =AI7 -> 4382190 | AG23: =IFERROR(AF23/AE23, " ") -> 1.4274918 | AI23: =AG7 -> 3069853 | AJ23: =AM7 -> 4382190 | AK23: =IFERROR(AJ23/AI23, " ") -> 1.4274918
B24: Нужно делать в день | D24: =(D21-D16)/($G$1-$C$1) -> 2967008.8 | F24: Нужно делать в день | H24: =(H21-H16)/($G$1-$C$1) -> 2608778.4 | K24: 46102 | L24: =SUM(M24:AA24) -> 26143611 | M24: 3522975 | N24: 2100022 | O24: 14680702 | P24: 5460096 | Q24: 232610 | R24: 50230 | S24: 10895 | T24: 28881 | U24: 0 | V24: 54798 | W24: 1472.35 | X24: 929.32 | AD24: Смарт–Сэйл | AE24: =AE8 -> 2257611 | AF24: =AI8 -> 1494137 | AG24: =IFERROR(AF24/AE24, " ") -> 0.66182217 | AI24: =AG8 -> 2257611 | AJ24: =AM8 -> 1494137 | AK24: =IFERROR(AJ24/AI24, " ") -> 0.66182217
B25: Дельта от плана | D25: =D16-D23 -> 2109121.5 | F25: Дельта от плана | H25: =H16-H23 -> 545471.84 | K25: 46103 | L25: =SUM(M25:AA25) -> 31068516 | M25: 3736853 | N25: 2627885 | O25: 17666377 | P25: 6631292 | Q25: 258740 | R25: 54402 | S25: 12918 | T25: 25542 | U25: 0 | V25: 54507 | W25: 0 | X25: 0 | AC25: Летуаль | AD25: Биг–Л | AE25: =AE9 -> 619304 | AF25: =AI9 -> 490176 | AG25: =IFERROR(AF25/AE25, " ") -> 0.79149497 | AI25: =AG9 -> 619304 | AJ25: =AM9 -> 490176 | AK25: =IFERROR(AJ25/AI25, " ") -> 0.79149497
B26: Прогноз по выручке | D26: =D16/$C$1*$G$1 -> 1.0756855e+08 | F26: Прогноз по выручке | H26: =H16/$C$1*$G$1 -> 84904425 | K26: 46104 | L26: =SUM(M26:AA26) -> 27972237 | M26: 3577557 | N26: 2219666 | O26: 16961692 | P26: 4833602 | Q26: 218223 | R26: 55500 | S26: 13293 | T26: 16275 | U26: 0 | V26: 66034 | W26: 4719.16 | X26: 5676.24 | AD26: Смарт–Сэйл | AE26: =AE10 -> 1719666 | AF26: =AI10 -> 1274528 | AG26: =IFERROR(AF26/AE26, " ") -> 0.74114857 | AI26: =AG10 -> 1719666 | AJ26: =AM10 -> 1274528 | AK26: =IFERROR(AJ26/AI26, " ") -> 0.74114857
B27: Прогноз по выручке (%) | D27: =D26/D21 -> 1.0239375 | F27: Прогноз по выручке (%) | H27: =H26/H21 -> 1.0077192 | K27: 46105 | L27: =SUM(M27:AA27) -> 26838275 | M27: 3737111 | N27: 2203706 | O27: 16411407 | P27: 4087386 | Q27: 238745 | R27: 47283 | S27: 13665 | T27: 31031 | U27: 0 | V27: 56167 | W27: 5302.95 | X27: 6471.06 | AC27: Золотое Яблоко | AD27: Биг–Л | AE27: =AE11 -> 141359 | AF27: =AI11 -> 100903 | AG27: =IFERROR(AF27/AE27, " ") -> 0.71380669 | AI27: =AG11 -> 141359 | AJ27: =AM11 -> 100903 | AK27: =IFERROR(AJ27/AI27, " ") -> 0.71380669
K28: 46106 | L28: =SUM(M28:AA28) -> 26147537 | M28: 4161394 | N28: 2565808 | O28: 14909070 | P28: 4095915 | Q28: 258536 | R28: 50745 | S28: 22289 | T28: 26028 | U28: 5558 | V28: 51721 | W28: 0 | X28: 473.45 | AD28: Смарт–Сэйл | AE28: =AE12 -> 1599107 | AF28: =AI12 -> 2120688 | AG28: =IFERROR(AF28/AE28, " ") -> 1.3261702 | AI28: =AG12 -> 1599107 | AJ28: =AM12 -> 2120688 | AK28: =IFERROR(AJ28/AI28, " ") -> 1.3261702
B29: Wildberries / Расход бонусы + рубли | K29: 46107 | L29: =SUM(M29:AA29) -> 24708477 | M29: 4790933 | N29: 2113040 | O29: 13811928 | P29: 3892542 | S29: 16811 | T29: 27660 | U29: 559 | V29: 53238 | W29: 0 | X29: 1765.74 | AE29: =SUM(AE19:AE28) -> 5.1917208e+08 | AF29: =SUM(AF19:AF28) -> 5.8046589e+08 | AG29: =IFERROR(AF29/AE29, " ") -> 1.1180607 | AI29: =SUM(AI19:AI24) -> 5.1509265e+08 | AJ29: =SUM(AJ19:AJ24) -> 5.7647959e+08 | AK29: =IFERROR(AJ29/AI29, " ") -> 1.1191765
B30: =B4 -> Биг–Л / Март | до | D30: =$D$4 -> 46107 | F30: =F4 -> Смарт/ Март| до | H30: =$D$4 -> 46107 | K30: 46108 | L30: =SUM(M30:AA30) -> 0
A31: =IFERROR(C31/$C$33, " ") -> 0.89593436 | B31: Затраты из РК | C31: 11596408 | F31: Затраты из РК | G31: 7142270 | I31: =IFERROR(G31/$G$33, " ") -> 0.95848558 | K31: 46109 | L31: =SUM(M31:AA31) -> 0 | AC31: Только рубли | AE31: реальная выручка | AF31: реклама | AG31: ДРР | AI31: ДРР план | AJ31: ДРР факт | AK31: дельта
A32: =IFERROR(C32/$C$33, " ") -> 0.10406564 | B32: Отзывы за баллы | C32: 1346959.9 | F32: Отзывы за баллы | G32: 309349.7 | I32: =IFERROR(G32/$G$33, " ") -> 0.041514424 | K32: 46110 | L32: =SUM(M32:AA32) -> 0 | AC32: WB | AD32: Биг–Л | AE32: =AM3 -> 290489634 | AF32: =C51 -> 0 | AG32: =AF32/AE32 -> 0 | AI32: =C36 -> 0.08 | AJ32: =AG32 -> 0 | AK32: =AJ32/AI32-1 -> -1
B33: Итого расходов | C33: =SUM(C31:C32) -> 12943368 | F33: Итого расходов | G33: =SUM(G31:G32) -> 7451619.7 | K33: 46111 | L33: =SUM(M33:AA33) -> 0 | AD33: Смарт–Сэйл | AE33: =AM4 -> 118684688 | AF33: =G51 -> 0 | AG33: =AF33/AE33 -> 0 | AI33: =G36 -> 0.08 | AJ33: =AG33 -> 0 | AK33: =AJ33/AI33-1 -> -1
B34: Выручка | D34: =O35 -> 290489634 | F34: Выручка | H34: =P35 -> 118684688 | K34: 46112 | L34: =SUM(M34:AA34) -> 0 | AC34: Ozon | AD34: Биг–Л | AE34: =AM5 -> 90218782 | AF34: =C15 -> 8020366 | AG34: =AF34/AE34 -> 0.088899072 | AI34: =C18 -> 0.15 | AJ34: =AG34 -> 0.088899072 | AK34: =AJ34/AI34-1 -> -0.40733952
B35: ДРР / Факт | D35: =C33/D34 -> 0.044557073 | F35: ДРР / Факт | H35: =G33/H34 -> 0.062785013 | K35: =L35/C1 -> 22331255 | L35: =SUM(L4:L34) -> 580612630 | M35: =SUM(M4:M34) -> 90218782 | N35: =SUM(N4:N34) -> 71210163 | O35: =SUM(O4:O34) -> 290489634 | P35: =SUM(P4:P34) -> 118684688 | Q35: =SUM(Q4:Q34) -> 4382190 | R35: =SUM(R4:R34) -> 1494137 | S35: =SUM(S4:S34) -> 490176 | ... AA35: =SUM(AA4:AA34) -> 0 | AD35: Смарт–Сэйл | AE35: =AM6 -> 71210163 | AF35: =G15 -> 9455466 | AG35: =AF35/AE35 -> 0.13278254 | AI35: =G18 -> 0.13 | AJ35: =AG35 -> 0.13278254 | AK35: =AJ35/AI35-1 -> 0.021404115
A36: =D35/C36 -> 0.55696342 | B36: ДРР / План | C36: 0.08 | D36: =D34*C36 -> 23239171 | F36: ДРР / План | G36: 0.08 | H36: =H34*G36 -> 9494775 | I36: =H35/G36 -> 0.78481266 | M36: =M35/$L$35 -> 0.1553855 | N36: =N35/$L$35 -> 0.1226466 | O36: =O35/$L$35 -> 0.50031573 | P36: =P35/$L$35 -> 0.20441286 | Q36: =Q35/$L$35 -> 0.0075475279 | R36: =R35/$L$35 -> 0.0025733801 | S36: =S35/$L$35 -> 0.0008442393 | T36: =T35/$L$35 -> 0.0021951434 | ... AA36: =AA35/$L$35 -> 0 | AC36: ЯМаркет | AD36: Биг–Л | AE36: =AM7 -> 4382190 | AF36: =C72 -> 530991 | AG36: =AF36/AE36 -> 0.12117024 | AI36: =C75 | AJ36: =AG36 -> 0.12117024 | AK36: =AJ36/AI36-1 -> #DIV/0!
B37: Перераход в деньгах | D37: =C33-D36 -> -10295803 | F37: Перераход в деньгах | H37: =G33-H36 -> -2043155.3 | AD37: Смарт–Сэйл | AE37: =AM8 -> 1494137 | AF37: =G72 -> 270412 | AG37: =AF37/AE37 -> 0.18098207 | AI37: =G75 | AJ37: =AG37 -> 0.18098207 | AK37: =AJ37/AI37-1 -> #DIV/0!
K38: Распределение по направлениям | M38: =SUM(M40:N40)/$L$40 -> 0.27803209 | O38: =SUM(O40:P40)/$L$40 -> 0.70472859 | Q38: =SUM(Q40:R40)/$L$40 -> 0.010120908 | S38: =SUM(S40:T40)/$L$40 -> 0.0030393827 | U38: =SUM(U40:V40)/$L$40 -> 0.0038262878 | W38: =SUM(W40:X40)/$L$40 -> 0.00025273424 | Y38: =SUM(Y40:Z40)/$L$40 -> 0 | AC38: Летуаль | AD38: Биг–Л | AE38: =AM9 -> 490176 | AF38: 0 | AG38: =AF38/AE38 -> 0 | AI38: =C91 -> 0.1 | AJ38: =AG38 -> 0 | AK38: =AJ38/AI38-1 -> -1
B39: План | D39: =O42 -> 2.0608031e+08 | F39: План | H39: =P42 -> 1.1437699e+08 | K39: Распределение продаж | L39: =L40/$L$40 -> 1 | M39: =M40/$L$40 -> 0.1553855 | N39: =N40/$L$40 -> 0.1226466 | O39: =O40/$L$40 -> 0.50031573 | P39: =P40/$L$40 -> 0.20441286 | Q39: =Q40/$L$40 -> 0.0075475279 | R39: =R40/$L$40 -> 0.0025733801 | S39: =S40/$L$40 -> 0.0008442393 | ... AA39: =AA40/$L$40 -> 0 | AD39: Смарт–Сэйл | AE39: =AM10 -> 1274528 | AF39: 0 | AG39: =AF39/AE39 -> 0 | AI39: =G91 -> 0.1 | AJ39: =AG39 -> 0 | AK39: =AJ39/AI39-1 -> -1
B40: Плато продаж | D40: =D34/$C$1 -> 11172678 | F40: Плато продаж | H40: =H34/$C$1 -> 4564795.7 | K40: Прогноз | L40: =L35/$C$1*$G$1 -> 692268905 | M40: =M35/$C$1*$G$1 -> 1.0756855e+08 | N40: =N35/$C$1*$G$1 -> 84904425 | O40: =O35/$C$1*$G$1 -> 3.4635303e+08 | P40: =P35/$C$1*$G$1 -> 1.4150867e+08 | Q40: =Q35/$C$1*$G$1 -> 5224918.8 | R40: =R35/$C$1*$G$1 -> 1781471 | S40: =S35/$C$1*$G$1 -> 584440.62 | ... AA40: =AA35/$C$1*$G$1 -> 0 | AC40: Золотое Яблоко | AD40: Биг–Л | AE40: =AM11 -> 100903 | AF40: 0 | AG40: =AF40/AE40 -> 0 | AI40: 0 | AJ40: =AG40 -> 0 | AK40: =AJ40/AI40-1 -> #DIV/0!
B41: Нужно сделать на вчера | D41: =D39/$G$1*$C$1 -> 1.7284155e+08 | F41: Нужно сделать на вчера | H41: =H39/$G$1*$C$1 -> 95929088 | K41: Плато продаж | L41: =L35/$C$1 -> 22331255 | M41: =M35/$C$1 -> 3469953.2 | N41: =N35/$C$1 -> 2738852.4 | O41: =O35/$C$1 -> 11172678 | P41: =P35/$C$1 -> 4564795.7 | Q41: =Q35/$C$1 -> 168545.77 | R41: =R35/$C$1 -> 57466.808 | S41: =S35/$C$1 -> 18852.923 | ... AA41: =AA35/$C$1 -> 0 | AD41: Смарт–Сэйл | AE41: =AM12 -> 2120688 | AF41: 0 | AG41: =AF41/AE41 -> 0 | AI41: 0 | AJ41: =AG41 -> 0 | AK41: =AJ41/AI41-1 -> #DIV/0!
B42: Нужно делать в день | D42: =(D39-D34)/($G$1-$C$1) -> -16881864 | F42: Нужно делать в день | H42: =(H39-H34)/($G$1-$C$1) -> -861539.77 | K42: Прошлый месяц | L42: =SUM(M42:V42) -> 5.1917208e+08 | M42: ='Февраль 26'!M35 -> 105053826 | N42: ='Февраль 26'!N35 -> 84254055 | O42: ='Февраль 26'!O35 -> 2.0608031e+08 | P42: ='Февраль 26'!P35 -> 1.1437699e+08 | Q42: ='Февраль 26'!Q35 -> 3069853 | R42: ='Февраль 26'!R35 -> 2257611 | S42: ='Февраль 26'!S35 -> 619304 | T42: ='Февраль 26'!T35 -> 1719666 | ... AA42: ='Февраль 26'!AA35 -> 0 | AE42: =SUM(AE32:AE41) -> 5.8046589e+08 | AF42: =SUM(AF32:AF41) -> 18277235 | AG42: =AF42/AE42 -> 0.031487182 | AI42: =F142 -> 0.096327028 | AJ42: =AG42 -> 0.031487182 | AK42: =AJ42/AI42-1 -> -0.67312205
B43: Дельта от плана | D43: =D34-D41 -> 1.1764808e+08 | F43: Дельта от плана | H43: =H34-H41 -> 22755600
B44: Прогноз по выручке | D44: =D34/$C$1*$G$1 -> 3.4635303e+08 | F44: Прогноз по выручке | H44: =H34/$C$1*$G$1 -> 1.4150867e+08 | K44: Рекламный расход , руб | L44: =SUM(M44:X44) -> 38730396 | M44: =C15 -> 8020366 | N44: =G15 -> 9455466 | O44: =C33 -> 12943368 | P44: =G33 -> 7451619.7 | Q44: =C72 -> 530991 | R44: =G72 -> 270412 | S44: =C88 -> 13460.13 | T44: =G88 -> 44712.84 | U44: 0 | V44: 0 | W44: 0 | X44: 0 | Y44: 0 | Z44: 0 | AA44: 0 | AC44: Рубли + Бонусы | AE44: реальная выручка | AF44: реклама | AG44: ДРР | AI44: ДРР план | AJ44: ДРР факт | AK44: дельта
B45: Прогноз по выручке (%) | D45: =D44/D39 -> 1.6806701 | F45: Прогноз по выручке (%) | H45: =H44/H39 -> 1.2372127 | K45: ДРР , % | L45: =L44/L35 -> 0.066706085 | M45: =IFERROR(M44/M35, " ") -> 0.088899072 | N45: =IFERROR(N44/N35, " ") -> 0.13278254 | O45: =IFERROR(O44/O35, " ") -> 0.044557073 | P45: =IFERROR(P44/P35, " ") -> 0.062785013 | Q45: =IFERROR(Q44/Q35, " ") -> 0.12117024 | R45: =IFERROR(R44/R35, " ") -> 0.18098207 | S45: =IFERROR(S44/S35, " ") -> 0.02745979 | T45: =IFERROR(T44/T35, " ") -> 0.035081881 | ... AA45: =IFERROR(AA44/AA35, " ") | AC45: WB | AD45: Биг–Л | AE45: =AE32 -> 290489634 | AF45: =C33 -> 12943368 | AG45: =AF45/AE45 -> 0.044557073 | AI45: =AI32 -> 0.08 | AJ45: =AG45 -> 0.044557073 | AK45: =AJ45/AI45-1 -> -0.44303658
AD46: Смарт–Сэйл | AE46: =AE33 -> 118684688 | AF46: =G33 -> 7451619.7 | AG46: =AF46/AE46 -> 0.062785013 | AI46: =AI33 -> 0.08 | AJ46: =AG46 -> 0.062785013 | AK46: =AJ46/AI46-1 -> -0.21518734
B47: Wildberries / Расход только рубли | K47: Прирост к прошлому месяцу , % | L47: =L40/L42-1 -> 0.33340934 | M47: =M40/M42-1 -> 0.02393746 | N47: =N40/N42-1 -> 0.0077191569 | O47: =O40/O42-1 -> 0.68067011 | P47: =P40/P42-1 -> 0.23721273 | Q47: =Q40/Q42-1 -> 0.70200946 | R47: =R40/R42-1 -> -0.21090434 | S47: =S40/S42-1 -> -0.056294461 | ... AA47: =AA40/AA42-1 -> #DIV/0! | AC47: Ozon | AD47: Биг–Л | AE47: =AE34 -> 90218782 | AF47: =AF34 -> 8020366 | AG47: =AF47/AE47 -> 0.088899072 | AI47: =AI34 -> 0.15 | AJ47: =AG47 -> 0.088899072 | AK47: =AJ47/AI47-1 -> -0.40733952
B48: =B30 -> Биг–Л / Март | до | D48: =$D$4 -> 46107 | F48: =F30 -> Смарт/ Март| до | H48: =$D$4 -> 46107 | K48: Прирост по направлениям , % | M48: =SUM(M40:N40)/SUM(M42:N42)-1 -> 0.016719283 | O48: =SUM(O40:P40)/SUM(O42:P42)-1 -> 0.52239218 | Q48: =SUM(Q40:R40)/SUM(Q42:R42)-1 -> 0.31514542 | S48: =SUM(S40:T40)/SUM(S42:T42)-1 -> -0.10042876 | U48: =SUM(U40:V40)/SUM(U42:V42)-1 -> 0.52190278 | W48: =SUM(W40:X40)/SUM(W42:X42)-1 -> -0.11906903 | Y48: =SUM(Y40:AA40)/SUM(Y42:AA42)-1 -> #DIV/0! | AD48: Смарт–Сэйл | AE48: =AE35 -> 71210163 | AF48: =AF35 -> 9455466 | AG48: =AF48/AE48 -> 0.13278254 | AI48: =AI35 -> 0.13 | AJ48: =AG48 -> 0.13278254 | AK48: =AJ48/AI48-1 -> 0.021404115
A49: =IFERROR(C49/$C$33, " ") -> 0 | B49: Затраты из РК | F49: Затраты из РК | I49: =IFERROR(G49/$G$33, " ") -> 0 | K49: Прирост к прошлому месяцу , руб | L49: =L40-L42 -> 1.7309682e+08 | M49: =M40-M42 -> 2514721.8 | N49: =N40-N42 -> 650370.27 | O49: =O40-O42 -> 140272711 | P49: =P40-P42 -> 27131677 | Q49: =Q40-Q42 -> 2155065.8 | R49: =R40-R42 -> -476139.96 | S49: =S40-S42 -> -34863.385 | ... AA49: =AA40-AA42 -> 0 | AC49: ЯМаркет | AD49: Биг–Л | AE49: =AE36 -> 4382190 | AF49: =AF36 -> 530991 | AG49: =AF49/AE49 -> 0.12117024 | AI49: =AI36 | AJ49: =AG49 -> 0.12117024 | AK49: =AJ49/AI49-1 -> #DIV/0!
A50: =IFERROR(C50/$C$33, " ") -> 0 | B50: Отзывы за баллы? | F50: Отзывы за баллы? | I50: =IFERROR(G50/$G$33, " ") -> 0 | K50: Прирост по направлениям , руб | M50: =SUM(M40:N40)-SUM(M42:N42) -> 3165092 | O50: =SUM(O40:P40)-SUM(O42:P42) -> 1.6740439e+08 | Q50: =SUM(Q40:R40)-SUM(Q42:R42) -> 1678925.9 | S50: =SUM(S40:T40)-SUM(S42:T42) -> -234899.85 | U50: =SUM(U40:V40)-SUM(U42:V42) -> 908354.04 | W50: =SUM(W40:X40)-SUM(W42:X42) -> -23648.077 | Y50: =SUM(Y40:AA40)-SUM(Y42:AA42) -> 0 | AD50: Смарт–Сэйл | AE50: =AE37 -> 1494137 | AF50: =AF37 -> 270412 | AG50: =AF50/AE50 -> 0.18098207 | AI50: =AI37 | AJ50: =AG50 -> 0.18098207 | AK50: =AJ50/AI50-1 -> #DIV/0!
B51: Итого расходов | C51: =SUM(C49:C50) -> 0 | F51: Итого расходов | G51: =SUM(G49:G50) -> 0 | AC51: Летуаль | AD51: Биг–Л | AE51: =AE38 -> 490176 | AF51: =AF38 -> 0 | AG51: =AF51/AE51 -> 0 | AI51: =AI38 -> 0.1 | AJ51: =AG51 -> 0 | AK51: =AJ51/AI51-1 -> -1
B52: Выручка | D52: =O35 -> 290489634 | F52: Выручка | H52: =P35 -> 118684688 | K52: хотим | L52: 700000000 | M52: =$L$52*M36 -> 1.0876985e+08 | N52: =$L$52*N36 -> 85852618 | O52: =$L$52*O36 -> 3.5022101e+08 | P52: =$L$52*P36 -> 1.43089e+08 | Q52: =$L$52*Q36 -> 5283269.5 | R52: =$L$52*R36 -> 1801366.1 | S52: =$L$52*S36 -> 590967.51 | T52: =$L$52*T36 -> 1536600.4 | ... AA52: =$L$52*AA36 -> 0 | AD52: Смарт–Сэйл | AE52: =AE39 -> 1274528 | AF52: =AF39 -> 0 | AG52: =AF52/AE52 -> 0 | AI52: =AI39 -> 0.1 | AJ52: =AG52 -> 0 | AK52: =AJ52/AI52-1 -> -1
B53: ДРР / Факт | D53: =C51/D52 -> 0 | F53: ДРР / Факт | H53: =G51/H52 -> 0 | K53: осталось сделать | L53: =L52-L35 -> 119387370 | M53: =M52-M35 -> 18551066 | N53: =N52-N35 -> 14642455 | O53: =O52-O35 -> 59731380 | P53: =P52-P35 -> 24404314 | Q53: =Q52-Q35 -> 901079.5 | R53: =R52-R35 -> 307229.08 | S53: =S52-S35 -> 100791.51 | ... AA53: =AA52-AA35 -> 0 | AC53: Золотое Яблоко | AD53: Биг–Л | AE53: =AE40 -> 100903 | AF53: =AF40 -> 0 | AG53: =AF53/AE53 -> 0 | AI53: =AI40 -> 0 | AJ53: =AG53 -> 0 | AK53: =AJ53/AI53-1 -> #DIV/0!
A54: =D53/C54 -> 0 | B54: ДРР / План | C54: 0.05 | D54: =D52*C54 -> 14524482 | F54: ДРР / План | G54: 0.05 | H54: =H52*G54 -> 5934234.4 | I54: =H53/G54 -> 0 | K54: нужно плато продаж | L54: =SUM(M54:V54) -> 23871439 | M54: =M53/($G$1-$C$1) -> 3710213.2 | N54: =N53/($G$1-$C$1) -> 2928490.9 | O54: =O53/($G$1-$C$1) -> 11946276 | P54: =P53/($G$1-$C$1) -> 4880862.7 | Q54: =Q53/($G$1-$C$1) -> 180215.9 | R54: =R53/($G$1-$C$1) -> 61445.817 | S54: =S53/($G$1-$C$1) -> 20158.302 | T54: =T53/($G$1-$C$1) -> 52414.48 | ... AA54: =AA53/($G$1-$C$1) -> 0 | AD54: Смарт–Сэйл | AE54: =AE41 -> 2120688 | AF54: =AF41 -> 0 | AG54: =AF54/AE54 -> 0 | AI54: =AI41 -> 0 | AJ54: =AG54 -> 0 | AK54: =AJ54/AI54-1 -> #DIV/0!
B55: Перераход в деньгах | D55: =C51-D54 -> -14524482 | F55: Перераход в деньгах | H55: =G51-H54 -> -5934234.4 | AE55: =SUM(AE45:AE54) -> 5.8046589e+08 | AF55: =SUM(AF45:AF54) -> 38672223 | AG55: =AF55/AE55 -> 0.066622731 | AI55: =AI42 -> 0.096327028 | AJ55: =AG55 -> 0.066622731 | AK55: =AJ55/AI55-1 -> -0.30836929
N56: 300000000
B57: План | D57: =O42 -> 2.0608031e+08 | F57: План | H57: =P42 -> 1.1437699e+08 | N57: =N56-SUM(M35:N35) -> 1.3857105e+08 | AE57: реальный план | AF57: реальная выручка | AG57: дельта | AI57: ДРР план | AJ57: ДРР факт | AK57: дельта
B58: Плато продаж | D58: =D52/$C$1 -> 11172678 | F58: Плато продаж | H58: =H52/$C$1 -> 4564795.7 | M58: =M35/SUM(M35:N35) -> 0.55887612 | N58: =N35/SUM(M35:N35) -> 0.44112388 | AC58: WB | AD58: Биг–Л | AE58: =AG3 -> 2.0608031e+08 | AF58: =AM3 -> 290489634 | AG58: =IFERROR(AF58/AE58, " ") -> 1.4095943 | AI58: =AI45 -> 0.08 | AJ58: =AJ45 -> 0.044557073 | AK58: =AJ58/AI58-1 -> -0.44303658
B59: Нужно сделать на вчера | D59: =D57/$G$1*$C$1 -> 1.7284155e+08 | F59: Нужно сделать на вчера | H59: =H57/$G$1*$C$1 -> 95929088 | M59: =N57*M58 -> 77444053 | N59: =N57*N58 -> 61127002 | AD59: Смарт–Сэйл | AE59: =AG4 -> 1.1437699e+08 | AF59: =AM4 -> 118684688 | AG59: =IFERROR(AF59/AE59, " ") -> 1.0376623 | AI59: =AI46 -> 0.08 | AJ59: =AJ46 -> 0.062785013 | AK59: =AJ59/AI59-1 -> -0.21518734
B60: Нужно делать в день | D60: =(D57-D52)/($G$1-$C$1) -> -16881864 | F60: Нужно делать в день | H60: =(H57-H52)/($G$1-$C$1) -> -861539.77 | L60: =SUM(M60:N60) -> 27714211 | M60: =M59/(G1-C1) -> 15488811 | N60: =N59/(G1-C1) -> 12225400 | AC60: Ozon | AD60: Биг–Л | AE60: =AG5 -> 105053826 | AF60: =AM5 -> 90218782 | AG60: =IFERROR(AF60/AE60, " ") -> 0.85878626 | AI60: =AI47 -> 0.15 | AJ60: =AJ47 -> 0.088899072 | AK60: =AJ60/AI60-1 -> -0.40733952
B61: Дельта от плана | D61: =D52-D59 -> 1.1764808e+08 | F61: Дельта от плана | H61: =H52-H59 -> 22755600 | AD61: Смарт–Сэйл | AE61: =AG6 -> 84254055 | AF61: =AM6 -> 71210163 | AG61: =IFERROR(AF61/AE61, " ") -> 0.84518381 | AI61: =AI48 -> 0.13 | AJ61: =AJ48 -> 0.13278254 | AK61: =AJ61/AI61-1 -> 0.021404115
B62: Прогноз по выручке | D62: =D52/$C$1*$G$1 -> 3.4635303e+08 | F62: Прогноз по выручке | H62: =H52/$C$1*$G$1 -> 1.4150867e+08 | M62: =M58 -> 0.55887612 | N62: =N58 -> 0.44112388 | AC62: ЯМаркет | AD62: Биг–Л | AE62: =AG7 -> 3069853 | AF62: =AM7 -> 4382190 | AG62: =IFERROR(AF62/AE62, " ") -> 1.4274918 | AI62: =AI49 | AJ62: =AJ49 -> 0.12117024 | AK62: =AJ62/AI62-1 -> #DIV/0!
B63: Прогноз по выручке (%) | D63: =D62/D57 -> 1.6806701 | F63: Прогноз по выручке (%) | H63: =H62/H57 -> 1.2372127 | M63: =$N$56*M62 -> 1.6766283e+08 | N63: =$N$56*N62 -> 1.3233717e+08 | AD63: Смарт–Сэйл | AE63: =AG8 -> 2257611 | AF63: =AM8 -> 1494137 | AG63: =IFERROR(AF63/AE63, " ") -> 0.66182217 | AI63: =AI50 | AJ63: =AJ50 -> 0.18098207 | AK63: =AJ63/AI63-1 -> #DIV/0!
AC64: Летуаль | AD64: Биг–Л | AE64: =AG9 -> 619304 | AF64: =AM9 -> 490176 | AG64: =IFERROR(AF64/AE64, " ") -> 0.79149497 | AI64: =AI51 -> 0.1 | AJ64: =AJ51 -> 0 | AK64: =AJ64/AI64-1 -> -1
B65: ЯМаркет | L65: =G1-C1 -> 5 | M65: =(M63-M35)/$L$65 -> 15488811 | N65: =(N63-N35)/$L$65 -> 12225400 | AD65: Смарт–Сэйл | AE65: =AG10 -> 1719666 | AF65: =AM10 -> 1274528 | AG65: =IFERROR(AF65/AE65, " ") -> 0.74114857 | AI65: =AI52 -> 0.1 | AJ65: =AJ52 -> 0 | AK65: =AJ65/AI65-1 -> -1
B66: =B30 -> Биг–Л / Март | до | D66: =$D$4 -> 46107 | F66: =F30 -> Смарт/ Март| до | H66: =$D$4 -> 46107 | AC66: Золотое Яблоко | AD66: Биг–Л | AE66: =AG11 -> 141359 | AF66: =AM11 -> 100903 | AG66: =IFERROR(AF66/AE66, " ") -> 0.71380669 | AI66: =AI53 -> 0 | AJ66: =AJ53 -> 0 | AK66: =AJ66/AI66-1 -> #DIV/0!
A67: =IFERROR(C67/$C$72, " ") -> 0.96900512 | B67: Буст продаж | C67: 514533 | F67: Буст продаж | G67: 231137 | I67: =IFERROR(G67/$G$72, " ") -> 0.85475866 | N67: 450000000 | AD67: Смарт–Сэйл | AE67: =AG12 -> 1599107 | AF67: =AM12 -> 2120688 | AG67: =IFERROR(AF67/AE67, " ") -> 1.3261702 | AI67: =AI54 -> 0 | AJ67: =AJ54 -> 0 | AK67: =AJ67/AI67-1 -> #DIV/0!
A68: =IFERROR(C68/$C$72, " ") -> 0.030994876 | B68: Буст показов | C68: 16458 | F68: Буст показов | G68: 39275 | I68: =IFERROR(G68/$G$72, " ") -> 0.14524134 | M68: =M35/SUM($M$35:$N$35) -> 0.55887612 | N68: =N35/SUM($M$35:$N$35) -> 0.44112388 | AE68: =AG13 -> 5.1917208e+08 | AF68: =AM13 -> 5.8046589e+08 | AG68: =IFERROR(AF68/AE68, " ") -> 1.1180607 | AI68: =AI55 -> 0.096327028 | AJ68: =AJ55 -> 0.066622731 | AK68: =AJ68/AI68-1 -> -0.30836929
A69: =IFERROR(C69/$C$72, " ") -> 0 | B69: Полки | F69: Полки | I69: =IFERROR(G69/$G$72, " ") -> 0 | M69: =$N$67*M68 -> 2.5149425e+08 | N69: =$N$67*N68 -> 1.9850575e+08
A70: =IFERROR(C70/$C$72, " ") -> 0 | B70: Охватное продвижение | F70: Охватное продвижение | I70: =IFERROR(G70/$G$72, " ") -> 0 | L70: 30 | M70: =M69/$L$70 -> 8383141.7 | N70: =N69/$L$70 -> 6616858.3 | AE70: Сентябрь | AF70: Октябрь | AK70: =AE70 -> Сентябрь | AL70: =AF70 -> Октябрь
A71: =IFERROR(C71/$C$72, " ") -> 0 | B71: Баннеры | F71: Баннеры | I71: =IFERROR(G71/$G$72, " ") -> 0 | AE71: реальная выручка | AF71: реальная выручка | AG71: дельта | AI71: Рубли + Бонусы | AK71: ДРР факт | AL71: ДРР факт | AM71: дельта
B72: Итого расходов | C72: =SUM(C67:C71) -> 530991 | F72: Итого расходов | G72: =SUM(G67:G71) -> 270412 | AC72: WB | AD72: Биг–Л | AE72: ='Сентябрь 25'!AA72 -> 34886232 | AF72: =AF58 -> 290489634 | AG72: =AF72/AE72-1 -> 7.3267701 | AI72: WB | AJ72: Биг–Л | AK72: ='Сентябрь 25'!AG72 -> 0.06874047 | AL72: =AJ45 -> 0.044557073 | AM72: =AL72/AK72-1 -> -0.35180727
B73: Выручка | D73: =Q35 -> 4382190 | F73: Выручка | H73: =R35 -> 1494137 | AD73: Смарт–Сэйл | AE73: ='Сентябрь 25'!AA73 -> 108267871 | AF73: =AF59 -> 118684688 | AG73: =AF73/AE73-1 -> 0.096213372 | AJ73: Смарт–Сэйл | AK73: ='Сентябрь 25'!AG73 -> 0.061662033 | AL73: =AJ46 -> 0.062785013 | AM73: =AL73/AK73-1 -> 0.018211863
B74: ДРР / Факт | D74: =C72/D73 -> 0.12117024 | F74: ДРР / Факт | H74: =G72/H73 -> 0.18098207 | AC74: Ozon | AD74: Биг–Л | AE74: ='Сентябрь 25'!AA74 -> 25030993 | AF74: =AF60 -> 90218782 | AG74: =AF74/AE74-1 -> 2.604283 | AI74: Ozon | AJ74: Биг–Л | AK74: ='Сентябрь 25'!AG74 -> 0.23173352 | AL74: =AJ47 -> 0.088899072 | AM74: =AL74/AK74-1 -> -0.6163737
A75: =D74/C75 -> #DIV/0! | B75: ДРР / План | D75: =D73*C75 -> 0 | F75: ДРР / План | H75: =H73*G75 -> 0 | I75: =H74/G75 -> #DIV/0! | AD75: Смарт–Сэйл | AE75: ='Сентябрь 25'!AA75 -> 50514010 | AF75: =AF61 -> 71210163 | AG75: =AF75/AE75-1 -> 0.40971116 | AJ75: Смарт–Сэйл | AK75: ='Сентябрь 25'!AG75 -> 0.11988367 | AL75: =AJ48 -> 0.13278254 | AM75: =AL75/AK75-1 -> 0.10759483
B76: Перераход в деньгах | D76: =C72-D75 -> 530991 | F76: Перераход в деньгах | H76: =G72-H75 -> 270412 | AC76: ЯМаркет | AD76: Биг–Л | AE76: ='Сентябрь 25'!AA76 -> -4890173.2 | AF76: =AF62 -> 4382190 | AG76: =AF76/AE76-1 -> -1.8961216 | AI76: ЯМаркет | AJ76: Биг–Л | AK76: ='Сентябрь 25'!AG76 -> -0.034747849 | AL76: =AJ49 -> 0.12117024 | AM76: =AL76/AK76-1 -> -4.4871292
AD77: Смарт–Сэйл | AE77: ='Сентябрь 25'!AA77 -> 3184978 | AF77: =AF63 -> 1494137 | AG77: =AF77/AE77-1 -> -0.53087996 | AJ77: Смарт–Сэйл | AK77: ='Сентябрь 25'!AG77 -> 0.20596751 | AL77: =AJ50 -> 0.18098207 | AM77: =AL77/AK77-1 -> -0.12130772
B78: План | D78: =Q42 -> 3069853 | F78: План | H78: =R42 -> 2257611 | AC78: Летуаль | AD78: Биг–Л | AE78: ='Сентябрь 25'!AA78 -> 101466 | AF78: =AF64 -> 490176 | AG78: =AF78/AE78-1 -> 3.8309384 | AI78: Летуаль | AJ78: Биг–Л | AK78: ='Сентябрь 25'!AG78 -> 0 | AL78: =AJ51 -> 0 | AM78: =AL78/AK78-1 -> #DIV/0!
B79: Плато продаж | D79: =D73/$C$1 -> 168545.77 | F79: Плато продаж | H79: =H73/$C$1 -> 57466.808 | AD79: Смарт–Сэйл | AE79: ='Сентябрь 25'!AA79 -> 314564 | AF79: =AF65 -> 1274528 | AG79: =AF79/AE79-1 -> 3.0517287 | AJ79: Смарт–Сэйл | AK79: ='Сентябрь 25'!AG79 -> 0 | AL79: =AJ52 -> 0 | AM79: =AL79/AK79-1 -> #DIV/0!
B80: Нужно сделать на вчера | D80: =D78/$G$1*$C$1 -> 2574715.4 | F80: Нужно сделать на вчера | H80: =H78/$G$1*$C$1 -> 1893480.2 | AC80: Золотое Яблоко | AD80: Биг–Л | AE80: ='Сентябрь 25'!AA80 -> 0 | AF80: =AF66 -> 100903 | AG80: =AF80/AE80-1 -> #DIV/0! | AI80: Золотое Яблоко | AJ80: Биг–Л | AK80: ='Сентябрь 25'!AG80 -> #DIV/0! | AL80: =AJ53 -> 0 | AM80: =AL80/AK80-1 -> #DIV/0!
B81: Нужно делать в день | D81: =(D78-D73)/($G$1-$C$1) -> -262467.4 | F81: Нужно делать в день | H81: =(H78-H73)/($G$1-$C$1) -> 152694.8 | AD81: Смарт–Сэйл | AE81: ='Сентябрь 25'!AA81 -> 959556 | AF81: =AF67 -> 2120688 | AG81: =AF81/AE81-1 -> 1.2100722 | AJ81: Смарт–Сэйл | AK81: ='Сентябрь 25'!AG81 -> 0 | AL81: =AJ54 -> 0 | AM81: =AL81/AK81-1 -> #DIV/0!
B82: Разница от плана | D82: =D73-D80 -> 1807474.6 | F82: Разница от плана | H82: =H73-H80 -> -399343.19 | AE82: ='Сентябрь 25'!AA82 -> 2.183695e+08 | AF82: =SUM(AF72:AF81) -> 5.8046589e+08 | AG82: =AF82/AE82-1 -> 1.6581821 | AK82: ='Сентябрь 25'!AG82 -> 0.099630962 | AL82: =AJ68 -> 0.066622731 | AM82: =AL82/AK82-1 -> -0.33130495
B83: Прогноз по выручке | D83: =D73/$C$1*$G$1 -> 5224918.8 | F83: Прогноз по выручке | H83: =H73/$C$1*$G$1 -> 1781471 | AG83: =AF82-AE82 -> 3.6209639e+08
B84: Прогноз по выручке (%) | D84: =D83/D78 -> 1.7020095 | F84: Прогноз по выручке (%) | H84: =H83/H78 -> 0.78909566
B86: Летуаль
B87: =B66 -> Биг–Л / Март | до | D87: =$D$4 -> 46107 | F87: =F66 -> Смарт/ Март| до | H87: =$D$4 -> 46107
B88: Реклама | C88: 13460.13 | F88: Реклама | G88: 44712.84
B89: Выручка | D89: =S35 -> 490176 | F89: Выручка | H89: =T35 -> 1274528
B90: ДРР / Факт | D90: =C88/D89 -> 0.02745979 | F90: ДРР / Факт | H90: =G88/H89 -> 0.035081881
B91: ДРР / План | C91: 0.1 | D91: =D89*C91 -> 49017.6 | F91: ДРР / План | G91: 0.1 | H91: =H89*G91 -> 127452.8
B92: Перераход в деньгах | D92: =C88-D91 -> -35557.47 | F92: Перераход в деньгах | H92: =G88-H91 -> -82739.96
B94: План | D94: =S42 -> 619304 | F94: План | H94: =T42 -> 1719666
B95: Плато продаж | D95: =D89/$C$1 -> 18852.923 | F95: Плато продаж | H95: =H89/$C$1 -> 49020.308
B96: Нужно сделать на вчера | D96: =D94/$G$1*$C$1 -> 519416.26 | F96: Нужно сделать на вчера | H96: =H94/$G$1*$C$1 -> 1442300.5
B97: Нужно делать в день | D97: =(D94-D89)/($G$1-$C$1) -> 25825.6 | F97: Нужно делать в день | H97: =(H94-H89)/($G$1-$C$1) -> 89027.6
B98: Разница от плана | D98: =D89-D96 -> -29240.258 | F98: Разница от плана | H98: =H89-H96 -> -167772.52
B99: Прогноз по выручке | D99: =D89/$C$1*$G$1 -> 584440.62 | F99: Прогноз по выручке | H99: =H89/$C$1*$G$1 -> 1519629.5
B100: Прогноз по выручке (%) | D100: =D99/D94 -> 0.94370554 | F100: Прогноз по выручке (%) | H100: =H99/H94 -> 0.88367714
B102: Магнит
B103: =B82 -> Разница от плана | D103: =$D$4 -> 46107 | F103: =F82 -> Разница от плана | H103: =$D$4 -> 46107
...

Sheet Февраль 26
A1: 3 | B1: Вчера | C1: 28 | F1: Дней в месяце | G1: 28
A2: Актуально на | B2: 45988 | M2: Оз | O2: Вб | Q2: Ям | S2: Лету | U2: ЗЯ | W2: Магнит Маркет | Y2: Сайт | AE2: план | AF2: ауты | AG2: реальный план | AI2: выручка | AJ2: отказы/возвраты | AK2: раздачи | AL2: выкупы | AM2: реальная выручка
B3: Ozon | M3: Биг–Л | N3: Смарт | O3: Биг–Л | P3: Смарт | Q3: Биг–Л | R3: Смарт | S3: Биг–Л | T3: Смарт | U3: Биг–Л | V3: Смарт | W3: Биг–Л | X3: Смарт | Y3: qeep | Z3: harly | AA3: Алтея | AC3: WB | AD3: Биг–Л | AE3: =D39 -> 199495328 | AG3: =AE3-AF3 -> 199495328 | AI3: =O35 -> 2.0608031e+08 | AM3: =AI3-SUM(AJ3:AL3) -> 2.0608031e+08
B4: Биг–Л / Февраль | до | D4: =TODAY()-1 -> 46107 | F4: Смарт/ Февраль| до | H4: =$D$4 -> 46107 | K4: 46054 | L4: =SUM(M4:AA4) -> 22380818 | M4: 5372144 | N4: 2769431 | O4: 7651982 | P4: 6259469 | Q4: 102903 | R4: 81221 | S4: 9901 | T4: 68464 | U4: 10862 | V4: 53890 | W4: 0 | X4: 551 | AD4: Смарт–Сэйл | AE4: =H39 -> 138055387 | AG4: =AE4-AF4 -> 138055387 | AI4: =P35 -> 1.1437699e+08 | AM4: =AI4-SUM(AJ4:AL4) -> 1.1437699e+08
A5: =IFERROR(C5/$C$15, " ") -> 0.89654243 | B5: Оплата за клик | C5: 13483878 | F5: Оплата за клик | G5: 10577282 | I5: =IFERROR(G5/$G$15, " ") -> 0.95763547 | K5: 46055 | L5: =SUM(M5:AA5) -> 18252037 | M5: 4368346 | N5: 2553900 | O5: 7276839 | P5: 3722942 | Q5: 107801 | R5: 118624 | S5: 7429 | T5: 44509 | U5: 9858 | V5: 41789 | W5: 0 | X5: 0 | AC5: Ozon | AD5: Биг–Л | AE5: =D21 -> 110647711 | AG5: =AE5-AF5 -> 110647711 | AI5: =M35 -> 105053826 | AM5: =AI5-SUM(AJ5:AL5) -> 105053826
A6: =IFERROR(C6/$C$15, " ") -> 0.0036552187 | B6: Оплата за заказ | C6: 54974 | F6: Оплата за заказ | G6: 179988 | I6: =IFERROR(G6/$G$15, " ") -> 0.016295575 | K6: 46056 | L6: =SUM(M6:AA6) -> 17986720 | M6: 4679661 | N6: 2818473 | O6: 6841463 | P6: 3302445 | Q6: 127025 | R6: 95317 | S6: 6880 | T6: 64340 | U6: 8993 | V6: 39046 | W6: 522.5 | X6: 2554.35 | AD6: Смарт–Сэйл | AE6: =H21 -> 80715472 | AG6: =AE6-AF6 -> 80715472 | AI6: =N35 -> 84254055 | AM6: =AI6-SUM(AJ6:AL6) -> 84254055
A7: =IFERROR(C7/$C$15, " ") -> 0.087439476 | B7: Медийка | C7: 1315078 | F7: Медийка | G7: 144385 | I7: =IFERROR(G7/$G$15, " ") -> 0.013072186 | K7: 46057 | L7: =SUM(M7:AA7) -> 17866750 | M7: 3988192 | N7: 2391656 | O7: 7177214 | P7: 3991472 | Q7: 109509 | R7: 104352 | S7: 11272 | T7: 46619 | U7: 11974 | V7: 34490 | W7: 0 | X7: 0 | AC7: ЯМаркет | AD7: Биг–Л | AE7: =D78 -> 3639698 | AG7: =AE7-AF7 -> 3639698 | AI7: =Q35 -> 3069853 | AM7: =AI7-SUM(AJ7:AL7) -> 3069853
A8: =IFERROR(C8/$C$15, " ") -> 0 | B8: Баллы за отзывы | C8: 0 | F8: Баллы за отзывы | G8: 1464 | I8: =IFERROR(G8/$G$15, " ") -> 0.00013254618 | K8: 46058 | L8: =SUM(M8:AA8) -> 19204974 | M8: 4047129 | N8: 2860213.1 | O8: 7304220 | P8: 4593798 | Q8: 168079 | R8: 87609 | S8: 16753 | T8: 42853 | U8: 15881 | V8: 64363 | W8: 2038.3 | X8: 2038 | AD8: Смарт–Сэйл | AE8: =H78 -> 2771328 | AG8: =AE8-AF8 -> 2771328 | AI8: =R35 -> 2257611 | AM8: =AI8-SUM(AJ8:AL8) -> 2257611
A9: =IFERROR(C9/$C$15, " ") -> 0.012204165 | B9: Бонусы продавца | C9: 183549 | F9: Бонусы продавца | G9: 142088 | I9: =IFERROR(G9/$G$15, " ") -> 0.012864222 | K9: 46059 | L9: =SUM(M9:AA9) -> 19252449 | M9: 4018207 | N9: 2954370.1 | O9: 7210530 | P9: 4716662 | Q9: 141692 | R9: 72584 | S9: 18005 | T9: 62434 | U9: 16359 | V9: 37574 | W9: 2830 | X9: 1202 | AC9: Летуаль | AD9: Биг–Л | AE9: =S42 -> 355446 | AG9: =AE9-AF9 -> 355446 | AI9: =S35 -> 619304 | AM9: =AI9-SUM(AJ9:AL9) -> 619304
A10: =IFERROR(C10/$C$15, " ") -> 0 | B10: Рассылки | C10: 0 | F10: Рассылки | I10: =IFERROR(G10/$G$15, " ") -> 0 | K10: 46060 | L10: =SUM(M10:AA10) -> 19269758 | M10: 3597521 | N10: 2791137.1 | O10: 7447201 | P10: 5027386 | Q10: 135696 | R10: 101265 | S10: 32554 | T10: 56939 | U10: 17159 | V10: 58983 | W10: 2680.65 | X10: 1236.15 | AD10: Смарт–Сэйл | AE10: =T42 -> 1486093 | AG10: =AE10-AF10 -> 1486093 | AI10: =T35 -> 1719666 | AM10: =AI10-SUM(AJ10:AL10) -> 1719666
A11: =IFERROR(C11/$C$15, " ") -> 0 | B11: Закрепление отзыва | C11: 0 | F11: Закрепление отзыва | I11: =IFERROR(G11/$G$15, " ") -> 0 | K11: 46061 | L11: =SUM(M11:AA11) -> 21288492 | M11: 3925173 | N11: 3399460.9 | O11: 8317863 | P11: 5272869 | Q11: 103297 | R11: 82209 | S11: 27343 | T11: 83038 | U11: 7335 | V11: 64213 | W11: 2899.95 | X11: 2791.65 | AC11: Золотое Яблоко | AD11: Биг–Л | AE11: =U42 -> 594263 | AG11: =AE11-AF11 -> 594263 | AI11: =U35 -> 141359 | AM11: =AI11-SUM(AJ11:AL11) -> 141359
B12: Иные электронные услуги | C12: 0 | F12: Иные электронные услуги | I12: =IFERROR(G12/$G$15, " ") -> 0 | K12: 46062 | L12: =SUM(M12:AA12) -> 19834724 | M12: 4011785 | N12: 4258828.4 | O12: 7284229 | P12: 3949382 | Q12: 72535 | R12: 87159 | S12: 31309 | T12: 81620 | U12: 8070 | V12: 49506 | W12: 0 | X12: 300.9 | AD12: Смарт–Сэйл | AE12: =V42 -> 954144 | AG12: =AE12-AF12 -> 954144 | AI12: =V35 -> 1599107 | AM12: =AI12-SUM(AJ12:AL12) -> 1599107
B13: Продвижение бренда | C13: 0 | F13: Продвижение бренда | I13: =IFERROR(G13/$G$15, " ") -> 0 | K13: 46063 | L13: =SUM(M13:AA13) -> 19306307 | M13: 3765396 | N13: 3473043 | O13: 7763233 | P13: 3903031 | Q13: 112806 | R13: 78188 | S13: 43065 | T13: 82671 | U13: 6499 | V13: 68985 | W13: 3685 | X13: 5705.25 | AD13: итог | AE13: =SUM(AE3:AE12) -> 5.3871487e+08 | AF13: =SUM(AF3:AF12) -> 0 | AG13: =SUM(AG3:AG12) -> 5.3871487e+08 | AI13: =SUM(AI3:AI12) -> 5.1917208e+08 | AJ13: =SUM(AJ3:AJ12) -> 0 | AK13: =SUM(AK3:AK12) -> 0 | AL13: =SUM(AL3:AL12) -> 0 | AM13: =SUM(AM3:AM12) -> 5.1917208e+08
B14: Ozon Рассрочка | C14: 2387 | F14: Ozon Рассрочка | K14: 46064 | L14: =SUM(M14:AA14) -> 18578760 | M14: 3627716 | N14: 3122784.5 | O14: 7461659 | P14: 3983616 | Q14: 119984 | R14: 91511 | S14: 43373 | T14: 53458 | U14: 2986 | V14: 68405 | W14: 1192.5 | X14: 2075
B15: Итого расходов | C15: =SUM(C5:C14) -> 15039866 | F15: Итого расходов | G15: =SUM(G5:G14) -> 11045207 | H15: =SUM(H5:H14) -> 0 | K15: 46065 | L15: =SUM(M15:AA15) -> 19675120 | M15: 3805866 | N15: 3383037.1 | O15: 7811860 | P15: 4297347 | Q15: 102139 | R15: 93039 | S15: 42722 | T15: 73921 | U15: 3146 | V15: 58589 | W15: 0 | X15: 3454
B16: Выручка | D16: =M35 -> 105053826 | F16: Выручка | H16: =N35 -> 84254055 | K16: 46066 | L16: =SUM(M16:AA16) -> 18815684 | M16: 3709816 | N16: 3562179 | O16: 7042533 | P16: 4074817 | Q16: 130371 | R16: 72650 | S16: 68327 | T16: 76897 | U16: 3171 | V16: 65863 | W16: 4897 | X16: 4163
B17: ДРР / Факт | D17: =C15/D16 -> 0.14316343 | F17: ДРР / Факт | H17: =G15/H16 -> 0.13109407 | K17: 46067 | L17: =SUM(M17:AA17) -> 17567891 | M17: 3629820 | N17: 3051682 | O17: 6742154 | P17: 3796162 | Q17: 109704 | R17: 79200 | S17: 41974 | T17: 48212 | U17: 1243 | V17: 67329 | W17: 0 | X17: 411 | AE17: Без вычетов | AI17: С вычетом всего
A18: =D17/C18 -> 0.95442286 | B18: ДРР / План | C18: 0.15 | D18: =D16*C18 -> 15758074 | F18: ДРР / План | G18: 0.13 | H18: =H16*G18 -> 10953027 | I18: =H17/G18 -> 1.0084159 | K18: 46068 | L18: =SUM(M18:AA18) -> 19726431 | M18: 3578944 | N18: 3280752 | O18: 8138150 | P18: 4331470 | Q18: 151378 | R18: 62711 | S18: 25886 | T18: 78643 | U18: 2302 | V18: 71783 | W18: 1150 | X18: 3261.8 | AE18: план | AF18: выручка | AG18: дельта | AI18: реальный план | AJ18: реальная выручка | AK18: дельта
B19: Перерасход в деньгах | D19: =C15-D18 -> -718207.9 | F19: Перераход в деньгах | H19: =G15-H18 -> 92179.824 | K19: 46069 | L19: =SUM(M19:AA19) -> 16983888 | M19: 3456749 | N19: 2778825 | O19: 6920459 | P19: 3469239 | Q19: 111219 | R19: 85493 | S19: 22261 | T19: 65822 | U19: 3325 | V19: 63582 | W19: 4686.29 | X19: 2227.69 | AC19: WB | AD19: Биг–Л | AE19: =AE3 -> 199495328 | AF19: =AI3 -> 2.0608031e+08 | AG19: =IFERROR(AF19/AE19, " ") -> 1.0330082 | AI19: =AG3 -> 199495328 | AJ19: =AM3 -> 2.0608031e+08 | AK19: =IFERROR(AJ19/AI19, " ") -> 1.0330082
K20: 46070 | L20: =SUM(M20:AA20) -> 16243698 | M20: 3509490 | N20: 2856296 | O20: 6445829 | P20: 3155216 | Q20: 83133 | R20: 51078 | S20: 22261 | T20: 50830 | U20: 1334 | V20: 59686 | W20: 1073.63 | X20: 7471.59 | AD20: Смарт–Сэйл | AE20: =AE4 -> 138055387 | AF20: =AI4 -> 1.1437699e+08 | AG20: =IFERROR(AF20/AE20, " ") -> 0.82848624 | AI20: =AG4 -> 138055387 | AJ20: =AM4 -> 1.1437699e+08 | AK20: =IFERROR(AJ20/AI20, " ") -> 0.82848624
B21: План | D21: =M42 -> 110647711 | F21: План | H21: =N42 -> 80715472 | K21: 46071 | L21: =SUM(M21:AA21) -> 17429785 | M21: 3662400 | N21: 2793781 | O21: 7322126 | P21: 3330989 | Q21: 102799 | R21: 86473 | S21: 14371 | T21: 53023 | U21: 3458 | V21: 51663 | W21: 3141.14 | X21: 5560.75 | AC21: Ozon | AD21: Биг–Л | AE21: =AE5 -> 110647711 | AF21: =AI5 -> 105053826 | AG21: =IFERROR(AF21/AE21, " ") -> 0.94944419 | AI21: =AG5 -> 110647711 | AJ21: =AM5 -> 105053826 | AK21: =IFERROR(AJ21/AI21, " ") -> 0.94944419
B22: Плато продаж | D22: =D16/$C$1 -> 3751922.4 | F22: Плато продаж | H22: =H16/$C$1 -> 3009073.4 | K22: 46072 | L22: =SUM(M22:AA22) -> 16646958 | M22: 3316224 | N22: 2724931 | O22: 6735823 | P22: 3574250 | Q22: 70209 | R22: 73933 | S22: 14399 | T22: 68151 | U22: 1334 | V22: 60674 | W22: 4255.47 | X22: 2774.15 | AD22: Смарт–Сэйл | AE22: =AE6 -> 80715472 | AF22: =AI6 -> 84254055 | AG22: =IFERROR(AF22/AE22, " ") -> 1.0438402 | AI22: =AG6 -> 80715472 | AJ22: =AM6 -> 84254055 | AK22: =IFERROR(AJ22/AI22, " ") -> 1.0438402
B23: Нужно сделать на вчера | D23: =D21/$G$1*$C$1 -> 110647711 | F23: Нужно сделать на вчера | H23: =H21/$G$1*$C$1 -> 80715472 | K23: 46073 | L23: =SUM(M23:AA23) -> 17953625 | M23: 3659255 | N23: 2991282.1 | O23: 6372463 | P23: 4658057 | Q23: 98858 | R23: 45473 | S23: 9943 | T23: 51014 | U23: 3998 | V23: 52311 | W23: 4799.27 | X23: 6172.05 | AC23: ЯМаркет | AD23: Биг–Л | AE23: =AE7 -> 3639698 | AF23: =AI7 -> 3069853 | AG23: =IFERROR(AF23/AE23, " ") -> 0.84343619 | AI23: =AG7 -> 3639698 | AJ23: =AM7 -> 3069853 | AK23: =IFERROR(AJ23/AI23, " ") -> 0.84343619
B24: Нужно делать в день | D24: =(D21-D16)/($G$1-$C$1) -> #DIV/0! | F24: Нужно делать в день | H24: =(H21-H16)/($G$1-$C$1) -> #DIV/0! | K24: 46074 | L24: =SUM(M24:AA24) -> 16345828 | M24: 3546840 | N24: 2829425 | O24: 6644788 | P24: 3108943 | Q24: 11248 | R24: 67592 | S24: 5464 | T24: 52171 | U24: 0 | V24: 61796 | W24: 2723.4 | X24: 14837.98 | AD24: Смарт–Сэйл | AE24: =AE8 -> 2771328 | AF24: =AI8 -> 2257611 | AG24: =IFERROR(AF24/AE24, " ") -> 0.81463147 | AI24: =AG8 -> 2771328 | AJ24: =AM8 -> 2257611 | AK24: =IFERROR(AJ24/AI24, " ") -> 0.81463147
B25: Дельта от плана | D25: =D16-D23 -> -5593885 | F25: Дельта от плана | H25: =H16-H23 -> 3538582.7 | K25: 46075 | L25: =SUM(M25:AA25) -> 18314277 | M25: 3445861 | N25: 3335429 | O25: 7327483 | P25: 3884241 | Q25: 119345 | R25: 61954 | S25: 8515 | T25: 77844 | U25: 0 | V25: 46057 | W25: 4026.27 | X25: 3521.69 | AC25: Летуаль | AD25: Биг–Л | AE25: =AE9 -> 355446 | AF25: =AI9 -> 619304 | AG25: =IFERROR(AF25/AE25, " ") -> 1.7423294 | AI25: =AG9 -> 355446 | AJ25: =AM9 -> 619304 | AK25: =IFERROR(AJ25/AI25, " ") -> 1.7423294
B26: Прогноз по выручке | D26: =D16/$C$1*$G$1 -> 105053826 | F26: Прогноз по выручке | H26: =H16/$C$1*$G$1 -> 84254055 | K26: 46076 | L26: =SUM(M26:AA26) -> 20182913 | M26: 3626455 | N26: 3158305.7 | O26: 8114736 | P26: 4977826 | Q26: 123444 | R26: 71588 | S26: 5464 | T26: 52202 | U26: 0 | V26: 31860 | W26: 7399.07 | X26: 13633.05 | AD26: Смарт–Сэйл | AE26: =AE10 -> 1486093 | AF26: =AI10 -> 1719666 | AG26: =IFERROR(AF26/AE26, " ") -> 1.1571725 | AI26: =AG10 -> 1486093 | AJ26: =AM10 -> 1719666 | AK26: =IFERROR(AJ26/AI26, " ") -> 1.1571725
B27: Прогноз по выручке (%) | D27: =D26/D21 -> 0.94944419 | F27: Прогноз по выручке (%) | H27: =H26/H21 -> 1.0438402 | K27: 46077 | L27: =SUM(M27:AA27) -> 18083192 | M27: 3380035 | N27: 2790555.1 | O27: 7879010 | P27: 3725965 | Q27: 100191 | R27: 80650 | S27: 11069 | T27: 55503 | U27: 2072 | V27: 50611 | W27: 3002.2 | X27: 4528.4 | AC27: Золотое Яблоко | AD27: Биг–Л | AE27: =AE11 -> 594263 | AF27: =AI11 -> 141359 | AG27: =IFERROR(AF27/AE27, " ") -> 0.23787279 | AI27: =AG11 -> 594263 | AJ27: =AM11 -> 141359 | AK27: =IFERROR(AJ27/AI27, " ") -> 0.23787279
K28: 46078 | L28: =SUM(M28:AA28) -> 18672838 | M28: 3622040 | N28: 2976212.1 | O28: 7904447 | P28: 3828920 | Q28: 119847 | R28: 80911 | S28: 20222 | T28: 59756 | U28: 0 | V28: 45359 | W28: 6573.56 | X28: 8550.24 | AD28: Смарт–Сэйл | AE28: =AE12 -> 954144 | AF28: =AI12 -> 1599107 | AG28: =IFERROR(AF28/AE28, " ") -> 1.6759598 | AI28: =AG12 -> 954144 | AJ28: =AM12 -> 1599107 | AK28: =IFERROR(AJ28/AI28, " ") -> 1.6759598
B29: Wildberries / Расход бонусы + рубли | K29: 46079 | L29: =SUM(M29:AA29) -> 18178155 | M29: 3491165 | N29: 2973035 | O29: 7591972 | P29: 3818584 | Q29: 81534 | R29: 74568 | S29: 17164 | T29: 44107 | U29: 0 | V29: 73990 | W29: 3658.51 | X29: 8377.93 | AE29: =SUM(AE19:AE28) -> 5.3871487e+08 | AF29: =SUM(AF19:AF28) -> 5.1917208e+08 | AG29: =IFERROR(AF29/AE29, " ") -> 0.96372332 | AI29: =SUM(AI19:AI24) -> 5.3532492e+08 | AJ29: =SUM(AJ19:AJ24) -> 5.1509265e+08 | AK29: =IFERROR(AJ29/AI29, " ") -> 0.96220562
B30: =B4 -> Биг–Л / Февраль | до | D30: =$D$4 -> 46107 | F30: =F4 -> Смарт/ Февраль| до | H30: =$D$4 -> 46107 | K30: 46080 | L30: =SUM(M30:AA30) -> 17083965 | M30: 3060688 | N30: 2685352 | O30: 7317169 | P30: 3643196 | Q30: 124962 | R30: 78003 | S30: 24396 | T30: 56772 | U30: 0 | V30: 86140 | W30: 1212 | X30: 6075
A31: =IFERROR(C31/$C$33, " ") -> 0.87143112 | B31: Затраты из РК | C31: 8602065 | F31: Затраты из РК | G31: 6013051 | I31: =IFERROR(G31/$G$33, " ") -> 0.97315757 | K31: 46081 | L31: =SUM(M31:AA31) -> 18244654 | M31: 3150908 | N31: 2689679 | O31: 8032879.2 | P31: 3978695.1 | Q31: 128145 | R31: 92256 | S31: 16982 | T31: 67853 | U31: 0 | V31: 70570 | W31: 8197.76 | X31: 8489.04 | AC31: Только рубли | AE31: реальная выручка | AF31: реклама | AG31: ДРР | AI31: ДРР план | AJ31: ДРР факт | AK31: дельта
A32: =IFERROR(C32/$C$33, " ") -> 0.12856888 | B32: Отзывы за баллы | C32: 1269128.3 | F32: Отзывы за баллы | G32: 165856.9 | I32: =IFERROR(G32/$G$33, " ") -> 0.02684243 | L32: =SUM(M32:AA32) -> 0 | AC32: WB | AD32: Биг–Л | AE32: =AM3 -> 2.0608031e+08 | AF32: =C51 -> 0 | AG32: =AF32/AE32 -> 0 | AI32: =C36 -> 0.08 | AJ32: =AG32 -> 0 | AK32: =AJ32/AI32-1 -> -1
B33: Итого расходов | C33: =SUM(C31:C32) -> 9871193.3 | F33: Итого расходов | G33: =SUM(G31:G32) -> 6178907.9 | L33: =SUM(M33:AA33) -> 0 | AD33: Смарт–Сэйл | AE33: =AM4 -> 1.1437699e+08 | AF33: =G51 -> 0 | AG33: =AF33/AE33 -> 0 | AI33: =G36 -> 0.08 | AJ33: =AG33 -> 0 | AK33: =AJ33/AI33-1 -> -1
B34: Выручка | D34: =O35 -> 2.0608031e+08 | F34: Выручка | H34: =P35 -> 1.1437699e+08 | L34: =SUM(M34:AA34) -> 0 | AC34: Ozon | AD34: Биг–Л | AE34: =AM5 -> 105053826 | AF34: =C15 -> 15039866 | AG34: =AF34/AE34 -> 0.14316343 | AI34: =C18 -> 0.15 | AJ34: =AG34 -> 0.14316343 | AK34: =AJ34/AI34-1 -> -0.045577137
B35: ДРР / Факт | D35: =C33/D34 -> 0.047899739 | F35: ДРР / Факт | H35: =G33/H34 -> 0.054022299 | K35: =L35/C1 -> 18548953 | L35: =SUM(L4:L34) -> 5.1937069e+08 | M35: =SUM(M4:M34) -> 105053826 | N35: =SUM(N4:N34) -> 84254055 | O35: =SUM(O4:O34) -> 2.0608031e+08 | P35: =SUM(P4:P34) -> 1.1437699e+08 | Q35: =SUM(Q4:Q34) -> 3069853 | R35: =SUM(R4:R34) -> 2257611 | S35: =SUM(S4:S34) -> 619304 | ... AA35: =SUM(AA4:AA34) -> 0 | AD35: Смарт–Сэйл | AE35: =AM6 -> 84254055 | AF35: =G15 -> 11045207 | AG35: =AF35/AE35 -> 0.13109407 | AI35: =G18 -> 0.13 | AJ35: =AG35 -> 0.13109407 | AK35: =AJ35/AI35-1 -> 0.0084159221
A36: =D35/C36 -> 0.59874674 | B36: ДРР / План | C36: 0.08 | D36: =D34*C36 -> 16486425 | F36: ДРР / План | G36: 0.08 | H36: =H34*G36 -> 9150159.1 | I36: =H35/G36 -> 0.67527874 | M36: =M35/$L$35 -> 0.20227138 | N36: =N35/$L$35 -> 0.16222335 | O36: =O35/$L$35 -> 0.39678849 | P36: =P35/$L$35 -> 0.22022226 | Q36: =Q35/$L$35 -> 0.0059107166 | R36: =R35/$L$35 -> 0.0043468202 | S36: =S35/$L$35 -> 0.0011924123 | T36: =T35/$L$35 -> 0.0033110571 | ... AA36: =AA35/$L$35 -> 0 | AC36: ЯМаркет | AD36: Биг–Л | AE36: =AM7 -> 3069853 | AF36: =C72 -> 585970 | AG36: =AF36/AE36 -> 0.19087885 | AI36: =C75 -> 0.18 | AJ36: =AG36 -> 0.19087885 | AK36: =AJ36/AI36-1 -> 0.060438037
B37: Перераход в деньгах | D37: =C33-D36 -> -6615231.8 | F37: Перераход в деньгах | H37: =G33-H36 -> -2971251.2 | AD37: Смарт–Сэйл | AE37: =AM8 -> 2257611 | AF37: =G72 -> 437052 | AG37: =AF37/AE37 -> 0.19359048 | AI37: =G75 -> 0.175 | AJ37: =AG37 -> 0.19359048 | AK37: =AJ37/AI37-1 -> 0.10623132
K38: Распределение по направлениям | M38: =SUM(M40:N40)/$L$40 -> 0.36449473 | O38: =SUM(O40:P40)/$L$40 -> 0.61701076 | Q38: =SUM(Q40:R40)/$L$40 -> 0.010257537 | S38: =SUM(S40:T40)/$L$40 -> 0.0045034694 | U38: =SUM(U40:V40)/$L$40 -> 0.0033511055 | W38: =SUM(W40:X40)/$L$40 -> 0.0003824015 | Y38: =SUM(Y40:Z40)/$L$40 -> 0 | AC38: Летуаль | AD38: Биг–Л | AE38: =AM9 -> 619304 | AF38: 0 | AG38: =AF38/AE38 -> 0 | AI38: =C91 -> 0.1 | AJ38: =AG38 -> 0 | AK38: =AJ38/AI38-1 -> -1
B39: План | D39: =O42 -> 199495328 | F39: План | H39: =P42 -> 138055387 | K39: Распределение продаж | L39: =L40/$L$40 -> 1 | M39: =M40/$L$40 -> 0.20227138 | N39: =N40/$L$40 -> 0.16222335 | O39: =O40/$L$40 -> 0.39678849 | P39: =P40/$L$40 -> 0.22022226 | Q39: =Q40/$L$40 -> 0.0059107166 | R39: =R40/$L$40 -> 0.0043468202 | S39: =S40/$L$40 -> 0.0011924123 | ... AA39: =AA40/$L$40 -> 0 | AD39: Смарт–Сэйл | AE39: =AM10 -> 1719666 | AF39: 0 | AG39: =AF39/AE39 -> 0 | AI39: =G91 -> 0.1 | AJ39: =AG39 -> 0 | AK39: =AJ39/AI39-1 -> -1
B40: Плато продаж | D40: =D34/$C$1 -> 7360011.2 | F40: Плато продаж | H40: =H34/$C$1 -> 4084892.5 | K40: Прогноз | L40: =L35/$C$1*$G$1 -> 5.1937069e+08 | M40: =M35/$C$1*$G$1 -> 105053826 | N40: =N35/$C$1*$G$1 -> 84254055 | O40: =O35/$C$1*$G$1 -> 2.0608031e+08 | P40: =P35/$C$1*$G$1 -> 1.1437699e+08 | Q40: =Q35/$C$1*$G$1 -> 3069853 | R40: =R35/$C$1*$G$1 -> 2257611 | S40: =S35/$C$1*$G$1 -> 619304 | ... AA40: =AA35/$C$1*$G$1 -> 0 | AC40: Золотое Яблоко | AD40: Биг–Л | AE40: =AM11 -> 141359 | AF40: 0 | AG40: =AF40/AE40 -> 0 | AI40: 0 | AJ40: =AG40 -> 0 | AK40: =AJ40/AI40-1 -> #DIV/0!
B41: Нужно сделать на вчера | D41: =D39/$G$1*$C$1 -> 199495328 | F41: Нужно сделать на вчера | H41: =H39/$G$1*$C$1 -> 138055387 | K41: Плато продаж | L41: =L35/$C$1 -> 18548953 | M41: =M35/$C$1 -> 3751922.4 | N41: =N35/$C$1 -> 3009073.4 | O41: =O35/$C$1 -> 7360011.2 | P41: =P35/$C$1 -> 4084892.5 | Q41: =Q35/$C$1 -> 109637.61 | R41: =R35/$C$1 -> 80628.964 | S41: =S35/$C$1 -> 22118 | ... AA41: =AA35/$C$1 -> 0 | AD41: Смарт–Сэйл | AE41: =AM12 -> 1599107 | AF41: 0 | AG41: =AF41/AE41 -> 0 | AI41: 0 | AJ41: =AG41 -> 0 | AK41: =AJ41/AI41-1 -> #DIV/0!
B42: Нужно делать в день | D42: =(D39-D34)/($G$1-$C$1) -> #DIV/0! | F42: Нужно делать в день | H42: =(H39-H34)/($G$1-$C$1) -> #DIV/0! | K42: Прошлый месяц | L42: =SUM(M42:V42) -> 5.3871487e+08 | M42: ='Январь 26'!M35 -> 110647711 | N42: ='Январь 26'!N35 -> 80715472 | O42: ='Январь 26'!O35 -> 199495328 | P42: ='Январь 26'!P35 -> 138055387 | Q42: ='Январь 26'!Q35 -> 3639698 | R42: ='Январь 26'!R35 -> 2771328 | S42: ='Январь 26'!S35 -> 355446 | T42: ='Январь 26'!T35 -> 1486093 | ... AA42: ='Январь 26'!AA35 -> 0 | AE42: =SUM(AE32:AE41) -> 5.1917208e+08 | AF42: =SUM(AF32:AF41) -> 27108095 | AG42: =AF42/AE42 -> 0.052214084 | AI42: =F142 -> 0.10345181 | AJ42: =AG42 -> 0.052214084 | AK42: =AJ42/AI42-1 -> -0.4952811
B43: Дельта от плана | D43: =D34-D41 -> 6584986.2 | F43: Дельта от плана | H43: =H34-H41 -> -23678398
B44: Прогноз по выручке | D44: =D34/$C$1*$G$1 -> 2.0608031e+08 | F44: Прогноз по выручке | H44: =H34/$C$1*$G$1 -> 1.1437699e+08 | K44: Рекламный расход , руб | L44: =SUM(M44:X44) -> 43158196 | M44: =C15 -> 15039866 | N44: =G15 -> 11045207 | O44: =C33 -> 9871193.3 | P44: =G33 -> 6178907.9 | Q44: =C72 -> 585970 | R44: =G72 -> 437052 | S44: =C88 | T44: =G88 | U44: 0 | V44: 0 | W44: 0 | X44: 0 | Y44: 0 | Z44: 0 | AA44: 0 | AC44: Рубли + Бонусы | AE44: реальная выручка | AF44: реклама | AG44: ДРР | AI44: ДРР план | AJ44: ДРР факт | AK44: дельта
B45: Прогноз по выручке (%) | D45: =D44/D39 -> 1.0330082 | F45: Прогноз по выручке (%) | H45: =H44/H39 -> 0.82848624 | K45: ДРР , % | L45: =L44/L35 -> 0.083097096 | M45: =IFERROR(M44/M35, " ") -> 0.14316343 | N45: =IFERROR(N44/N35, " ") -> 0.13109407 | O45: =IFERROR(O44/O35, " ") -> 0.047899739 | P45: =IFERROR(P44/P35, " ") -> 0.054022299 | Q45: =IFERROR(Q44/Q35, " ") -> 0.19087885 | R45: =IFERROR(R44/R35, " ") -> 0.19359048 | S45: =IFERROR(S44/S35, " ") -> 0 | T45: =IFERROR(T44/T35, " ") -> 0 | ... AA45: =IFERROR(AA44/AA35, " ") | AC45: WB | AD45: Биг–Л | AE45: =AE32 -> 2.0608031e+08 | AF45: =C33 -> 9871193.3 | AG45: =AF45/AE45 -> 0.047899739 | AI45: =AI32 -> 0.08 | AJ45: =AG45 -> 0.047899739 | AK45: =AJ45/AI45-1 -> -0.40125326
AD46: Смарт–Сэйл | AE46: =AE33 -> 1.1437699e+08 | AF46: =G33 -> 6178907.9 | AG46: =AF46/AE46 -> 0.054022299 | AI46: =AI33 -> 0.08 | AJ46: =AG46 -> 0.054022299 | AK46: =AJ46/AI46-1 -> -0.32472126
B47: Wildberries / Расход только рубли | K47: Прирост к прошлому месяцу , % | L47: =L40/L42-1 -> -0.035908008 | M47: =M40/M42-1 -> -0.050555813 | N47: =N40/N42-1 -> 0.043840203 | O47: =O40/O42-1 -> 0.033008222 | P47: =P40/P42-1 -> -0.17151376 | Q47: =Q40/Q42-1 -> -0.15656381 | R47: =R40/R42-1 -> -0.18536853 | S47: =S40/S42-1 -> 0.74232936 | ... AA47: =AA40/AA42-1 -> #DIV/0! | AC47: Ozon | AD47: Биг–Л | AE47: =AE34 -> 105053826 | AF47: =AF34 -> 15039866 | AG47: =AF47/AE47 -> 0.14316343 | AI47: =AI34 -> 0.15 | AJ47: =AG47 -> 0.14316343 | AK47: =AJ47/AI47-1 -> -0.045577137
B48: =B30 -> Биг–Л / Февраль | до | D48: =$D$4 -> 46107 | F48: =F30 -> Смарт/ Февраль| до | H48: =$D$4 -> 46107 | K48: Прирост по направлениям , % | M48: =SUM(M40:N40)/SUM(M42:N42)-1 -> -0.010740322 | O48: =SUM(O40:P40)/SUM(O42:P42)-1 -> -0.050639536 | Q48: =SUM(Q40:R40)/SUM(Q42:R42)-1 -> -0.16901538 | S48: =SUM(S40:T40)/SUM(S42:T42)-1 -> 0.27011701 | U48: =SUM(U40:V40)/SUM(U42:V42)-1 -> 0.12403651 | W48: =SUM(W40:X40)/SUM(W42:X42)-1 -> 1.7950529 | Y48: =SUM(Y40:AA40)/SUM(Y42:AA42)-1 -> -1 | AD48: Смарт–Сэйл | AE48: =AE35 -> 84254055 | AF48: =AF35 -> 11045207 | AG48: =AF48/AE48 -> 0.13109407 | AI48: =AI35 -> 0.13 | AJ48: =AG48 -> 0.13109407 | AK48: =AJ48/AI48-1 -> 0.0084159221
A49: =IFERROR(C49/$C$33, " ") -> 0 | B49: Затраты из РК | F49: Затраты из РК | I49: =IFERROR(G49/$G$33, " ") -> 0 | K49: Прирост к прошлому месяцу , руб | L49: =L40-L42 -> -19344178 | M49: =M40-M42 -> -5593885 | N49: =N40-N42 -> 3538582.7 | O49: =O40-O42 -> 6584986.2 | P49: =P40-P42 -> -23678398 | Q49: =Q40-Q42 -> -569845 | R49: =R40-R42 -> -513717 | S49: =S40-S42 -> 263858 | ... AA49: =AA40-AA42 -> 0 | AC49: ЯМаркет | AD49: Биг–Л | AE49: =AE36 -> 3069853 | AF49: =AF36 -> 585970 | AG49: =AF49/AE49 -> 0.19087885 | AI49: =AI36 -> 0.18 | AJ49: =AG49 -> 0.19087885 | AK49: =AJ49/AI49-1 -> 0.060438037
A50: =IFERROR(C50/$C$33, " ") -> 0 | B50: Отзывы за баллы? | F50: Отзывы за баллы? | I50: =IFERROR(G50/$G$33, " ") -> 0 | K50: Прирост по направлениям , руб | M50: =SUM(M40:N40)-SUM(M42:N42) -> -2055302.3 | O50: =SUM(O40:P40)-SUM(O42:P42) -> -17093412 | Q50: =SUM(Q40:R40)-SUM(Q42:R42) -> -1083562 | S50: =SUM(S40:T40)-SUM(S42:T42) -> 497431 | U50: =SUM(U40:V40)-SUM(U42:V42) -> 192059 | W50: =SUM(W40:X40)-SUM(W42:X42) -> 127551.11 | Y50: =SUM(Y40:AA40)-SUM(Y42:AA42) -> -36781 | AD50: Смарт–Сэйл | AE50: =AE37 -> 2257611 | AF50: =AF37 -> 437052 | AG50: =AF50/AE50 -> 0.19359048 | AI50: =AI37 -> 0.175 | AJ50: =AG50 -> 0.19359048 | AK50: =AJ50/AI50-1 -> 0.10623132
B51: Итого расходов | C51: =SUM(C49:C50) -> 0 | F51: Итого расходов | G51: =SUM(G49:G50) -> 0 | AC51: Летуаль | AD51: Биг–Л | AE51: =AE38 -> 619304 | AF51: =AF38 -> 0 | AG51: =AF51/AE51 -> 0 | AI51: =AI38 -> 0.1 | AJ51: =AG51 -> 0 | AK51: =AJ51/AI51-1 -> -1
B52: Выручка | D52: =O35 -> 2.0608031e+08 | F52: Выручка | H52: =P35 -> 1.1437699e+08 | K52: хотим | L52: 750000000 | M52: =$L$52*M36 -> 151703534 | N52: =$L$52*N36 -> 1.2166751e+08 | O52: =$L$52*O36 -> 2.9759137e+08 | P52: =$L$52*P36 -> 1.651667e+08 | Q52: =$L$52*Q36 -> 4433037.5 | R52: =$L$52*R36 -> 3260115.1 | S52: =$L$52*S36 -> 894309.22 | T52: =$L$52*T36 -> 2483292.8 | ... AA52: =$L$52*AA36 -> 0 | AD52: Смарт–Сэйл | AE52: =AE39 -> 1719666 | AF52: =AF39 -> 0 | AG52: =AF52/AE52 -> 0 | AI52: =AI39 -> 0.1 | AJ52: =AG52 -> 0 | AK52: =AJ52/AI52-1 -> -1
B53: ДРР / Факт | D53: =C51/D52 -> 0 | F53: ДРР / Факт | H53: =G51/H52 -> 0 | K53: осталось сделать | L53: =L52-L35 -> 2.3062931e+08 | M53: =M52-M35 -> 46649708 | N53: =N52-N35 -> 37413460 | O53: =O52-O35 -> 91511055 | P53: =P52-P35 -> 50789708 | Q53: =Q52-Q35 -> 1363184.5 | R53: =R52-R35 -> 1002504.1 | S53: =S52-S35 -> 275005.22 | ... AA53: =AA52-AA35 -> 0 | AC53: Золотое Яблоко | AD53: Биг–Л | AE53: =AE40 -> 141359 | AF53: =AF40 -> 0 | AG53: =AF53/AE53 -> 0 | AI53: =AI40 -> 0 | AJ53: =AG53 -> 0 | AK53: =AJ53/AI53-1 -> #DIV/0!
A54: =D53/C54 -> 0 | B54: ДРР / План | C54: 0.05 | D54: =D52*C54 -> 10304016 | F54: ДРР / План | G54: 0.05 | H54: =H52*G54 -> 5718849.5 | I54: =H53/G54 -> 0 | K54: нужно плато продаж | L54: =SUM(M54:V54) -> #DIV/0! | M54: =M53/($G$1-$C$1) -> #DIV/0! | N54: =N53/($G$1-$C$1) -> #DIV/0! | O54: =O53/($G$1-$C$1) -> #DIV/0! | P54: =P53/($G$1-$C$1) -> #DIV/0! | Q54: =Q53/($G$1-$C$1) -> #DIV/0! | R54: =R53/($G$1-$C$1) -> #DIV/0! | S54: =S53/($G$1-$C$1) -> #DIV/0! | T54: =T53/($G$1-$C$1) -> #DIV/0! | ... AA54: =AA53/($G$1-$C$1) -> #DIV/0! | AD54: Смарт–Сэйл | AE54: =AE41 -> 1599107 | AF54: =AF41 -> 0 | AG54: =AF54/AE54 -> 0 | AI54: =AI41 -> 0 | AJ54: =AG54 -> 0 | AK54: =AJ54/AI54-1 -> #DIV/0!
B55: Перераход в деньгах | D55: =C51-D54 -> -10304016 | F55: Перераход в деньгах | H55: =G51-H54 -> -5718849.5 | AE55: =SUM(AE45:AE54) -> 5.1917208e+08 | AF55: =SUM(AF45:AF54) -> 43158196 | AG55: =AF55/AE55 -> 0.083128884 | AI55: =AI42 -> 0.10345181 | AJ55: =AG55 -> 0.083128884 | AK55: =AJ55/AI55-1 -> -0.19644824
N56: 210000000 | Q56: =SUM(Q44:R44)/SUM(Q40:R40) -> 0.19202795
B57: План | D57: =O42 -> 199495328 | F57: План | H57: =P42 -> 138055387 | N57: =N56-SUM(M35:N35) -> 20692119 | AE57: реальный план | AF57: реальная выручка | AG57: дельта | AI57: ДРР план | AJ57: ДРР факт | AK57: дельта
B58: Плато продаж | D58: =D52/$C$1 -> 7360011.2 | F58: Плато продаж | H58: =H52/$C$1 -> 4084892.5 | M58: =M35/SUM(M35:N35) -> 0.55493636 | N58: =N35/SUM(M35:N35) -> 0.44506364 | AC58: WB | AD58: Биг–Л | AE58: =AG3 -> 199495328 | AF58: =AM3 -> 2.0608031e+08 | AG58: =IFERROR(AF58/AE58, " ") -> 1.0330082 | AI58: =AI45 -> 0.08 | AJ58: =AJ45 -> 0.047899739 | AK58: =AJ58/AI58-1 -> -0.40125326
B59: Нужно сделать на вчера | D59: =D57/$G$1*$C$1 -> 199495328 | F59: Нужно сделать на вчера | H59: =H57/$G$1*$C$1 -> 138055387 | M59: =N57*M58 -> 11482809 | N59: =N57*N58 -> 9209309.8 | AD59: Смарт–Сэйл | AE59: =AG4 -> 138055387 | AF59: =AM4 -> 1.1437699e+08 | AG59: =IFERROR(AF59/AE59, " ") -> 0.82848624 | AI59: =AI46 -> 0.08 | AJ59: =AJ46 -> 0.054022299 | AK59: =AJ59/AI59-1 -> -0.32472126
B60: Нужно делать в день | D60: =(D57-D52)/($G$1-$C$1) -> #DIV/0! | F60: Нужно делать в день | H60: =(H57-H52)/($G$1-$C$1) -> #DIV/0! | L60: =SUM(M60:N60) -> #DIV/0! | M60: =M59/(G1-C1) -> #DIV/0! | N60: =N59/(G1-C1) -> #DIV/0! | AC60: Ozon | AD60: Биг–Л | AE60: =AG5 -> 110647711 | AF60: =AM5 -> 105053826 | AG60: =IFERROR(AF60/AE60, " ") -> 0.94944419 | AI60: =AI47 -> 0.15 | AJ60: =AJ47 -> 0.14316343 | AK60: =AJ60/AI60-1 -> -0.045577137
B61: Дельта от плана | D61: =D52-D59 -> 6584986.2 | F61: Дельта от плана | H61: =H52-H59 -> -23678398 | AD61: Смарт–Сэйл | AE61: =AG6 -> 80715472 | AF61: =AM6 -> 84254055 | AG61: =IFERROR(AF61/AE61, " ") -> 1.0438402 | AI61: =AI48 -> 0.13 | AJ61: =AJ48 -> 0.13109407 | AK61: =AJ61/AI61-1 -> 0.0084159221
B62: Прогноз по выручке | D62: =D52/$C$1*$G$1 -> 2.0608031e+08 | F62: Прогноз по выручке | H62: =H52/$C$1*$G$1 -> 1.1437699e+08 | M62: =M58 -> 0.55493636 | N62: =N58 -> 0.44506364 | AC62: ЯМаркет | AD62: Биг–Л | AE62: =AG7 -> 3639698 | AF62: =AM7 -> 3069853 | AG62: =IFERROR(AF62/AE62, " ") -> 0.84343619 | AI62: =AI49 -> 0.18 | AJ62: =AJ49 -> 0.19087885 | AK62: =AJ62/AI62-1 -> 0.060438037
B63: Прогноз по выручке (%) | D63: =D62/D57 -> 1.0330082 | F63: Прогноз по выручке (%) | H63: =H62/H57 -> 0.82848624 | M63: =$N$56*M62 -> 116536635 | N63: =$N$56*N62 -> 93463365 | AD63: Смарт–Сэйл | AE63: =AG8 -> 2771328 | AF63: =AM8 -> 2257611 | AG63: =IFERROR(AF63/AE63, " ") -> 0.81463147 | AI63: =AI50 -> 0.175 | AJ63: =AJ50 -> 0.19359048 | AK63: =AJ63/AI63-1 -> 0.10623132
AC64: Летуаль | AD64: Биг–Л | AE64: =AG9 -> 355446 | AF64: =AM9 -> 619304 | AG64: =IFERROR(AF64/AE64, " ") -> 1.7423294 | AI64: =AI51 -> 0.1 | AJ64: =AJ51 -> 0 | AK64: =AJ64/AI64-1 -> -1
B65: ЯМаркет | L65: =G1-C1 -> 0 | M65: =(M63-M35)/$L$65 -> #DIV/0! | N65: =(N63-N35)/$L$65 -> #DIV/0! | AD65: Смарт–Сэйл | AE65: =AG10 -> 1486093 | AF65: =AM10 -> 1719666 | AG65: =IFERROR(AF65/AE65, " ") -> 1.1571725 | AI65: =AI52 -> 0.1 | AJ65: =AJ52 -> 0 | AK65: =AJ65/AI65-1 -> -1
B66: =B30 -> Биг–Л / Февраль | до | D66: =$D$4 -> 46107 | F66: =F30 -> Смарт/ Февраль| до | H66: =$D$4 -> 46107 | AC66: Золотое Яблоко | AD66: Биг–Л | AE66: =AG11 -> 594263 | AF66: =AM11 -> 141359 | AG66: =IFERROR(AF66/AE66, " ") -> 0.23787279 | AI66: =AI53 -> 0 | AJ66: =AJ53 -> 0 | AK66: =AJ66/AI66-1 -> #DIV/0!
A67: =IFERROR(C67/$C$72, " ") -> 0.99640767 | B67: Буст продаж | C67: 583865 | F67: Буст продаж | G67: 434737 | I67: =IFERROR(G67/$G$72, " ") -> 0.99470315 | N67: 450000000 | AD67: Смарт–Сэйл | AE67: =AG12 -> 954144 | AF67: =AM12 -> 1599107 | AG67: =IFERROR(AF67/AE67, " ") -> 1.6759598 | AI67: =AI54 -> 0 | AJ67: =AJ54 -> 0 | AK67: =AJ67/AI67-1 -> #DIV/0!
A68: =IFERROR(C68/$C$72, " ") -> 0.0035923341 | B68: Буст показов | C68: 2105 | F68: Буст показов | G68: 2315 | I68: =IFERROR(G68/$G$72, " ") -> 0.0052968525 | M68: =M35/SUM($M$35:$N$35) -> 0.55493636 | N68: =N35/SUM($M$35:$N$35) -> 0.44506364 | AE68: =AG13 -> 5.3871487e+08 | AF68: =AM13 -> 5.1917208e+08 | AG68: =IFERROR(AF68/AE68, " ") -> 0.96372332 | AI68: =AI55 -> 0.10345181 | AJ68: =AJ55 -> 0.083128884 | AK68: =AJ68/AI68-1 -> -0.19644824
A69: =IFERROR(C69/$C$72, " ") -> 0 | B69: Полки | F69: Полки | I69: =IFERROR(G69/$G$72, " ") -> 0 | M69: =$N$67*M68 -> 2.4972136e+08 | N69: =$N$67*N68 -> 2.0027864e+08
A70: =IFERROR(C70/$C$72, " ") -> 0 | B70: Охватное продвижение | F70: Охватное продвижение | I70: =IFERROR(G70/$G$72, " ") -> 0 | L70: 30 | M70: =M69/$L$70 -> 8324045.4 | N70: =N69/$L$70 -> 6675954.6 | AE70: Сентябрь | AF70: Октябрь | AK70: =AE70 -> Сентябрь | AL70: =AF70 -> Октябрь
A71: =IFERROR(C71/$C$72, " ") -> 0 | B71: Баннеры | F71: Баннеры | I71: =IFERROR(G71/$G$72, " ") -> 0 | AE71: реальная выручка | AF71: реальная выручка | AG71: дельта | AI71: Рубли + Бонусы | AK71: ДРР факт | AL71: ДРР факт | AM71: дельта
B72: Итого расходов | C72: =SUM(C67:C71) -> 585970 | F72: Итого расходов | G72: =SUM(G67:G71) -> 437052 | AC72: WB | AD72: Биг–Л | AE72: ='Сентябрь 25'!AA72 -> 34886232 | AF72: =AF58 -> 2.0608031e+08 | AG72: =AF72/AE72-1 -> 4.9072104 | AI72: WB | AJ72: Биг–Л | AK72: ='Сентябрь 25'!AG72 -> 0.06874047 | AL72: =AJ45 -> 0.047899739 | AM72: =AL72/AK72-1 -> -0.30317993
B73: Выручка | D73: =Q35 -> 3069853 | F73: Выручка | H73: =R35 -> 2257611 | AD73: Смарт–Сэйл | AE73: ='Сентябрь 25'!AA73 -> 108267871 | AF73: =AF59 -> 1.1437699e+08 | AG73: =AF73/AE73-1 -> 0.056425956 | AJ73: Смарт–Сэйл | AK73: ='Сентябрь 25'!AG73 -> 0.061662033 | AL73: =AJ46 -> 0.054022299 | AM73: =AL73/AK73-1 -> -0.12389688
B74: ДРР / Факт | D74: =C72/D73 -> 0.19087885 | F74: ДРР / Факт | H74: =G72/H73 -> 0.19359048 | AC74: Ozon | AD74: Биг–Л | AE74: ='Сентябрь 25'!AA74 -> 25030993 | AF74: =AF60 -> 105053826 | AG74: =AF74/AE74-1 -> 3.19695 | AI74: Ozon | AJ74: Биг–Л | AK74: ='Сентябрь 25'!AG74 -> 0.23173352 | AL74: =AJ47 -> 0.14316343 | AM74: =AL74/AK74-1 -> -0.38220663
A75: =D74/C75 -> 1.060438 | B75: ДРР / План | C75: 0.18 | D75: =D73*C75 -> 552573.54 | F75: ДРР / План | G75: 0.175 | H75: =H73*G75 -> 395081.92 | I75: =H74/G75 -> 1.1062313 | AD75: Смарт–Сэйл | AE75: ='Сентябрь 25'!AA75 -> 50514010 | AF75: =AF61 -> 84254055 | AG75: =AF75/AE75-1 -> 0.66793441 | AJ75: Смарт–Сэйл | AK75: ='Сентябрь 25'!AG75 -> 0.11988367 | AL75: =AJ48 -> 0.13109407 | AM75: =AL75/AK75-1 -> 0.09351063
B76: Перераход в деньгах | D76: =C72-D75 -> 33396.46 | F76: Перераход в деньгах | H76: =G72-H75 -> 41970.075 | AC76: ЯМаркет | AD76: Биг–Л | AE76: ='Сентябрь 25'!AA76 -> -4890173.2 | AF76: =AF62 -> 3069853 | AG76: =AF76/AE76-1 -> -1.6277596 | AI76: ЯМаркет | AJ76: Биг–Л | AK76: ='Сентябрь 25'!AG76 -> -0.034747849 | AL76: =AJ49 -> 0.19087885 | AM76: =AL76/AK76-1 -> -6.4932565
AD77: Смарт–Сэйл | AE77: ='Сентябрь 25'!AA77 -> 3184978 | AF77: =AF63 -> 2257611 | AG77: =AF77/AE77-1 -> -0.29116904 | AJ77: Смарт–Сэйл | AK77: ='Сентябрь 25'!AG77 -> 0.20596751 | AL77: =AJ50 -> 0.19359048 | AM77: =AL77/AK77-1 -> -0.060092158
B78: План | D78: =Q42 -> 3639698 | F78: План | H78: =R42 -> 2771328 | AC78: Летуаль | AD78: Биг–Л | AE78: ='Сентябрь 25'!AA78 -> 101466 | AF78: =AF64 -> 619304 | AG78: =AF78/AE78-1 -> 5.1035618 | AI78: Летуаль | AJ78: Биг–Л | AK78: ='Сентябрь 25'!AG78 -> 0 | AL78: =AJ51 -> 0 | AM78: =AL78/AK78-1 -> #DIV/0!
B79: Плато продаж | D79: =D73/$C$1 -> 109637.61 | F79: Плато продаж | H79: =H73/$C$1 -> 80628.964 | AD79: Смарт–Сэйл | AE79: ='Сентябрь 25'!AA79 -> 314564 | AF79: =AF65 -> 1719666 | AG79: =AF79/AE79-1 -> 4.4668239 | AJ79: Смарт–Сэйл | AK79: ='Сентябрь 25'!AG79 -> 0 | AL79: =AJ52 -> 0 | AM79: =AL79/AK79-1 -> #DIV/0!
B80: Нужно сделать на вчера | D80: =D78/$G$1*$C$1 -> 3639698 | F80: Нужно сделать на вчера | H80: =H78/$G$1*$C$1 -> 2771328 | AC80: Золотое Яблоко | AD80: Биг–Л | AE80: ='Сентябрь 25'!AA80 -> 0 | AF80: =AF66 -> 141359 | AG80: =AF80/AE80-1 -> #DIV/0! | AI80: Золотое Яблоко | AJ80: Биг–Л | AK80: ='Сентябрь 25'!AG80 -> #DIV/0! | AL80: =AJ53 -> 0 | AM80: =AL80/AK80-1 -> #DIV/0!
B81: Нужно делать в день | D81: =(D78-D73)/($G$1-$C$1) -> #DIV/0! | F81: Нужно делать в день | H81: =(H78-H73)/($G$1-$C$1) -> #DIV/0! | AD81: Смарт–Сэйл | AE81: ='Сентябрь 25'!AA81 -> 959556 | AF81: =AF67 -> 1599107 | AG81: =AF81/AE81-1 -> 0.66650722 | AJ81: Смарт–Сэйл | AK81: ='Сентябрь 25'!AG81 -> 0 | AL81: =AJ54 -> 0 | AM81: =AL81/AK81-1 -> #DIV/0!
B82: Разница от плана | D82: =D73-D80 -> -569845 | F82: Разница от плана | H82: =H73-H80 -> -513717 | AE82: ='Сентябрь 25'!AA82 -> 2.183695e+08 | AF82: =SUM(AF72:AF81) -> 5.1917208e+08 | AG82: =AF82/AE82-1 -> 1.3774936 | AK82: ='Сентябрь 25'!AG82 -> 0.099630962 | AL82: =AJ68 -> 0.083128884 | AM82: =AL82/AK82-1 -> -0.16563202
B83: Прогноз по выручке | D83: =D73/$C$1*$G$1 -> 3069853 | F83: Прогноз по выручке | H83: =H73/$C$1*$G$1 -> 2257611 | AG83: =AF82-AE82 -> 3.0080259e+08
B84: Прогноз по выручке (%) | D84: =D83/D78 -> 0.84343619 | F84: Прогноз по выручке (%) | H84: =H83/H78 -> 0.81463147
B86: Летуаль
B87: =B66 -> Биг–Л / Февраль | до | D87: =$D$4 -> 46107 | F87: =F66 -> Смарт/ Февраль| до | H87: =$D$4 -> 46107
B88: Реклама | D88: 22723.09 | F88: Реклама | H88: 60254.48
B89: Выручка | D89: =S35 -> 619304 | F89: Выручка | H89: =T35 -> 1719666
B90: ДРР / Факт | D90: =D88/D89 -> 0.036691334 | F90: ДРР / Факт | H90: =H88/H89 -> 0.035038478
B91: ДРР / План | C91: 0.1 | D91: =D89*C91 -> 61930.4 | F91: ДРР / План | G91: 0.1 | H91: =H89*G91 -> 171966.6
B92: Перераход в деньгах | D92: =C88-D91 -> -61930.4 | F92: Перераход в деньгах | H92: =G88-H91 -> -171966.6
B94: План | D94: =S42 -> 355446 | F94: План | H94: =T42 -> 1486093
B95: Плато продаж | D95: =D89/$C$1 -> 22118 | F95: Плато продаж | H95: =H89/$C$1 -> 61416.643
B96: Нужно сделать на вчера | D96: =D94/$G$1*$C$1 -> 355446 | F96: Нужно сделать на вчера | H96: =H94/$G$1*$C$1 -> 1486093
B97: Нужно делать в день | D97: =(D94-D89)/($G$1-$C$1) -> #DIV/0! | F97: Нужно делать в день | H97: =(H94-H89)/($G$1-$C$1) -> #DIV/0!
B98: Разница от плана | D98: =D89-D96 -> 263858 | F98: Разница от плана | H98: =H89-H96 -> 233573
B99: Прогноз по выручке | D99: =D89/$C$1*$G$1 -> 619304 | F99: Прогноз по выручке | H99: =H89/$C$1*$G$1 -> 1719666
B100: Прогноз по выручке (%) | D100: =D99/D94 -> 1.7423294 | F100: Прогноз по выручке (%) | H100: =H99/H94 -> 1.1571725
B102: Магнит
B103: =B82 -> Разница от плана | D103: =$D$4 -> 46107 | F103: =F82 -> Разница от плана | H103: =$D$4 -> 46107
...

Sheet Январь 26
A1: 3 | B1: Вчера | C1: 31 | F1: Дней в месяце | G1: 31
A2: Актуально на | B2: 45988 | M2: Оз | O2: Вб | Q2: Ям | S2: Лету | U2: ЗЯ | W2: Магнит Маркет | Y2: Сайт | AE2: план | AF2: ауты | AG2: реальный план | AI2: выручка | AJ2: отказы/возвраты | AK2: раздачи | AL2: выкупы | AM2: реальная выручка
B3: Ozon | M3: Биг–Л | N3: Смарт | O3: Биг–Л | P3: Смарт | Q3: Биг–Л | R3: Смарт | S3: Биг–Л | T3: Смарт | U3: Биг–Л | V3: Смарт | W3: Биг–Л | X3: Смарт | Y3: qeep | Z3: harly | AA3: Алтея | AC3: WB | AD3: Биг–Л | AE3: =D39 -> 113971735 | AG3: =AE3-AF3 -> 113971735 | AI3: =O35 -> 199495328 | AK3: =13501+762213 -> 775714 | AM3: =AI3-SUM(AJ3:AL3) -> 198719614
B4: Биг–Л / Январь | до | D4: 46053 | F4: Смарт/ Январь| до | H4: =$D$4 -> 46053 | K4: 46023 | L4: =SUM(M4:AA4) -> 10758032 | M4: 2560744 | N4: 1562108 | O4: 4229443 | P4: 2168992 | Q4: 98667 | R4: 46740 | S4: 2057 | T4: 45718 | U4: 1399 | V4: 42164 | W4: 0 | X4: 0 | Y4: 0 | AD4: Смарт–Сэйл | AE4: =H39 -> 110544589 | AG4: =AE4-AF4 -> 110544589 | AI4: =P35 -> 138055387 | AK4: =13766+940304 -> 954070 | AM4: =AI4-SUM(AJ4:AL4) -> 137101317
A5: =IFERROR(C5/$C$15, " ") -> 0.92309184 | B5: Оплата за клик | C5: 14024803 | F5: Оплата за клик | G5: 9067823 | I5: =IFERROR(G5/$G$15, " ") -> 0.94906971 | K5: 46024 | L5: =SUM(M5:AA5) -> 14913776 | M5: 3453779 | N5: 2177124 | O5: 5623274 | P5: 3361853 | Q5: 127362 | R5: 71748 | S5: 710 | T5: 54536 | U5: 2798 | V5: 39410 | W5: 0 | X5: 0 | Y5: 1182 | AC5: Ozon | AD5: Биг–Л | AE5: =D21 -> 96599698 | AG5: =AE5-AF5 -> 96599698 | AI5: =M35 -> 110647711 | AJ5: =AI5/80962*(6339+107) -> 8809505 | AK5: =15257+466756 -> 482013 | AM5: =AI5-SUM(AJ5:AL5) -> 101356193
A6: =IFERROR(C6/$C$15, " ") -> 0.027410783 | B6: Оплата за заказ | C6: 416460 | F6: Оплата за заказ | G6: 184960 | I6: =IFERROR(G6/$G$15, " ") -> 0.019358553 | K6: 46025 | L6: =SUM(M6:AA6) -> 15612171 | M6: 3710342 | N6: 2148368 | O6: 5297359 | P6: 4115128 | Q6: 131603 | R6: 86801 | S6: 4325 | T6: 54824 | U6: 6121 | V6: 55878 | W6: 0 | X6: 1422 | Y6: 0 | AD6: Смарт–Сэйл | AE6: =H21 -> 86342890 | AG6: =AE6-AF6 -> 86342890 | AI6: =N35 -> 80715472 | AJ6: =AI6/74719*(4982+97) -> 5486608.3 | AK6: =531+520719 -> 521250 | AM6: =AI6-SUM(AJ6:AL6) -> 74707614
A7: =IFERROR(C7/$C$15, " ") -> 0.037284417 | B7: Медийка | C7: 566473 | F7: Медийка | G7: 168528 | I7: =IFERROR(G7/$G$15, " ") -> 0.017638723 | K7: 46026 | L7: =SUM(M7:AA7) -> 15957648 | M7: 3924482 | N7: 2310076 | O7: 5439555 | P7: 3953389 | Q7: 129200 | R7: 109900 | S7: 2345 | T7: 39288 | U7: 6837 | V7: 40020 | W7: 0 | X7: 1017 | Y7: 1539 | AC7: ЯМаркет | AD7: Биг–Л | AE7: =D78 -> 3741104 | AG7: =AE7-AF7 -> 3741104 | AI7: =Q35 -> 3639698 | AJ7: =AI7/3564*(459+7) -> 475897.66 | AK7: =2520+11217 -> 13737 | AM7: =AI7-SUM(AJ7:AL7) -> 3150063.3
A8: =IFERROR(C8/$C$15, " ") -> 1.9284828e-05 | B8: Баллы за отзывы | C8: 293 | F8: Баллы за отзывы | G8: 2416 | I8: =IFERROR(G8/$G$15, " ") -> 0.00025286692 | K8: 46027 | L8: =SUM(M8:AA8) -> 15762072 | M8: 3770933 | N8: 2366459 | O8: 5510412 | P8: 3845833 | Q8: 105654 | R8: 73717 | S8: 2499 | T8: 39729 | U8: 12117 | V8: 32364 | W8: 0 | X8: 2355 | Y8: 0 | AD8: Смарт–Сэйл | AE8: =H78 -> 3478652 | AG8: =AE8-AF8 -> 3478652 | AI8: =R35 -> 2771328 | AJ8: =AI8/3587*(313+4) -> 244915.24 | AK8: =17845 -> 17845 | AM8: =AI8-SUM(AJ8:AL8) -> 2508567.8
A9: =IFERROR(C9/$C$15, " ") -> 0.011964031 | B9: Бонусы продавца | C9: 181773 | F9: Бонусы продавца | G9: 130706 | I9: =IFERROR(G9/$G$15, " ") -> 0.013680142 | K9: 46028 | L9: =SUM(M9:AA9) -> 15506133 | M9: 3908307 | N9: 2397154.1 | O9: 5188588 | P9: 3742674 | Q9: 89656 | R9: 112022 | S9: 0 | T9: 30184 | U9: 10552 | V9: 25808 | W9: 0 | X9: 1188 | Y9: 0 | AC9: Летуаль | AD9: Биг–Л | AE9: =S42 -> 341575 | AG9: =AE9-AF9 -> 341575 | AI9: =S35 -> 355446 | AM9: =AI9-SUM(AJ9:AL9) -> 355446
A10: =IFERROR(C10/$C$15, " ") -> 0 | B10: Рассылки | C10: 0 | F10: Рассылки | I10: =IFERROR(G10/$G$15, " ") -> 0 | K10: 46029 | L10: =SUM(M10:AA10) -> 17363056 | M10: 4793004 | N10: 2326980 | O10: 5856182 | P10: 4156421 | Q10: 99819 | R10: 62851 | S10: 3675 | T10: 21380 | U10: 11642 | V10: 28993 | W10: 0 | X10: 2109 | Y10: 0 | AD10: Смарт–Сэйл | AE10: =T42 -> 1332348 | AG10: =AE10-AF10 -> 1332348 | AI10: =T35 -> 1486093 | AK10: =9113 -> 9113 | AM10: =AI10-SUM(AJ10:AL10) -> 1476980
A11: =IFERROR(C11/$C$15, " ") -> 0 | B11: Закрепление отзыва | C11: 0 | F11: Закрепление отзыва | I11: =IFERROR(G11/$G$15, " ") -> 0 | K11: 46030 | L11: =SUM(M11:AA11) -> 19627323 | M11: 4807368 | N11: 2446234 | O11: 6530839 | P11: 5574038 | Q11: 89892 | R11: 89707 | S11: 5707 | T11: 32069 | U11: 13711 | V11: 32468 | W11: 0 | X11: 1367 | Y11: 3923 | AC11: Золотое Яблоко | AD11: Биг–Л | AE11: =U42 -> 108947 | AG11: =AE11-AF11 -> 108947 | AI11: =U35 -> 594263 | AK11: =6497+248803 -> 255300 | AM11: =AI11-SUM(AJ11:AL11) -> 338963
B12: Иные электронные услуги | C12: 0 | F12: Иные электронные услуги | I12: =IFERROR(G12/$G$15, " ") -> 0 | K12: 46031 | L12: =SUM(M12:AA12) -> 20330202 | M12: 4572678 | N12: 2541646 | O12: 6459515 | P12: 6455582 | Q12: 160570 | R12: 75490 | S12: 2778 | T12: 25216 | U12: 11835 | V12: 23800 | W12: 0 | X12: 1092 | Y12: 0 | AD12: Смарт–Сэйл | AE12: =V42 -> 787175 | AG12: =AE12-AF12 -> 787175 | AI12: =V35 -> 954144 | AK12: =5070+101552 -> 106622 | AM12: =AI12-SUM(AJ12:AL12) -> 847522
B13: Продвижение бренда | C13: 0 | F13: Продвижение бренда | I13: =IFERROR(G13/$G$15, " ") -> 0 | K13: 46032 | L13: =SUM(M13:AA13) -> 19711678 | M13: 4112819 | N13: 2588222 | O13: 6455940 | P13: 6248328 | Q13: 143984 | R13: 80890 | S13: 852 | T13: 38289 | U13: 8440 | V13: 28341 | W13: 519 | X13: 2034 | Y13: 3020 | AD13: итог | AE13: =SUM(AE3:AE12) -> 4.1724871e+08 | AF13: =SUM(AF3:AF12) -> 0 | AG13: =SUM(AG3:AG12) -> 4.1724871e+08 | AI13: =SUM(AI3:AI12) -> 5.3871487e+08 | AJ13: =SUM(AJ3:AJ12) -> 15016926 | AK13: =SUM(AK3:AK12) -> 3135664 | AL13: =SUM(AL3:AL12) -> 0 | AM13: =SUM(AM3:AM12) -> 5.2056228e+08
B14: Ozon Рассрочка | C14: 3489 | F14: Ozon Рассрочка | K14: 46033 | L14: =SUM(M14:AA14) -> 21605574 | M14: 4530575 | N14: 2714630.1 | O14: 7582307 | P14: 6418527 | Q14: 133673 | R14: 113443 | S14: 2345 | T14: 51187 | U14: 18379 | V14: 40154 | W14: 0 | X14: 354 | Y14: 0
B15: Итого расходов | C15: =SUM(C5:C14) -> 15193291 | F15: Итого расходов | G15: =SUM(G5:G14) -> 9554433 | H15: =SUM(H5:H14) -> 0 | K15: 46034 | L15: =SUM(M15:AA15) -> 17591225 | M15: 3580582 | N15: 2588648 | O15: 6323347 | P15: 4793010 | Q15: 130482 | R15: 87713 | S15: 4132 | T15: 53349 | U15: 5913 | V15: 21940 | W15: 0 | X15: 2109 | Y15: 0
B16: Выручка | D16: =M35 -> 110647711 | F16: Выручка | H16: =N35 -> 80715472 | K16: 46035 | L16: =SUM(M16:AA16) -> 17669184 | M16: 3405536 | N16: 2677293 | O16: 6413931 | P16: 4804282 | Q16: 122025 | R16: 129246 | S16: 4559 | T16: 65581 | U16: 14141 | V16: 31532 | W16: 0 | X16: 1058 | Y16: 0
B17: ДРР / Факт | D17: =C15/D16 -> 0.13731229 | F17: ДРР / Факт | H17: =G15/H16 -> 0.11837177 | K17: 46036 | L17: =SUM(M17:AA17) -> 18073795 | M17: 3259110 | N17: 2927401 | O17: 6758846 | P17: 4620942 | Q17: 218720 | R17: 89354 | S17: 652 | T17: 39190 | U17: 131760 | V17: 27470 | W17: 0 | X17: 350 | Y17: 0 | AE17: Без вычетов | AI17: С вычетом всего
A18: =D17/C18 -> 0.66981607 | B18: ДРР / План | C18: 0.205 | D18: =D16*C18 -> 22682781 | F18: ДРР / План | G18: 0.115 | H18: =H16*G18 -> 9282279.3 | I18: =H17/G18 -> 1.0293197 | K18: 46037 | L18: =SUM(M18:AA18) -> 17661106 | M18: 3263746 | N18: 3173546.1 | O18: 6575053 | P18: 4240112 | Q18: 142817 | R18: 92858 | S18: 4989 | T18: 46946 | U18: 91475 | V18: 25202 | W18: 4362 | X18: 0 | Y18: 0 | AE18: план | AF18: выручка | AG18: дельта | AI18: реальный план | AJ18: реальная выручка | AK18: дельта
B19: Перерасход в деньгах | D19: =C15-D18 -> -7489489.8 | F19: Перераход в деньгах | H19: =G15-H18 -> 272153.66 | K19: 46038 | L19: =SUM(M19:AA19) -> 16899560 | M19: 3144609 | N19: 2930262 | O19: 6141720 | P19: 4373897 | Q19: 82701 | R19: 89159 | S19: 13252 | T19: 28135 | U19: 60952 | V19: 18068 | W19: 4951 | X19: 11854 | Y19: 0 | AC19: WB | AD19: Биг–Л | AE19: =AE3 -> 113971735 | AF19: =AI3 -> 199495328 | AG19: =IFERROR(AF19/AE19, " ") -> 1.750393 | AI19: =AG3 -> 113971735 | AJ19: =AM3 -> 198719614 | AK19: =IFERROR(AJ19/AI19, " ") -> 1.7435868
K20: 46039 | L20: =SUM(M20:AA20) -> 18037985 | M20: 3689405 | N20: 2894971 | O20: 6713211 | P20: 4378824 | Q20: 129013 | R20: 90801 | S20: 20641 | T20: 42831 | U20: 55712 | V20: 22226 | W20: 0 | X20: 350 | Y20: 0 | AD20: Смарт–Сэйл | AE20: =AE4 -> 110544589 | AF20: =AI4 -> 138055387 | AG20: =IFERROR(AF20/AE20, " ") -> 1.2488661 | AI20: =AG4 -> 110544589 | AJ20: =AM4 -> 137101317 | AK20: =IFERROR(AJ20/AI20, " ") -> 1.2402354
B21: План | D21: =M42 -> 96599698 | F21: План | H21: =N42 -> 86342890 | K21: 46040 | L21: =SUM(M21:AA21) -> 18685904 | M21: 3653633 | N21: 2944215 | O21: 7220542 | P21: 4541922 | Q21: 135656 | R21: 84878 | S21: 15716 | T21: 54000 | U21: 13200 | V21: 19972 | W21: 0 | X21: 350 | Y21: 1820 | AC21: Ozon | AD21: Биг–Л | AE21: =AE5 -> 96599698 | AF21: =AI5 -> 110647711 | AG21: =IFERROR(AF21/AE21, " ") -> 1.145425 | AI21: =AG5 -> 96599698 | AJ21: =AM5 -> 101356193 | AK21: =IFERROR(AJ21/AI21, " ") -> 1.0492392
B22: Плато продаж | D22: =D16/$C$1 -> 3569281 | F22: Плато продаж | H22: =H16/$C$1 -> 2603724.9 | K22: 46041 | L22: =SUM(M22:AA22) -> 15737815 | M22: 3019828 | N22: 2676091 | O22: 6463237 | P22: 3278254 | Q22: 108977 | R22: 91125 | S22: 13229 | T22: 32886 | U22: 10429 | V22: 21021 | W22: 4951 | X22: 12856 | Y22: =3260+1671 -> 4931 | AD22: Смарт–Сэйл | AE22: =AE6 -> 86342890 | AF22: =AI6 -> 80715472 | AG22: =IFERROR(AF22/AE22, " ") -> 0.93482478 | AI22: =AG6 -> 86342890 | AJ22: =AM6 -> 74707614 | AK22: =IFERROR(AJ22/AI22, " ") -> 0.86524339
B23: Нужно сделать на вчера | D23: =D21/$G$1*$C$1 -> 96599698 | F23: Нужно сделать на вчера | H23: =H21/$G$1*$C$1 -> 86342890 | K23: 46042 | L23: =SUM(M23:AA23) -> 16806629 | M23: 3319665 | N23: 2624808.1 | O23: 7008494 | P23: 3568647 | Q23: 116701 | R23: 89586 | S23: 12058 | T23: 36967 | U23: 7030 | V23: 18125 | W23: 0 | X23: 625 | Y23: 3923 | AC23: ЯМаркет | AD23: Биг–Л | AE23: =AE7 -> 3741104 | AF23: =AI7 -> 3639698 | AG23: =IFERROR(AF23/AE23, " ") -> 0.9728941 | AI23: =AG7 -> 3741104 | AJ23: =AM7 -> 3150063.3 | AK23: =IFERROR(AJ23/AI23, " ") -> 0.84201437
B24: Нужно делать в день | D24: =(D21-D16)/($G$1-$C$1) -> #DIV/0! | F24: Нужно делать в день | H24: =(H21-H16)/($G$1-$C$1) -> #DIV/0! | K24: 46043 | L24: =SUM(M24:AA24) -> 16307741 | M24: 3428781 | N24: 2824083 | O24: 6595730 | P24: 3178278 | Q24: 98397 | R24: 101178 | S24: 21004 | T24: 33265 | U24: 7567 | V24: 13033 | W24: 0 | X24: 963 | Y24: 5462 | AD24: Смарт–Сэйл | AE24: =AE8 -> 3478652 | AF24: =AI8 -> 2771328 | AG24: =IFERROR(AF24/AE24, " ") -> 0.79666721 | AI24: =AG8 -> 3478652 | AJ24: =AM8 -> 2508567.8 | AK24: =IFERROR(AJ24/AI24, " ") -> 0.72113214
B25: Дельта от плана | D25: =D16-D23 -> 14048013 | F25: Дельта от плана | H25: =H16-H23 -> -5627417 | K25: 46044 | L25: =SUM(M25:AA25) -> 15948570 | M25: 3208929 | N25: 2682373 | O25: 6712160 | P25: 3081188 | Q25: 81765 | R25: 102694 | S25: 13929 | T25: 31414 | U25: 5837 | V25: 18559 | W25: 0 | X25: 412 | Y25: 9310 | AC25: Летуаль | AD25: Биг–Л | AE25: =AE9 -> 341575 | AF25: =AI9 -> 355446 | AG25: =IFERROR(AF25/AE25, " ") -> 1.0406089 | AI25: =AG9 -> 341575 | AJ25: =AM9 -> 355446 | AK25: =IFERROR(AJ25/AI25, " ") -> 1.0406089
B26: Прогноз по выручке | D26: =D16/$C$1*$G$1 -> 110647711 | F26: Прогноз по выручке | H26: =H16/$C$1*$G$1 -> 80715472 | K26: 46045 | L26: =SUM(M26:AA26) -> 16037350 | M26: 3114310 | N26: 2489130 | O26: 6691021 | P26: 3428916 | Q26: 100361 | R26: 118655 | S26: 26964 | T26: 35129 | U26: 6793 | V26: 23951 | W26: 0 | X26: 2119.6 | Y26: 0 | AD26: Смарт–Сэйл | AE26: =AE10 -> 1332348 | AF26: =AI10 -> 1486093 | AG26: =IFERROR(AF26/AE26, " ") -> 1.115394 | AI26: =AG10 -> 1332348 | AJ26: =AM10 -> 1476980 | AK26: =IFERROR(AJ26/AI26, " ") -> 1.1085542
B27: Прогноз по выручке (%) | D27: =D26/D21 -> 1.145425 | F27: Прогноз по выручке (%) | H27: =H26/H21 -> 0.93482478 | K27: 46046 | L27: =SUM(M27:AA27) -> 17236473 | M27: 3218517 | N27: 2311041 | O27: 7087777 | P27: 4363050 | Q27: 81270 | R27: 82784 | S27: 15162 | T27: 50584 | U27: 0 | V27: 22682 | W27: 0 | X27: 1934.72 | Y27: 1671 | AC27: Золотое Яблоко | AD27: Биг–Л | AE27: =AE11 -> 108947 | AF27: =AI11 -> 594263 | AG27: =IFERROR(AF27/AE27, " ") -> 5.4546064 | AI27: =AG11 -> 108947 | AJ27: =AM11 -> 338963 | AK27: =IFERROR(AJ27/AI27, " ") -> 3.1112651
K28: 46047 | L28: =SUM(M28:AA28) -> 18387426 | M28: 3209513 | N28: 2556223 | O28: 8207164 | P28: 4081725 | Q28: 134816 | R28: 89292 | S28: 21601 | T28: 51382 | U28: 14338 | V28: 19152 | W28: 1721.5 | X28: 499 | AD28: Смарт–Сэйл | AE28: =AE12 -> 787175 | AF28: =AI12 -> 954144 | AG28: =IFERROR(AF28/AE28, " ") -> 1.2121117 | AI28: =AG12 -> 787175 | AJ28: =AM12 -> 847522 | AK28: =IFERROR(AJ28/AI28, " ") -> 1.0766627
B29: Wildberries / Расход бонусы + рубли | K29: 46048 | L29: =SUM(M29:AA29) -> 17262930 | M29: 2821820 | N29: 2460326 | O29: 7796368 | P29: 3864302 | Q29: 132330 | R29: 79854 | S29: 17500 | T29: 65196 | U29: 12731 | V29: 11897 | W29: 0 | X29: 606 | AE29: =SUM(AE19:AE28) -> 4.1724871e+08 | AF29: =SUM(AF19:AF28) -> 5.3871487e+08 | AG29: =IFERROR(AF29/AE29, " ") -> 1.2911121 | AI29: =SUM(AI19:AI24) -> 4.1467867e+08 | AJ29: =SUM(AJ19:AJ24) -> 5.1754337e+08 | AK29: =IFERROR(AJ29/AI29, " ") -> 1.2480588
B30: =B4 -> Биг–Л / Январь | до | D30: =$D$4 -> 46053 | F30: =F4 -> Смарт/ Январь| до | H30: =$D$4 -> 46053 | K30: 46049 | L30: =SUM(M30:AA30) -> 17041905 | M30: 2794855 | N30: 3064152.1 | O30: 6673030 | P30: 4242575 | Q30: 109414 | R30: 78086 | S30: 17404 | T30: 41577 | U30: 10202 | V30: 9903 | W30: 0 | X30: 707
A31: =IFERROR(C31/$C$33, " ") -> 0.7738597 | B31: Затраты из РК | C31: 7405850 | F31: Затраты из РК | G31: 5522659 | I31: =IFERROR(G31/$G$33, " ") -> 0.97238956 | K31: 46050 | L31: =SUM(M31:AA31) -> 17583543 | M31: 3017452 | N31: 2834095 | O31: 6280295 | P31: 5172583 | Q31: 101257 | R31: 77444 | S31: 16060 | T31: 58970 | U31: 11046 | V31: 13929 | W31: 0 | X31: 412 | AC31: Только рубли | AE31: реальная выручка | AF31: реклама | AG31: ДРР | AI31: ДРР план | AJ31: ДРР факт | AK31: дельта
A32: =IFERROR(C32/$C$33, " ") -> 0.2261403 | B32: Отзывы за баллы | C32: 2164166.4 | F32: Отзывы за баллы | G32: 156812.7 | I32: =IFERROR(G32/$G$33, " ") -> 0.027610438 | K32: 46051 | L32: =SUM(M32:AA32) -> 19036655 | M32: 3497809 | N32: 3194764 | O32: 6253583 | P32: 5723933 | Q32: 102004 | R32: 98401 | S32: 12647 | T32: 49844 | U32: 14099 | V32: 88643 | W32: 0 | X32: 928.2 | AC32: WB | AD32: Биг–Л | AE32: =AM3 -> 198719614 | AF32: =C51 -> 4572564 | AG32: =AF32/AE32 -> 0.023010129 | AH32: =AE32/(AE32+AE33) -> 0.59174279 | AI32: =C36 -> 0.07 | AJ32: =AG32 -> 0.023010129 | AK32: =AJ32/AI32-1 -> -0.67128387
B33: Итого расходов | C33: =SUM(C31:C32) -> 9570016.4 | F33: Итого расходов | G33: =SUM(G31:G32) -> 5679471.7 | K33: 46052 | L33: =SUM(M33:AA33) -> 18776797 | M33: 3753135 | N33: 2542336 | O33: 6120832 | P33: 5913138 | Q33: 76364 | R33: 81417 | S33: 59578 | T33: 159684 | U33: 2950 | V33: 64373 | W33: 0 | X33: 2990 | AD33: Смарт–Сэйл | AE33: =AM4 -> 137101317 | AF33: =G51 -> 3391496 | AG33: =AF33/AE33 -> 0.024737151 | AH33: =AE33/(AE33+AE34) -> 0.57495072 | AI33: =G36 -> 0.07 | AJ33: =AG33 -> 0.024737151 | AK33: =AJ33/AI33-1 -> -0.64661213
B34: Выручка | D34: =O35 -> 199495328 | E34: 73474830 | F34: Выручка | H34: =P35 -> 138055387 | J34: =I35/H34 -> 0.14354939 | K34: 46053 | L34: =SUM(M34:AA34) -> 20892450 | M34: 4101445 | N34: 2740713 | O34: 7285573 | P34: 6365044 | Q34: 124548 | R34: 93494 | S34: 17076 | T34: 76743 | U34: 14257 | V34: 73066 | W34: 0 | X34: 491 | AC34: Ozon | AD34: Биг–Л | AE34: =AM5 -> 101356193 | AF34: =C15 -> 15193291 | AG34: =AF34/AE34 -> 0.14989998 | AH34: =AE34/(AE34+AE35) -> 0.57567875 | AI34: =C18 -> 0.205 | AJ34: =AG34 -> 0.14989998 | AK34: =AJ34/AI34-1 -> -0.2687806
B35: ДРР / Факт | D35: =C33/D34 -> 0.04797113 | E35: =E34/D34 -> 0.36830351 | F35: ДРР / Факт | H35: =G33/H34 -> 0.041139081 | I35: 19817766 | K35: =L35/C1 -> 17381378 | L35: =SUM(L4:L34) -> 5.3882271e+08 | M35: =SUM(M4:M34) -> 110647711 | N35: =SUM(N4:N34) -> 80715472 | O35: =SUM(O4:O34) -> 199495328 | P35: =SUM(P4:P34) -> 138055387 | Q35: =SUM(Q4:Q34) -> 3639698 | R35: =SUM(R4:R34) -> 2771328 | S35: =SUM(S4:S34) -> 355446 | ... AA35: =SUM(AA4:AA34) -> 0 | AD35: Смарт–Сэйл | AE35: =AM6 -> 74707614 | AF35: =G15 -> 9554433 | AG35: =AF35/AE35 -> 0.12789102 | AH35: =AE35/(AE35+AE36) -> 0.95954075 | AI35: =G18 -> 0.115 | AJ35: =AG35 -> 0.12789102 | AK35: =AJ35/AI35-1 -> 0.11209583
A36: =D35/C36 -> 0.68530186 | B36: ДРР / План | C36: 0.07 | D36: =D34*C36 -> 13964673 | E36: 73 474 830 | F36: ДРР / План | G36: 0.07 | H36: =H34*G36 -> 9663877.1 | I36: =H35/G36 -> 0.58770115 | M36: =M35/$L$35 -> 0.20535087 | N36: =N35/$L$35 -> 0.14979969 | O36: =O35/$L$35 -> 0.37024299 | P36: =P35/$L$35 -> 0.25621672 | Q36: =Q35/$L$35 -> 0.0067549083 | R36: =R35/$L$35 -> 0.0051433022 | S36: =S35/$L$35 -> 0.00065967153 | T36: =T35/$L$35 -> 0.0027580371 | ... AA36: =AA35/$L$35 -> 0 | AC36: ЯМаркет | AD36: Биг–Л | AE36: =AM7 -> 3150063.3 | AF36: =C72 -> 461196 | AG36: =AF36/AE36 -> 0.14640848 | AH36: =AE36/(AE36+AE37) -> 0.55668293 | AI36: =C75 -> 0.18 | AJ36: =AG36 -> 0.14640848 | AK36: =AJ36/AI36-1 -> -0.18661953
B37: Перераход в деньгах | D37: =C33-D36 -> -4394656.6 | F37: Перераход в деньгах | H37: =G33-H36 -> -3984405.4 | AD37: Смарт–Сэйл | AE37: =AM8 -> 2508567.8 | AF37: =G72 -> 482427 | AG37: =AF37/AE37 -> 0.19231173 | AH37: =AE37/(AE37+AE38) -> 0.87589236 | AI37: =G75 -> 0.175 | AJ37: =AG37 -> 0.19231173 | AK37: =AJ37/AI37-1 -> 0.09892416
K38: Распределение по направлениям | M38: =SUM(M40:N40)/$L$40 -> 0.35515055 | O38: =SUM(O40:P40)/$L$40 -> 0.62645971 | Q38: =SUM(Q40:R40)/$L$40 -> 0.01189821 | S38: =SUM(S40:T40)/$L$40 -> 0.0034177086 | U38: =SUM(U40:V40)/$L$40 -> 0.0028736855 | W38: =SUM(W40:X40)/$L$40 -> 0.00013187458 | Y38: =SUM(Y40:Z40)/$L$40 -> 6.8261785e-05 | AC38: Летуаль | AD38: Биг–Л | AE38: =AM9 -> 355446 | AF38: 0 | AG38: =AF38/AE38 -> 0 | AH38: =AE38/(AE38+AE39) -> 0.19397564 | AI38: =C91 -> 0.15 | AJ38: =AG38 -> 0 | AK38: =AJ38/AI38-1 -> -1
B39: План | D39: =O42 -> 113971735 | F39: План | H39: =P42 -> 110544589 | K39: Распределение продаж | L39: =L40/$L$40 -> 1 | M39: =M40/$L$40 -> 0.20535087 | N39: =N40/$L$40 -> 0.14979969 | O39: =O40/$L$40 -> 0.37024299 | P39: =P40/$L$40 -> 0.25621672 | Q39: =Q40/$L$40 -> 0.0067549083 | R39: =R40/$L$40 -> 0.0051433022 | S39: =S40/$L$40 -> 0.00065967153 | ... AA39: =AA40/$L$40 -> 0 | AD39: Смарт–Сэйл | AE39: =AM10 -> 1476980 | AF39: 0 | AG39: =AF39/AE39 -> 0 | AH39: =AE39/(AE39+AE40) -> 0.81334051 | AI39: =G91 -> 0.15 | AJ39: =AG39 -> 0 | AK39: =AJ39/AI39-1 -> -1
B40: Плато продаж | D40: =D34/$C$1 -> 6435333.2 | F40: Плато продаж | H40: =H34/$C$1 -> 4453399.6 | K40: Прогноз | L40: =L35/$C$1*$G$1 -> 5.3882271e+08 | M40: =M35/$C$1*$G$1 -> 110647711 | N40: =N35/$C$1*$G$1 -> 80715472 | O40: =O35/$C$1*$G$1 -> 199495328 | P40: =P35/$C$1*$G$1 -> 138055387 | Q40: =Q35/$C$1*$G$1 -> 3639698 | R40: =R35/$C$1*$G$1 -> 2771328 | S40: =S35/$C$1*$G$1 -> 355446 | ... AA40: =AA35/$C$1*$G$1 -> 0 | AC40: Золотое Яблоко | AD40: Биг–Л | AE40: =AM11 -> 338963 | AF40: 0 | AG40: =AF40/AE40 -> 0 | AH40: =AE40/(AE40+AE41) -> 0.28568671 | AI40: 0 | AJ40: =AG40 -> 0 | AK40: =AJ40/AI40-1 -> #DIV/0!
B41: Нужно сделать на вчера | D41: =D39/$G$1*$C$1 -> 113971735 | F41: Нужно сделать на вчера | H41: =H39/$G$1*$C$1 -> 110544589 | K41: Плато продаж | L41: =L35/$C$1 -> 17381378 | M41: =M35/$C$1 -> 3569281 | N41: =N35/$C$1 -> 2603724.9 | O41: =O35/$C$1 -> 6435333.2 | P41: =P35/$C$1 -> 4453399.6 | Q41: =Q35/$C$1 -> 117409.61 | R41: =R35/$C$1 -> 89397.677 | S41: =S35/$C$1 -> 11466 | ... AA41: =AA35/$C$1 -> 0 | AD41: Смарт–Сэйл | AE41: =AM12 -> 847522 | AF41: 0 | AG41: =AF41/AE41 -> 0 | AH41: =AE41/(AE41+AE42) -> 0.0016254432 | AI41: 0 | AJ41: =AG41 -> 0 | AK41: =AJ41/AI41-1 -> #DIV/0!
B42: Нужно делать в день | D42: =(D39-D34)/($G$1-$C$1) -> #DIV/0! | F42: Нужно делать в день | H42: =(H39-H34)/($G$1-$C$1) -> #DIV/0! | K42: Прошлый месяц | L42: =SUM(M42:V42) -> 4.1724871e+08 | M42: ='Декабрь 25'!M35 -> 96599698 | N42: ='Декабрь 25'!N35 -> 86342890 | O42: ='Декабрь 25'!O35 -> 113971735 | P42: ='Декабрь 25'!P35 -> 110544589 | Q42: ='Декабрь 25'!Q35 -> 3741104 | R42: ='Декабрь 25'!R35 -> 3478652 | S42: ='Декабрь 25'!S35 -> 341575 | T42: ='Декабрь 25'!T35 -> 1332348 | ... X42: ='Декабрь 25'!X35 -> 36021.18 | Y42: 1 | Z42: 0 | AA42: 0 | AE42: =SUM(AE32:AE41) -> 5.2056228e+08 | AF42: =SUM(AF32:AF41) -> 33655407 | AG42: =AF42/AE42 -> 0.064652028 | AH42: =AE42/(AE42+AE43) -> 1 | AI42: =F142 -> 0.10613092 | AJ42: =AG42 -> 0.064652028 | AK42: =AJ42/AI42-1 -> -0.39082757
B43: Дельта от плана | D43: =D34-D41 -> 85523593 | F43: Дельта от плана | H43: =H34-H41 -> 27510798
B44: Прогноз по выручке | D44: =D34/$C$1*$G$1 -> 199495328 | F44: Прогноз по выручке | H44: =H34/$C$1*$G$1 -> 138055387 | K44: Рекламный расход , руб | L44: =SUM(M44:X44) -> 40940835 | M44: =C15 -> 15193291 | N44: =G15 -> 9554433 | O44: =C33 -> 9570016.4 | P44: =G33 -> 5679471.7 | Q44: =C72 -> 461196 | R44: =G72 -> 482427 | S44: =C88 | T44: =G88 | U44: 0 | V44: 0 | W44: 0 | X44: 0 | Y44: 0 | Z44: 0 | AA44: 0 | AC44: Рубли + Бонусы | AE44: реальная выручка | AF44: реклама | AG44: ДРР | AI44: ДРР план | AJ44: ДРР факт | AK44: дельта
B45: Прогноз по выручке (%) | D45: =D44/D39 -> 1.750393 | F45: Прогноз по выручке (%) | H45: =H44/H39 -> 1.2488661 | K45: ДРР , % | L45: =L44/L35 -> 0.075982015 | M45: =IFERROR(M44/M35, " ") -> 0.13731229 | N45: =IFERROR(N44/N35, " ") -> 0.11837177 | O45: =IFERROR(O44/O35, " ") -> 0.04797113 | P45: =IFERROR(P44/P35, " ") -> 0.041139081 | Q45: =IFERROR(Q44/Q35, " ") -> 0.12671271 | R45: =IFERROR(R44/R35, " ") -> 0.17407791 | S45: =IFERROR(S44/S35, " ") -> 0 | T45: =IFERROR(T44/T35, " ") -> 0 | ... AA45: =IFERROR(AA44/AA35, " ") | AC45: WB | AD45: Биг–Л | AE45: =AE32 -> 198719614 | AF45: =C33 -> 9570016.4 | AG45: =AF45/AE45 -> 0.048158389 | AI45: =AI32 -> 0.07 | AJ45: =AG45 -> 0.048158389 | AK45: =AJ45/AI45-1 -> -0.31202302
AD46: Смарт–Сэйл | AE46: =AE33 -> 137101317 | AF46: =G33 -> 5679471.7 | AG46: =AF46/AE46 -> 0.041425362 | AI46: =AI33 -> 0.07 | AJ46: =AG46 -> 0.041425362 | AK46: =AJ46/AI46-1 -> -0.40820911
B47: Wildberries / Расход только рубли | K47: Прирост к прошлому месяцу , % | L47: =L40/L42-1 -> 0.29137057 | M47: =M40/M42-1 -> 0.14542502 | N47: =N40/N42-1 -> -0.065175222 | O47: =O40/O42-1 -> 0.75039301 | P47: =P40/P42-1 -> 0.24886608 | Q47: =Q40/Q42-1 -> -0.027105902 | R47: =R40/R42-1 -> -0.20333279 | S47: =S40/S42-1 -> 0.040608944 | ... AA47: =AA40/AA42-1 -> #DIV/0! | AC47: Ozon | AD47: Биг–Л | AE47: =AE34 -> 101356193 | AF47: =AF34 -> 15193291 | AG47: =AF47/AE47 -> 0.14989998 | AI47: =AI34 -> 0.205 | AJ47: =AG47 -> 0.14989998 | AK47: =AJ47/AI47-1 -> -0.2687806
B48: =B30 -> Биг–Л / Январь | до | D48: =$D$4 -> 46053 | F48: =F30 -> Смарт/ Январь| до | H48: =$D$4 -> 46053 | K48: Прирост по направлениям , % | M48: =SUM(M40:N40)/SUM(M42:N42)-1 -> 0.046028626 | O48: =SUM(O40:P40)/SUM(O42:P42)-1 -> 0.50345734 | Q48: =SUM(Q40:R40)/SUM(Q42:R42)-1 -> -0.11201625 | S48: =SUM(S40:T40)/SUM(S42:T42)-1 -> 0.10013364 | U48: =SUM(U40:V40)/SUM(U42:V42)-1 -> 0.72789754 | W48: =SUM(W40:X40)/SUM(W42:X42)-1 -> 0.74428273 | Y48: =SUM(Y40:AA40)/SUM(Y42:AA42)-1 -> 36780 | AD48: Смарт–Сэйл | AE48: =AE35 -> 74707614 | AF48: =AF35 -> 9554433 | AG48: =AF48/AE48 -> 0.12789102 | AI48: =AI35 -> 0.115 | AJ48: =AG48 -> 0.12789102 | AK48: =AJ48/AI48-1 -> 0.11209583
A49: =IFERROR(C49/$C$33, " ") -> 0.47780106 | B49: Затраты из РК | C49: 4572564 | F49: Затраты из РК | G49: 3391496 | I49: =IFERROR(G49/$G$33, " ") -> 0.59714991 | K49: Прирост к прошлому месяцу , руб | L49: =L40-L42 -> 121573996 | M49: =M40-M42 -> 14048013 | N49: =N40-N42 -> -5627417 | O49: =O40-O42 -> 85523593 | P49: =P40-P42 -> 27510798 | Q49: =Q40-Q42 -> -101406 | R49: =R40-R42 -> -707324 | S49: =S40-S42 -> 13871 | ... AA49: =AA40-AA42 -> 0 | AC49: ЯМаркет | AD49: Биг–Л | AE49: =AE36 -> 3150063.3 | AF49: =AF36 -> 461196 | AG49: =AF49/AE49 -> 0.14640848 | AI49: =AI36 -> 0.18 | AJ49: =AG49 -> 0.14640848 | AK49: =AJ49/AI49-1 -> -0.18661953
A50: =IFERROR(C50/$C$33, " ") -> 0 | B50: Отзывы за баллы? | F50: Отзывы за баллы? | I50: =IFERROR(G50/$G$33, " ") -> 0 | K50: Прирост по направлениям , руб | M50: =SUM(M40:N40)-SUM(M42:N42) -> 8420596 | O50: =SUM(O40:P40)-SUM(O42:P42) -> 113034391 | Q50: =SUM(Q40:R40)-SUM(Q42:R42) -> -808730 | S50: =SUM(S40:T40)-SUM(S42:T42) -> 167616 | U50: =SUM(U40:V40)-SUM(U42:V42) -> 652285 | W50: =SUM(W40:X40)-SUM(W42:X42) -> 30319.92 | Y50: =SUM(Y40:AA40)-SUM(Y42:AA42) -> 36780 | AD50: Смарт–Сэйл | AE50: =AE37 -> 2508567.8 | AF50: =AF37 -> 482427 | AG50: =AF50/AE50 -> 0.19231173 | AI50: =AI37 -> 0.175 | AJ50: =AG50 -> 0.19231173 | AK50: =AJ50/AI50-1 -> 0.09892416
B51: Итого расходов | C51: =SUM(C49:C50) -> 4572564 | F51: Итого расходов | G51: =SUM(G49:G50) -> 3391496 | AC51: Летуаль | AD51: Биг–Л | AE51: =AE38 -> 355446 | AF51: =AF38 -> 0 | AG51: =AF51/AE51 -> 0 | AI51: =AI38 -> 0.15 | AJ51: =AG51 -> 0 | AK51: =AJ51/AI51-1 -> -1
B52: Выручка | D52: =O35 -> 199495328 | F52: Выручка | H52: =P35 -> 138055387 | K52: хотим | L52: 750000000 | M52: =$L$52*M36 -> 1.5401315e+08 | N52: =$L$52*N36 -> 1.1234976e+08 | O52: =$L$52*O36 -> 2.7768224e+08 | P52: =$L$52*P36 -> 1.9216254e+08 | Q52: =$L$52*Q36 -> 5066181.2 | R52: =$L$52*R36 -> 3857476.6 | S52: =$L$52*S36 -> 494753.65 | T52: =$L$52*T36 -> 2068527.8 | ... AA52: =$L$52*AA36 -> 0 | AD52: Смарт–Сэйл | AE52: =AE39 -> 1476980 | AF52: =AF39 -> 0 | AG52: =AF52/AE52 -> 0 | AI52: =AI39 -> 0.15 | AJ52: =AG52 -> 0 | AK52: =AJ52/AI52-1 -> -1
B53: ДРР / Факт | D53: =C51/D52 -> 0.022920657 | F53: ДРР / Факт | H53: =G51/H52 -> 0.024566198 | K53: осталось сделать | L53: =L52-L35 -> 2.1117729e+08 | M53: =M52-M35 -> 43365440 | N53: =N52-N35 -> 31634292 | O53: =O52-O35 -> 78186911 | P53: =P52-P35 -> 54107153 | Q53: =Q52-Q35 -> 1426483.2 | R53: =R52-R35 -> 1086148.6 | S53: =S52-S35 -> 139307.65 | ... AA53: =AA52-AA35 -> 0 | AC53: Золотое Яблоко | AD53: Биг–Л | AE53: =AE40 -> 338963 | AF53: =AF40 -> 0 | AG53: =AF53/AE53 -> 0 | AI53: =AI40 -> 0 | AJ53: =AG53 -> 0 | AK53: =AJ53/AI53-1 -> #DIV/0!
A54: =D53/C54 -> 0.32743796 | B54: ДРР / План | C54: 0.07 | D54: =D52*C54 -> 13964673 | F54: ДРР / План | G54: 0.07 | H54: =H52*G54 -> 9663877.1 | I54: =H53/G54 -> 0.35094569 | K54: нужно плато продаж | L54: =SUM(M54:V54) -> #DIV/0! | M54: =M53/($G$1-$C$1) -> #DIV/0! | N54: =N53/($G$1-$C$1) -> #DIV/0! | O54: =O53/($G$1-$C$1) -> #DIV/0! | P54: =P53/($G$1-$C$1) -> #DIV/0! | Q54: =Q53/($G$1-$C$1) -> #DIV/0! | R54: =R53/($G$1-$C$1) -> #DIV/0! | S54: =S53/($G$1-$C$1) -> #DIV/0! | T54: =T53/($G$1-$C$1) -> #DIV/0! | ... AA54: =AA53/($G$1-$C$1) -> #DIV/0! | AD54: Смарт–Сэйл | AE54: =AE41 -> 847522 | AF54: =AF41 -> 0 | AG54: =AF54/AE54 -> 0 | AI54: =AI41 -> 0 | AJ54: =AG54 -> 0 | AK54: =AJ54/AI54-1 -> #DIV/0!
B55: Перераход в деньгах | D55: =C51-D54 -> -9392109 | F55: Перераход в деньгах | H55: =G51-H54 -> -6272381.1 | AE55: =SUM(AE45:AE54) -> 5.2056228e+08 | AF55: =SUM(AF45:AF54) -> 40940835 | AG55: =AF55/AE55 -> 0.078647333 | AI55: =AI42 -> 0.10613092 | AJ55: =AG55 -> 0.078647333 | AK55: =AJ55/AI55-1 -> -0.25895926
N56: 210000000 | R56: =SUM(Q44:R44)/SUM(Q40:R40) -> 0.14718752
B57: План | D57: =O42 -> 113971735 | F57: План | H57: =P42 -> 110544589 | N57: =N56-SUM(M35:N35) -> 18636816 | AE57: реальный план | AF57: реальная выручка | AG57: дельта | AI57: ДРР план | AJ57: ДРР факт | AK57: дельта
B58: Плато продаж | D58: =D52/$C$1 -> 6435333.2 | F58: Плато продаж | H58: =H52/$C$1 -> 4453399.6 | M58: =M35/SUM(M35:N35) -> 0.57820793 | N58: =N35/SUM(M35:N35) -> 0.42179207 | AC58: WB | AD58: Биг–Л | AE58: =AG3 -> 113971735 | AF58: =AM3 -> 198719614 | AG58: =IFERROR(AF58/AE58, " ") -> 1.7435868 | AI58: =AI45 -> 0.07 | AJ58: =AJ45 -> 0.048158389 | AK58: =AJ58/AI58-1 -> -0.31202302
B59: Нужно сделать на вчера | D59: =D57/$G$1*$C$1 -> 113971735 | F59: Нужно сделать на вчера | H59: =H57/$G$1*$C$1 -> 110544589 | M59: =N57*M58 -> 10775955 | N59: =N57*N58 -> 7860861.3 | AD59: Смарт–Сэйл | AE59: =AG4 -> 110544589 | AF59: =AM4 -> 137101317 | AG59: =IFERROR(AF59/AE59, " ") -> 1.2402354 | AI59: =AI46 -> 0.07 | AJ59: =AJ46 -> 0.041425362 | AK59: =AJ59/AI59-1 -> -0.40820911
B60: Нужно делать в день | D60: =(D57-D52)/($G$1-$C$1) -> #DIV/0! | F60: Нужно делать в день | H60: =(H57-H52)/($G$1-$C$1) -> #DIV/0! | L60: =SUM(M60:N60) -> #DIV/0! | M60: =M59/(G1-C1) -> #DIV/0! | N60: =N59/(G1-C1) -> #DIV/0! | AC60: Ozon | AD60: Биг–Л | AE60: =AG5 -> 96599698 | AF60: =AM5 -> 101356193 | AG60: =IFERROR(AF60/AE60, " ") -> 1.0492392 | AI60: =AI47 -> 0.205 | AJ60: =AJ47 -> 0.14989998 | AK60: =AJ60/AI60-1 -> -0.2687806
B61: Дельта от плана | D61: =D52-D59 -> 85523593 | F61: Дельта от плана | H61: =H52-H59 -> 27510798 | AD61: Смарт–Сэйл | AE61: =AG6 -> 86342890 | AF61: =AM6 -> 74707614 | AG61: =IFERROR(AF61/AE61, " ") -> 0.86524339 | AI61: =AI48 -> 0.115 | AJ61: =AJ48 -> 0.12789102 | AK61: =AJ61/AI61-1 -> 0.11209583
B62: Прогноз по выручке | D62: =D52/$C$1*$G$1 -> 199495328 | F62: Прогноз по выручке | H62: =H52/$C$1*$G$1 -> 138055387 | M62: =M58 -> 0.57820793 | N62: =N58 -> 0.42179207 | AC62: ЯМаркет | AD62: Биг–Л | AE62: =AG7 -> 3741104 | AF62: =AM7 -> 3150063.3 | AG62: =IFERROR(AF62/AE62, " ") -> 0.84201437 | AI62: =AI49 -> 0.18 | AJ62: =AJ49 -> 0.14640848 | AK62: =AJ62/AI62-1 -> -0.18661953
B63: Прогноз по выручке (%) | D63: =D62/D57 -> 1.750393 | F63: Прогноз по выручке (%) | H63: =H62/H57 -> 1.2488661 | M63: =$N$56*M62 -> 1.2142367e+08 | N63: =$N$56*N62 -> 88576334 | AD63: Смарт–Сэйл | AE63: =AG8 -> 3478652 | AF63: =AM8 -> 2508567.8 | AG63: =IFERROR(AF63/AE63, " ") -> 0.72113214 | AI63: =AI50 -> 0.175 | AJ63: =AJ50 -> 0.19231173 | AK63: =AJ63/AI63-1 -> 0.09892416
AC64: Летуаль | AD64: Биг–Л | AE64: =AG9 -> 341575 | AF64: =AM9 -> 355446 | AG64: =IFERROR(AF64/AE64, " ") -> 1.0406089 | AI64: =AI51 -> 0.15 | AJ64: =AJ51 -> 0 | AK64: =AJ64/AI64-1 -> -1
B65: ЯМаркет | L65: =G1-C1 -> 0 | M65: =(M63-M35)/$L$65 -> #DIV/0! | N65: =(N63-N35)/$L$65 -> #DIV/0! | AD65: Смарт–Сэйл | AE65: =AG10 -> 1332348 | AF65: =AM10 -> 1476980 | AG65: =IFERROR(AF65/AE65, " ") -> 1.1085542 | AI65: =AI52 -> 0.15 | AJ65: =AJ52 -> 0 | AK65: =AJ65/AI65-1 -> -1
B66: =B30 -> Биг–Л / Январь | до | D66: =$D$4 -> 46053 | F66: =F30 -> Смарт/ Январь| до | H66: =$D$4 -> 46053 | AC66: Золотое Яблоко | AD66: Биг–Л | AE66: =AG11 -> 108947 | AF66: =AM11 -> 338963 | AG66: =IFERROR(AF66/AE66, " ") -> 3.1112651 | AI66: =AI53 -> 0 | AJ66: =AJ53 -> 0 | AK66: =AJ66/AI66-1 -> #DIV/0!
A67: =IFERROR(C67/$C$72, " ") -> 0.9033643 | B67: Буст продаж | C67: 416628 | F67: Буст продаж | G67: 410047 | I67: =IFERROR(G67/$G$72, " ") -> 0.84996694 | N67: 450000000 | AD67: Смарт–Сэйл | AE67: =AG12 -> 787175 | AF67: =AM12 -> 847522 | AG67: =IFERROR(AF67/AE67, " ") -> 1.0766627 | AI67: =AI54 -> 0 | AJ67: =AJ54 -> 0 | AK67: =AJ67/AI67-1 -> #DIV/0!
A68: =IFERROR(C68/$C$72, " ") -> 0.096635704 | B68: Буст показов | C68: 44568 | F68: Буст показов | G68: 72380 | I68: =IFERROR(G68/$G$72, " ") -> 0.15003306 | M68: =M35/SUM($M$35:$N$35) -> 0.57820793 | N68: =N35/SUM($M$35:$N$35) -> 0.42179207 | AE68: =AG13 -> 4.1724871e+08 | AF68: =AM13 -> 5.2056228e+08 | AG68: =IFERROR(AF68/AE68, " ") -> 1.2476067 | AI68: =AI55 -> 0.10613092 | AJ68: =AJ55 -> 0.078647333 | AK68: =AJ68/AI68-1 -> -0.25895926
A69: =IFERROR(C69/$C$72, " ") -> 0 | B69: Полки | F69: Полки | I69: =IFERROR(G69/$G$72, " ") -> 0 | M69: =$N$67*M68 -> 2.6019357e+08 | N69: =$N$67*N68 -> 1.8980643e+08
A70: =IFERROR(C70/$C$72, " ") -> 0 | B70: Охватное продвижение | F70: Охватное продвижение | I70: =IFERROR(G70/$G$72, " ") -> 0 | L70: 30 | M70: =M69/$L$70 -> 8673119 | N70: =N69/$L$70 -> 6326881 | AE70: Декабрь | AF70: Январь | AK70: =AE70 -> Декабрь | AL70: =AF70 -> Январь
A71: =IFERROR(C71/$C$72, " ") -> 0 | B71: Баннеры | F71: Баннеры | I71: =IFERROR(G71/$G$72, " ") -> 0 | AE71: реальная выручка | AF71: реальная выручка | AG71: дельта | AI71: Рубли + Бонусы | AK71: ДРР факт | AL71: ДРР факт | AM71: дельта
B72: Итого расходов | C72: =SUM(C67:C71) -> 461196 | F72: Итого расходов | G72: =SUM(G67:G71) -> 482427 | AC72: WB | AD72: Биг–Л | AE72: ='Декабрь 25'!AC80 -> 113706034 | AF72: =AF58 -> 198719614 | AG72: =AF72/AE72-1 -> 0.74766111 | AI72: WB | AJ72: Биг–Л | AK72: ='Декабрь 25'!AI80 -> 0.046196278 | AL72: =AJ45 -> 0.048158389 | AM72: =AL72/AK72-1 -> 0.04247334
B73: Выручка | D73: =Q35 -> 3639698 | F73: Выручка | H73: =R35 -> 2771328 | AD73: Смарт–Сэйл | AE73: ='Декабрь 25'!AC81 -> 109193402 | AF73: =AF59 -> 137101317 | AG73: =AF73/AE73-1 -> 0.25558243 | AJ73: Смарт–Сэйл | AK73: ='Декабрь 25'!AI81 -> 0.046543169 | AL73: =AJ46 -> 0.041425362 | AM73: =AL73/AK73-1 -> -0.10995829
B74: ДРР / Факт | D74: =C72/D73 -> 0.12671271 | F74: ДРР / Факт | H74: =G72/H73 -> 0.17407791 | AC74: Ozon | AD74: Биг–Л | AE74: ='Декабрь 25'!AC82 -> 87879383 | AF74: =AF60 -> 101356193 | AG74: =AF74/AE74-1 -> 0.15335577 | AI74: Ozon | AJ74: Биг–Л | AK74: ='Декабрь 25'!AI82 -> 0.14585267 | AL74: =AJ47 -> 0.14989998 | AM74: =AL74/AK74-1 -> 0.02774925
A75: =D74/C75 -> 0.7039595 | B75: ДРР / План | C75: 0.18 | D75: =D73*C75 -> 655145.64 | F75: ДРР / План | G75: 0.175 | H75: =H73*G75 -> 484982.4 | I75: =H74/G75 -> 0.99473094 | AD75: Смарт–Сэйл | AE75: ='Декабрь 25'!AC83 -> 79878694 | AF75: =AF61 -> 74707614 | AG75: =AF75/AE75-1 -> -0.064736663 | AJ75: Смарт–Сэйл | AK75: ='Декабрь 25'!AI83 -> 0.1371911 | AL75: =AJ48 -> 0.12789102 | AM75: =AL75/AK75-1 -> -0.067789241
B76: Перераход в деньгах | D76: =C72-D75 -> -193949.64 | F76: Перераход в деньгах | H76: =G72-H75 -> -2555.4 | AC76: ЯМаркет | AD76: Биг–Л | AE76: ='Декабрь 25'!AC84 -> 3359015.8 | AF76: =AF62 -> 3150063.3 | AG76: =AF76/AE76-1 -> -0.062206462 | AI76: ЯМаркет | AJ76: Биг–Л | AK76: ='Декабрь 25'!AI84 -> 0.17943113 | AL76: =AJ49 -> 0.14640848 | AM76: =AL76/AK76-1 -> -0.18404077
AD77: Смарт–Сэйл | AE77: ='Декабрь 25'!AC85 -> 3190903.3 | AF77: =AF63 -> 2508567.8 | AG77: =AF77/AE77-1 -> -0.21383775 | AJ77: Смарт–Сэйл | AK77: ='Декабрь 25'!AI85 -> 0.20999132 | AL77: =AJ50 -> 0.19231173 | AM77: =AL77/AK77-1 -> -0.084192008
B78: План | D78: =Q42 -> 3741104 | F78: План | H78: =R42 -> 3478652 | AC78: Летуаль | AD78: Биг–Л | AE78: ='Декабрь 25'!AC86 -> 328073 | AF78: =AF64 -> 355446 | AG78: =AF78/AE78-1 -> 0.083435699 | AI78: Летуаль | AJ78: Биг–Л | AK78: ='Декабрь 25'!AI86 -> 0 | AL78: =AJ51 -> 0 | AM78: =AL78/AK78-1 -> #DIV/0!
B79: Плато продаж | D79: =D73/$C$1 -> 117409.61 | F79: Плато продаж | H79: =H73/$C$1 -> 89397.677 | AD79: Смарт–Сэйл | AE79: ='Декабрь 25'!AC87 -> 1282517 | AF79: =AF65 -> 1476980 | AG79: =AF79/AE79-1 -> 0.15162606 | AJ79: Смарт–Сэйл | AK79: ='Декабрь 25'!AI87 -> 0 | AL79: =AJ52 -> 0 | AM79: =AL79/AK79-1 -> #DIV/0!
B80: Нужно сделать на вчера | D80: =D78/$G$1*$C$1 -> 3741104 | F80: Нужно сделать на вчера | H80: =H78/$G$1*$C$1 -> 3478652 | AC80: Золотое Яблоко | AD80: Биг–Л | AE80: ='Декабрь 25'!AC88 -> 74449 | AF80: =AF66 -> 338963 | AG80: =AF80/AE80-1 -> 3.5529557 | AI80: Золотое Яблоко | AJ80: Биг–Л | AK80: ='Декабрь 25'!AI88 -> 0 | AL80: =AJ53 -> 0 | AM80: =AL80/AK80-1 -> #DIV/0!
B81: Нужно делать в день | D81: =(D78-D73)/($G$1-$C$1) -> #DIV/0! | F81: Нужно делать в день | H81: =(H78-H73)/($G$1-$C$1) -> #DIV/0! | AD81: Смарт–Сэйл | AE81: ='Декабрь 25'!AC89 -> 710399 | AF81: =AF67 -> 847522 | AG81: =AF81/AE81-1 -> 0.19302251 | AJ81: Смарт–Сэйл | AK81: ='Декабрь 25'!AI89 -> 0 | AL81: =AJ54 -> 0 | AM81: =AL81/AK81-1 -> #DIV/0!
B82: Разница от плана | D82: =D73-D80 -> -101406 | F82: Разница от плана | H82: =H73-H80 -> -707324 | AE82: =SUM(AE72:AE81) -> 399602870 | AF82: =SUM(AF72:AF81) -> 5.2056228e+08 | AG82: =AF82/AE82-1 -> 0.30269905 | AK82: ='Декабрь 25'!AH92 -> 0.086934403 | AL82: =AJ68 -> 0.078647333 | AM82: =AL82/AK82-1 -> -0.095325552
B83: Прогноз по выручке | D83: =D73/$C$1*$G$1 -> 3639698 | F83: Прогноз по выручке | H83: =H73/$C$1*$G$1 -> 2771328 | AG83: =AF82-AE82 -> 1.2095941e+08
B84: Прогноз по выручке (%) | D84: =D83/D78 -> 0.9728941 | F84: Прогноз по выручке (%) | H84: =H83/H78 -> 0.79666721
B86: Летуаль
B87: =B66 -> Биг–Л / Январь | до | D87: =$D$4 -> 46053 | F87: =F66 -> Смарт/ Январь| до | H87: =$D$4 -> 46053
B88: Реклама | D88: 23945.9 | F88: Реклама | H88: 63087.19
B89: Выручка | D89: =S35 -> 355446 | F89: Выручка | H89: =T35 -> 1486093
B90: ДРР / Факт | D90: =D88/D89 -> 0.067368602 | F90: ДРР / Факт | H90: =H88/H89 -> 0.042451711
B91: ДРР / План | C91: 0.15 | D91: =D89*C91 -> 53316.9 | F91: ДРР / План | G91: 0.15 | H91: =H89*G91 -> 222913.95
B92: Перераход в деньгах | D92: =C88-D91 -> -53316.9 | F92: Перераход в деньгах | H92: =G88-H91 -> -222913.95
B94: План | D94: =S42 -> 341575 | F94: План | H94: =T42 -> 1332348
B95: Плато продаж | D95: =D89/$C$1 -> 11466 | F95: Плато продаж | H95: =H89/$C$1 -> 47938.484
B96: Нужно сделать на вчера | D96: =D94/$G$1*$C$1 -> 341575 | F96: Нужно сделать на вчера | H96: =H94/$G$1*$C$1 -> 1332348
B97: Нужно делать в день | D97: =(D94-D89)/($G$1-$C$1) -> #DIV/0! | F97: Нужно делать в день | H97: =(H94-H89)/($G$1-$C$1) -> #DIV/0!
B98: Разница от плана | D98: =D89-D96 -> 13871 | F98: Разница от плана | H98: =H89-H96 -> 153745
B99: Прогноз по выручке | D99: =D89/$C$1*$G$1 -> 355446 | F99: Прогноз по выручке | H99: =H89/$C$1*$G$1 -> 1486093
B100: Прогноз по выручке (%) | D100: =D99/D94 -> 1.0406089 | F100: Прогноз по выручке (%) | H100: =H99/H94 -> 1.115394
B102: Магнит
B103: =B82 -> Разница от плана | D103: =$D$4 -> 46053 | F103: =F82 -> Разница от плана | H103: =$D$4 -> 46053
...

Sheet Декабрь 25
A1: 3 | B1: Вчера | C1: 31 | F1: Дней в месяце | G1: 31
A2: Актуально на | B2: 46022 | M2: Оз | O2: Вб | Q2: Ям | S2: Лету | U2: ЗЯ | W2: Магнит Маркет | AB2: план | AC2: ауты | AD2: реальный план | AF2: выручка | AG2: отказы/возвраты | AH2: раздачи | AI2: выкупы | AJ2: реальная выручка
B3: Ozon | M3: Биг–Л | N3: Смарт | O3: Биг–Л | P3: Смарт | Q3: Биг–Л | R3: Смарт | S3: Биг–Л | T3: Смарт | U3: Биг–Л | V3: Смарт | W3: Биг–Л | X3: Смарт | Z3: WB | AA3: Биг–Л | AB3: =D39 -> 103370590 | AD3: =AB3-AC3 -> 103370590 | AF3: =O35 -> 113971735 | AH3: =1800+263901 -> 265701 | AJ3: =AF3-SUM(AG3:AI3) -> 113706034
B4: Биг–Л / Ноябрь | до | D4: =TODAY()-1 -> 46107 | F4: Смарт / Декабрь| до | H4: =$D$4 -> 46107 | K4: 45992 | L4: =SUM(M4:X4) -> 12621391 | M4: 2348963 | N4: 2898929.1 | O4: 3616967 | P4: 3509563 | Q4: 65103 | R4: 91393 | S4: 17685 | T4: 60837 | V4: 11951 | W4: 0 | X4: 0 | AA4: Смарт–Сэйл | AB4: =H39 -> 124247057 | AD4: =AB4-AC4 -> 124247057 | AF4: =P35 -> 110544589 | AH4: =28907+1322280 -> 1351187 | AJ4: =AF4-SUM(AG4:AI4) -> 109193402
A5: =IFERROR(C5/$C$15, " ") -> 0.9209805 | B5: Оплата за клик | C5: 11804615 | F5: Оплата за клик | G5: 10022821 | H5: 368630 | I5: =IFERROR(G5/$G$15, " ") -> 0.91460396 | K5: 45993 | L5: =SUM(M5:X5) -> 12055242 | M5: 2720347 | N5: 2750788 | O5: 3361085 | P5: 2870498 | Q5: 114964 | R5: 140722 | S5: 19993 | T5: 69540 | V5: 6491 | W5: 0 | X5: 814.4 | Z5: Ozon | AA5: Биг–Л | AB5: =D21 -> 68328978 | AD5: =AB5-AC5 -> 68328978 | AF5: =M35 -> 96599698 | AG5: =AF5/79355*(6496+66) -> 7987993.4 | AH5: =17128+715194 -> 732322 | AJ5: =AF5-SUM(AG5:AI5) -> 87879383
A6: =IFERROR(C6/$C$15, " ") -> 0.052100485 | B6: Оплата за заказ | C6: 667795 | F6: Оплата за заказ | G6: 555930 | H6: 3064 | I6: =IFERROR(G6/$G$15, " ") -> 0.050729807 | K6: 45994 | L6: =SUM(M6:X6) -> 14114630 | M6: 3028089 | N6: 3048715.1 | O6: 3986511 | P6: 3745955 | Q6: 90370 | R6: 152662 | S6: 9962 | T6: 41817 | V6: 10549 | W6: 0 | X6: 0 | AA6: Смарт–Сэйл | AB6: =H21 -> 73964393 | AD6: =AB6-AC6 -> 73964393 | AF6: =N35 -> 86342890 | AG6: =AF6/85340*(5785+94) -> 5948088.2 | AH6: =516107 -> 516107 | AJ6: =AF6-SUM(AG6:AI6) -> 79878694
A7: =IFERROR(C7/$C$15, " ") -> 0.013733004 | B7: Медийка | C7: 176022 | F7: Медийка | G7: 199419 | H7: 9571 | I7: =IFERROR(G7/$G$15, " ") -> 0.018197412 | K7: 45995 | L7: =SUM(M7:X7) -> 13301924 | M7: 2696101 | N7: 3017920.1 | O7: 3627559 | P7: 3646639 | Q7: 111668 | R7: 134129 | S7: 12162 | T7: 40785 | V7: 14146 | W7: 0 | X7: 814.4 | Z7: ЯМаркет | AA7: Биг–Л | AB7: =D78 -> 2491703 | AD7: =AB7-AC7 -> 2491703 | AF7: =Q35 -> 3741104 | AG7: =AF7/4436*354 -> 298546.17 | AH7: 83542 | AJ7: =AF7-SUM(AG7:AI7) -> 3359015.8
A8: =IFERROR(C8/$C$15, " ") -> 0.00033142336 | B8: Баллы за отзывы | C8: 4248 | F8: Баллы за отзывы | G8: 4541 | H8: 504 | I8: =IFERROR(G8/$G$15, " ") -> 0.00041437601 | K8: 45996 | L8: =SUM(M8:X8) -> 13344410 | M8: 3005335 | N8: 2928242 | O8: 3832361 | P8: 3269890 | Q8: 108809 | R8: 130447 | S8: 11076 | T8: 43974 | V8: 14276 | W8: 0 | X8: 0 | AA8: Смарт–Сэйл | AB8: =H78 -> 4455445 | AD8: =AB8-AC8 -> 4455445 | AF8: =R35 -> 3478652 | AG8: =AF8/5096*344 -> 234822.66 | AH8: 52926 | AJ8: =AF8-SUM(AG8:AI8) -> 3190903.3
A9: =IFERROR(C9/$C$15, " ") -> 0.012683965 | B9: Бонусы продавца | C9: 162576 | F9: Бонусы продавца | G9: 163324 | H9: 5649 | I9: =IFERROR(G9/$G$15, " ") -> 0.014903666 | K9: 45997 | L9: =SUM(M9:X9) -> 14034429 | M9: 3192032 | N9: 3059169 | O9: 3592132 | P9: 3862451 | Q9: 122857 | R9: 144391 | S9: 9170 | T9: 37926 | V9: 14301 | W9: 0 | X9: 0 | Z9: Летуаль | AA9: Биг–Л | AB9: =S42 -> 357438 | AD9: =AB9-AC9 -> 357438 | AF9: =S35 -> 341575 | AH9: =1200+12302 -> 13502 | AJ9: =AF9-SUM(AG9:AI9) -> 328073
A10: =IFERROR(C10/$C$15, " ") -> 0 | B10: Рассылки | C10: 0 | F10: Рассылки | G10: 12611 | H10: 0 | I10: =IFERROR(G10/$G$15, " ") -> 0.0011507809 | K10: 45998 | L10: =SUM(M10:X10) -> 15208375 | M10: 3067649 | N10: 3149598.2 | O10: 4283439 | P10: 4303678 | Q10: 132807 | R10: 163980 | S10: 15530 | T10: 67339 | V10: 24355 | W10: 0 | X10: 0 | AA10: Смарт–Сэйл | AB10: =T42 -> 1099783 | AD10: =AB10-AC10 -> 1099783 | AF10: =T35 -> 1332348 | AH10: =49831 -> 49831 | AJ10: =AF10-SUM(AG10:AI10) -> 1282517
A11: =IFERROR(C11/$C$15, " ") -> 0 | B11: Закрепление отзыва | C11: 0 | F11: Закрепление отзыва | H11: 0 | I11: =IFERROR(G11/$G$15, " ") -> 0 | K11: 45999 | L11: =SUM(M11:X11) -> 13657181 | M11: 3122113 | N11: 2979476 | O11: 3936946 | P11: 3228434 | Q11: 152478 | R11: 117561 | S11: 12620 | T11: 80627 | V11: 26112 | W11: 0 | X11: 814.4 | Z11: Золотое Яблоко | AA11: Биг–Л | AB11: =U42 -> 0 | AD11: =AB11-AC11 -> 0 | AF11: =U35 -> 108947 | AH11: =34498 -> 34498 | AJ11: =AF11-SUM(AG11:AI11) -> 74449
B12: Иные электронные услуги | C12: 0 | F12: Иные электронные услуги | H12: 0 | I12: =IFERROR(G12/$G$15, " ") -> 0 | K12: 46000 | L12: =SUM(M12:X12) -> 13488241 | M12: 2980974 | N12: 3079510.1 | O12: 3805093 | P12: 3318450 | Q12: 123931 | R12: 103883 | S12: 8340 | T12: 34905 | V12: 28886 | W12: 0 | X12: 4268.8 | AA12: Смарт–Сэйл | AB12: =V42 -> 1079042 | AD12: =AB12-AC12 -> 1079042 | AF12: =V35 -> 787175 | AH12: =76776 -> 76776 | AJ12: =AF12-SUM(AG12:AI12) -> 710399
B13: Продвижение бренда | C13: 0 | F13: Продвижение бренда | H13: 0 | I13: =IFERROR(G13/$G$15, " ") -> 0 | K13: 46001 | L13: =SUM(M13:X13) -> 15003459 | M13: 3589572 | N13: 3258993 | O13: 3808180 | P13: 3928646 | Q13: 202549 | R13: 104560 | S13: 5422 | T13: 36893 | U13: 27885 | V13: 40308 | W13: 0 | X13: 451.2 | Z13: Магнит Маркет | AA13: Биг–Л | AB13: =W42 -> 2049 | AD13: =AB13-AC13 -> 2049 | AF13: =W35 -> 4715.92 | AJ13: =AF13-SUM(AG13:AI13) -> 4715.92
B14: Ozon Рассрочка | C14: 2187 | F14: Ozon Рассрочка | K14: 46002 | L14: =SUM(M14:X14) -> 15038525 | M14: 3577493 | N14: 3336345.1 | O14: 3703451 | P14: 4093944 | Q14: 141638 | R14: 98712 | S14: 6067 | T14: 35370 | U14: 6067 | V14: 35370 | W14: 415.36 | X14: 3652.48 | AA14: Смарт–Сэйл | AB14: =X42 -> 17685.2 | AD14: =AB14-AC14 -> 17685.2 | AF14: =X35 -> 36021.18 | AJ14: =AF14-SUM(AG14:AI14) -> 36021.18
B15: Итого расходов | C15: =SUM(C5:C14) -> 12817443 | F15: Итого расходов | G15: =SUM(G5:G14) -> 10958646 | H15: =SUM(H5:H14) -> 387418 | K15: 46003 | L15: =SUM(M15:X15) -> 14152621 | M15: 3499214 | N15: 3034905 | O15: 3681772 | P15: 3640624 | Q15: 120204 | R15: 101213 | S15: 5225 | T15: 28826 | U15: 0 | V15: 37015 | W15: 0 | X15: 3623 | AA15: итог | AB15: =SUM(AB3:AB14) -> 3.7941416e+08 | AC15: =SUM(AC3:AC14) -> 0 | AD15: =SUM(AD3:AD14) -> 3.7941416e+08 | AF15: =SUM(AF3:AF14) -> 4.1728945e+08 | AG15: =SUM(AG3:AG14) -> 14469450 | AH15: =SUM(AH3:AH14) -> 3176392 | AI15: =SUM(AI3:AI14) -> 0 | AJ15: =SUM(AJ3:AJ14) -> 3.9964361e+08
B16: Выручка | D16: =M35 -> 96599698 | F16: Выручка | H16: =N35 -> 86342890 | K16: 46004 | L16: =SUM(M16:X16) -> 14346924 | M16: 3618865 | N16: 3180181 | O16: 3452323 | P16: 3708455 | Q16: 150785 | R16: 135876 | S16: 14599 | T16: 46100 | U16: 1998 | V16: 36362 | W16: 0 | X16: 1379.84 | AH16: =AH15/AF15 -> 0.0076119634
B17: ДРР / Факт | D17: =C15/D16 -> 0.13268616 | F17: ДРР / Факт | H17: =G15/H16 -> 0.12692007 | K17: 46005 | L17: =SUM(M17:X17) -> 14285437 | M17: 3762019 | N17: 2994484.1 | O17: 3249906 | P17: 3874535 | Q17: 140620 | R17: 158142 | S17: 8932 | T17: 52471 | U17: 1998 | V17: 41027 | W17: 0 | X17: 1303.04 | AB17: Без вычетов | AF17: С вычетом всего
A18: =D17/C18 -> 0.64724956 | B18: ДРР / План | C18: 0.205 | D18: =D16*C18 -> 19802938 | F18: ДРР / План | G18: 0.115 | H18: =H16*G18 -> 9929432.3 | I18: =H17/G18 -> 1.1036528 | K18: 46006 | L18: =SUM(M18:X18) -> 14399032 | M18: 4091505 | N18: 2903381 | O18: 3456522 | P18: 3585919 | Q18: 157226 | R18: 134159 | S18: 8560 | T18: 37394 | U18: 0 | V18: 22610 | W18: 0 | X18: 1756.16 | AB18: план | AC18: выручка | AD18: дельта | AF18: реальный план | AG18: реальная выручка | AH18: дельта
B19: Перерасход в деньгах | D19: =C15-D18 -> -6985495.1 | F19: Перераход в деньгах | H19: =G15-H18 -> 1029213.7 | K19: 46007 | L19: =SUM(M19:X19) -> 13611196 | M19: 3648925 | N19: 2729347.7 | O19: 3344262 | P19: 3518564 | Q19: 138344 | R19: 153189 | S19: 17038 | T19: 32675 | U19: 0 | V19: 24919 | W19: 1218.56 | X19: 2714.24 | Z19: WB | AA19: Биг–Л | AB19: =AB3 -> 103370590 | AC19: =AF3 -> 113971735 | AD19: =IFERROR(AC19/AB19, " ") -> 1.1025547 | AF19: =AD3 -> 103370590 | AG19: =AJ3 -> 113706034 | AH19: =IFERROR(AG19/AF19, " ") -> 1.0999844
K20: 46008 | L20: =SUM(M20:X20) -> 13513728 | M20: 3735610 | N20: 2813146.1 | O20: 3353286 | P20: 3215322 | Q20: 148528 | R20: 153189 | S20: 17501 | T20: 46671 | U20: 5686 | V20: 23463 | W20: 0 | X20: 1326.1 | AA20: Смарт–Сэйл | AB20: =AB4 -> 124247057 | AC20: =AF4 -> 110544589 | AD20: =IFERROR(AC20/AB20, " ") -> 0.88971596 | AF20: =AD4 -> 124247057 | AG20: =AJ4 -> 109193402 | AH20: =IFERROR(AG20/AF20, " ") -> 0.87884095
B21: План | D21: =M42 -> 68328978 | F21: План | H21: =N42 -> 73964393 | K21: 46009 | L21: =SUM(M21:X21) -> 14152201 | M21: 3308389 | N21: 2648887 | O21: 3972611 | P21: 3870388 | Q21: 137088 | R21: 132065 | S21: 16276 | T21: 35302 | U21: 5162 | V21: 25230 | W21: 0 | X21: 803.12 | Z21: Ozon | AA21: Биг–Л | AB21: =AB5 -> 68328978 | AC21: =AF5 -> 96599698 | AD21: =IFERROR(AC21/AB21, " ") -> 1.4137442 | AF21: =AD5 -> 68328978 | AG21: =AJ5 -> 87879383 | AH21: =IFERROR(AG21/AF21, " ") -> 1.2861217
B22: Плато продаж | D22: =D16/$C$1 -> 3116119.3 | F22: Плато продаж | H22: =H16/$C$1 -> 2785254.5 | K22: 46010 | L22: =SUM(M22:X22) -> 13563759 | M22: 2969237 | N22: 2675429 | O22: 3802489 | P22: 3851382 | Q22: 110874 | R22: 78049 | S22: 6094 | T22: 46344 | U22: 4958 | V22: 18258 | W22: 0 | X22: 645 | AA22: Смарт–Сэйл | AB22: =AB6 -> 73964393 | AC22: =AF6 -> 86342890 | AD22: =IFERROR(AC22/AB22, " ") -> 1.1673575 | AF22: =AD6 -> 73964393 | AG22: =AJ6 -> 79878694 | AH22: =IFERROR(AG22/AF22, " ") -> 1.0799615
B23: Нужно сделать на вчера | D23: =D21/$G$1*$C$1 -> 68328978 | F23: Нужно сделать на вчера | H23: =H21/$G$1*$C$1 -> 73964393 | K23: 46011 | L23: =SUM(M23:X23) -> 13733664 | M23: 2988436 | N23: 2762642 | O23: 3832319 | P23: 3863483 | Q23: 97660 | R23: 128223 | S23: 2726 | T23: 33158 | U23: 3264 | V23: 21753 | W23: 0 | X23: 0 | Z23: ЯМаркет | AA23: Биг–Л | AB23: =AB7 -> 2491703 | AC23: =AF7 -> 3741104 | AD23: =IFERROR(AC23/AB23, " ") -> 1.5014245 | AF23: =AD7 -> 2491703 | AG23: =AJ7 -> 3359015.8 | AH23: =IFERROR(AG23/AF23, " ") -> 1.3480803
B24: Нужно делать в день | D24: =(D21-D16)/($G$1-$C$1) -> #DIV/0! | F24: Нужно делать в день | H24: =(H21-H16)/($G$1-$C$1) -> #DIV/0! | K24: 46012 | L24: =SUM(M24:X24) -> 16475111 | M24: 3857367 | N24: 3236106 | O24: 4236802 | P24: 4828999 | Q24: 109326 | R24: 114189 | S24: 9955 | T24: 56421 | U24: 3184 | V24: 20547 | W24: 1198 | X24: 1017 | AA24: Смарт–Сэйл | AB24: =AB8 -> 4455445 | AC24: =AF8 -> 3478652 | AD24: =IFERROR(AC24/AB24, " ") -> 0.78076421 | AF24: =AD8 -> 4455445 | AG24: =AJ8 -> 3190903.3 | AH24: =IFERROR(AG24/AF24, " ") -> 0.71618061
B25: Дельта от плана | D25: =D16-D23 -> 28270720 | F25: Дельта от плана | H25: =H16-H23 -> 12378497 | K25: 46013 | L25: =SUM(M25:X25) -> 13857822 | M25: 2964641 | N25: 3015680 | O25: 3819899 | P25: 3767995 | Q25: 100314 | R25: 105724 | S25: 8963 | T25: 38684 | U25: 1984 | V25: 32054 | W25: 1884 | X25: 0 | Z25: Летуаль | AA25: Биг–Л | AB25: =AB9 -> 357438 | AC25: =AF9 -> 341575 | AD25: =IFERROR(AC25/AB25, " ") -> 0.95562028 | AF25: =AD9 -> 357438 | AG25: =AJ9 -> 328073 | AH25: =IFERROR(AG25/AF25, " ") -> 0.91784589
B26: Прогноз по выручке | D26: =D16/$C$1*$G$1 -> 96599698 | F26: Прогноз по выручке | H26: =H16/$C$1*$G$1 -> 86342890 | K26: 46014 | L26: =SUM(M26:X26) -> 13768264 | M26: 3162668 | N26: 3085949.5 | O26: 3664429 | P26: 3551603 | Q26: 106788 | R26: 108875 | S26: 0 | T26: 17252 | U26: 4788 | V26: 61900 | W26: 0 | X26: 4012 | AA26: Смарт–Сэйл | AB26: =AB10 -> 1099783 | AC26: =AF10 -> 1332348 | AD26: =IFERROR(AC26/AB26, " ") -> 1.2114644 | AF26: =AD10 -> 1099783 | AG26: =AJ10 -> 1282517 | AH26: =IFERROR(AG26/AF26, " ") -> 1.1661546
B27: Прогноз по выручке (%) | D27: =D26/D21 -> 1.4137442 | F27: Прогноз по выручке (%) | H27: =H26/H21 -> 1.1673575 | K27: 46015 | L27: =SUM(M27:X27) -> 13459046 | M27: 3261774 | N27: 2808628 | O27: 3788683 | P27: 3344398 | Q27: 104260 | R27: 83621 | S27: 536 | T27: 25309 | U27: 2997 | V27: 38840 | W27: 0 | X27: 0 | Z27: Золотое Яблоко | AA27: Биг–Л | AB27: =AB11 -> 0 | AC27: =AF11 -> 108947 | AD27: =IFERROR(AC27/AB27, " ") | AF27: =AD11 -> 0 | AG27: =AJ11 -> 74449 | AH27: =IFERROR(AG27/AF27, " ")
K28: 46016 | L28: =SUM(M28:X28) -> 13897814 | M28: 3356397 | N28: 2499393 | O28: 3937025 | P28: 3837098 | Q28: 86936 | R28: 111506 | S28: 4022 | T28: 30363 | U28: 8443 | V28: 25539 | W28: 0 | X28: 1092 | AA28: Смарт–Сэйл | AB28: =AB12 -> 1079042 | AC28: =AF12 -> 787175 | AD28: =IFERROR(AC28/AB28, " ") -> 0.72951285 | AF28: =AD12 -> 1079042 | AG28: =AJ12 -> 710399 | AH28: =IFERROR(AG28/AF28, " ") -> 0.65836084
B29: Wildberries / Расход бонусы + рубли | K29: 46017 | L29: =SUM(M29:X29) -> 12928102 | M29: 3138019 | N29: 2499858 | O29: 3582823 | P29: 3438266 | Q29: 113536 | R29: 93059 | S29: 10021 | T29: 25383 | U29: 2344 | V29: 23850 | W29: 0 | X29: 943 | Z29: Магнит Маркет | AA29: Биг–Л | AB29: =AB13 -> 2049 | AC29: =AF13 -> 4715.92 | AD29: =IFERROR(AC29/AB29, " ") -> 2.3015715 | AF29: =AD13 -> 2049 | AG29: =AJ13 -> 4715.92 | AH29: =IFERROR(AG29/AF29, " ") -> 2.3015715
B30: =B4 -> Биг–Л / Ноябрь | до | D30: =$D$4 -> 46107 | F30: =F4 -> Смарт / Декабрь| до | H30: =$D$4 -> 46107 | K30: 46018 | L30: =SUM(M30:X30) -> 14052291 | M30: 2864733 | N30: 2481405 | O30: 4405457 | P30: 4018919 | Q30: 108218 | R30: 85275 | S30: 20457 | T30: 32097 | U30: 9338 | V30: 26392 | W30: 0 | X30: 0 | AA30: Смарт–Сэйл | AB30: =AB14 -> 17685.2 | AC30: =AF14 -> 36021.18 | AD30: =IFERROR(AC30/AB30, " ") -> 2.036798 | AF30: =AD14 -> 17685.2 | AG30: =AJ14 -> 36021.18 | AH30: =IFERROR(AG30/AF30, " ") -> 2.036798
A31: =IFERROR(C31/$C$33, " ") -> 0.64489831 | B31: Затраты из РК | C31: 3387519 | F31: Затраты из РК | G31: 5040907 | I31: =IFERROR(G31/$G$33, " ") -> 0.99187361 | K31: 46019 | L31: =SUM(M31:X31) -> 14357885 | M31: 2718725 | N31: 2431864 | O31: 4409921 | P31: 4505970 | Q31: 123133 | R31: 72167 | S31: 17497 | T31: 45329 | U31: 8704 | V31: 24221 | W31: 0 | X31: 354 | AB31: =SUM(AB19:AB30) -> 3.7941416e+08 | AC31: =SUM(AC19:AC30) -> 4.1728945e+08 | AD31: =IFERROR(AC31/AB31, " ") -> 1.0998257 | AF31: =SUM(AF19:AF30) -> 3.7941416e+08 | AG31: =SUM(AG19:AG30) -> 3.9964361e+08 | AH31: =IFERROR(AG31/AF31, " ") -> 1.0533176
A32: =IFERROR(C32/$C$33, " ") -> 0.35510169 | B32: Отзывы за баллы | C32: 1865276.6 | F32: Отзывы за баллы | G32: 41300 | I32: =IFERROR(G32/$G$33, " ") -> 0.0081263908 | K32: 46020 | L32: =SUM(M32:X32) -> 11148926 | M32: 2410845 | N32: 2086957.4 | O32: 3486085 | P32: 2884095 | Q32: 127642 | R32: 58407 | S32: 21734 | T32: 36962 | U32: 8187 | V32: 25628 | W32: 0 | X32: 2384
B33: Итого расходов | C33: =SUM(C31:C32) -> 5252795.6 | F33: Итого расходов | G33: =SUM(G31:G32) -> 5082207 | K33: 46021 | L33: =SUM(M33:X33) -> 9623069 | M33: 2448993 | N33: 1790507 | O33: 2900772 | P33: 2221734 | Q33: 110092 | R33: 51215 | S33: 20297 | T33: 58658 | U33: 1960 | V33: 16988 | W33: 0 | X33: 1853 | Z33: Только рубли | AB33: реальная выручка | AC33: реклама | AD33: ДРР | AF33: ДРР план | AG33: ДРР факт | AH33: дельта
B34: Выручка | D34: =O35 -> 113971735 | F34: Выручка | H34: =P35 -> 110544589 | K34: 46022 | L34: =SUM(M34:X34) -> 6094748 | M34: 1464668 | N34: 1156453 | O34: 2040625 | P34: 1238692 | Q34: 82356 | R34: 38069 | S34: 3115 | T34: 56936 | U34: 0 | V34: 13834 | W34: 0 | X34: 0 | Z34: WB | AA34: Биг–Л | AB34: =AJ3 -> 113706034 | AC34: =C51 -> 2547543 | AD34: =AC34/AB34 -> 0.022404642 | AF34: =C36 -> 0.07 | AG34: =AD34 -> 0.022404642 | AH34: =AG34/AF34-1 -> -0.67993368
B35: ДРР / Факт | D35: =C33/D34 -> 0.046088582 | F35: ДРР / Факт | H35: =G33/H34 -> 0.045974272 | K35: =L35/C1 -> 13460950 | L35: =SUM(L4:L34) -> 4.1728945e+08 | M35: =SUM(M4:M34) -> 96599698 | N35: =SUM(N4:N34) -> 86342890 | O35: =SUM(O4:O34) -> 113971735 | P35: =SUM(P4:P34) -> 110544589 | Q35: =SUM(Q4:Q34) -> 3741104 | R35: =SUM(R4:R34) -> 3478652 | S35: =SUM(S4:S34) -> 341575 | ... X35: =SUM(X4:X34) -> 36021.18 | AA35: Смарт–Сэйл | AB35: =AJ4 -> 109193402 | AC35: =G51 -> 3936644 | AD35: =AC35/AB35 -> 0.036052032 | AF35: =G36 -> 0.07 | AG35: =AD35 -> 0.036052032 | AH35: =AG35/AF35-1 -> -0.48497097
A36: =D35/C36 -> 0.65840831 | B36: ДРР / План | C36: 0.07 | D36: =D34*C36 -> 7978021.5 | F36: ДРР / План | G36: 0.07 | H36: =H34*G36 -> 7738121.2 | I36: =H35/G36 -> 0.65677531 | M36: =M35/$L$35 -> 0.23149327 | N36: =N35/$L$35 -> 0.20691367 | O36: =O35/$L$35 -> 0.27312393 | P36: =P35/$L$35 -> 0.26491106 | Q36: =Q35/$L$35 -> 0.0089652494 | R36: =R35/$L$35 -> 0.0083363047 | S36: =S35/$L$35 -> 0.00081855652 | T36: =T35/$L$35 -> 0.0031928629 | ... X36: =X35/$L$35 -> 8.6321809e-05 | Z36: Ozon | AA36: Биг–Л | AB36: =AJ5 -> 87879383 | AC36: =C15 -> 12817443 | AD36: =AC36/AB36 -> 0.14585267 | AF36: =C18 -> 0.205 | AG36: =AD36 -> 0.14585267 | AH36: =AG36/AF36-1 -> -0.28852354
B37: Перераход в деньгах | D37: =C33-D36 -> -2725225.9 | F37: Перераход в деньгах | H37: =G33-H36 -> -2655914.2 | AA37: Смарт–Сэйл | AB37: =AJ6 -> 79878694 | AC37: =G15 -> 10958646 | AD37: =AC37/AB37 -> 0.1371911 | AF37: =G18 -> 0.115 | AG37: =AD37 -> 0.1371911 | AH37: =AG37/AF37-1 -> 0.19296609
K38: Распределение по направлениям | M38: =SUM(M40:N40)/$L$40 -> 0.43840693 | O38: =SUM(O40:P40)/$L$40 -> 0.53803499 | Q38: =SUM(Q40:R40)/$L$40 -> 0.017301554 | S38: =SUM(S40:T40)/$L$40 -> 0.0040114194 | U38: =SUM(U40:V40)/$L$40 -> 0.002147483 | W38: =SUM(W40:X40)/$L$40 -> 9.7623125e-05 | Z38: ЯМаркет | AA38: Биг–Л | AB38: =AJ7 -> 3359015.8 | AC38: =C72 -> 602712 | AD38: =AC38/AB38 -> 0.17943113 | AF38: =C75 -> 0.18 | AG38: =AD38 -> 0.17943113 | AH38: =AG38/AF38-1 -> -0.0031603985
B39: План | D39: =O42 -> 103370590 | F39: План | H39: =P42 -> 124247057 | K39: Распределение продаж | L39: =L40/$L$40 -> 1 | M39: =M40/$L$40 -> 0.23149327 | N39: =N40/$L$40 -> 0.20691367 | O39: =O40/$L$40 -> 0.27312393 | P39: =P40/$L$40 -> 0.26491106 | Q39: =Q40/$L$40 -> 0.0089652494 | R39: =R40/$L$40 -> 0.0083363047 | S39: =S40/$L$40 -> 0.00081855652 | ... X39: =X40/$L$40 -> 8.6321809e-05 | AA39: Смарт–Сэйл | AB39: =AJ8 -> 3190903.3 | AC39: =G72 -> 670062 | AD39: =AC39/AB39 -> 0.20999132 | AF39: =G75 -> 0.175 | AG39: =AD39 -> 0.20999132 | AH39: =AG39/AF39-1 -> 0.19995039
B40: Плато продаж | D40: =D34/$C$1 -> 3676507.6 | F40: Плато продаж | H40: =H34/$C$1 -> 3565954.5 | K40: Прогноз | L40: =L35/$C$1*$G$1 -> 4.1728945e+08 | M40: =M35/$C$1*$G$1 -> 96599698 | N40: =N35/$C$1*$G$1 -> 86342890 | O40: =O35/$C$1*$G$1 -> 113971735 | P40: =P35/$C$1*$G$1 -> 110544589 | Q40: =Q35/$C$1*$G$1 -> 3741104 | R40: =R35/$C$1*$G$1 -> 3478652 | S40: =S35/$C$1*$G$1 -> 341575 | ... X40: =X35/$C$1*$G$1 -> 36021.18 | Z40: Летуаль | AA40: Биг–Л | AB40: =AJ9 -> 328073 | AC40: 0 | AD40: =AC40/AB40 -> 0 | AF40: =C91 -> 0.15 | AG40: =AD40 -> 0 | AH40: =AG40/AF40-1 -> -1
B41: Нужно сделать на вчера | D41: =D39/$G$1*$C$1 -> 103370590 | F41: Нужно сделать на вчера | H41: =H39/$G$1*$C$1 -> 124247057 | K41: Плато продаж | L41: =L35/$C$1 -> 13460950 | M41: =M35/$C$1 -> 3116119.3 | N41: =N35/$C$1 -> 2785254.5 | O41: =O35/$C$1 -> 3676507.6 | P41: =P35/$C$1 -> 3565954.5 | Q41: =Q35/$C$1 -> 120680.77 | R41: =R35/$C$1 -> 112214.58 | S41: =S35/$C$1 -> 11018.548 | ... X41: =X35/$C$1 -> 1161.9735 | AA41: Смарт–Сэйл | AB41: =AJ10 -> 1282517 | AC41: 0 | AD41: =AC41/AB41 -> 0 | AF41: =G91 -> 0.15 | AG41: =AD41 -> 0 | AH41: =AG41/AF41-1 -> -1
B42: Нужно делать в день | D42: =(D39-D34)/($G$1-$C$1) -> #DIV/0! | F42: Нужно делать в день | H42: =(H39-H34)/($G$1-$C$1) -> #DIV/0! | K42: Прошлый месяц | L42: =SUM(M42:V42) -> 3.7939443e+08 | M42: ='Ноябрь 25'!M35 -> 68328978 | N42: ='Ноябрь 25'!N35 -> 73964393 | O42: ='Ноябрь 25'!O35 -> 103370590 | P42: ='Ноябрь 25'!P35 -> 124247057 | Q42: ='Ноябрь 25'!Q35 -> 2491703 | R42: ='Ноябрь 25'!R35 -> 4455445 | S42: ='Ноябрь 25'!S35 -> 357438 | T42: ='Ноябрь 25'!T35 -> 1099783 | ... X42: ='Ноябрь 25'!X35 -> 17685.2 | Z42: Золотое Яблоко | AA42: Биг–Л | AB42: =AJ11 -> 74449 | AC42: 0 | AD42: =AC42/AB42 -> 0 | AF42: 0 | AG42: =AD42 -> 0 | AH42: =AG42/AF42-1 -> #DIV/0!
B43: Дельта от плана | D43: =D34-D41 -> 10601145 | F43: Дельта от плана | H43: =H34-H41 -> -13702468 | AA43: Смарт–Сэйл | AB43: =AJ12 -> 710399 | AC43: 0 | AD43: =AC43/AB43 -> 0 | AF43: 0 | AG43: =AD43 -> 0 | AH43: =AG43/AF43-1 -> #DIV/0!
B44: Прогноз по выручке | D44: =D34/$C$1*$G$1 -> 113971735 | F44: Прогноз по выручке | H44: =H34/$C$1*$G$1 -> 110544589 | K44: Рекламный расход , руб | L44: =SUM(M44:X44) -> 35383866 | M44: =C15 -> 12817443 | N44: =G15 -> 10958646 | O44: =C33 -> 5252795.6 | P44: =G33 -> 5082207 | Q44: =C72 -> 602712 | R44: =G72 -> 670062 | S44: =C88 | T44: =G88 | U44: 0 | V44: 0 | W44: 0 | X44: 0 | Z44: Магнит Маркет | AA44: Биг–Л | AB44: =AJ13 -> 4715.92 | AC44: 0 | AD44: =AC44/AB44 -> 0 | AF44: 0 | AG44: =AD44 -> 0 | AH44: =AG44/AF44-1 -> #DIV/0!
B45: Прогноз по выручке (%) | D45: =D44/D39 -> 1.1025547 | F45: Прогноз по выручке (%) | H45: =H44/H39 -> 0.88971596 | K45: ДРР , % | L45: =L44/L35 -> 0.084794537 | M45: =IFERROR(M44/M35, " ") -> 0.13268616 | N45: =IFERROR(N44/N35, " ") -> 0.12692007 | O45: =IFERROR(O44/O35, " ") -> 0.046088582 | P45: =IFERROR(P44/P35, " ") -> 0.045974272 | Q45: =IFERROR(Q44/Q35, " ") -> 0.16110538 | R45: =IFERROR(R44/R35, " ") -> 0.19262116 | S45: =IFERROR(S44/S35, " ") -> 0 | T45: =IFERROR(T44/T35, " ") -> 0 | ... X45: =IFERROR(X44/X35, " ") -> 0 | AA45: Смарт–Сэйл | AB45: =AJ14 -> 36021.18 | AC45: 0 | AD45: =AC45/AB45 -> 0 | AF45: 0 | AG45: =AD45 -> 0 | AH45: =AG45/AF45-1 -> #DIV/0!
AB46: =SUM(AB34:AB45) -> 3.9964361e+08 | AC46: =SUM(AC34:AC45) -> 31533050 | AD46: =AC46/AB46 -> 0.078902926 | AF46: =F142 -> 0.11284129 | AG46: =AD46 -> 0.078902926 | AH46: =AG46/AF46-1 -> -0.30076194
B47: Wildberries / Расход только рубли | K47: Прирост к прошлому месяцу , % | L47: =L40/L42-1 -> 0.099882913 | M47: =M40/M42-1 -> 0.41374422 | N47: =N40/N42-1 -> 0.16735751 | O47: =O40/O42-1 -> 0.10255475 | P47: =P40/P42-1 -> -0.11028404 | Q47: =Q40/Q42-1 -> 0.50142453 | R47: =R40/R42-1 -> -0.21923579 | S47: =S40/S42-1 -> -0.044379725 | ... X47: =X40/X42-1 -> 1.036798
B48: =B30 -> Биг–Л / Ноябрь | до | D48: =$D$4 -> 46107 | F48: =F30 -> Смарт / Декабрь| до | H48: =$D$4 -> 46107 | K48: Прирост по направлениям , % | M48: =SUM(M40:N40)/SUM(M42:N42)-1 -> 0.28567189 | O48: =SUM(O40:P40)/SUM(O42:P42)-1 -> -0.013625143 | Q48: =SUM(Q40:R40)/SUM(Q42:R42)-1 -> 0.039240275 | S48: =SUM(S40:T40)/SUM(S42:T42)-1 -> 0.14870908 | U48: =SUM(U40:V40)/SUM(U42:V42)-1 -> -0.16952074 | W48: =SUM(W40:X40)/SUM(W42:X42)-1 -> 1.0642894 | Z48: Рубли + Бонусы | AB48: реальная выручка | AC48: реклама | AD48: ДРР | AF48: ДРР план | AG48: ДРР факт | AH48: дельта
A49: =IFERROR(C49/$C$33, " ") -> 0.46185901 | B49: Затраты из РК | C49: 2426051 | F49: Затраты из РК | G49: 3895344 | I49: =IFERROR(G49/$G$33, " ") -> 0.76646701 | K49: Прирост к прошлому месяцу , руб | L49: =L40-L42 -> 37895021 | M49: =M40-M42 -> 28270720 | N49: =N40-N42 -> 12378497 | O49: =O40-O42 -> 10601145 | P49: =P40-P42 -> -13702468 | Q49: =Q40-Q42 -> 1249401 | R49: =R40-R42 -> -976793 | S49: =S40-S42 -> -15863 | ... X49: =X40-X42 -> 18335.98 | Z49: WB | AA49: Биг–Л | AB49: =AB34 -> 113706034 | AC49: =C33 -> 5252795.6 | AD49: =AC49/AB49 -> 0.046196278 | AF49: =AF34 -> 0.07 | AG49: =AD49 -> 0.046196278 | AH49: =AG49/AF49-1 -> -0.34005317
A50: =IFERROR(C50/$C$33, " ") -> 0.023129017 | B50: Отзывы за баллы? | C50: 121492 | F50: Отзывы за баллы? | G50: 41300 | I50: =IFERROR(G50/$G$33, " ") -> 0.0081263908 | K50: Прирост по направлениям , руб | M50: =SUM(M40:N40)-SUM(M42:N42) -> 40649217 | O50: =SUM(O40:P40)-SUM(O42:P42) -> -3101323 | Q50: =SUM(Q40:R40)-SUM(Q42:R42) -> 272608 | S50: =SUM(S40:T40)-SUM(S42:T42) -> 216702 | U50: =SUM(U40:V40)-SUM(U42:V42) -> -182920 | W50: =SUM(W40:X40)-SUM(W42:X42) -> 21002.9 | AA50: Смарт–Сэйл | AB50: =AB35 -> 109193402 | AC50: =G33 -> 5082207 | AD50: =AC50/AB50 -> 0.046543169 | AF50: =AF35 -> 0.07 | AG50: =AD50 -> 0.046543169 | AH50: =AG50/AF50-1 -> -0.33509758
B51: Итого расходов | C51: =SUM(C49:C50) -> 2547543 | F51: Итого расходов | G51: =SUM(G49:G50) -> 3936644 | Z51: Ozon | AA51: Биг–Л | AB51: =AB36 -> 87879383 | AC51: =AC36 -> 12817443 | AD51: =AC51/AB51 -> 0.14585267 | AF51: =AF36 -> 0.205 | AG51: =AD51 -> 0.14585267 | AH51: =AG51/AF51-1 -> -0.28852354
B52: Выручка | D52: =O35 -> 113971735 | F52: Выручка | H52: =P35 -> 110544589 | K52: хотим | L52: 500000000 | M52: =$L$52*M36 -> 1.1574663e+08 | N52: =$L$52*N36 -> 1.0345683e+08 | O52: =$L$52*O36 -> 1.3656197e+08 | P52: =$L$52*P36 -> 1.3245553e+08 | Q52: =$L$52*Q36 -> 4482624.7 | R52: =$L$52*R36 -> 4168152.4 | S52: =$L$52*S36 -> 409278.26 | T52: =$L$52*T36 -> 1596431.4 | ... X52: =$L$52*X36 -> 43160.904 | AA52: Смарт–Сэйл | AB52: =AB37 -> 79878694 | AC52: =AC37 -> 10958646 | AD52: =AC52/AB52 -> 0.1371911 | AF52: =AF37 -> 0.115 | AG52: =AD52 -> 0.1371911 | AH52: =AG52/AF52-1 -> 0.19296609
B53: ДРР / Факт | D53: =C51/D52 -> 0.02235241 | F53: ДРР / Факт | H53: =G51/H52 -> 0.035611368 | K53: осталось сделать | L53: =L52-L35 -> 82710550 | M53: =M52-M35 -> 19146936 | N53: =N52-N35 -> 17113943 | O53: =O52-O35 -> 22590231 | P53: =P52-P35 -> 21910939 | Q53: =Q52-Q35 -> 741520.71 | R53: =R52-R35 -> 689500.35 | S53: =S52-S35 -> 67703.26 | ... X53: =X52-X35 -> 7139.7243 | Z53: ЯМаркет | AA53: Биг–Л | AB53: =AB38 -> 3359015.8 | AC53: =AC38 -> 602712 | AD53: =AC53/AB53 -> 0.17943113 | AF53: =AF38 -> 0.18 | AG53: =AD53 -> 0.17943113 | AH53: =AG53/AF53-1 -> -0.0031603985
A54: =D53/C54 -> 0.31932015 | B54: ДРР / План | C54: 0.07 | D54: =D52*C54 -> 7978021.5 | F54: ДРР / План | G54: 0.07 | H54: =H52*G54 -> 7738121.2 | I54: =H53/G54 -> 0.50873382 | K54: нужно плато продаж | L54: =SUM(M54:V54) -> #DIV/0! | M54: =M53/($G$1-$C$1) -> #DIV/0! | N54: =N53/($G$1-$C$1) -> #DIV/0! | O54: =O53/($G$1-$C$1) -> #DIV/0! | P54: =P53/($G$1-$C$1) -> #DIV/0! | Q54: =Q53/($G$1-$C$1) -> #DIV/0! | R54: =R53/($G$1-$C$1) -> #DIV/0! | S54: =S53/($G$1-$C$1) -> #DIV/0! | T54: =T53/($G$1-$C$1) -> #DIV/0! | ... X54: =X53/($G$1-$C$1) -> #DIV/0! | AA54: Смарт–Сэйл | AB54: =AB39 -> 3190903.3 | AC54: =AC39 -> 670062 | AD54: =AC54/AB54 -> 0.20999132 | AF54: =AF39 -> 0.175 | AG54: =AD54 -> 0.20999132 | AH54: =AG54/AF54-1 -> 0.19995039
B55: Перераход в деньгах | D55: =C51-D54 -> -5430478.5 | F55: Перераход в деньгах | H55: =G51-H54 -> -3801477.2 | Z55: Летуаль | AA55: Биг–Л | AB55: =AB40 -> 328073 | AC55: =AC40 -> 0 | AD55: =AC55/AB55 -> 0 | AF55: =AF40 -> 0.15 | AG55: =AD55 -> 0 | AH55: =AG55/AF55-1 -> -1
N56: 250000000 | R56: =SUM(Q44:R44)/SUM(Q40:R40) -> 0.17629045 | AA56: Смарт–Сэйл | AB56: =AB41 -> 1282517 | AC56: =AC41 -> 0 | AD56: =AC56/AB56 -> 0 | AF56: =AF41 -> 0.15 | AG56: =AD56 -> 0 | AH56: =AG56/AF56-1 -> -1
B57: План | D57: =O42 -> 103370590 | F57: План | H57: =P42 -> 124247057 | N57: =N56-SUM(M35:N35) -> 67057412 | Z57: Золотое Яблоко | AA57: Биг–Л | AB57: =AB42 -> 74449 | AC57: =AC42 -> 0 | AD57: =AC57/AB57 -> 0 | AF57: =AF42 -> 0 | AG57: =AD57 -> 0 | AH57: =AG57/AF57-1 -> #DIV/0!
B58: Плато продаж | D58: =D52/$C$1 -> 3676507.6 | F58: Плато продаж | H58: =H52/$C$1 -> 3565954.5 | M58: =M35/SUM(M35:N35) -> 0.52803286 | N58: =N35/SUM(M35:N35) -> 0.47196714 | AA58: Смарт–Сэйл | AB58: =AB43 -> 710399 | AC58: =AC43 -> 0 | AD58: =AC58/AB58 -> 0 | AF58: =AF43 -> 0 | AG58: =AD58 -> 0 | AH58: =AG58/AF58-1 -> #DIV/0!
B59: Нужно сделать на вчера | D59: =D57/$G$1*$C$1 -> 103370590 | F59: Нужно сделать на вчера | H59: =H57/$G$1*$C$1 -> 124247057 | M59: =N57*M58 -> 35408517 | N59: =N57*N58 -> 31648895 | Z59: Магнит Маркет | AA59: Биг–Л | AB59: =AB44 -> 4715.92 | AC59: =AC44 -> 0 | AD59: =AC59/AB59 -> 0 | AF59: =AF44 -> 0 | AG59: =AD59 -> 0 | AH59: =AG59/AF59-1 -> #DIV/0!
B60: Нужно делать в день | D60: =(D57-D52)/($G$1-$C$1) -> #DIV/0! | F60: Нужно делать в день | H60: =(H57-H52)/($G$1-$C$1) -> #DIV/0! | L60: =SUM(M60:N60) -> #DIV/0! | M60: =M59/(G1-C1) -> #DIV/0! | N60: =N59/(G1-C1) -> #DIV/0! | AA60: Смарт–Сэйл | AB60: =AB45 -> 36021.18 | AC60: =AC45 -> 0 | AD60: =AC60/AB60 -> 0 | AF60: =AF45 -> 0 | AG60: =AD60 -> 0 | AH60: =AG60/AF60-1 -> #DIV/0!
B61: Дельта от плана | D61: =D52-D59 -> 10601145 | F61: Дельта от плана | H61: =H52-H59 -> -13702468 | AB61: =SUM(AB49:AB60) -> 3.9964361e+08 | AC61: =SUM(AC49:AC60) -> 35383866 | AD61: =AC61/AB61 -> 0.08853855 | AF61: =AF46 -> 0.11284129 | AG61: =AD61 -> 0.08853855 | AH61: =AG61/AF61-1 -> -0.215371
B62: Прогноз по выручке | D62: =D52/$C$1*$G$1 -> 113971735 | F62: Прогноз по выручке | H62: =H52/$C$1*$G$1 -> 110544589 | M62: =M58 -> 0.52803286 | N62: =N58 -> 0.47196714
B63: Прогноз по выручке (%) | D63: =D62/D57 -> 1.1025547 | F63: Прогноз по выручке (%) | H63: =H62/H57 -> 0.88971596 | M63: =$N$56*M62 -> 1.3200822e+08 | N63: =$N$56*N62 -> 1.1799178e+08 | AB63: реальный план | AC63: реальная выручка | AD63: дельта | AF63: ДРР план | AG63: ДРР факт | AH63: дельта
Z64: WB | AA64: Биг–Л | AB64: =AD3 -> 103370590 | AC64: =AJ3 -> 113706034 | AD64: =IFERROR(AC64/AB64, " ") -> 1.0999844 | AF64: =AF49 -> 0.07 | AG64: =AG49 -> 0.046196278 | AH64: =AG64/AF64-1 -> -0.34005317
B65: ЯМаркет | L65: =G1-C1 -> 0 | M65: =(M63-M35)/$L$65 -> #DIV/0! | N65: =(N63-N35)/$L$65 -> #DIV/0! | AA65: Смарт–Сэйл | AB65: =AD4 -> 124247057 | AC65: =AJ4 -> 109193402 | AD65: =IFERROR(AC65/AB65, " ") -> 0.87884095 | AF65: =AF50 -> 0.07 | AG65: =AG50 -> 0.046543169 | AH65: =AG65/AF65-1 -> -0.33509758
B66: =B30 -> Биг–Л / Ноябрь | до | D66: =$D$4 -> 46107 | F66: =F30 -> Смарт / Декабрь| до | H66: =$D$4 -> 46107 | Z66: Ozon | AA66: Биг–Л | AB66: =AD5 -> 68328978 | AC66: =AJ5 -> 87879383 | AD66: =IFERROR(AC66/AB66, " ") -> 1.2861217 | AF66: =AF51 -> 0.205 | AG66: =AG51 -> 0.14585267 | AH66: =AG66/AF66-1 -> -0.28852354
A67: =IFERROR(C67/$C$72, " ") -> 0.95120389 | B67: Буст продаж | C67: 573302 | F67: Буст продаж | G67: 632602 | I67: =IFERROR(G67/$G$72, " ") -> 0.94409473 | N67: 500000000 | AA67: Смарт–Сэйл | AB67: =AD6 -> 73964393 | AC67: =AJ6 -> 79878694 | AD67: =IFERROR(AC67/AB67, " ") -> 1.0799615 | AF67: =AF52 -> 0.115 | AG67: =AG52 -> 0.1371911 | AH67: =AG67/AF67-1 -> 0.19296609
A68: =IFERROR(C68/$C$72, " ") -> 0.048796108 | B68: Буст показов | C68: 29410 | F68: Буст показов | G68: 37460 | I68: =IFERROR(G68/$G$72, " ") -> 0.055905274 | M68: =M35/SUM($M$35:$N$35) -> 0.52803286 | N68: =N35/SUM($M$35:$N$35) -> 0.47196714 | Z68: ЯМаркет | AA68: Биг–Л | AB68: =AD7 -> 2491703 | AC68: =AJ7 -> 3359015.8 | AD68: =IFERROR(AC68/AB68, " ") -> 1.3480803 | AF68: =AF53 -> 0.18 | AG68: =AG53 -> 0.17943113 | AH68: =AG68/AF68-1 -> -0.0031603985
A69: =IFERROR(C69/$C$72, " ") -> 0 | B69: Полки | F69: Полки | I69: =IFERROR(G69/$G$72, " ") -> 0 | M69: =$N$67*M68 -> 2.6401643e+08 | N69: =$N$67*N68 -> 2.3598357e+08 | AA69: Смарт–Сэйл | AB69: =AD8 -> 4455445 | AC69: =AJ8 -> 3190903.3 | AD69: =IFERROR(AC69/AB69, " ") -> 0.71618061 | AF69: =AF54 -> 0.175 | AG69: =AG54 -> 0.20999132 | AH69: =AG69/AF69-1 -> 0.19995039
A70: =IFERROR(C70/$C$72, " ") -> 0 | B70: Охватное продвижение | F70: Охватное продвижение | I70: =IFERROR(G70/$G$72, " ") -> 0 | L70: 30 | M70: =M69/$L$70 -> 8800547.7 | N70: =N69/$L$70 -> 7866119 | Z70: Летуаль | AA70: Биг–Л | AB70: =AD9 -> 357438 | AC70: =AJ9 -> 328073 | AD70: =IFERROR(AC70/AB70, " ") -> 0.91784589 | AF70: =AF55 -> 0.15 | AG70: =AG55 -> 0 | AH70: =AG70/AF70-1 -> -1
A71: =IFERROR(C71/$C$72, " ") -> 0 | B71: Баннеры | F71: Баннеры | I71: =IFERROR(G71/$G$72, " ") -> 0 | AA71: Смарт–Сэйл | AB71: =AD10 -> 1099783 | AC71: =AJ10 -> 1282517 | AD71: =IFERROR(AC71/AB71, " ") -> 1.1661546 | AF71: =AF56 -> 0.15 | AG71: =AG56 -> 0 | AH71: =AG71/AF71-1 -> -1
B72: Итого расходов | C72: =SUM(C67:C71) -> 602712 | F72: Итого расходов | G72: =SUM(G67:G71) -> 670062 | Z72: Золотое Яблоко | AA72: Биг–Л | AB72: =AD11 -> 0 | AC72: =AJ11 -> 74449 | AD72: =IFERROR(AC72/AB72, " ") | AF72: =AF57 -> 0 | AG72: =AG57 -> 0 | AH72: =AG72/AF72-1 -> #DIV/0!
B73: Выручка | D73: =Q35 -> 3741104 | F73: Выручка | H73: =R35 -> 3478652 | AA73: Смарт–Сэйл | AB73: =AD12 -> 1079042 | AC73: =AJ12 -> 710399 | AD73: =IFERROR(AC73/AB73, " ") -> 0.65836084 | AF73: =AF58 -> 0 | AG73: =AG58 -> 0 | AH73: =AG73/AF73-1 -> #DIV/0!
B74: ДРР / Факт | D74: =C72/D73 -> 0.16110538 | F74: ДРР / Факт | H74: =G72/H73 -> 0.19262116 | Z74: Магнит Маркет | AA74: Биг–Л | AB74: =AD13 -> 2049 | AC74: =AJ13 -> 4715.92 | AD74: =IFERROR(AC74/AB74, " ") -> 2.3015715 | AF74: =AF59 -> 0 | AG74: =AG59 -> 0 | AH74: =AG74/AF74-1 -> #DIV/0!
A75: =D74/C75 -> 0.89502992 | B75: ДРР / План | C75: 0.18 | D75: =D73*C75 -> 673398.72 | F75: ДРР / План | G75: 0.175 | H75: =H73*G75 -> 608764.1 | I75: =H74/G75 -> 1.1006924 | AA75: Смарт–Сэйл | AB75: =AD14 -> 17685.2 | AC75: =AJ14 -> 36021.18 | AD75: =IFERROR(AC75/AB75, " ") -> 2.036798 | AF75: =AF60 -> 0 | AG75: =AG60 -> 0 | AH75: =AG75/AF75-1 -> #DIV/0!
B76: Перераход в деньгах | D76: =C72-D75 -> -70686.72 | F76: Перераход в деньгах | H76: =G72-H75 -> 61297.9 | AB76: =AD15 -> 3.7941416e+08 | AC76: =AJ15 -> 3.9964361e+08 | AD76: =IFERROR(AC76/AB76, " ") -> 1.0533176 | AF76: =AF61 -> 0.11284129 | AG76: =AG61 -> 0.08853855 | AH76: =AG76/AF76-1 -> -0.215371
B78: План | D78: =Q42 -> 2491703 | F78: План | H78: =R42 -> 4455445 | AB78: Ноябрь | AC78: Декабрь | AH78: =AB78 -> Ноябрь | AI78: =AC78 -> Декабрь
B79: Плато продаж | D79: =D73/$C$1 -> 120680.77 | F79: Плато продаж | H79: =H73/$C$1 -> 112214.58 | AB79: реальная выручка | AC79: реальная выручка | AD79: дельта | AF79: Рубли + Бонусы | AH79: ДРР факт | AI79: ДРР факт | AJ79: дельта
B80: Нужно сделать на вчера | D80: =D78/$G$1*$C$1 -> 2491703 | F80: Нужно сделать на вчера | H80: =H78/$G$1*$C$1 -> 4455445 | Z80: WB | AA80: Биг–Л | AB80: ='Ноябрь 25'!AJ3 -> 103176599 | AC80: =AJ3 -> 113706034 | AD80: =AC80/AB80-1 -> 0.10205255 | AF80: WB | AG80: Биг–Л | AH80: ='Ноябрь 25'!AG51 -> 0.044298204 | AI80: =AG49 -> 0.046196278 | AJ80: =AI80/AH80-1 -> 0.042847667
B81: Нужно делать в день | D81: =(D78-D73)/($G$1-$C$1) -> #DIV/0! | F81: Нужно делать в день | H81: =(H78-H73)/($G$1-$C$1) -> #DIV/0! | AA81: Смарт–Сэйл | AB81: ='Ноябрь 25'!AJ4 -> 123878665 | AC81: =AJ4 -> 109193402 | AD81: =AC81/AB81-1 -> -0.11854554 | AG81: Смарт–Сэйл | AH81: ='Ноябрь 25'!AG52 -> 0.053795736 | AI81: =AG50 -> 0.046543169 | AJ81: =AI81/AH81-1 -> -0.13481676
B82: Разница от плана | D82: =D73-D80 -> 1249401 | F82: Разница от плана | H82: =H73-H80 -> -976793 | Z82: Ozon | AA82: Биг–Л | AB82: ='Ноябрь 25'!AJ5 -> 64355951 | AC82: =AJ5 -> 87879383 | AD82: =AC82/AB82-1 -> 0.36552068 | AF82: Ozon | AG82: Биг–Л | AH82: ='Ноябрь 25'!AG53 -> 0.16882464 | AI82: =AG51 -> 0.14585267 | AJ82: =AI82/AH82-1 -> -0.13606995
B83: Прогноз по выручке | D83: =D73/$C$1*$G$1 -> 3741104 | F83: Прогноз по выручке | H83: =H73/$C$1*$G$1 -> 3478652 | AA83: Смарт–Сэйл | AB83: ='Ноябрь 25'!AJ6 -> 70026828 | AC83: =AJ6 -> 79878694 | AD83: =AC83/AB83-1 -> 0.14068702 | AG83: Смарт–Сэйл | AH83: ='Ноябрь 25'!AG54 -> 0.12597148 | AI83: =AG52 -> 0.1371911 | AJ83: =AI83/AH83-1 -> 0.089064792
B84: Прогноз по выручке (%) | D84: =D83/D78 -> 1.5014245 | F84: Прогноз по выручке (%) | H84: =H83/H78 -> 0.78076421 | Z84: ЯМаркет | AA84: Биг–Л | AB84: ='Ноябрь 25'!AJ7 -> 2174848.7 | AC84: =AJ7 -> 3359015.8 | AD84: =AC84/AB84-1 -> 0.54448252 | AF84: ЯМаркет | AG84: Биг–Л | AH84: ='Ноябрь 25'!AG55 -> 0.2053444 | AI84: =AG53 -> 0.17943113 | AJ84: =AI84/AH84-1 -> -0.12619419
AA85: Смарт–Сэйл | AB85: ='Ноябрь 25'!AJ8 -> 3962550.1 | AC85: =AJ8 -> 3190903.3 | AD85: =AC85/AB85-1 -> -0.19473489 | AG85: Смарт–Сэйл | AH85: ='Ноябрь 25'!AG56 -> 0.20395099 | AI85: =AG54 -> 0.20999132 | AJ85: =AI85/AH85-1 -> 0.029616585
B86: Летуаль | Z86: Летуаль | AA86: Биг–Л | AB86: ='Ноябрь 25'!AJ9 -> 354043 | AC86: =AJ9 -> 328073 | AD86: =AC86/AB86-1 -> -0.073352672 | AF86: Летуаль | AG86: Биг–Л | AH86: ='Ноябрь 25'!AG57 -> 0 | AI86: =AG55 -> 0 | AJ86: =AI86/AH86-1 -> #DIV/0!
B87: =B66 -> Биг–Л / Ноябрь | до | D87: =$D$4 -> 46107 | F87: =F66 -> Смарт / Декабрь| до | H87: =$D$4 -> 46107 | AA87: Смарт–Сэйл | AB87: ='Ноябрь 25'!AJ10 -> 1090118 | AC87: =AJ10 -> 1282517 | AD87: =AC87/AB87-1 -> 0.17649374 | AG87: Смарт–Сэйл | AH87: ='Ноябрь 25'!AG58 -> 0 | AI87: =AG56 -> 0 | AJ87: =AI87/AH87-1 -> #DIV/0!
B88: Реклама | D88: 12358.77 | F88: Реклама | H88: 39638.09 | Z88: Золотое Яблоко | AA88: Биг–Л | AB88: ='Ноябрь 25'!AJ11 -> 0 | AC88: =AJ11 -> 74449 | AD88: =AC88/AB88-1 -> #DIV/0! | AF88: Золотое Яблоко | AG88: Биг–Л | AH88: ='Ноябрь 25'!AG59 -> #DIV/0! | AI88: =AG57 -> 0 | AJ88: =AI88/AH88-1 -> #DIV/0!
B89: Выручка | D89: =S35 -> 341575 | F89: Выручка | H89: =T35 -> 1332348 | AA89: Смарт–Сэйл | AB89: ='Ноябрь 25'!AJ12 -> 1079042 | AC89: =AJ12 -> 710399 | AD89: =AC89/AB89-1 -> -0.34163916 | AG89: Смарт–Сэйл | AH89: ='Ноябрь 25'!AG60 -> 0 | AI89: =AG58 -> 0 | AJ89: =AI89/AH89-1 -> #DIV/0!
B90: ДРР / Факт | D90: =C88/D89 -> 0 | F90: ДРР / Факт | H90: =G88/H89 -> 0 | Z90: Магнит Маркет | AA90: Биг–Л | AB90: ='Ноябрь 25'!AJ13 -> 1391 | AC90: =AJ13 -> 4715.92 | AF90: Магнит Маркет | AG90: Биг–Л | AH90: ='Ноябрь 25'!AG61 -> 0 | AI90: =AG59 -> 0 | AJ90: =AI90/AH90-1 -> #DIV/0!
B91: ДРР / План | C91: 0.15 | D91: =D89*C91 -> 51236.25 | F91: ДРР / План | G91: 0.15 | H91: =H89*G91 -> 199852.2 | AA91: Смарт–Сэйл | AB91: ='Ноябрь 25'!AJ14 -> 14588.2 | AC91: =AJ14 -> 36021.18 | AG91: Смарт–Сэйл | AH91: ='Ноябрь 25'!AG62 -> 0 | AI91: =AG60 -> 0 | AJ91: =AI91/AH91-1 -> #DIV/0!
B92: Перераход в деньгах | D92: =C88-D91 -> -51236.25 | F92: Перераход в деньгах | H92: =G88-H91 -> -199852.2 | AB92: =SUM(AB80:AB91) -> 3.7011462e+08 | AC92: =SUM(AC80:AC91) -> 3.9964361e+08 | AD92: =AC92/AB92-1 -> 0.079783344 | AH92: ='Ноябрь 25'!AG63 -> 0.086934403 | AI92: =AG61 -> 0.08853855 | AJ92: =AI92/AH92-1 -> 0.018452385
AD93: =AC92-AB92 -> 29528983
B94: План | D94: =S42 -> 357438 | F94: План | H94: =T42 -> 1099783
B95: Плато продаж | D95: =D89/$C$1 -> 11018.548 | F95: Плато продаж | H95: =H89/$C$1 -> 42978.968
B96: Нужно сделать на вчера | D96: =D94/$G$1*$C$1 -> 357438 | F96: Нужно сделать на вчера | H96: =H94/$G$1*$C$1 -> 1099783
B97: Нужно делать в день | D97: =(D94-D89)/($G$1-$C$1) -> #DIV/0! | F97: Нужно делать в день | H97: =(H94-H89)/($G$1-$C$1) -> #DIV/0!
B98: Разница от плана | D98: =D89-D96 -> -15863 | F98: Разница от плана | H98: =H89-H96 -> 232565
B99: Прогноз по выручке | D99: =D89/$C$1*$G$1 -> 341575 | F99: Прогноз по выручке | H99: =H89/$C$1*$G$1 -> 1332348
B100: Прогноз по выручке (%) | D100: =D99/D94 -> 0.95562028 | F100: Прогноз по выручке (%) | H100: =H99/H94 -> 1.2114644
B102: Магнит
...

Sheet Ноябрь 25
A1: 3 | B1: Вчера | C1: 30 | F1: Дней в месяце | G1: 30
A2: Актуально на | B2: 45991 | M2: Оз | O2: Вб | Q2: Ям | S2: Лету | U2: ЗЯ | W2: Магнит Маркет | AB2: план (ПП) | AC2: ауты | AD2: реальный план | AF2: выручка | AG2: отказы/возвраты | AH2: раздачи | AI2: выкупы | AJ2: реальная выручка
B3: Ozon | M3: Биг–Л | N3: Смарт | O3: Биг–Л | P3: Смарт | Q3: Биг–Л | R3: Смарт | S3: Биг–Л | T3: Смарт | U3: Биг–Л | V3: Смарт | W3: Биг–Л | X3: Смарт | Z3: WB | AA3: Биг–Л | AB3: =D39 -> 73239180 | AD3: =AB3-AC3 -> 73239180 | AF3: =O35 -> 103370590 | AH3: =6763+187228 -> 193991 | AJ3: =AF3-SUM(AG3:AI3) -> 103176599
B4: Биг–Л / Ноябрь | до | D4: 45991 | F4: Смарт / Ноябрь | до | H4: =$D$4 -> 45991 | K4: 45962 | L4: =SUM(M4:X4) -> 11629847 | M4: 1731918 | N4: 2260251 | O4: 2963798 | P4: 4455715 | Q4: 25725 | R4: 108694 | S4: 6251 | T4: 23333 | V4: 54162 | AA4: Смарт–Сэйл | AB4: =H39 -> 126203637 | AD4: =AB4-AC4 -> 126203637 | AF4: =P35 -> 124247057 | AH4: =11852+356540 -> 368392 | AJ4: =AF4-SUM(AG4:AI4) -> 123878665
A5: =IFERROR(C5/$C$15, " ") -> 0.8737718 | B5: Оплата за клик | C5: 9493417 | F5: Оплата за клик | G5: 7530357 | H5: 3459260 | I5: =IFERROR(G5/$G$15, " ") -> 0.85364812 | K5: 45963 | L5: =SUM(M5:X5) -> 11803036 | M5: 1821579 | N5: 2209959 | O5: 3175791 | P5: 4370161 | Q5: 32801 | R5: 115688 | S5: 6731 | T5: 13534 | V5: 56792 | Z5: Ozon | AA5: Биг–Л | AB5: =D21 -> 45495371 | AD5: =AB5-AC5 -> 45495371 | AF5: =M35 -> 68328978 | AG5: =AF5/66378*(3513+81) -> 3699634.6 | AH5: =9444+263948 -> 273392 | AJ5: =AF5-SUM(AG5:AI5) -> 64355951
A6: =IFERROR(C6/$C$15, " ") -> 0.11532839 | B6: Оплата за заказ | C6: 1253028 | F6: Оплата за заказ | G6: 750101 | H6: 563877 | I6: =IFERROR(G6/$G$15, " ") -> 0.085032132 | K6: 45964 | L6: =SUM(M6:X6) -> 11743838 | M6: 1806600 | N6: 2128041 | O6: 3412318 | P6: 4162343 | Q6: 25677 | R6: 130908 | S6: 4252 | T6: 20123 | V6: 53576 | AA6: Смарт–Сэйл | AB6: =H21 -> 74046375 | AD6: =AB6-AC6 -> 74046375 | AF6: =N35 -> 73964393 | AG6: =AF6/81964*(3746+101) -> 3471536.5 | AH6: =4839+461189 -> 466028 | AJ6: =AF6-SUM(AG6:AI6) -> 70026828
A7: =IFERROR(C7/$C$15, " ") -> 0 | B7: Медийка | C7: 0 | F7: Медийка | G7: 156736 | I7: =IFERROR(G7/$G$15, " ") -> 0.017767736 | K7: 45965 | L7: =SUM(M7:X7) -> 11432053 | M7: 1702647 | N7: 2080610.1 | O7: 3337075 | P7: 4102142 | Q7: 34865 | R7: 119677 | S7: 7710 | T7: 15867 | V7: 31460 | Z7: ЯМаркет | AA7: Биг–Л | AB7: =D78 -> 1604498 | AD7: =AB7-AC7 -> 1604498 | AF7: =Q35 -> 2491703 | AG7: =AF7/2732*(211+2) -> 194265.28 | AH7: =4251+118338 -> 122589 | AJ7: =AF7-SUM(AG7:AI7) -> 2174848.7
A8: =IFERROR(C8/$C$15, " ") -> 0.00022531333 | B8: Баллы за отзывы | C8: 2448 | F8: Баллы за отзывы | G8: 10529 | H8: 8078 | K8: 45966 | L8: =SUM(M8:X8) -> 12273335 | M8: 1857111 | N8: 2230079.1 | O8: 3669615 | P8: 4149454 | Q8: 121151 | R8: 172346 | S8: 7218 | T8: 22465 | V8: 43896 | AA8: Смарт–Сэйл | AB8: =H78 -> 4572310 | AD8: =AB8-AC8 -> 4572310 | AF8: =R35 -> 4455445 | AG8: =AF8/6338*(450+3) -> 318446.92 | AH8: =3018+171430 -> 174448 | AJ8: =AF8-SUM(AG8:AI8) -> 3962550.1
A9: =IFERROR(C9/$C$15, " ") -> 0.010556132 | B9: Бонусы продавца | C9: 114691 | F9: Бонусы продавца | G9: 138767 | H9: 81614 | I9: =IFERROR(G9/$G$15, " ") -> 0.015730753 | K9: 45967 | L9: =SUM(M9:X9) -> 12195122 | M9: 1806029 | N9: 2247173 | O9: 3801850 | P9: 4082080 | Q9: 52381 | R9: 138947 | S9: 4413 | T9: 18321 | V9: 43928 | Z9: Летуаль | AA9: Биг–Л | AB9: =S42 -> 262675 | AD9: =AB9-AC9 -> 262675 | AF9: =S35 -> 357438 | AH9: =3395 -> 3395 | AJ9: =AF9-SUM(AG9:AI9) -> 354043
A10: =IFERROR(C10/$C$15, " ") -> 0 | B10: Рассылки | C10: 0 | F10: Рассылки | G10: 6091 | I10: =IFERROR(G10/$G$15, " ") -> 0.0006904813 | K10: 45968 | L10: =SUM(M10:X10) -> 11891247 | M10: 1861690 | N10: 2259995 | O10: 3723488 | P10: 3764924 | Q10: 62234 | R10: 129672 | S10: 8091 | T10: 44771 | V10: 36382 | AA10: Смарт–Сэйл | AB10: =T42 -> 827330 | AD10: =AB10-AC10 -> 827330 | AF10: =T35 -> 1099783 | AH10: =9665 -> 9665 | AJ10: =AF10-SUM(AG10:AI10) -> 1090118
A11: =IFERROR(C11/$C$15, " ") -> 2.3009939e-05 | B11: Закрепление отзыва | C11: 250 | F11: Закрепление отзыва | I11: =IFERROR(G11/$G$15, " ") -> 0 | K11: 45969 | L11: =SUM(M11:X11) -> 11578045 | M11: 1685928 | N11: 2339557 | O11: 3283345 | P11: 4016122 | Q11: 68518 | R11: 122283 | S11: 6237 | T11: 19645 | V11: 36410 | Z11: Золотое Яблоко | AA11: Биг–Л | AB11: =U42 -> 0 | AD11: =AB11-AC11 -> 0 | AF11: =U35 -> 0 | AJ11: =AF11-SUM(AG11:AI11) -> 0
B12: Иные электронные услуги | C12: 0 | F12: Иные электронные услуги | G12: 165599 | H12: 113751 | I12: =IFERROR(G12/$G$15, " ") -> 0.018772453 | K12: 45970 | L12: =SUM(M12:X12) -> 13204877 | M12: 1954127 | N12: 2401329 | O12: 3969205 | P12: 4608078 | Q12: 71058 | R12: 133819 | S12: 7080 | T12: 24443 | V12: 35738 | AA12: Смарт–Сэйл | AB12: =V42 -> 1794605 | AD12: =AB12-AC12 -> 1794605 | AF12: =V35 -> 1079042 | AJ12: =AF12-SUM(AG12:AI12) -> 1079042
B13: Продвижение бренда | C13: 0 | F13: Продвижение бренда | G13: 63203 | H13: =SUM(H5:H12) -> 4226580 | I13: =IFERROR(G13/$G$15, " ") -> 0.0071647496 | K13: 45971 | L13: =SUM(M13:X13) -> 13480671 | M13: 2474505 | N13: 2553944.1 | O13: 3886555 | P13: 4166475 | Q13: 112809 | R13: 198757 | S13: 8819 | T13: 28023 | V13: 50242 | X13: 542 | Z13: Магнит Маркет | AA13: Биг–Л | AB13: 0 | AD13: =AB13-AC13 -> 0 | AF13: =W35 -> 2049 | AH13: =658 -> 658 | AJ13: =AF13-SUM(AG13:AI13) -> 1391
B14: Ozon Рассрочка | C14: 1036 | F14: Ozon Рассрочка | K14: 45972 | L14: =SUM(M14:X14) -> 15626273 | M14: 3045200 | N14: 3020427.8 | O14: 4336280 | P14: 4692022 | Q14: 148468 | R14: 265371 | S14: 11423 | T14: 31073 | V14: 76008 | W14: 0 | X14: 0 | AA14: Смарт–Сэйл | AB14: 0 | AD14: =AB14-AC14 -> 0 | AF14: =X35 -> 17685.2 | AH14: =3097 -> 3097 | AJ14: =AF14-SUM(AG14:AI14) -> 14588.2
B15: Итого расходов | C15: =SUM(C5:C14) -> 10864870 | F15: Итого расходов | G15: =SUM(G5:G14) -> 8821383 | H15: =SUM(H5) -> 3459260 | K15: 45973 | L15: =SUM(M15:X15) -> 14571767 | M15: 2808715 | N15: 2510006.1 | O15: 3951887 | P15: 4865096 | Q15: 111215 | R15: 236626 | S15: 13124 | T15: 34607 | V15: 40491 | W15: 0 | X15: 0 | AA15: итог | AB15: =SUM(AB3:AB14) -> 3.2804598e+08 | AC15: =SUM(AC3:AC14) -> 0 | AD15: =SUM(AD3:AD14) -> 3.2804598e+08 | AF15: =SUM(AF3:AF14) -> 3.7941416e+08 | AG15: =SUM(AG3:AG14) -> 7683883.3 | AH15: =SUM(AH3:AH14) -> 1615655 | AI15: =SUM(AI3:AI14) -> 0 | AJ15: =SUM(AJ3:AJ14) -> 3.7011462e+08
B16: Выручка | D16: =M35 -> 68328978 | F16: Выручка | H16: =N35 -> 73964393 | K16: 45974 | L16: =SUM(M16:X16) -> 15623833 | M16: 2749995 | N16: 2554313 | O16: 3886298 | P16: 6044334 | Q16: 124510 | R16: 197290 | S16: 9462 | T16: 21351 | V16: 34889 | W16: 1391 | X16: 0 | AH16: =AH15/AF15 -> 0.0042582886
B17: ДРР / Факт | D17: =C15/D16 -> 0.15900823 | F17: ДРР / Факт | H17: =G15/H16 -> 0.11926527 | K17: 45975 | L17: =SUM(M17:X17) -> 13587990 | M17: 2554697 | N17: 2478850 | O17: 3333302 | P17: 4832612 | Q17: 98006 | R17: 187620 | S17: 16980 | T17: 39389 | V17: 45720 | W17: 0 | X17: 814.4
A18: =D17/C18 -> 0.77564991 | B18: ДРР / План | C18: 0.205 | D18: =D16*C18 -> 14007440 | F18: ДРР / План | G18: 0.115 | H18: =H16*G18 -> 8505905.2 | I18: =H17/G18 -> 1.0370893 | K18: 45976 | L18: =SUM(M18:X18) -> 12643412 | M18: 2637349 | N18: 2233887 | O18: 3044860 | P18: 4431701 | Q18: 83652 | R18: 147073 | S18: 13654 | T18: 20823 | V18: 29599 | W18: 0 | X18: 814.4
B19: Перерасход в деньгах | D19: =C15-D18 -> -3142570.5 | F19: Перераход в деньгах | H19: =G15-H18 -> 315477.84 | K19: 45977 | L19: =SUM(M19:X19) -> 14333940 | M19: 2950217 | N19: 2443626.1 | O19: 3710586 | P19: 4885653 | Q19: 94182 | R19: 172419 | S19: 13719 | T19: 28056 | V19: 34982 | W19: 0 | X19: 500 | AB19: Без вычетов | AF19: С вычетом всего
K20: 45978 | L20: =SUM(M20:X20) -> 12187671 | M20: 2510335 | N20: 2240351 | O20: 3080380 | P20: 4098869 | Q20: 82320 | R20: 127734 | S20: 5103 | T20: 15220 | V20: 27359 | W20: 0 | X20: 0 | AB20: план (ПП) | AC20: выручка | AD20: дельта | AF20: реальный план | AG20: реальная выручка | AH20: дельта
B21: План | D21: =M42 -> 45495371 | F21: План | H21: =N42 -> 74046375 | K21: 45979 | L21: =SUM(M21:X21) -> 12258064 | M21: 2394143 | N21: 2161236 | O21: 3088791 | P21: 4318785 | Q21: 100618 | R21: 131558 | S21: 7529 | T21: 12449 | V21: 42600 | W21: 0 | X21: 355 | Z21: WB | AA21: Биг–Л | AB21: =AB3 -> 73239180 | AC21: =AF3 -> 103370590 | AD21: =IFERROR(AC21/AB21, " ") -> 1.4114111 | AF21: =AD3 -> 73239180 | AG21: =AJ3 -> 103176599 | AH21: =IFERROR(AG21/AF21, " ") -> 1.4087623
B22: Плато продаж | D22: =D16/$C$1 -> 2277632.6 | F22: Плато продаж | H22: =H16/$C$1 -> 2465479.8 | K22: 45980 | L22: =SUM(M22:X22) -> 11481818 | M22: 2260476 | N22: 2186913.1 | O22: 2903112 | P22: 3850661 | Q22: 75917 | R22: 151531 | S22: 1615 | T22: 15333 | V22: 33883 | W22: 658 | X22: 1719 | AA22: Смарт–Сэйл | AB22: =AB4 -> 126203637 | AC22: =AF4 -> 124247057 | AD22: =IFERROR(AC22/AB22, " ") -> 0.98449664 | AF22: =AD4 -> 126203637 | AG22: =AJ4 -> 123878665 | AH22: =IFERROR(AG22/AF22, " ") -> 0.98157761
B23: Нужно сделать на вчера | D23: =D21/$G$1*$C$1 -> 45495371 | F23: Нужно сделать на вчера | H23: =H21/$G$1*$C$1 -> 74046375 | K23: 45981 | L23: =SUM(M23:X23) -> 12087911 | M23: 2432752 | N23: 2750771 | O23: 2879787 | P23: 3731215 | Q23: 111653 | R23: 125475 | S23: 6783 | T23: 25468 | V23: 22213 | W23: 0 | X23: 1793.6 | Z23: Ozon | AA23: Биг–Л | AB23: =AB5 -> 45495371 | AC23: =AF5 -> 68328978 | AD23: =IFERROR(AC23/AB23, " ") -> 1.5018886 | AF23: =AD5 -> 45495371 | AG23: =AJ5 -> 64355951 | AH23: =IFERROR(AG23/AF23, " ") -> 1.4145604
B24: Нужно делать в день | D24: =(D21-D16)/($G$1-$C$1) -> #DIV/0! | F24: Нужно делать в день | H24: =(H21-H16)/($G$1-$C$1) -> #DIV/0! | K24: 45982 | L24: =SUM(M24:X24) -> 10700008 | M24: 2072178 | N24: 2377663 | O24: 2632151 | P24: 3294636 | Q24: 100328 | R24: 131848 | S24: 18829 | T24: 51736 | V24: 19261 | W24: 0 | X24: 1378.4 | AA24: Смарт–Сэйл | AB24: =AB6 -> 74046375 | AC24: =AF6 -> 73964393 | AD24: =IFERROR(AC24/AB24, " ") -> 0.99889282 | AF24: =AD6 -> 74046375 | AG24: =AJ6 -> 70026828 | AH24: =IFERROR(AG24/AF24, " ") -> 0.94571582
B25: Дельта от плана | D25: =D16-D23 -> 22833607 | F25: Дельта от плана | H25: =H16-H23 -> -81982.6 | K25: 45983 | L25: =SUM(M25:X25) -> 11367170 | M25: 2110849 | N25: 2811323.1 | O25: 2579849 | P25: 3498829 | Q25: 104144 | R25: 144223 | S25: 26696 | T25: 52892 | V25: 37551 | W25: 0 | X25: 814.4 | Z25: ЯМаркет | AA25: Биг–Л | AB25: =AB7 -> 1604498 | AC25: =AF7 -> 2491703 | AD25: =IFERROR(AC25/AB25, " ") -> 1.5529486 | AF25: =AD7 -> 1604498 | AG25: =AJ7 -> 2174848.7 | AH25: =IFERROR(AG25/AF25, " ") -> 1.3554699
B26: Прогноз по выручке | D26: =D16/$C$1*$G$1 -> 68328978 | F26: Прогноз по выручке | H26: =H16/$C$1*$G$1 -> 73964393 | K26: 45984 | L26: =SUM(M26:X26) -> 12417922 | M26: 2147168 | N26: 3029457.1 | O26: 2924741 | P26: 3993676 | Q26: 71759 | R26: 121367 | S26: 36634 | T26: 68676 | V26: 23569 | W26: 0 | X26: 874.4 | AA26: Смарт–Сэйл | AB26: =AB8 -> 4572310 | AC26: =AF8 -> 4455445 | AD26: =IFERROR(AC26/AB26, " ") -> 0.97444071 | AF26: =AD8 -> 4572310 | AG26: =AJ8 -> 3962550.1 | AH26: =IFERROR(AG26/AF26, " ") -> 0.86664073
B27: Прогноз по выручке (%) | D27: =D26/D21 -> 1.5018886 | F27: Прогноз по выручке (%) | H27: =H26/H21 -> 0.99889282 | K27: 45985 | L27: =SUM(M27:X27) -> 12089211 | M27: 2232258 | N27: 2537265 | O27: 3569395 | P27: 3367733 | Q27: 128670 | R27: 159721 | S27: 19590 | T27: 55960 | V27: 18619 | W27: 0 | X27: 0 | Z27: Летуаль | AA27: Биг–Л | AB27: =AB9 -> 262675 | AC27: =AF9 -> 357438 | AD27: =IFERROR(AC27/AB27, " ") -> 1.3607614 | AF27: =AD9 -> 262675 | AG27: =AJ9 -> 354043 | AH27: =IFERROR(AG27/AF27, " ") -> 1.3478367
K28: 45986 | L28: =SUM(M28:X28) -> 12245606 | M28: 2325849 | N28: 2457582 | O28: 3669417 | P28: 3497780 | Q28: 70265 | R28: 131956 | S28: 12957 | T28: 55565 | V28: 22042 | W28: 0 | X28: 2192.8 | AA28: Смарт–Сэйл | AB28: =AB10 -> 827330 | AC28: =AF10 -> 1099783 | AD28: =IFERROR(AC28/AB28, " ") -> 1.329316 | AF28: =AD10 -> 827330 | AG28: =AJ10 -> 1090118 | AH28: =IFERROR(AG28/AF28, " ") -> 1.3176338
B29: Wildberries / Расход бонусы + рубли | K29: 45987 | L29: =SUM(M29:X29) -> 12235399 | M29: 2405725 | N29: 2518471.1 | O29: 3463724 | P29: 3518911 | Q29: 76199 | R29: 141871 | S29: 15587 | T29: 73179 | V29: 21448 | W29: 0 | X29: 284 | Z29: Золотое Яблоко | AA29: Биг–Л | AB29: =AB11 -> 0 | AC29: =AF11 -> 0 | AD29: =IFERROR(AC29/AB29, " ") | AF29: =AD11 -> 0 | AG29: =AJ11 -> 0 | AH29: =IFERROR(AG29/AF29, " ")
B30: =B4 -> Биг–Л / Ноябрь | до | D30: =$D$4 -> 45991 | F30: =F4 -> Смарт / Ноябрь | до | H30: =$D$4 -> 45991 | K30: 45988 | L30: =SUM(M30:X30) -> 12067787 | M30: 2297798 | N30: 2499604 | O30: 3443773 | P30: 3533710 | Q30: 68854 | R30: 128656 | S30: 11858 | T30: 65076 | V30: 15798 | W30: 0 | X30: 2659.8 | AA30: Смарт–Сэйл | AB30: =AB12 -> 1794605 | AC30: =AF12 -> 1079042 | AD30: =IFERROR(AC30/AB30, " ") -> 0.60126992 | AF30: =AD12 -> 1794605 | AG30: =AJ12 -> 1079042 | AH30: =IFERROR(AG30/AF30, " ") -> 0.60126992
A31: =IFERROR(C31/$C$33, " ") -> 0 | B31: Затраты из РК | F31: Затраты из РК | I31: =IFERROR(G31/$G$33, " ") -> 0 | K31: 45989 | L31: =SUM(M31:X31) -> 13129103 | M31: 2762179 | N31: 2796128 | O31: 3688641 | P31: 3546653 | Q31: 91677 | R31: 142042 | S31: 13214 | T31: 60990 | V31: 26264 | W31: 0 | X31: 1315 | Z31: Магнит Маркет | AA31: Биг–Л | AC31: =AF13 -> 2049 | AD31: =IFERROR(AC31/AB31, " ") | AF31: =AD13 -> 0 | AG31: =AJ13 -> 1391 | AH31: =IFERROR(AG31/AF31, " ")
A32: =IFERROR(C32/$C$33, " ") -> 0 | B32: Отзывы за баллы | F32: Отзывы за баллы | I32: =IFERROR(G32/$G$33, " ") -> 0 | K32: 45990 | L32: =SUM(M32:X32) -> 13417101 | M32: 2516868 | N32: 2875822 | O32: 3676789 | P32: 4053774 | Q32: 56946 | R32: 122322 | S32: 17642 | T32: 72478 | V32: 22832 | W32: 0 | X32: 1628 | AA32: Смарт–Сэйл | AC32: =AF14 -> 17685.2 | AD32: =IFERROR(AC32/AB32, " ") | AF32: =AD14 -> 0 | AG32: =AJ14 -> 14588.2 | AH32: =IFERROR(AG32/AF32, " ")
B33: Итого расходов | C33: 4570538 | F33: Итого расходов | G33: 6664144 | K33: 45991 | L33: =SUM(M33:X33) -> 14110105 | M33: 2412093 | N33: 2769758 | O33: 4283787 | P33: 4312913 | Q33: 85101 | R33: 117951 | S33: 18237 | T33: 68937 | V33: 41328 | W33: 0 | X33: 0 | AB33: =SUM(AB21:AB32) -> 3.2804598e+08 | AC33: =SUM(AC21:AC32) -> 3.7941416e+08 | AD33: =IFERROR(AC33/AB33, " ") -> 1.1565884 | AF33: =SUM(AF21:AF32) -> 3.2804598e+08 | AG33: =SUM(AG21:AG32) -> 3.7011462e+08 | AH33: =IFERROR(AG33/AF33, " ") -> 1.1282401
B34: Выручка | D34: =O35 -> 103370590 | F34: Выручка | H34: =P35 -> 124247057
B35: ДРР / Факт | D35: =C33/D34 -> 0.044215071 | F35: ДРР / Факт | H35: =G33/H34 -> 0.053636232 | K35: =L35/C1 -> 12647139 | L35: =SUM(L4:L34) -> 3.7941416e+08 | M35: =SUM(M4:M34) -> 68328978 | N35: =SUM(N4:N34) -> 73964393 | O35: =SUM(O4:O34) -> 103370590 | P35: =SUM(P4:P34) -> 124247057 | Q35: =SUM(Q4:Q34) -> 2491703 | R35: =SUM(R4:R34) -> 4455445 | S35: =SUM(S4:S34) -> 357438 | ... X35: =SUM(X4:X34) -> 17685.2 | Z35: Только рубли | AB35: реальная выручка | AC35: реклама | AD35: ДРР | AF35: ДРР план | AG35: ДРР факт | AH35: дельта
A36: =D35/C36 -> 0.63164387 | B36: ДРР / План | C36: 0.07 | D36: =D34*C36 -> 7235941.3 | F36: ДРР / План | G36: 0.07 | H36: =H34*G36 -> 8697294 | I36: =H35/G36 -> 0.76623189 | M36: =M35/$L$35 -> 0.18009074 | N36: =N35/$L$35 -> 0.19494368 | O36: =O35/$L$35 -> 0.27244789 | P36: =P35/$L$35 -> 0.32747079 | Q36: =Q35/$L$35 -> 0.0065672377 | R36: =R35/$L$35 -> 0.011742959 | S36: =S35/$L$35 -> 0.0009420787 | T36: =T35/$L$35 -> 0.0028986345 | ... X36: =X35/$L$35 -> 4.661186e-05 | Z36: WB | AA36: Биг–Л | AB36: =AJ3 -> 103176599 | AC36: =C51 -> 3591756 | AD36: =AC36/AB36 -> 0.034811731 | AF36: =C36 -> 0.07 | AG36: =AD36 -> 0.034811731 | AH36: =AG36/AF36-1 -> -0.50268956
B37: Перераход в деньгах | D37: =C33-D36 -> -2665403.3 | F37: Перераход в деньгах | H37: =G33-H36 -> -2033150 | AA37: Смарт–Сэйл | AB37: =AJ4 -> 123878665 | AC37: =G51 -> 2569910 | AD37: =AC37/AB37 -> 0.02074538 | AF37: =G36 -> 0.07 | AG37: =AD37 -> 0.02074538 | AH37: =AG37/AF37-1 -> -0.70363743
K38: Распределение по направлениям | M38: =SUM(M40:N40)/$L$40 -> 0.37503442 | O38: =SUM(O40:P40)/$L$40 -> 0.59991869 | Q38: =SUM(Q40:R40)/$L$40 -> 0.018310197 | S38: =SUM(S40:T40)/$L$40 -> 0.0038407132 | U38: =SUM(U40:V40)/$L$40 -> 0.0028439687 | W38: =SUM(W40:X40)/$L$40 -> 5.2012291e-05 | Z38: Ozon | AA38: Биг–Л | AB38: =AJ5 -> 64355951 | AC38: =C15 -> 10864870 | AD38: =AC38/AB38 -> 0.16882464 | AF38: =C18 -> 0.205 | AG38: =AD38 -> 0.16882464 | AH38: =AG38/AF38-1 -> -0.1764652
B39: План | D39: =O42 -> 73239180 | F39: План | H39: =P42 -> 126203637 | K39: Распределение продаж | L39: =L40/$L$40 -> 1 | M39: =M40/$L$40 -> 0.18009074 | N39: =N40/$L$40 -> 0.19494368 | O39: =O40/$L$40 -> 0.27244789 | P39: =P40/$L$40 -> 0.32747079 | Q39: =Q40/$L$40 -> 0.0065672377 | R39: =R40/$L$40 -> 0.011742959 | S39: =S40/$L$40 -> 0.0009420787 | ... X39: =X40/$L$40 -> 4.661186e-05 | AA39: Смарт–Сэйл | AB39: =AJ6 -> 70026828 | AC39: =G15 -> 8821383 | AD39: =AC39/AB39 -> 0.12597148 | AF39: =G18 -> 0.115 | AG39: =AD39 -> 0.12597148 | AH39: =AG39/AF39-1 -> 0.095404151
B40: Плато продаж | D40: =D34/$C$1 -> 3445686.3 | F40: Плато продаж | H40: =H34/$C$1 -> 4141568.6 | K40: Прогноз | L40: =L35/$C$1*$G$1 -> 3.7941416e+08 | M40: =M35/$C$1*$G$1 -> 68328978 | N40: =N35/$C$1*$G$1 -> 73964393 | O40: =O35/$C$1*$G$1 -> 103370590 | P40: =P35/$C$1*$G$1 -> 124247057 | Q40: =Q35/$C$1*$G$1 -> 2491703 | R40: =R35/$C$1*$G$1 -> 4455445 | S40: =S35/$C$1*$G$1 -> 357438 | ... X40: =X35/$C$1*$G$1 -> 17685.2 | Z40: ЯМаркет | AA40: Биг–Л | AB40: =AJ7 -> 2174848.7 | AC40: =C72 -> 446593 | AD40: =AC40/AB40 -> 0.2053444 | AF40: =C75 -> 0.18 | AG40: =AD40 -> 0.2053444 | AH40: =AG40/AF40-1 -> 0.14080221
B41: Нужно сделать на вчера | D41: =D39/$G$1*$C$1 -> 73239180 | F41: Нужно сделать на вчера | H41: =H39/$G$1*$C$1 -> 126203637 | K41: Плато продаж | L41: =L35/$C$1 -> 12647139 | M41: =M35/$C$1 -> 2277632.6 | N41: =N35/$C$1 -> 2465479.8 | O41: =O35/$C$1 -> 3445686.3 | P41: =P35/$C$1 -> 4141568.6 | Q41: =Q35/$C$1 -> 83056.767 | R41: =R35/$C$1 -> 148514.83 | S41: =S35/$C$1 -> 11914.6 | ... X41: =X35/$C$1 -> 589.50667 | AA41: Смарт–Сэйл | AB41: =AJ8 -> 3962550.1 | AC41: =G72 -> 808166 | AD41: =AC41/AB41 -> 0.20395099 | AF41: =G75 -> 0.175 | AG41: =AD41 -> 0.20395099 | AH41: =AG41/AF41-1 -> 0.16543421
B42: Нужно делать в день | D42: =(D39-D34)/($G$1-$C$1) -> #DIV/0! | F42: Нужно делать в день | H42: =(H39-H34)/($G$1-$C$1) -> #DIV/0! | K42: Прошлый месяц | L42: =SUM(M42:V42) -> 3.2804598e+08 | M42: ='Октябрь 25'!M35 -> 45495371 | N42: ='Октябрь 25'!N35 -> 74046375 | O42: ='Октябрь 25'!O35 -> 73239180 | P42: ='Октябрь 25'!P35 -> 126203637 | Q42: ='Октябрь 25'!Q35 -> 1604498 | R42: ='Октябрь 25'!R35 -> 4572310 | S42: ='Октябрь 25'!S35 -> 262675 | T42: ='Октябрь 25'!T35 -> 827330 | ... V42: ='Октябрь 25'!V35 -> 1794605 | W42: 0 | X42: 0 | Z42: Летуаль | AA42: Биг–Л | AB42: =AJ9 -> 354043 | AC42: 0 | AD42: =AC42/AB42 -> 0 | AF42: =C91 -> 0.15 | AG42: =AD42 -> 0 | AH42: =AG42/AF42-1 -> -1
B43: Дельта от плана | D43: =D34-D41 -> 30131410 | F43: Дельта от плана | H43: =H34-H41 -> -1956580 | AA43: Смарт–Сэйл | AB43: =AJ10 -> 1090118 | AC43: 0 | AD43: =AC43/AB43 -> 0 | AF43: =G91 -> 0.15 | AG43: =AD43 -> 0 | AH43: =AG43/AF43-1 -> -1
B44: Прогноз по выручке | D44: =D34/$C$1*$G$1 -> 103370590 | F44: Прогноз по выручке | H44: =H34/$C$1*$G$1 -> 124247057 | K44: Рекламный расход , руб | L44: =SUM(M44:X44) -> 32224726 | M44: =C15 -> 10864870 | N44: =G15 -> 8821383 | O44: =C33 -> 4570538 | P44: =G33 -> 6664144 | Q44: =C72 -> 446593 | R44: =G72 -> 808166 | S44: =C88 -> 12690.93 | T44: =G88 -> 36341.09 | U44: 0 | V44: 0 | W44: 0 | X44: 0 | Z44: Золотое Яблоко | AA44: Биг–Л | AB44: =AJ11 -> 0 | AC44: 0 | AD44: =AC44/AB44 -> #DIV/0! | AF44: 0 | AG44: =AD44 -> #DIV/0! | AH44: =AG44/AF44-1 -> #DIV/0!
B45: Прогноз по выручке (%) | D45: =D44/D39 -> 1.4114111 | F45: Прогноз по выручке (%) | H45: =H44/H39 -> 0.98449664 | K45: ДРР , % | L45: =L44/L35 -> 0.08493285 | M45: =IFERROR(M44/M35, " ") -> 0.15900823 | N45: =IFERROR(N44/N35, " ") -> 0.11926527 | O45: =IFERROR(O44/O35, " ") -> 0.044215071 | P45: =IFERROR(P44/P35, " ") -> 0.053636232 | Q45: =IFERROR(Q44/Q35, " ") -> 0.17923204 | R45: =IFERROR(R44/R35, " ") -> 0.18138839 | S45: =IFERROR(S44/S35, " ") -> 0.035505262 | T45: =IFERROR(T44/T35, " ") -> 0.033043873 | ... X45: =IFERROR(X44/X35, " ") -> 0 | AA45: Смарт–Сэйл | AB45: =AJ12 -> 1079042 | AC45: 0 | AD45: =AC45/AB45 -> 0 | AF45: 0 | AG45: =AD45 -> 0 | AH45: =AG45/AF45-1 -> #DIV/0!
Z46: Магнит Маркет | AA46: Биг–Л | AB46: =AJ13 -> 1391 | AC46: 0 | AD46: =AC46/AB46 -> 0 | AF46: 0 | AG46: =AD46 -> 0 | AH46: =AG46/AF46-1 -> #DIV/0!
B47: Wildberries / Расход только рубли | K47: Прирост к прошлому месяцу , % | L47: =L40/L42-1 -> 0.15658836 | M47: =M40/M42-1 -> 0.50188858 | N47: =N40/N42-1 -> -0.0011071791 | O47: =O40/O42-1 -> 0.41141108 | P47: =P40/P42-1 -> -0.015503357 | Q47: =Q40/Q42-1 -> 0.55294865 | R47: =R40/R42-1 -> -0.025559291 | S47: =S40/S42-1 -> 0.3607614 | ... X47: =X40/X42-1 -> #DIV/0! | AA47: Смарт–Сэйл | AB47: =AJ14 -> 14588.2 | AC47: 0 | AD47: =AC47/AB47 -> 0 | AF47: 0 | AG47: =AD47 -> 0 | AH47: =AG47/AF47-1 -> #DIV/0!
B48: =B30 -> Биг–Л / Ноябрь | до | D48: =$D$4 -> 45991 | F48: =F30 -> Смарт / Ноябрь | до | H48: =$D$4 -> 45991 | K48: Прирост по направлениям , % | M48: =SUM(M40:N40)/SUM(M42:N42)-1 -> 0.19032367 | O48: =SUM(O40:P40)/SUM(O42:P42)-1 -> 0.14126771 | Q48: =SUM(Q40:R40)/SUM(Q42:R42)-1 -> 0.1247149 | S48: =SUM(S40:T40)/SUM(S42:T42)-1 -> 0.33689387 | U48: =SUM(U40:V40)/SUM(U42:V42)-1 -> -0.39873008 | W48: =SUM(W40:X40)/SUM(W42:X42)-1 -> #DIV/0! | AB48: =SUM(AB36:AB47) -> 3.7011462e+08 | AC48: =SUM(AC36:AC47) -> 27102678 | AD48: =AC48/AB48 -> 0.073227795 | AF48: =F142 -> 0.10545004 | AG48: =AD48 -> 0.073227795 | AH48: =AG48/AF48-1 -> -0.30556884
A49: =IFERROR(C49/$C$33, " ") -> 0 | B49: Затраты из РК | F49: Затраты из РК | I49: =IFERROR(G49/$G$33, " ") -> 0 | K49: Прирост к прошлому месяцу , руб | L49: =L40-L42 -> 51368182 | M49: =M40-M42 -> 22833607 | N49: =N40-N42 -> -81982.6 | O49: =O40-O42 -> 30131410 | P49: =P40-P42 -> -1956580 | Q49: =Q40-Q42 -> 887205 | R49: =R40-R42 -> -116865 | S49: =S40-S42 -> 94763 | ... X49: =X40-X42 -> 17685.2
A50: =IFERROR(C50/$C$33, " ") -> 0 | B50: Отзывы за баллы? | F50: Отзывы за баллы? | I50: =IFERROR(G50/$G$33, " ") -> 0 | K50: Прирост по направлениям , руб | M50: =SUM(M40:N40)-SUM(M42:N42) -> 22751624 | O50: =SUM(O40:P40)-SUM(O42:P42) -> 28174830 | Q50: =SUM(Q40:R40)-SUM(Q42:R42) -> 770340 | S50: =SUM(S40:T40)-SUM(S42:T42) -> 367216 | U50: =SUM(U40:V40)-SUM(U42:V42) -> -715563 | W50: =SUM(W40:X40)-SUM(W42:X42) -> 19734.2 | Z50: Рубли + Бонусы | AB50: реальная выручка | AC50: реклама | AD50: ДРР | AF50: ДРР план | AG50: ДРР факт | AH50: дельта
B51: Итого расходов | C51: 3591756 | F51: Итого расходов | G51: 2569910 | Z51: WB | AA51: Биг–Л | AB51: =AB36 -> 103176599 | AC51: =C33 -> 4570538 | AD51: =AC51/AB51 -> 0.044298204 | AF51: =AF36 -> 0.07 | AG51: =AD51 -> 0.044298204 | AH51: =AG51/AF51-1 -> -0.36716852
B52: Выручка | D52: =O35 -> 103370590 | F52: Выручка | H52: =P35 -> 124247057 | K52: хотим | L52: 400000000 | M52: =$L$52*M36 -> 72036297 | N52: =$L$52*N36 -> 77977472 | O52: =$L$52*O36 -> 108979158 | P52: =$L$52*P36 -> 1.3098832e+08 | Q52: =$L$52*Q36 -> 2626895.1 | R52: =$L$52*R36 -> 4697183.6 | S52: =$L$52*S36 -> 376831.48 | T52: =$L$52*T36 -> 1159453.8 | ... X52: =$L$52*X36 -> 18644.744 | AA52: Смарт–Сэйл | AB52: =AB37 -> 123878665 | AC52: =G33 -> 6664144 | AD52: =AC52/AB52 -> 0.053795736 | AF52: =AF37 -> 0.07 | AG52: =AD52 -> 0.053795736 | AH52: =AG52/AF52-1 -> -0.23148948
B53: ДРР / Факт | D53: =C51/D52 -> 0.034746401 | F53: ДРР / Факт | H53: =G51/H52 -> 0.02068387 | K53: осталось сделать | L53: =L52-L35 -> 20585837 | M53: =M52-M35 -> 3707318.7 | N53: =N52-N35 -> 4013078.8 | O53: =O52-O35 -> 5608568 | P53: =P52-P35 -> 6741260.4 | Q53: =Q52-Q35 -> 135192.09 | R53: =R52-R35 -> 241738.64 | S53: =S52-S35 -> 19393.479 | ... X53: =X52-X35 -> 959.54417 | Z53: Ozon | AA53: Биг–Л | AB53: =AB38 -> 64355951 | AC53: =AC38 -> 10864870 | AD53: =AC53/AB53 -> 0.16882464 | AF53: =AF38 -> 0.205 | AG53: =AD53 -> 0.16882464 | AH53: =AG53/AF53-1 -> -0.1764652
A54: =D53/C54 -> 0.49637716 | B54: ДРР / План | C54: 0.07 | D54: =D52*C54 -> 7235941.3 | F54: ДРР / План | G54: 0.07 | H54: =H52*G54 -> 8697294 | I54: =H53/G54 -> 0.29548386 | K54: нужно плато продаж | L54: =SUM(M54:V54) -> #DIV/0! | M54: =M53/($G$1-$C$1) -> #DIV/0! | N54: =N53/($G$1-$C$1) -> #DIV/0! | O54: =O53/($G$1-$C$1) -> #DIV/0! | P54: =P53/($G$1-$C$1) -> #DIV/0! | Q54: =Q53/($G$1-$C$1) -> #DIV/0! | R54: =R53/($G$1-$C$1) -> #DIV/0! | S54: =S53/($G$1-$C$1) -> #DIV/0! | T54: =T53/($G$1-$C$1) -> #DIV/0! | ... X54: =X53/($G$1-$C$1) -> #DIV/0! | AA54: Смарт–Сэйл | AB54: =AB39 -> 70026828 | AC54: =AC39 -> 8821383 | AD54: =AC54/AB54 -> 0.12597148 | AF54: =AF39 -> 0.115 | AG54: =AD54 -> 0.12597148 | AH54: =AG54/AF54-1 -> 0.095404151
B55: Перераход в деньгах | D55: =C51-D54 -> -3644185.3 | F55: Перераход в деньгах | H55: =G51-H54 -> -6127384 | Z55: ЯМаркет | AA55: Биг–Л | AB55: =AB40 -> 2174848.7 | AC55: =AC40 -> 446593 | AD55: =AC55/AB55 -> 0.2053444 | AF55: =AF40 -> 0.18 | AG55: =AD55 -> 0.2053444 | AH55: =AG55/AF55-1 -> 0.14080221
N56: 140000000 | AA56: Смарт–Сэйл | AB56: =AB41 -> 3962550.1 | AC56: =AC41 -> 808166 | AD56: =AC56/AB56 -> 0.20395099 | AF56: =AF41 -> 0.175 | AG56: =AD56 -> 0.20395099 | AH56: =AG56/AF56-1 -> 0.16543421
B57: План | D57: =O42 -> 73239180 | F57: План | H57: =P42 -> 126203637 | N57: =N56-SUM(M35:N35) -> -2293370.7 | Z57: Летуаль | AA57: Биг–Л | AB57: =AB42 -> 354043 | AC57: =AC42 -> 0 | AD57: =AC57/AB57 -> 0 | AF57: =AF42 -> 0.15 | AG57: =AD57 -> 0 | AH57: =AG57/AF57-1 -> -1
B58: Плато продаж | D58: =D52/$C$1 -> 3445686.3 | F58: Плато продаж | H58: =H52/$C$1 -> 4141568.6 | M58: =M35/SUM(M35:N35) -> 0.4801979 | N58: =N35/SUM(M35:N35) -> 0.5198021 | AA58: Смарт–Сэйл | AB58: =AB43 -> 1090118 | AC58: =AC43 -> 0 | AD58: =AC58/AB58 -> 0 | AF58: =AF43 -> 0.15 | AG58: =AD58 -> 0 | AH58: =AG58/AF58-1 -> -1
B59: Нужно сделать на вчера | D59: =D57/$G$1*$C$1 -> 73239180 | F59: Нужно сделать на вчера | H59: =H57/$G$1*$C$1 -> 126203637 | M59: =N57*M58 -> -1101271.8 | N59: =N57*N58 -> -1192098.9 | Z59: Золотое Яблоко | AA59: Биг–Л | AB59: =AB44 -> 0 | AC59: =AC44 -> 0 | AD59: =AC59/AB59 -> #DIV/0! | AF59: =AF44 -> 0 | AG59: =AD59 -> #DIV/0! | AH59: =AG59/AF59-1 -> #DIV/0!
B60: Нужно делать в день | D60: =(D57-D52)/($G$1-$C$1) -> #DIV/0! | F60: Нужно делать в день | H60: =(H57-H52)/($G$1-$C$1) -> #DIV/0! | L60: =SUM(M60:N60) -> #DIV/0! | M60: =M59/(G1-C1) -> #DIV/0! | N60: =N59/(G1-C1) -> #DIV/0! | AA60: Смарт–Сэйл | AB60: =AB45 -> 1079042 | AC60: =AC45 -> 0 | AD60: =AC60/AB60 -> 0 | AF60: =AF45 -> 0 | AG60: =AD60 -> 0 | AH60: =AG60/AF60-1 -> #DIV/0!
B61: Дельта от плана | D61: =D52-D59 -> 30131410 | F61: Дельта от плана | H61: =H52-H59 -> -1956580 | Z61: Магнит Маркет | AA61: Биг–Л | AB61: =AB46 -> 1391 | AC61: =AC46 -> 0 | AD61: =AC61/AB61 -> 0 | AF61: =AF46 -> 0 | AG61: =AD61 -> 0 | AH61: =AG61/AF61-1 -> #DIV/0!
B62: Прогноз по выручке | D62: =D52/$C$1*$G$1 -> 103370590 | F62: Прогноз по выручке | H62: =H52/$C$1*$G$1 -> 124247057 | M62: =M58 -> 0.4801979 | N62: =N58 -> 0.5198021 | AA62: Смарт–Сэйл | AB62: =AB47 -> 14588.2 | AC62: =AC47 -> 0 | AD62: =AC62/AB62 -> 0 | AF62: =AF47 -> 0 | AG62: =AD62 -> 0 | AH62: =AG62/AF62-1 -> #DIV/0!
B63: Прогноз по выручке (%) | D63: =D62/D57 -> 1.4114111 | F63: Прогноз по выручке (%) | H63: =H62/H57 -> 0.98449664 | M63: =$N$56*M62 -> 67227706 | N63: =$N$56*N62 -> 72772294 | AB63: =SUM(AB51:AB62) -> 3.7011462e+08 | AC63: =SUM(AC51:AC62) -> 32175694 | AD63: =AC63/AB63 -> 0.086934403 | AF63: =AF48 -> 0.10545004 | AG63: =AD63 -> 0.086934403 | AH63: =AG63/AF63-1 -> -0.17558683
B65: ЯМаркет | L65: =G1-C1 -> 0 | M65: =(M63-M35)/$L$65 -> #DIV/0! | N65: =(N63-N35)/$L$65 -> #DIV/0! | AB65: реальный план | AC65: реальная выручка | AD65: дельта | AF65: ДРР план | AG65: ДРР факт | AH65: дельта
B66: =B30 -> Биг–Л / Ноябрь | до | D66: =$D$4 -> 45991 | F66: =F30 -> Смарт / Ноябрь | до | H66: =$D$4 -> 45991 | Z66: WB | AA66: Биг–Л | AB66: =AD3 -> 73239180 | AC66: =AJ3 -> 103176599 | AD66: =IFERROR(AC66/AB66, " ") -> 1.4087623 | AF66: =AF51 -> 0.07 | AG66: =AG51 -> 0.044298204 | AH66: =AG66/AF66-1 -> -0.36716852
A67: =IFERROR(C67/$C$72, " ") -> 0.95559939 | B67: Буст продаж | C67: 426764 | F67: Буст продаж | G67: 776693 | I67: =IFERROR(G67/$G$72, " ") -> 0.96105627 | AA67: Смарт–Сэйл | AB67: =AD4 -> 126203637 | AC67: =AJ4 -> 123878665 | AD67: =IFERROR(AC67/AB67, " ") -> 0.98157761 | AF67: =AF52 -> 0.07 | AG67: =AG52 -> 0.053795736 | AH67: =AG67/AF67-1 -> -0.23148948
A68: =IFERROR(C68/$C$72, " ") -> 0.041041843 | B68: Буст показов | C68: 18329 | F68: Буст показов | G68: 29973 | I68: =IFERROR(G68/$G$72, " ") -> 0.037087678 | Z68: Ozon | AA68: Биг–Л | AB68: =AD5 -> 45495371 | AC68: =AJ5 -> 64355951 | AD68: =IFERROR(AC68/AB68, " ") -> 1.4145604 | AF68: =AF53 -> 0.205 | AG68: =AG53 -> 0.16882464 | AH68: =AG68/AF68-1 -> -0.1764652
A69: =IFERROR(C69/$C$72, " ") -> 0 | B69: Полки | F69: Полки | I69: =IFERROR(G69/$G$72, " ") -> 0 | AA69: Смарт–Сэйл | AB69: =AD6 -> 74046375 | AC69: =AJ6 -> 70026828 | AD69: =IFERROR(AC69/AB69, " ") -> 0.94571582 | AF69: =AF54 -> 0.115 | AG69: =AG54 -> 0.12597148 | AH69: =AG69/AF69-1 -> 0.095404151
A70: =IFERROR(C70/$C$72, " ") -> 0.0033587629 | B70: Охватное продвижение | C70: 1500 | F70: Охватное продвижение | G70: 1500 | I70: =IFERROR(G70/$G$72, " ") -> 0.0018560543 | Z70: ЯМаркет | AA70: Биг–Л | AB70: =AD7 -> 1604498 | AC70: =AJ7 -> 2174848.7 | AD70: =IFERROR(AC70/AB70, " ") -> 1.3554699 | AF70: =AF55 -> 0.18 | AG70: =AG55 -> 0.2053444 | AH70: =AG70/AF70-1 -> 0.14080221
A71: =IFERROR(C71/$C$72, " ") -> 0 | B71: Баннеры | F71: Баннеры | I71: =IFERROR(G71/$G$72, " ") -> 0 | AA71: Смарт–Сэйл | AB71: =AD8 -> 4572310 | AC71: =AJ8 -> 3962550.1 | AD71: =IFERROR(AC71/AB71, " ") -> 0.86664073 | AF71: =AF56 -> 0.175 | AG71: =AG56 -> 0.20395099 | AH71: =AG71/AF71-1 -> 0.16543421
B72: Итого расходов | C72: =SUM(C67:C71) -> 446593 | F72: Итого расходов | G72: =SUM(G67:G71) -> 808166 | Z72: Летуаль | AA72: Биг–Л | AB72: =AD9 -> 262675 | AC72: =AJ9 -> 354043 | AD72: =IFERROR(AC72/AB72, " ") -> 1.3478367 | AF72: =AF57 -> 0.15 | AG72: =AG57 -> 0 | AH72: =AG72/AF72-1 -> -1
B73: Выручка | D73: =Q35 -> 2491703 | F73: Выручка | H73: =R35 -> 4455445 | AA73: Смарт–Сэйл | AB73: =AD10 -> 827330 | AC73: =AJ10 -> 1090118 | AD73: =IFERROR(AC73/AB73, " ") -> 1.3176338 | AF73: =AF58 -> 0.15 | AG73: =AG58 -> 0 | AH73: =AG73/AF73-1 -> -1
B74: ДРР / Факт | D74: =C72/D73 -> 0.17923204 | F74: ДРР / Факт | H74: =G72/H73 -> 0.18138839 | Z74: Золотое Яблоко | AA74: Биг–Л | AB74: =AD11 -> 0 | AC74: =AJ11 -> 0 | AD74: =IFERROR(AC74/AB74, " ") | AF74: =AF59 -> 0 | AG74: =AG59 -> #DIV/0! | AH74: =AG74/AF74-1 -> #DIV/0!
A75: =D74/C75 -> 0.99573353 | B75: ДРР / План | C75: 0.18 | D75: =D73*C75 -> 448506.54 | F75: ДРР / План | G75: 0.175 | H75: =H73*G75 -> 779702.88 | I75: =H74/G75 -> 1.0365051 | AA75: Смарт–Сэйл | AB75: =AD12 -> 1794605 | AC75: =AJ12 -> 1079042 | AD75: =IFERROR(AC75/AB75, " ") -> 0.60126992 | AF75: =AF60 -> 0 | AG75: =AG60 -> 0 | AH75: =AG75/AF75-1 -> #DIV/0!
B76: Перераход в деньгах | D76: =C72-D75 -> -1913.54 | F76: Перераход в деньгах | H76: =G72-H75 -> 28463.125 | Z76: Магнит Маркет | AA76: Биг–Л | AB76: =AD13 -> 0 | AC76: =AJ13 -> 1391 | AD76: =IFERROR(AC76/AB76, " ") | AF76: =AF61 -> 0 | AG76: =AG61 -> 0 | AH76: =AG76/AF76-1 -> #DIV/0!
AA77: Смарт–Сэйл | AB77: =AD14 -> 0 | AC77: =AJ14 -> 14588.2 | AD77: =IFERROR(AC77/AB77, " ") | AF77: =AF62 -> 0 | AG77: =AG62 -> 0 | AH77: =AG77/AF77-1 -> #DIV/0!
B78: План | D78: =Q42 -> 1604498 | F78: План | H78: =R42 -> 4572310 | AB78: =SUM(AB66:AB77) -> 3.2804598e+08 | AC78: =SUM(AC66:AC77) -> 3.7011462e+08 | AD78: =IFERROR(AC78/AB78, " ") -> 1.1282401 | AF78: =AF63 -> 0.10545004 | AG78: =AG63 -> 0.086934403 | AH78: =AG78/AF78-1 -> -0.17558683
B79: Плато продаж | D79: =D73/$C$1 -> 83056.767 | F79: Плато продаж | H79: =H73/$C$1 -> 148514.83
B80: Нужно сделать на вчера | D80: =D78/$G$1*$C$1 -> 1604498 | F80: Нужно сделать на вчера | H80: =H78/$G$1*$C$1 -> 4572310 | AB80: Октябрь | AC80: Ноябрь | AH80: =AB80 -> Октябрь | AI80: =AC80 -> Ноябрь
B81: Нужно делать в день | D81: =(D78-D73)/($G$1-$C$1) -> #DIV/0! | F81: Нужно делать в день | H81: =(H78-H73)/($G$1-$C$1) -> #DIV/0! | AB81: реальная выручка | AC81: реальная выручка | AD81: дельта | AF81: Рубли + Бонусы | AH81: ДРР факт | AI81: ДРР факт | AJ81: дельта
B82: Разница от плана | D82: =D73-D80 -> 887205 | F82: Разница от плана | H82: =H73-H80 -> -116865 | Z82: WB | AA82: Биг–Л | AB82: ='Октябрь 25'!AA72 -> 72685329 | AC82: =AC66 -> 103176599 | AD82: =AC82/AB82-1 -> 0.4194969 | AF82: WB | AG82: Биг–Л | AH82: ='Октябрь 25'!AG72 -> 0.068856578 | AI82: =AG51 -> 0.044298204 | AJ82: =AI82/AH82-1 -> -0.35665981
B83: Прогноз по выручке | D83: =D73/$C$1*$G$1 -> 2491703 | F83: Прогноз по выручке | H83: =H73/$C$1*$G$1 -> 4455445 | AA83: Смарт–Сэйл | AB83: ='Октябрь 25'!AA73 -> 125083651 | AC83: =AC67 -> 123878665 | AD83: =AC83/AB83-1 -> -0.0096334412 | AG83: Смарт–Сэйл | AH83: ='Октябрь 25'!AG73 -> 0.071416224 | AI83: =AG52 -> 0.053795736 | AJ83: =AI83/AH83-1 -> -0.24672947
B84: Прогноз по выручке (%) | D84: =D83/D78 -> 1.5529486 | F84: Прогноз по выручке (%) | H84: =H83/H78 -> 0.97444071 | Z84: Ozon | AA84: Биг–Л | AB84: ='Октябрь 25'!AA74 -> 42706261 | AC84: =AC68 -> 64355951 | AD84: =AC84/AB84-1 -> 0.50694417 | AF84: Ozon | AG84: Биг–Л | AH84: ='Октябрь 25'!AG74 -> 0.19483508 | AI84: =AG53 -> 0.16882464 | AJ84: =AI84/AH84-1 -> -0.13349982
AA85: Смарт–Сэйл | AB85: ='Октябрь 25'!AA75 -> 70145511 | AC85: =AC69 -> 70026828 | AD85: =AC85/AB85-1 -> -0.0016919586 | AG85: Смарт–Сэйл | AH85: ='Октябрь 25'!AG75 -> 0.11896716 | AI85: =AG54 -> 0.12597148 | AJ85: =AI85/AH85-1 -> 0.058876094
B86: Летуаль | Z86: ЯМаркет | AA86: Биг–Л | AB86: ='Октябрь 25'!AA76 -> 1535419 | AC86: =AC70 -> 2174848.7 | AD86: =AC86/AB86-1 -> 0.41645292 | AF86: ЯМаркет | AG86: Биг–Л | AH86: ='Октябрь 25'!AG76 -> 0.19766852 | AI86: =AG55 -> 0.2053444 | AJ86: =AI86/AH86-1 -> 0.038832072
B87: =B66 -> Биг–Л / Ноябрь | до | D87: =$D$4 -> 45991 | F87: =F66 -> Смарт / Ноябрь | до | H87: =$D$4 -> 45991 | AA87: Смарт–Сэйл | AB87: ='Октябрь 25'!AA77 -> 4473055 | AC87: =AC71 -> 3962550.1 | AD87: =AC87/AB87-1 -> -0.11412892 | AG87: Смарт–Сэйл | AH87: ='Октябрь 25'!AG77 -> 0.18851657 | AI87: =AG56 -> 0.20395099 | AJ87: =AI87/AH87-1 -> 0.081872982
B88: Реклама | C88: 12690.93 | F88: Реклама | G88: 36341.09 | Z88: Летуаль | AA88: Биг–Л | AB88: ='Октябрь 25'!AA78 -> 231207 | AC88: =AC72 -> 354043 | AD88: =AC88/AB88-1 -> 0.53128149 | AF88: Летуаль | AG88: Биг–Л | AH88: ='Октябрь 25'!AG78 -> 0 | AI88: =AG57 -> 0 | AJ88: =AI88/AH88-1 -> #DIV/0!
B89: Выручка | D89: =S35 -> 357438 | F89: Выручка | H89: =T35 -> 1099783 | AA89: Смарт–Сэйл | AB89: ='Октябрь 25'!AA79 -> 748213 | AC89: =AC73 -> 1090118 | AD89: =AC89/AB89-1 -> 0.45696212 | AG89: Смарт–Сэйл | AH89: ='Октябрь 25'!AG79 -> 0 | AI89: =AG58 -> 0 | AJ89: =AI89/AH89-1 -> #DIV/0!
B90: ДРР / Факт | D90: =C88/D89 -> 0.035505262 | F90: ДРР / Факт | H90: =G88/H89 -> 0.033043873 | Z90: Золотое Яблоко | AA90: Биг–Л | AB90: ='Октябрь 25'!AA80 -> 0 | AC90: =AC74 -> 0 | AD90: =AC90/AB90-1 -> #DIV/0! | AF90: Золотое Яблоко | AG90: Биг–Л | AH90: ='Октябрь 25'!AG80 -> #DIV/0! | AI90: =AG59 -> #DIV/0! | AJ90: =AI90/AH90-1 -> #DIV/0!
B91: ДРР / План | C91: 0.15 | D91: =D89*C91 -> 53615.7 | F91: ДРР / План | G91: 0.15 | H91: =H89*G91 -> 164967.45 | AA91: Смарт–Сэйл | AB91: ='Октябрь 25'!AA81 -> 1708169 | AC91: =AC75 -> 1079042 | AD91: =AC91/AB91-1 -> -0.36830489 | AG91: Смарт–Сэйл | AH91: ='Октябрь 25'!AG81 -> 0 | AI91: =AG60 -> 0 | AJ91: =AI91/AH91-1 -> #DIV/0!
B92: Перераход в деньгах | D92: =C88-D91 -> -40924.77 | F92: Перераход в деньгах | H92: =G88-H91 -> -128626.36 | Z92: Магнит Маркет | AA92: Биг–Л | AB92: 0 | AC92: =AC76 -> 1391 | AD92: =AC92/AB92-1 -> #DIV/0! | AF92: Магнит Маркет | AG92: Биг–Л | AI92: =AG61 -> 0 | AJ92: =AI92/AH92-1 -> #DIV/0!
AA93: Смарт–Сэйл | AB93: 0 | AC93: =AC77 -> 14588.2 | AD93: =AC93/AB93-1 -> #DIV/0! | AG93: Смарт–Сэйл | AH93: ='Октябрь 25'!AG83 | AI93: =AG62 -> 0 | AJ93: =AI93/AH93-1 -> #DIV/0!
B94: План | D94: =S42 -> 262675 | F94: План | H94: =T42 -> 827330 | AB94: =SUM(AB82:AB93) -> 3.1931682e+08 | AC94: =SUM(AC82:AC93) -> 3.7011462e+08 | AD94: =AC94/AB94-1 -> 0.15908279 | AH94: ='Октябрь 25'!AG82 -> 0.099431982 | AI94: =AG63 -> 0.086934403 | AJ94: =AI94/AH94-1 -> -0.12568973
B95: Плато продаж | D95: =D89/$C$1 -> 11914.6 | F95: Плато продаж | H95: =H89/$C$1 -> 36659.433 | AD95: =AC94-AB94 -> 50797809
B96: Нужно сделать на вчера | D96: =D94/$G$1*$C$1 -> 262675 | F96: Нужно сделать на вчера | H96: =H94/$G$1*$C$1 -> 827330
B97: Нужно делать в день | D97: =(D94-D89)/($G$1-$C$1) -> #DIV/0! | F97: Нужно делать в день | H97: =(H94-H89)/($G$1-$C$1) -> #DIV/0!
B98: Разница от плана | D98: =D89-D96 -> 94763 | F98: Разница от плана | H98: =H89-H96 -> 272453
B99: Прогноз по выручке | D99: =D89/$C$1*$G$1 -> 357438 | F99: Прогноз по выручке | H99: =H89/$C$1*$G$1 -> 1099783
B100: Прогноз по выручке (%) | D100: =D99/D94 -> 1.3607614 | F100: Прогноз по выручке (%) | H100: =H99/H94 -> 1.329316
B102: Магнит
...

Sheet Октябрь 25
B1: Вчера | C1: 31 | F1: Дней в месяце | G1: 31 | S1: 86млн – весь лету / сентябрь
A2: Актуально на | B2: 45961 | M2: Оз | O2: Вб | Q2: Ям | S2: Лету | U2: ЗЯ | Z2: план | AA2: ауты | AB2: реальный план | AD2: выручка | AE2: отказы/возвраты | AF2: раздачи | AG2: выкупы | AH2: реальная выручка
B3: Ozon | M3: Биг–Л | N3: Смарт | O3: Биг–Л | P3: Смарт | Q3: Биг–Л | R3: Смарт | S3: Биг–Л | T3: Смарт | U3: Биг–Л | V3: Смарт | X3: WB | Y3: Биг–Л | Z3: =D39 -> 35109564 | AB3: =Z3-AA3 -> 35109564 | AD3: =O35 -> 73239180 | AF3: =10362+543489 -> 553851 | AH3: =AD3-SUM(AE3:AG3) -> 72685329
B4: Биг–Л / Октябрь | до | D4: 45961 | F4: Смарт / Октябрь | до | H4: =$D$4 -> 45961 | K4: 45931 | L4: =SUM(M4:V4) -> 9327513 | M4: 1219043 | N4: 2362845 | O4: 1619662 | P4: 3885289 | Q4: 31999 | R4: 129144 | S4: 3220 | T4: 13046 | V4: 63265 | Y4: Смарт–Сэйл | Z4: =H39 -> 109216574 | AB4: =Z4-AA4 -> 109216574 | AD4: =P35 -> 126203637 | AF4: =13403+1106583 -> 1119986 | AH4: =AD4-SUM(AE4:AG4) -> 125083651
A5: =IFERROR(C5/$C$15, " ") -> 0.87340863 | B5: Оплата за клик | C5: 7267352 | F5: Оплата за клик | G5: 6415627 | I5: =IFERROR(G5/$G$15, " ") -> 0.76879782 | K5: 45932 | L5: =SUM(M5:V5) -> 8799539.1 | M5: 1102784 | N5: 2059145.1 | O5: 1579881 | P5: 3811545 | Q5: 31912 | R5: 133083 | S5: 3804 | T5: 18066 | V5: 59319 | X5: Ozon | Y5: Биг–Л | Z5: =D21 -> 26956516 | AB5: =Z5-AA5 -> 26956516 | AD5: =M35 -> 45495371 | AE5: =AD5/46857*(2461+58) -> 2445799.8 | AF5: =7569+335741 -> 343310 | AH5: =AD5-SUM(AE5:AG5) -> 42706261
A6: =IFERROR(C6/$C$15, " ") -> 0.11194352 | B6: Оплата за заказ | C6: 931446 | F6: Оплата за заказ | G6: 1337891 | I6: =IFERROR(G6/$G$15, " ") -> 0.16032224 | K6: 45933 | L6: =SUM(M6:V6) -> 8467185 | M6: 1040727 | N6: 2063434 | O6: 1409576 | P6: 3697124 | Q6: 25720 | R6: 128548 | S6: 5762 | T6: 18986 | V6: 77308 | Y6: Смарт–Сэйл | Z6: =H21 -> 54265632 | AB6: =Z6-AA6 -> 54265632 | AD6: =N35 -> 74046375 | AE6: =AD6/80565*(3586+124) -> 3409818.8 | AF6: =8231+482814 -> 491045 | AH6: =AD6-SUM(AE6:AG6) -> 70145511
A7: =IFERROR(C7/$C$15, " ") -> 0 | B7: Медийка | C7: 0 | F7: Медийка | G7: 68409 | I7: =IFERROR(G7/$G$15, " ") -> 0.0081975916 | K7: 45934 | L7: =SUM(M7:V7) -> 8597094 | M7: 1031952 | N7: 2082398 | O7: 1503918 | P7: 3725867 | Q7: 33975 | R7: 132302 | S7: 9912 | T7: 24414 | V7: 52356 | X7: ЯМаркет | Y7: Биг–Л | Z7: =D78 -> 811287 | AB7: =Z7-AA7 -> 811287 | AD7: =Q35 -> 1604498 | AF7: =453+68626 -> 69079 | AH7: =AD7-SUM(AE7:AG7) -> 1535419
A8: =IFERROR(C8/$C$15, " ") -> 0.00072686384 | B8: Баллы за отзывы | C8: 6048 | F8: Баллы за отзывы | G8: 12641 | K8: 45935 | L8: =SUM(M8:V8) -> 10490847 | M8: 1130542 | N8: 2423173 | O8: 1581435 | P8: 5098431 | Q8: 25693 | R8: 137323 | S8: 11312 | T8: 16470 | V8: 66468 | Y8: Смарт–Сэйл | Z8: =H78 -> 3339067 | AB8: =Z8-AA8 -> 3339067 | AD8: =R35 -> 4572310 | AF8: =99255 -> 99255 | AH8: =AD8-SUM(AE8:AG8) -> 4473055
A9: =IFERROR(C9/$C$15, " ") -> 0.010776285 | B9: Бонусы продавца | C9: 89666 | F9: Бонусы продавца | G9: 155215 | I9: =IFERROR(G9/$G$15, " ") -> 0.018599734 | K9: 45936 | L9: =SUM(M9:V9) -> 9607909 | M9: 1092833 | N9: 2212456 | O9: 1632248 | P9: 4412919 | Q9: 37318 | R9: 142155 | S9: 5424 | T9: 21560 | V9: 50996 | X9: Летуаль | Y9: Биг–Л | Z9: =S42 -> 101466 | AB9: =Z9-AA9 -> 101466 | AD9: =S35 -> 262675 | AF9: =2205+29263 -> 31468 | AH9: =AD9-SUM(AE9:AG9) -> 231207
A10: =IFERROR(C10/$C$15, " ") -> 0 | B10: Рассылки | C10: 0 | F10: Рассылки | G10: 0 | I10: =IFERROR(G10/$G$15, " ") -> 0 | K10: 45937 | L10: =SUM(M10:V10) -> 9718589 | M10: 1186794 | N10: 2380755 | O10: 1762281 | P10: 4098091 | Q10: 52374 | R10: 158829 | S10: 8214 | T10: 30484 | V10: 40767 | Y10: Смарт–Сэйл | Z10: =T42 -> 364665 | AB10: =Z10-AA10 -> 364665 | AD10: =T35 -> 827330 | AF10: =650+78467 -> 79117 | AH10: =AD10-SUM(AE10:AG10) -> 748213
A11: =IFERROR(C11/$C$15, " ") -> 0.0030045628 | B11: Закрепление отзыва | C11: 25000 | F11: Закрепление отзыва | G11: 19600 | I11: =IFERROR(G11/$G$15, " ") -> 0.0023487084 | K11: 45938 | L11: =SUM(M11:V11) -> 9122470 | M11: 1246419 | N11: 2112887 | O11: 1753064 | P11: 3784105 | Q11: 41212 | R11: 107197 | S11: 5750 | T11: 24631 | V11: 47205 | X11: Золотое Яблоко | Y11: Биг–Л | Z11: =U42 -> 0 | AB11: =Z11-AA11 -> 0 | AD11: =U35 -> 0 | AH11: =AD11-SUM(AE11:AG11) -> 0
B12: Иные электронные услуги | C12: 0 | F12: Иные электронные услуги | G12: 328642 | K12: 45939 | L12: =SUM(M12:V12) -> 9534994.1 | M12: 1260469 | N12: 2341390.1 | O12: 1925588 | P12: 3726511 | Q12: 45762 | R12: 119085 | S12: 7602 | T12: 23781 | V12: 84806 | Y12: Смарт–Сэйл | Z12: =V42 -> 996378 | AB12: =Z12-AA12 -> 996378 | AD12: =V35 -> 1794605 | AF12: =3436+83000 -> 86436 | AH12: =AD12-SUM(AE12:AG12) -> 1708169
B13: Продвижение бренда | C13: 9 | F13: Продвижение бренда | G13: 126 | K13: 45940 | L13: =SUM(M13:V13) -> 9593651 | M13: 1305862 | N13: 2607713 | O13: 1705165 | P13: 3568083 | Q13: 38187 | R13: 263857 | S13: 6675 | T13: 27525 | V13: 70584 | Y13: итог | Z13: =SUM(Z3:Z12) -> 231161149 | AA13: =SUM(AA3:AA12) -> 0 | AB13: =SUM(AB3:AB12) -> 231161149 | AD13: =SUM(AD3:AD12) -> 3.2804598e+08 | AE13: =SUM(AE3:AE12) -> 5855618.6 | AF13: =SUM(AF3:AF12) -> 2873547 | AG13: =SUM(AG3:AG12) -> 0 | AH13: =SUM(AH3:AH12) -> 3.1931682e+08
B14: Ozon Рассрочка | C14: 1157 | F14: Ozon Рассрочка | G14: 6861 | K14: 45941 | L14: =SUM(M14:V14) -> 9106229 | M14: 1178482 | N14: 2340674 | O14: 1648022 | P14: 3569774 | Q14: 60455 | R14: 199755 | S14: 6679 | T14: 21773 | V14: 80615 | AF14: =AF13/AD13 -> 0.008759586
B15: Итого расходов | C15: =SUM(C5:C14) -> 8320678 | F15: Итого расходов | G15: =SUM(G5:G14) -> 8345012 | K15: 45942 | L15: =SUM(M15:V15) -> 10552985 | M15: 1224254 | N15: 2639505.1 | O15: 1968752 | P15: 4363983 | Q15: 52899 | R15: 187287 | S15: 4832 | T15: 35435 | V15: 76038
B16: Выручка | D16: =M35 -> 45495371 | F16: Выручка | H16: =N35 -> 74046375 | K16: 45943 | L16: =SUM(M16:V16) -> 9838514 | M16: 1194391 | N16: 2585888 | O16: 1943228 | P16: 3804228 | Q16: 56209 | R16: 166899 | S16: 7885 | T16: 21803 | V16: 57983
B17: ДРР / Факт | D17: =C15/D16 -> 0.18289065 | F17: ДРР / Факт | H17: =G15/H16 -> 0.1126998 | K17: 45944 | L17: =SUM(M17:V17) -> 9131740 | M17: 1286473 | N17: 2469992 | O17: 1908827 | P17: 3130653 | Q17: 44696 | R17: 189093 | S17: 2172 | T17: 22119 | V17: 77715 | Z17: Без вычетов | AD17: С вычетом всего
A18: =D17/C18 -> 0.89214951 | B18: ДРР / План | C18: 0.205 | D18: =D16*C18 -> 9326551.1 | F18: ДРР / План | G18: 0.115 | H18: =H16*G18 -> 8515333.2 | I18: =H17/G18 -> 0.9799983 | K18: 45945 | L18: =SUM(M18:V18) -> 9806979 | M18: 1553038 | N18: 2780838 | O18: 2019424 | P18: 3164830 | Q18: 62843 | R18: 126457 | S18: 6301 | T18: 23854 | V18: 69394 | Z18: план | AA18: выручка | AB18: дельта | AD18: реальный план | AE18: реальная выручка | AF18: дельта
B19: Перерасход в деньгах | D19: =C15-D18 -> -1005873.1 | F19: Перераход в деньгах | H19: =G15-H18 -> -170321.16 | K19: 45946 | L19: =SUM(M19:V19) -> 9949012.6 | M19: 1413970 | N19: 2635921.6 | O19: 2112643 | P19: 3442793 | Q19: 60686 | R19: 178766 | S19: 10033 | T19: 28153 | V19: 66047 | X19: WB | Y19: Биг–Л | Z19: =Z3 -> 35109564 | AA19: =AD3 -> 73239180 | AB19: =IFERROR(AA19/Z19, " ") -> 2.0860179 | AD19: =AB3 -> 35109564 | AE19: =AH3 -> 72685329 | AF19: =IFERROR(AE19/AD19, " ") -> 2.070243
K20: 45947 | L20: =SUM(M20:V20) -> 9471728 | M20: 1331642 | N20: 2527647 | O20: 2089733 | P20: 3233115 | Q20: 50518 | R20: 148368 | S20: 6861 | T20: 21734 | V20: 62110 | Y20: Смарт–Сэйл | Z20: =Z4 -> 109216574 | AA20: =AD4 -> 126203637 | AB20: =IFERROR(AA20/Z20, " ") -> 1.1555356 | AD20: =AB4 -> 109216574 | AE20: =AH4 -> 125083651 | AF20: =IFERROR(AE20/AD20, " ") -> 1.1452809
B21: План | D21: =M42 -> 26956516 | E21: 40000000 | F21: План | H21: =N42 -> 54265632 | K21: 45948 | L21: =SUM(M21:V21) -> 9897958 | M21: 1426287 | N21: 2341601 | O21: 2033321 | P21: 3808165 | Q21: 48733 | R21: 152718 | S21: 8767 | T21: 26578 | V21: 51788 | X21: Ozon | Y21: Биг–Л | Z21: =Z5 -> 26956516 | AA21: =AD5 -> 45495371 | AB21: =IFERROR(AA21/Z21, " ") -> 1.6877319 | AD21: =AB5 -> 26956516 | AE21: =AH5 -> 42706261 | AF21: =IFERROR(AE21/AD21, " ") -> 1.5842649
B22: Плато продаж | D22: =D16/$C$1 -> 1467592.6 | E22: =E21-D16 -> -5495371 | F22: Плато продаж | H22: =H16/$C$1 -> 2388592.8 | K22: 45949 | L22: =SUM(M22:V22) -> 11311455 | M22: 1492787 | N22: 2553560 | O22: 2552011 | P22: 4393980 | Q22: 43210 | R22: 158887 | S22: 9127 | T22: 41179 | V22: 66714 | Y22: Смарт–Сэйл | Z22: =Z6 -> 54265632 | AA22: =AD6 -> 74046375 | AB22: =IFERROR(AA22/Z22, " ") -> 1.364517 | AD22: =AB6 -> 54265632 | AE22: =AH6 -> 70145511 | AF22: =IFERROR(AE22/AD22, " ") -> 1.2926324
B23: Нужно сделать на вчера | D23: =D21/$G$1*$C$1 -> 26956516 | E23: =E22/(G1-C1) -> #DIV/0! | F23: Нужно сделать на вчера | H23: =H21/$G$1*$C$1 -> 54265632 | K23: 45950 | L23: =SUM(M23:V23) -> 11133284 | M23: 1710277 | N23: 2407202.1 | O23: 2796271 | P23: 3845205 | Q23: 97212 | R23: 163717 | S23: 7253 | T23: 35089 | V23: 71058 | X23: ЯМаркет | Y23: Биг–Л | Z23: =Z7 -> 811287 | AA23: =AD7 -> 1604498 | AB23: =IFERROR(AA23/Z23, " ") -> 1.9777194 | AD23: =AB7 -> 811287 | AE23: =AH7 -> 1535419 | AF23: =IFERROR(AE23/AD23, " ") -> 1.8925719
B24: Нужно делать в день | D24: =(D21-D16)/($G$1-$C$1) -> #DIV/0! | F24: Нужно делать в день | H24: =(H21-H16)/($G$1-$C$1) -> #DIV/0! | K24: 45951 | L24: =SUM(M24:V24) -> 11829779 | M24: 1809603 | N24: 2496151 | O24: 3022180 | P24: 4171463 | Q24: 68050 | R24: 151117 | S24: 9461 | T24: 38580 | V24: 63174 | Y24: Смарт–Сэйл | Z24: =Z8 -> 3339067 | AA24: =AD8 -> 4572310 | AB24: =IFERROR(AA24/Z24, " ") -> 1.3693376 | AD24: =AB8 -> 3339067 | AE24: =AH8 -> 4473055 | AF24: =IFERROR(AE24/AD24, " ") -> 1.3396122
B25: Дельта от плана | D25: =D16-D23 -> 18538855 | F25: Дельта от плана | H25: =H16-H23 -> 19780743 | K25: 45952 | L25: =SUM(M25:V25) -> 12960039 | M25: 1926981 | N25: 2445286 | O25: 3264604 | P25: 5057768 | Q25: 57231 | R25: 123923 | S25: 7204 | T25: 24050 | V25: 52992 | X25: Летуаль | Y25: Биг–Л | Z25: =Z9 -> 101466 | AA25: =AD9 -> 262675 | AB25: =IFERROR(AA25/Z25, " ") -> 2.5887982 | AD25: =AB9 -> 101466 | AE25: =AH9 -> 231207 | AF25: =IFERROR(AE25/AD25, " ") -> 2.2786648
B26: Прогноз по выручке | D26: =D16/$C$1*$G$1 -> 45495371 | F26: Прогноз по выручке | H26: =H16/$C$1*$G$1 -> 74046375 | K26: 45953 | L26: =SUM(M26:V26) -> 12188480 | M26: 1827161 | N26: 2667559.1 | O26: 2948725 | P26: 4482936 | Q26: 70335 | R26: 122345 | S26: 9051 | T26: 17055 | V26: 43313 | Y26: Смарт–Сэйл | Z26: =Z10 -> 364665 | AA26: =AD10 -> 827330 | AB26: =IFERROR(AA26/Z26, " ") -> 2.2687398 | AD26: =AB10 -> 364665 | AE26: =AH10 -> 748213 | AF26: =IFERROR(AE26/AD26, " ") -> 2.0517818
B27: Прогноз по выручке (%) | D27: =D26/D21 -> 1.6877319 | F27: Прогноз по выручке (%) | H27: =H26/H21 -> 1.364517 | K27: 45954 | L27: =SUM(M27:V27) -> 11343390 | M27: 1760641 | N27: 2293737 | O27: 2989814 | P27: 4019797 | Q27: 72665 | R27: 130254 | S27: 6377 | T27: 22042 | V27: 48063 | X27: Золотое Яблоко | Y27: Биг–Л | Z27: =Z11 -> 0 | AA27: =AD11 -> 0 | AB27: =IFERROR(AA27/Z27, " ") | AD27: =AB11 -> 0 | AE27: =AH11 -> 0 | AF27: =IFERROR(AE27/AD27, " ")
K28: 45955 | L28: =SUM(M28:V28) -> 12578271 | M28: 1824647 | N28: 2288475 | O28: 3637013 | P28: 4554963 | Q28: 73465 | R28: 117808 | S28: 8952 | T28: 20231 | V28: 52717 | Y28: Смарт–Сэйл | Z28: =Z12 -> 996378 | AA28: =AD12 -> 1794605 | AB28: =IFERROR(AA28/Z28, " ") -> 1.8011287 | AD28: =AB12 -> 996378 | AE28: =AH12 -> 1708169 | AF28: =IFERROR(AE28/AD28, " ") -> 1.7143785
B29: Wildberries / Расход бонусы + рубли | K29: 45956 | L29: =SUM(M29:V29) -> 13090943 | M29: 2098970 | N29: 2227084.1 | O29: 3743999 | P29: 4744009 | Q29: 66327 | R29: 130758 | S29: 8661 | T29: 21114 | V29: 50021 | Z29: =SUM(Z19:Z28) -> 231161149 | AA29: =SUM(AA19:AA28) -> 3.2804598e+08 | AB29: =IFERROR(AA29/Z29, " ") -> 1.4191225 | AD29: =SUM(AD19:AD24) -> 229698640 | AE29: =SUM(AE19:AE24) -> 3.1662923e+08 | AF29: =IFERROR(AE29/AD29, " ") -> 1.3784549
B30: =B4 -> Биг–Л / Октябрь | до | D30: =$D$4 -> 45961 | F30: =F4 -> Смарт / Октябрь | до | H30: =$D$4 -> 45961 | K30: 45957 | L30: =SUM(M30:V30) -> 11997117 | M30: 1705290 | N30: 2424895 | O30: 3582929 | P30: 4029869 | Q30: 69148 | R30: 130889 | S30: 8313 | T30: 15566 | V30: 30218
A31: =IFERROR(C31/$C$33, " ") -> 0.84802841 | B31: Затраты из РК | C31: 4244266 | F31: Затраты из РК | G31: 8684753 | I31: =IFERROR(G31/$G$33, " ") -> 0.9722099 | K31: 45958 | L31: =SUM(M31:V31) -> 12089133 | M31: 1737792 | N31: 2417236 | O31: 3308348 | P31: 4326129 | Q31: 73327 | R31: 124751 | S31: 19878 | T31: 41587 | V31: 40085 | X31: Только рубли | Z31: реальная выручка | AA31: реклама | AB31: ДРР | AD31: ДРР план | AE31: ДРР факт | AF31: дельта
A32: =IFERROR(C32/$C$33, " ") -> 0.15197159 | B32: Отзывы за баллы | C32: 760597 | F32: Отзывы за баллы | G32: 248249 | I32: =IFERROR(G32/$G$33, " ") -> 0.027790098 | K32: 45959 | L32: =SUM(M32:V32) -> 12392895 | M32: 1871922 | N32: 2364122 | O32: 3128964 | P32: 4701256 | Q32: 50229 | R32: 183849 | S32: 17100 | T32: 39825 | V32: 35628 | X32: WB | Y32: Биг–Л | Z32: =AH3 -> 72685329 | AA32: =C51 -> 5001850 | AB32: =AA32/Z32 -> 0.068815125 | AD32: =C36 -> 0.07 | AE32: =AB32 -> 0.068815125 | AF32: =AE32/AD32-1 -> -0.016926786
B33: Итого расходов | C33: =SUM(C31:C32) -> 5004863 | F33: Итого расходов | G33: =SUM(G31:G32) -> 8933002 | K33: 45960 | L33: =SUM(M33:V33) -> 12437930 | M33: 1852921 | N33: 2304647.1 | O33: 3119353 | P33: 4900410 | Q33: 26800 | R33: 120853 | S33: 17017 | T33: 56365 | V33: 39564 | Y33: Смарт–Сэйл | Z33: =AH4 -> 125083651 | AA33: =G51 -> 4782522 | AB33: =AA33/Z33 -> 0.038234589 | AD33: =G36 -> 0.07 | AE33: =AB33 -> 0.038234589 | AF33: =AE33/AD33-1 -> -0.45379158
B34: Выручка | D34: =O35 -> 73239180 | F34: Выручка | H34: =P35 -> 126203637 | K34: 45961 | L34: =SUM(M34:V34) -> 11678328 | M34: 1650417 | N34: 2188158 | O34: 2948201 | P34: 4650346 | Q34: 35308 | R34: 112293 | S34: 13076 | T34: 34235 | V34: 46294 | X34: Ozon | Y34: Биг–Л | Z34: =AH5 -> 42706261 | AA34: =C15 -> 8320678 | AB34: =AA34/Z34 -> 0.19483508 | AD34: =C18 -> 0.205 | AE34: =AB34 -> 0.19483508 | AF34: =AE34/AD34-1 -> -0.049584956
B35: ДРР / Факт | D35: =C33/D34 -> 0.068335869 | F35: ДРР / Факт | H35: =G33/H34 -> 0.070782445 | K35: =L35/C1 -> 10582128 | L35: =SUM(L4:L34) -> 3.2804598e+08 | M35: =SUM(M4:M34) -> 45495371 | N35: =SUM(N4:N34) -> 74046375 | O35: =SUM(O4:O34) -> 73239180 | P35: =SUM(P4:P34) -> 126203637 | Q35: =SUM(Q4:Q34) -> 1604498 | R35: =SUM(R4:R34) -> 4572310 | S35: =SUM(S4:S34) -> 262675 | ... V35: =SUM(V4:V34) -> 1794605 | Y35: Смарт–Сэйл | Z35: =AH6 -> 70145511 | AA35: =G15 -> 8345012 | AB35: =AA35/Z35 -> 0.11896716 | AD35: =G18 -> 0.115 | AE35: =AB35 -> 0.11896716 | AF35: =AE35/AD35-1 -> 0.034497008
