Workbook

Sheet Инфо по SKU
A1: А пон | D1: Андрей Л | E1: Андрей Л | F1: Вячеслав | G1: Продукты | H1: Продукты | K1: Вячеслав | L1: Анна З | M1: Анна З | N1: Анна З | O1: Анна З | P1: Анна З | Q1: Анна З | S1: Вячеслав | T1: Анна З | U1: Анна З | V1: Анна З | W1: Анна З | X1: Анна З | Y1: Анна З | AA1: Анна З | AB1: Анна З | AC1: Анна З | AD1: Анна З | AE1: Анна З | AF1: Анна З | AH1: Вячеслав | AI1: Маркетолог по МП | AJ1: Маркетолог по МП | AK1: Маркетолог по МП | AL1: Маркетолог по МП | AM1: Маркетолог по МП | AN1: Маркетолог по МП | AP1: Анна З | AQ1: Анна З | AR1: Анна З | AS1: Анна З | AT1: Анна З | AU1: Анна З | AW1: Маркетолог по МП | AX1: Маркетолог по МП | AY1: Маркетолог по МП | AZ1: Маркетолог по МП | BA1: Маркетолог по МП | BB1: Маркетолог по МП | BJ1: @dropdown | BL1: Продуктологи | BM1: Продуктологи | BN1: Продуктологи | BO1: Продуктологи | BP1: Продуктологи | BS1: Продуктологи | BT1: Аня З / Продуктологи | BU1: Продуктологи | BV1: Продуктологи | BW1: Продуктологи | BX1: Продуктологи | BY1: Продуктологи | BZ1: Продуктологи | CB1: Продуктологи | CC1: Продуктологи | CF1: Продуктологи / Аня З | CG1: Аня Клименко | CH1: Александра З | CI1: Александра З | CJ1: Александра З | CM1: Автоматом / Таблица инвентаризация себеса | CZ1: Маркетинг + Продукты | DA1: Маркетинг + Продукты | DB1: Маркетинг + Продукты | DC1: Александра З | DD1: Маркетинг + Продукты | DE1: Маркетинг + Продукты | DF1: Маркетинг + Продукты | DG1: Леша В | DH1: Леша В | DI1: Леша В | DJ1: Продукты + Леша В | DK1: Продукты + Леша В | DL1: Продукты + Леша В | DM1: Продукты + Леша В | DN1: Продукты + Леша В | DO1: Леша В | DP1: Леша В | DQ1: Леша В | DR1: Леша В | DS1: Леша В | DT1: Леша В | DU1: Леша В | DV1: Леша В | DW1: Леша В | DX1: Леша В | DY1: Леша В | DZ1: Леша В | EA1: Леша В | EB1: Леша В | EC1: Леша В | ED1: Леша В | EE1: Леша В | EF1: Леша В | EG1: Леша В | EH1: Леша В | EI1: Леша В | EJ1: Леша В | EK1: Леша В | EL1: Леша В | EM1: Леша В | EN1: Леша В | EO1: Леша В | EP1: Леша В | EQ1: Леша В | ER1: Леша В | ES1: Продукты + Леша В | ET1: Продукты + Леша В | EU1: Продукты + Леша В | EV1: Продукты + Леша В | EW1: Продукты + Леша В | EX1: Продукты + Леша В | EY1: Продукты + Леша В | EZ1: Продукты + Леша В | FA1: Продукты + Леша В | FB1: Продукты + Леша В | FC1: Продукты + Леша В | FD1: Продукты + Леша В | FE1: Продукты + Леша В | FF1: Продукты + Леша В | FG1: Продукты + Леша В | FH1: Продукты + Леша В
I2: Идентификация товаров | J2: Товар заведен | R2: SKU МП + 1С | Z2: Артикула МП | AG2: Наименования МП + 1С | AO2: Ссылки на товар | AV2: Категория товара на МП | BC2: Ответственные по МП | BK2: Документы и маркировка | BR2: Характеристики продукта | CE2: Макет / Дизайн / Этикетка | CL2: Производственный блок | CX2: Габариты товара & Логистический блок | DO2: new | DP2: new | DQ2: new | DR2: new | DS2: new | DT2: new | DU2: new | DV2: new | DW2: new | DX2: new | DY2: new | DZ2: new | EA2: new | EB2: new | EC2: new | ED2: new | EE2: new | EF2: new | EG2: new | EH2: new | EI2: new | EJ2: new | EK2: new | EL2: new | EM2: new | EN2: new | EO2: new | EP2: new | EQ2: new | ER2: new | ES2: будет заполняться постепенно
G3: Перепроверить / Влад / Сходится ли с 1с | AH3: копия столбца G | BO3: Аня З | BW3: спецификация | CA3: спецификация | CF3: спецификация | CM3: Инвентаризация себестоимости МП май 2024 | CZ3: new | DA3: new | DB3: new | DD3: new | DE3: new | DF3: new | DG3: Таблица от Вики | DO3: Габариты единицы товара с упаковкой | ES3: данных нет | ET3: данных нет | EU3: данных нет | EV3: данных нет | EW3: данных нет | EX3: данных нет | EY3: данных нет | EZ3: данных нет | FA3: данных нет | FB3: данных нет | FC3: данных нет | FD3: данных нет | FE3: данных нет | FF3: данных нет | FG3: данных нет | FH3: данных нет
D4: Актуальность товара | F4: Блок 1С | G4: Категории внутреннего распределения | BO4: kma.biz | BT4: new составы меняются | BU4: Рекомендации по применению Переименовываем | BY4: new | BZ4: Уточнить у Саши что имела ввиду | CA4: new | CG4: new | CI4: new | CJ4: new | CM4: Формулой | CO4: продукты | CR4: new | CS4: new | CT4: new | CU4: new | CV4: new | CY4: Файл от Вики / чат | CZ4: Необходимость доп упаковки | DD4: Требования МП по упаковке | DG4: Вид расходника | DJ4: Штука | DO4: Ozon | DT4: WB | DY4: YM | ED4: Лету | EI4: ЗЯ | EN4: Магнит Маркет | ES4: Блок – Смотка | EX4: Короб | FC4: Паллет
A5: Направление | B5: SKU | C5: Бренд | D5: Статус товара | E5: Комментарий | F5: Полное наименование | G5: Категория 1 | H5: Категория 2 | K5: 1С | L5: WB | M5: Ozon | N5: ЯМаркет | O5: Золотое Яблоко | P5: Летуаль | Q5: Магнит Маркет | S5: 1С | T5: WB | U5: Ozon | V5: ЯМаркет | W5: Золотое Яблоко | X5: Летуаль | Y5: Магнит Маркет | AA5: WB | AB5: Ozon | AC5: ЯМаркет | AD5: Золотое Яблоко | AE5: Летуаль | AF5: Магнит Маркет | AH5: 1С | AI5: WB | AJ5: Ozon | AK5: ЯМаркет | AL5: Золотое Яблоко | AM5: Летуаль | AN5: Магнит Маркет | AP5: WB | AQ5: Ozon | AR5: ЯМаркет | AS5: Золотое Яблоко | AT5: Летуаль | AU5: Магнит Маркет | AW5: WB | AX5: Ozon | AY5: ЯМаркет | AZ5: Золотое Яблоко | BA5: Летуаль | BB5: Магнит Маркет | BD5: WB | BE5: Ozon | BF5: ЯМаркет | BG5: Золотое Яблоко | BH5: Летуаль | BI5: Магнит Маркет | BL5: ШК | BM5: ТНВЭД | BN5: Документы качества | BO5: Ссылка на документы | BP5: Маркировка | BS5: Состав | BT5: Дата изменения состава | BU5: Применение | BV5: Противопоказания | BW5: Хранение | BX5: Количество | BY5: Форма выпуска | BZ5: Масса капсулы / таблетки | CA5: Срок годности на этикетке | CB5: Срок годности для нас | CC5: Продакт файл | CF5: Этикетка | CG5: Дата изменения | CH5: Этикетка (+ коробка) | CI5: Мокап | CJ5: Креативы | CM5: Себестоимость | CN5: Производитель | CO5: Альтернативный производитель | CP5: Контакты производителя | CQ5: Срок производства | CR5: Адрес производства | CS5: Срок доставки до нашего склада | CT5: Возможность отправлять прямо на МП | CU5: Типография этикетки | CV5: Контакт типографии | CY5: Необходимость доупаковки товара | CZ5: Oz | DA5: Wb | DB5: YM | DC5: Этикетка для склада | DD5: Oz | DE5: Wb | DF5: YM | DG5: Oz | DH5: Wb | DI5: YM | DJ5: Высота | DK5: Ширина | DL5: Глубина | DM5: Объем | DN5: Вес | DO5: Высота | DP5: Ширина | DQ5: Глубина | DR5: Объем | DS5: Вес | DT5: Высота | DU5: Ширина | DV5: Глубина | DW5: Объем | DX5: Вес | DY5: Высота | DZ5: Ширина | EA5: Глубина | EB5: Объем | EC5: Вес | ED5: Высота | EE5: Ширина | EF5: Глубина | EG5: Объем | EH5: Вес | EI5: Высота | EJ5: Ширина | EK5: Глубина | EL5: Объем | EM5: Вес | EN5: Высота | EO5: Ширина | EP5: Глубина | EQ5: Объем | ER5: Вес | ES5: Высота | ET5: Ширина | EU5: Глубина | EV5: Объем | EW5: Вес | EX5: Высота | EY5: Ширина | EZ5: Глубина | FA5: Объем | FB5: Количество | FC5: Высота | FD5: Ширина | FE5: Гоубина | FF5: Объем | FG5: Количество | FH5: Кратность коробов к ряду
A6: Биг-Л | B6: harly_paste_75ml_v2 | C6: Harly | D6: Актуальный | F6: Паста для вывода шерсти кошек ,Harly, 75 мл | G6: Корма и Кормовые добавки | H6: Витамины для кошек | K6: TRUE | L6: TRUE | M6: TRUE | N6: FALSE | O6: FALSE | P6: FALSE | Q6: FALSE | S6: HB101100407 | T6: harly_paste_75ml_v2 | U6: harly_paste_75ml_v2 | AA6: 473683865 | AB6: 2517120405 | AH6: Паста для вывода шерсти кошек ,Harly, 75 мл | AI6: Паста для вывода шерсти кошек и хорьков 75 мл | AJ6: Паста для вывода шерсти кошек и хорьков Harly 75 мл | AP6: https://www.wildberries.ru/catalog/473683865/detail.aspx | AQ6: https://www.ozon.ru/product/2517120405 | AW6: Пасты для животных | AX6: Паста для вывода шерсти кошек и хорьков Harly 75 мл | BD6: Алексей | BE6: Кристина | BF6: Анна Пирогова | BG6: Екатерина Доможирова | BH6: Екатерина Доможирова | BI6: Екатерина Доможирова | BL6: 4605543013096 | BM6: 2309909609 | BN6: ДС | BO6: https://drive.google.com/drive/folders/1PqXUMTMlCs1-1shAXBWFmXZz1thQTrG7 | BP6: меркурий, ЧЗ | BS6: масло растительное пищевое, гидролизат белковый, жир растительный, стабилизатор, экстракт солода, масло клещевины, волокна растительные пищевые, масло вазелиновое, лецитин соевый, экстракт кошачьей мяты, антиоксидант, консервант. | BU6: давать один раз в день до кормления или добавлять в корм: кошкам массой более 2 кг - 5 см пасты; кошкам массой до 2 кг, котятам, хорькам - 2 см пасты. В период линьки порцию можно увеличить вдвое. | BW6: Хранить в течение 12 месяцев при температуре от 0 до 25 ℃. Вскрытую упаковку рекомендуется хранить в холодильнике. | BX6: 75 | BY6: мл | CA6: 12 месяцев | CB6: 12 месяцев | CC6: https://docs.google.com/document/d/1XPxvc0_rnwY-m_Fi8Z3tguz_Y9D15h6gupsd_lqR5Tk/edit | CG6: 46083 | CH6: https://disk.yandex.ru/d/5CofSvNzSJz4RA | CM6: =IFERROR(VLOOKUP(B6,CC!A:D,4,0)," ") -> 145.43 | CN6: ООО "ВЕДА" | CP6: "Дмитрий Алексеев / Dmitry Alekseev Коммерческий директор ООО ""ВЕДА Вет-Фарм"" / Commercial Director VEDA Vet-Farm +7-919-766-6452 dmitriy.alexeev@vedaved.ru " | CQ6: 30 | CS6: 1 | CT6: нет | CY6: FALSE | CZ6: FALSE | DA6: FALSE | DB6: FALSE | DC6: ссылка на папку | DG6: Короб | DJ6: 5 | DK6: 15 | DL6: 5 | DM6: 375 | DN6: 0.092
A7: Биг-Л | B7: Harly_cat_support_100tabs | C7: Harly | D7: Актуальный | F7: Витамины для кастрированных котов, Harly, 100 таблеток | G7: Корма и Кормовые добавки | H7: Витамины для кошек | K7: TRUE | L7: TRUE | M7: TRUE | N7: TRUE | O7: FALSE | P7: FALSE | Q7: FALSE | S7: HB101100400 | T7: Harly_cat_support_100tabs | U7: Harly_cat_support_100tabs | V7: Harly_cat_support_100tabs | AA7: 163683380 | AB7: 1010948247 | AC7: 102632683755 | AH7: Витамины для кастрированных котов, Harly, 100 таблеток | AI7: Витамины для кастрированных и стерилизованных кошек | AJ7: Витамины для кастрированных и стерилизованных котов, 100 таблеток | AK7: Витамины для кошек кастрированных и стерилизованных котов, 100 таблеток | AP7: https://www.wildberries.ru/catalog/163683380/detail.aspx | AQ7: https://www.ozon.ru/product/1010948247 | AR7: https://market.yandex.ru/card/cat-support-dlya-kastrirovannykh-i-sterilizovannykh-kotov/103542519891?businessId=8291477&clid=8291477&model_id=44497703&distr_type=8&pp=605 | AW7: Витамины и добавки для животных | AX7: Витамины для кастрированных и стерилизованных котов, 100 таблеток | AY7: товары для животных / ветаптека / витамины для животных и птиц | BD7: Алексей | BE7: Кристина | BF7: Анна Пирогова | BG7: Екатерина Доможирова | BH7: Екатерина Доможирова | BI7: Екатерина Доможирова | BL7: 4605543011153 | BM7: 2309903100 | BN7: СТО 42310364-0042-2023 | BO7: https://drive.google.com/drive/folders/1EJ8QC9PqNnODOuu3qt12V3UPgRlQGVat | BP7: меркурий | BS7: лактоза; дрожжи пивные; фитокомплекс: листьев березы, створок фасоли, листьев подорожника большого, травы душицы, корней одуванчика, травы тысячелистника, цветков ноготков, травы зверобоя, цветков лабазника вязолистного, листьев мяты перечной, цветков ромашки; минеральный комплекс; мука рыбная; крахмал; стеарат кальция; L-карнитин; ПВП; таурин; сера; масло рыжиковое; краситель пищевой. | BU7: корм дают ежедневно по 1 г (2 шт.) 2 раза в день | BW7: при температуре от 0 до 25 oС | BX7: 100 | BY7: Таблетки | CA7: 18 месяцев | CB7: 18 месяцев | CC7: https://docs.google.com/document/d/1RTioq-2_e3hK5brYg7srNivrKihOx92EEEbnue87y00/edit?tab=t.0 | CF7: https://drive.google.com/drive/u/0/folders/1g_p7fO6i6NuPWi4GRMAvunnDvxfLGqJC | CM7: =IFERROR(VLOOKUP(B7,CC!A:D,4,0)," ") -> 53.65 | CN7: ООО "ВЕДА" | CP7: Дмитрий Алексеев / Dmitry Alekseev Коммерческий директор ООО "ВЕДА Вет-Фарм" / Commercial Director VEDA Vet-Farm +7-919-766-6452 dmitriy.alexeev@vedaved.ru | CQ7: 30 | CS7: 1 | CT7: нет | CY7: FALSE | CZ7: FALSE | DA7: FALSE | DB7: FALSE | DG7: Термо | DJ7: 4 | DK7: 8 | DL7: 4 | DM7: 128 | DN7: 0.06
A8: Биг-Л | B8: Harly_cat_teeth_bones_100tabs | C8: Harly | D8: Актуальный | E8: кд | F8: Витамины для костей для кошек, Harly, 100 таблеток | G8: Корма и Кормовые добавки | H8: Витамины для кошек | K8: TRUE | L8: TRUE | M8: TRUE | N8: TRUE | O8: FALSE | P8: FALSE | Q8: FALSE | S8: HB101100401 | T8: Harly_cat_teeth_bones_100tabs | U8: Harly_cat_teeth_bones_100tabs | V8: Harly_cat_teeth_bones_100tabs | AA8: 163688556 | AB8: 1018532111 | AC8: 102625995832 | AH8: Витамины для костей для кошек, Harly, 100 таблеток | AI8: Витамины для кошек для костей и зубов | AJ8: Витамины для кошек для костей и зубов, 100 таблеток | AK8: Витамины для кошек для костей и зубов, комплекс витаминов для кошек 100 таблеток | AP8: https://www.wildberries.ru/catalog/163688556/detail.aspx | AQ8: https://www.ozon.ru/product/1018532111 | AR8: https://market.yandex.ru/card/teeth--bones-funktsionalnyy-korm-dlya-zubov-i-kostey-dlya-koshek/103614081635?businessId=8291477&clid=8291477&model_id=44500665&distr_type=8&pp=605 | AW8: Витамины и добавки для животных | AX8: Витамины для кошек для костей и зубов, 100 таблеток | AY8: товары для животных / ветаптека / витамины для животных и птиц | BD8: Алексей | BE8: Кристина | BF8: Анна Пирогова | BG8: Екатерина Доможирова | BH8: Екатерина Доможирова | BI8: Екатерина Доможирова | BL8: 4605543011160 | BM8: 2309903100 | BN8: СТО 42310364-0043-2023 | BO8: https://drive.google.com/drive/folders/1mpyXfn29J6FjP1QVEKQT3NjykIDvNJyV | BP8: меркурий | BS8: дрожжи пивные, лактоза; крахмал; фитокомплекс: корневищ аира, травы хвоща полевого, цветков лабазника вязолистного, травы фиалки, листьев березы, листьев шалфея, корней лопуха, почек березовых, цветков ноготков, листьев мяты перечной, почек сосны; природный минеральный комплекс; паровая мука рыбная; гидролизат коллагена; L-карнитин; таурин; сера; стеарат кальция. | BU8: котятам по 0,5г - 1 г (1-2 шт) 2 раза в день; кошкам старше 8 месяцев по 1-1,5 г (2-3 шт) раза в день; длястареющим животных по 1 г (1) 2 раза в день | BW8: при температуре от 0 до 25 oС | BX8: 100 | BY8: Таблетки | CA8: 18 месяцев | CB8: 18 месяцев | CC8: https://docs.google.com/document/d/1nRMqrHOUL-HxNDtP1kKkagtZQlN6WmJEcH715UB0ctc/edit?tab=t.0 | CF8: https://drive.google.com/drive/u/0/folders/1g_p7fO6i6NuPWi4GRMAvunnDvxfLGqJC | CM8: =IFERROR(VLOOKUP(B8,CC!A:D,4,0)," ") -> 53.65 | CN8: ООО "ВЕДА" | CP8: Дмитрий Алексеев / Dmitry Alekseev Коммерческий директор ООО "ВЕДА Вет-Фарм" / Commercial Director VEDA Vet-Farm +7-919-766-6452 dmitriy.alexeev@vedaved.ru | CQ8: 30 | CS8: 1 | CT8: нет | CY8: FALSE | CZ8: FALSE | DA8: FALSE | DB8: FALSE | DG8: и тд | DJ8: 4 | DK8: 8 | DL8: 4 | DM8: 128 | DN8: 0.06
A9: Биг-Л | B9: harly_paste_75ml | C9: Harly | D9: Вывод | E9: Перезавели v2 | F9: Паста для вывода шерсти кошек ,Harly, 75 мл | G9: Корма и Кормовые добавки | H9: Витамины для кошек | K9: TRUE | L9: TRUE | M9: TRUE | N9: TRUE | O9: FALSE | P9: FALSE | Q9: FALSE | S9: HB101100408 | T9: harly_paste_75ml | U9: harly_paste_75ml | V9: harly_paste_75ml | AA9: 265523439 | AB9: 1711363073 | AC9: 103597697138 | AH9: Паста для вывода шерсти кошек ,Harly, 75 мл | AI9: Паста для вывода шерсти кошек и хорьков 75 мл | AJ9: Паста для вывода шерсти кошек и хорьков Harly 75 мл | AK9: Паста для вывода шерсти кошек и хорьков, мальт-паста для животных Harly 75 мл | AP9: https://www.wildberries.ru/catalog/265523439/detail.aspx | AQ9: https://www.ozon.ru/product/1711363073 | AR9: https://market.yandex.ru/card/harly-pasta-dlya-vyvedeniya-shersti/103614089888?businessId=8291477&clid=8291477&model_id=824211224&distr_type=8&pp=605 | AW9: Пасты для животных | AX9: Паста для вывода шерсти кошек и хорьков Harly 75 мл | AY9: товары для животных / ветаптека / витамины для животных и птиц | BD9: Выведено | BE9: Кристина | BF9: Анна Пирогова | BG9: Екатерина Доможирова | BH9: Екатерина Доможирова | BI9: Екатерина Доможирова | BL9: 4605543013096 | BM9: 2309909609 | BN9: ДС | BP9: меркурий, ЧЗ | BS9: Состав : масло растительное пищевое, гидролизат белковый, жир растительный, стабилизатор, экстракт солода, масло клещевины, волокна растительные пищевые, масло вазелиновое, лецитин соевый, экстракт кошачьей мяты, антиоксидант, консервант. | BU9: давать один раз в день до кормления или добавлять в корм: кошкам массой более 2 кг - 5 см пасты; кошкам массой до 2 кг, котятам, хорькам - 2 см пасты. В период линьки порцию можно увеличить вдвое. | BW9: Хранить в течение 12 месяцев при температуре от 0 до 25 ℃. Вскрытую упаковку рекомендуется хранить в холодильнике. | BX9: 75 | BY9: мл | CA9: 12 месяцев | CB9: 12 месяцев | CC9: https://docs.google.com/document/d/1XPxvc0_rnwY-m_Fi8Z3tguz_Y9D15h6gupsd_lqR5Tk/edit | CM9: =IFERROR(VLOOKUP(B9,CC!A:D,4,0)," ") -> 102 | CN9: ООО "ВЕДА" | CP9: Дмитрий Алексеев / Dmitry Alekseev Коммерческий директор ООО "ВЕДА Вет-Фарм" / Commercial Director VEDA Vet-Farm +7-919-766-6452 dmitriy.alexeev@vedaved.ru | CQ9: 30 | CS9: 1 | CT9: нет | CY9: FALSE | CZ9: FALSE | DA9: FALSE | DB9: FALSE | DJ9: 5 | DK9: 15 | DL9: 5 | DM9: 375 | DN9: 0.092
A10: Биг-Л | B10: Harly_Skin_Coat | C10: Harly | D10: Актуальный | F10: Витамины для здоровой шерсти для собак, Harly, 100 таблеток | G10: Корма и Кормовые добавки | H10: Витамины для собак | K10: TRUE | L10: TRUE | M10: TRUE | N10: TRUE | O10: FALSE | P10: FALSE | Q10: FALSE | S10: HB101100402 | T10: Harly_Skin_Coat | U10: Harly_Skin_Coat | V10: Harly_Skin_Coat | AA10: 150253274 | AB10: 884560852 | AC10: 102626212762 | AH10: Витамины для здоровой шерсти для собак, Harly, 100 таблеток | AI10: Витамины для собак и щенков для здоровой и красивой шерсти | AJ10: Витамины для собак и щенков для здоровой и красивой шерсти, 100 таблеток | AK10: Витамины для собак и щенков для здоровой и красивой шерсти, 100 таблеток | AP10: https://www.wildberries.ru/catalog/150253274/detail.aspx | AQ10: https://www.ozon.ru/product/884560852 | AR10: https://market.yandex.ru/card/skin--coat-funktsionalnyy-korm-dlya-sobak-dlya-shersti/103614081637?businessId=8291477&clid=8291477&model_id=44886188&distr_type=8&pp=605 | AW10: Витамины и добавки для животных | AX10: Витамины для собак и щенков для здоровой и красивой шерсти, 100 таблеток | AY10: товары для животных / ветаптека / витамины для животных и птиц | BD10: Алексей | BE10: Кристина | BF10: Анна Пирогова | BG10: Екатерина Доможирова | BH10: Екатерина Доможирова | BI10: Екатерина Доможирова | BL10: 4605543011092 | BM10: 2309903100 | BN10: СТО 42310364-0061-2022 | BO10: https://drive.google.com/drive/folders/1MFf-7yPFgLdMXDrXjcxVgFiVJH8U2vuD | BP10: меркурий | BS10: корней лопуха, листьев крапивы, листьев березы, цветков ромашки, травы чабреца, корневищ аира, травы череды, корней солодки, травы подмаренника, листьев подорожника, травы тысячелистника; минеральный комплекс; дрожжи пивные; L-карнитин; гидролизат коллагена; сера; вспомогательные компоненты. | BU10: щенкам и собакам мелких пород (10 кг) по 0,5г(1шт) 2 раза в день;собакам средних размеров (до 30 кг) по 1-1,5 г (2-3 шт) раза в день;собакам крупных размеров (свыше 30 кг) по 2,5 (5 шт) 2 раза в день | BW10: при температуре от 0 до 25 oС | BX10: 100 | BY10: таблеток | CA10: 18 месяцев | CB10: 18 месяцев | CC10: https://docs.google.com/document/d/1UikjX911kCO0UpzSvjsVdQLtyppRaN72OG_7o70i1iQ/edit?tab=t.0 | CF10: https://drive.google.com/drive/u/0/folders/1g_p7fO6i6NuPWi4GRMAvunnDvxfLGqJC | CM10: =IFERROR(VLOOKUP(B10,CC!A:D,4,0)," ") -> 53.4 | CN10: ООО "ВЕДА" | CP10: Дмитрий Алексеев / Dmitry Alekseev Коммерческий директор ООО "ВЕДА Вет-Фарм" / Commercial Director VEDA Vet-Farm +7-919-766-6452 dmitriy.alexeev@vedaved.ru | CQ10: 30 | CS10: 1 | CT10: нет | CY10: FALSE | CZ10: FALSE | DA10: FALSE | DB10: FALSE | DJ10: 4 | DK10: 8 | DL10: 4 | DM10: 128 | DN10: 0.06
A11: Биг-Л | B11: harly_dog_antiallergy_100tabs | C11: Harly | D11: Актуальный | F11: Витамины противоаллергические собакам, Harly, 100 таблеток | G11: Корма и Кормовые добавки | H11: Витамины для собак | K11: TRUE | L11: TRUE | M11: TRUE | N11: TRUE | O11: FALSE | P11: FALSE | Q11: FALSE | S11: HB101100405 | T11: harly_dog_antiallergy_100tabs | U11: harly_dog_antiallergy_100tabs | V11: harly_dog_antiallergy_100tabs | AA11: 232468472 | AB11: 1581829359 | AC11: 103527751380 | AH11: Витамины противоаллергические собакам, Harly, 100 таблеток | AI11: Витамины противоаллергические собакам | AJ11: Витамины противоаллергические собакам Harly Dog Anti-Allergy 100 таблеток | AK11: Витамины противоаллергические для собак Harly Dog Anti-Allergy 100 таблеток | AP11: https://www.wildberries.ru/catalog/232468472/detail.aspx | AQ11: https://www.ozon.ru/product/1581829359 | AR11: https://market.yandex.ru/card/anti-allergy-dlya-sobak--1/103542523691?businessId=8291477&clid=8291477&model_id=679202716&distr_type=8&pp=605 | AW11: Витамины и добавки для животных | AX11: Витамины противоаллергические собакам Harly Dog Anti-Allergy 100 таблеток | AY11: товары для животных / ветаптека / витамины для животных и птиц / витамины для животных и птиц | BD11: Алексей | BE11: Кристина | BF11: Анна Пирогова | BG11: Екатерина Доможирова | BH11: Екатерина Доможирова | BI11: Екатерина Доможирова | BL11: 4605543012471 | BM11: 2309903100 | BN11: N РОСС RU Д-RU.PA01.B.15564/24 от 16.04.2024 до 14.04.2027 | BO11: https://drive.google.com/drive/folders/1o1P40yl_7ZR8-xRy4wZf7EhJzyXZkr3- | BP11: меркурий | BS11: лактоза; дрожжи пищевые пивные сухие; фитокомплекс: травы сушеницы топяной, травы череды, травы тысячелистника, травы чистотела, почек березовых, листьев березы, листьев подорожника большого, корней лопуха, корней одуванчика, цветков ноготков; минеральный комплекс (кальция фосфат дефторированный); крахмал; стеарат кальция; L-карнитин; ПВП; сера кормовая; вкусо-ароматическая пищевая добавка «Бекон». | BU11: Рекомендации по кормлению: щенкам и собакам мелких пород (до 10 кг) по 0,5 г (1 шт.) 2 раза в день; собакам средних размеров (до 30 кг) по 1 – 1,5 г (2-3 шт.) 2 раза в день; собакам крупных размеров (свыше 30 кг) по 2,5 г (5 шт.) 2 раза в день. | BW11: при температуре от 0 до 25 oС | BX11: 100 | BY11: таблеток | CA11: 18 месяцев | CB11: 18 месяцев | CC11: https://docs.google.com/document/d/1Fy9Ve-kCbeluAI0L32QSpa4uGjqvZAu9KV47IS7glV4/edit | CM11: =IFERROR(VLOOKUP(B11,CC!A:D,4,0)," ") -> 53.75 | CN11: ООО "ВЕДА" | CP11: Дмитрий Алексеев / Dmitry Alekseev Коммерческий директор ООО "ВЕДА Вет-Фарм" / Commercial Director VEDA Vet-Farm +7-919-766-6452 dmitriy.alexeev@vedaved.ru | CQ11: 30 | CS11: 1 | CT11: нет | CY11: FALSE | CZ11: FALSE | DA11: FALSE | DB11: FALSE | DJ11: 4 | DK11: 8 | DL11: 4 | DM11: 128 | DN11: 0.06
A12: Биг-Л | B12: Harly_Joint_Care | C12: Harly | D12: Актуальный | F12: Витамины для костей суставов для собак, Harly, 100 таблеток | G12: Корма и Кормовые добавки | H12: Витамины для собак | K12: TRUE | L12: TRUE | M12: TRUE | N12: TRUE | O12: FALSE | P12: FALSE | Q12: FALSE | S12: HB101100403 | T12: Harly_Joint_Care | U12: Harly_Joint_Care | V12: Harly_Joint_Care | AA12: 150262548 | AB12: 884578393 | AC12: 102626212766 | AH12: Витамины для костей суставов для собак, Harly, 100 таблеток | AI12: Витамины для собак и щенков для костей суставов и связок | AJ12: Витамины для собак и щенков для костей суставов и связок 100 таблеток | AK12: Витамины для собак и щенков для костей суставов и связок 100 таблеток | AP12: https://www.wildberries.ru/catalog/150262548/detail.aspx | AQ12: https://www.ozon.ru/product/884578393 | AR12: https://market.yandex.ru/card/joint-care-funktsionalnyy-korm-dlya-sobak-dlya-sustavov/103542518194?businessId=8291477&clid=8291477&model_id=44500663&distr_type=8&pp=605 | AW12: Витамины и добавки для животных | AX12: Витамины для собак и щенков для костей суставов и связок 100 таблеток | AY12: товары для животных / ветаптека / витамины для животных и птиц | BD12: Алексей | BE12: Кристина | BF12: Анна Пирогова | BG12: Екатерина Доможирова | BH12: Екатерина Доможирова | BI12: Екатерина Доможирова | BL12: 4605543011085 | BM12: 2309903100 | BN12: СТО 42310364-0060-2022 | BO12: https://drive.google.com/drive/folders/1IQ51gbZJ8MzYP29NXeoOOScaQ0jQZK3C | BP12: меркурий | BS12: коры дуба, листьев эвкалипта, корней окопника, корневищ аира, травы фиалки, листьев березы, корней одуванчика, травы зверобоя, побегов багульника, цветков лабазника вязолистного; дрожжи пивные; гидролизат коллагена; L-карнитин; сера; витамин D3; вспомогательные компоненты. | BU12: корм дают ежедневно по 1 г (2 шт.) 2 раза в день | BW12: при температуре от 0 до 25 oС | BX12: 100 | BY12: таблеток | CA12: 18 месяцев | CB12: 18 месяцев | CC12: https://docs.google.com/document/d/1P2KK6r50RbQvRpU3E3b6nd7ld16cP7H7MoVk9M_1Ums/edit?tab=t.0 | CF12: https://drive.google.com/drive/u/0/folders/1g_p7fO6i6NuPWi4GRMAvunnDvxfLGqJC | CM12: =IFERROR(VLOOKUP(B12,CC!A:D,4,0)," ") -> 53.4 | CN12: ООО "ВЕДА" | CP12: Дмитрий Алексеев / Dmitry Alekseev Коммерческий директор ООО "ВЕДА Вет-Фарм" / Commercial Director VEDA Vet-Farm +7-919-766-6452 dmitriy.alexeev@vedaved.ru | CQ12: 30 | CS12: 1 | CT12: нет | CY12: FALSE | CZ12: FALSE | DA12: FALSE | DB12: FALSE | DJ12: 8 | DK12: 4 | DL12: 8 | DM12: 256 | DN12: 0.063
A13: Биг-Л | B13: harly_sardineoil_250ml | C13: Harly | D13: Новинка | F13: Harly масло сардины 250 мл | G13: Корма и Кормовые добавки | H13: Витамины для собак | K13: FALSE | L13: TRUE | M13: TRUE | N13: FALSE | O13: FALSE | P13: FALSE | Q13: FALSE | T13: harly_sardineoil_250ml | U13: harly_sardineoil_250ml | V13: harly_sardineoil_250ml | AA13: 786916846 | AB13: 3463925696 | AC13: 5077651579 | BE13: Семен | BL13: 4620290621547 | BM13: 2309109000 | BO13: https://drive.google.com/drive/u/0/folders/1f6GGEzLVv8y1ay2J45GONVZoZVXjddLa | BP13: ЧЗ | BS13: 100% масло сардины | BU13: одно нажатие дозатора – 1,15 мл. Суточная норма: на каждые 5 кг веса питомца – 1,15 мл. | BW13: Хранить в прохладном, защищенном от света месте (в летний период не выше 30 С). Вскрытый флакон хранить в холодильнике при температуре от +4 С до +8 С. | BX13: 250 | BY13: мл | CA13: 12 месяцев | CC13: https://docs.google.com/document/d/1BKKy3Blk0MIwdeRBkS6P1iBdo8cf4Nqv_AtheYEpn50/edit?tab=t.0 | CM13: =IFERROR(VLOOKUP(B13,CC!A:D,4,0)," ") | CN13: ООО Терра-пласт | CP13: Гордиенко Евгения Степановна (812)748-22-25(доб.101) +7(962)689-06-49 stm@gkfavorite.ru | CQ13: 30 | CY13: FALSE | CZ13: FALSE | DA13: FALSE | DB13: FALSE
A14: Биг-Л | B14: Harly_dog_teeth_bones_100tabs | C14: Harly | D14: Актуальный | F14: Витамины для костей для собак, ,Harly, 100 таблеток | G14: Корма и Кормовые добавки | H14: Витамины для собак | K14: TRUE | L14: TRUE | M14: TRUE | N14: TRUE | O14: FALSE | P14: FALSE | Q14: FALSE | S14: HB101100404 | T14: Harly_dog_teeth_bones_100tabs | U14: Harly_dog_teeth_bones_100tabs | V14: Harly_dog_teeth_bones_100tabs | AA14: 163687757 | AB14: 1018530861 | AC14: 102621828617 | AH14: Витамины для костей для собак, ,Harly, 100 таблеток | AI14: Витамины для собак и щенков для костей и зубов | AJ14: Витамины для собак и щенков для костей и зубов, 100 таблеток | AK14: Витамины для собак и щенков для костей и зубов, 100 таблеток | AP14: https://www.wildberries.ru/catalog/163687757/detail.aspx | AQ14: https://www.ozon.ru/product/1018530861 | AR14: https://market.yandex.ru/card/teeth--bones-funktsionalnyy-korm-dlya-zubov-i-kostey-dlya-sobak/103614081636?businessId=8291477&clid=8291477&model_id=44502679&distr_type=8&pp=605 | AW14: Витамины и добавки для животных | AX14: Витамины для собак и щенков для костей и зубов, 100 таблеток | AY14: товары для животных / ветаптека / витамины для животных и птиц | BD14: Алексей | BE14: Кристина | BF14: Анна Пирогова | BG14: Екатерина Доможирова | BH14: Екатерина Доможирова | BI14: Екатерина Доможирова | BL14: 4605543011177 | BM14: 2309903100 | BN14: СТО 42310364-0044-2023 | BO14: https://drive.google.com/drive/folders/1p5gWqcP76Vsv2Evi4DwpeTeky0kE3iyV | BP14: меркурий | BS14: лактоза; дрожжи пивные; фитокомплекс: корневищ аира, травы хвоща полевого, цветков лабазника вязолистного, травы фиалки, листьев березы, листьев шалфея, корней лопуха, почек березовых, цветков ноготков, листьев мяты перечной, почек сосны; минеральный комплекс; крахмал; стеарат кальция; L-карнитин; ПВП; гидролизат коллагена; ароматическая пищевая добавка; сера. | BU14: щенкам и собакам мелких пород (10 кг) по 0,5г(1шт) 2 раза в день;собакам средних размеров (до 30 кг) по 1-1,5 г (2-3 шт) раза в день;собакам крупных размеров (свыше 30 кг) по 2,5 (5 шт) 2 раза в день | BW14: при температуре от 0 до 25 oС | BX14: 100 | BY14: таблеток | CA14: 18 месяцев | CB14: 18 месяцев | CC14: https://docs.google.com/document/d/1GIhxI6rjxcKWcXkVQWFOUMR8k_q55sJ6ghopBpX2UKc/edit?tab=t.0 | CF14: https://drive.google.com/drive/u/0/folders/1g_p7fO6i6NuPWi4GRMAvunnDvxfLGqJC | CM14: =IFERROR(VLOOKUP(B14,CC!A:D,4,0)," ") -> 53.4 | CN14: ООО "ВЕДА" | CP14: Дмитрий Алексеев / Dmitry Alekseev Коммерческий директор ООО "ВЕДА Вет-Фарм" / Commercial Director VEDA Vet-Farm +7-919-766-6452 dmitriy.alexeev@vedaved.ru | CQ14: 30 | CS14: 1 | CT14: нет | CY14: FALSE | CZ14: FALSE | DA14: FALSE | DB14: FALSE | DJ14: 4 | DK14: 8 | DL14: 4 | DM14: 128 | DN14: 0.06
A15: Биг-Л | B15: Harly_dogcat_probiotics_20tabs | C15: Harly | D15: Актуальный | F15: Пребиотик для собак и кошек ,Harly, 20 таб | G15: Корма и Кормовые добавки | H15: Витамины общие | K15: TRUE | L15: TRUE | M15: TRUE | N15: TRUE | O15: FALSE | P15: FALSE | Q15: FALSE | S15: HB101100409 | T15: Harly_dogcat_probiotics_20tabs | U15: Harly_dogcat_probiotics_20tabs | V15: Harly_dogcat_probiotics_20tabs | AA15: 232465954 | AB15: 1581825452 | AC15: 103510407614 | AH15: Пребиотик для собак и кошек ,Harly, 20 таб | AI15: Пробиотик для собак и кошек лактобактерии для профилактики | AJ15: Пребиотик для собак и кошек лактобактерии для профилактики жкт | AK15: Пробиотик для собак и кошек лактобактерии для профилактики жкт, витамины для животных 20 шт. в упаковке | AP15: https://www.wildberries.ru/catalog/232465954/detail.aspx | AQ15: https://www.ozon.ru/product/1581825452 | AR15: https://market.yandex.ru/card/dog-and-cat-probiotics--1/103542563878?businessId=8291477&clid=8291477&model_id=616053073&distr_type=8&pp=605 | AW15: Витамины и добавки для животных | AX15: Пребиотик для собак и кошек лактобактерии для профилактики жкт | AY15: товары для животных / ветаптека / ветеринарные препараты | BD15: Алексей | BE15: Семен | BF15: Анна Пирогова | BG15: Екатерина Доможирова | BH15: Екатерина Доможирова | BI15: Екатерина Доможирова | BL15: 4605543012495 | BM15: 2309903100 | BN15: N РОСС RU Д-RU.PA01.B.15696/24 от 16.04.2024 до 15.04.2027 | BO15: https://drive.google.com/drive/folders/1L065BxHDMUdVQxodAmNqzK24QFsduBfI | BP15: меркурий | BS15: комплекс лиофильно высушенных культур пробиотических бактерий - бифидобактерий, лактобактерий, стрептококков; вспомогательные компоненты: лактоза, крахмал, стеарат кальция. | BU15: Рекомендации по кормлению: функциональный корм дают 2 раза в сутки из расчета: собакам - по 1 таблетке на каждые 10 кг массы; кошкам и собакам мелких пород - по 1 таблетке; щенкам мелких пород, котятам, хорькам и грызунам - по 1 таблетке. Можно растворять в воде для выпаивания или смешивать с небольшим количеством любимого корма. Продолжительность включения в рацион 5-10 дней. Ограничений для применения и несовместимости с различными рационами и кормами не выявлено. | BW15: Хранить в течение 12 месяцев при температуре от 0 до 10 ºС. Допускается хранение не более 10 суток при температуре до 25 ºС. | BX15: 20 | BY15: таблеток | CA15: 1 год | CB15: 12 месяцев | CC15: https://docs.google.com/document/d/16CMvYUaTc8W6xLuW6xuJqCabd0q3Dqms08x9tXcTvjI/edit | CM15: =IFERROR(VLOOKUP(B15,CC!A:D,4,0)," ") -> 51.86 | CN15: ООО "ВЕДА" | CP15: Дмитрий Алексеев / Dmitry Alekseev Коммерческий директор ООО "ВЕДА Вет-Фарм" / Commercial Director VEDA Vet-Farm +7-919-766-6452 dmitriy.alexeev@vedaved.ru | CQ15: 30 | CS15: 1 | CT15: нет | CY15: FALSE | CZ15: FALSE | DA15: FALSE | DB15: FALSE | DJ15: 5 | DK15: 8 | DL15: 5 | DM15: 200 | DN15: 0.018
A16: Биг-Л | B16: qeep_perfect_spray_200ml | C16: qeep | D16: Актуальный | E16: Внимание, Цена ВБ | F16: Спрей солевой для объема волос, ,qeep, 200 мл | G16: Косметика | H16: Волосы | K16: TRUE | L16: TRUE | M16: TRUE | N16: TRUE | O16: TRUE | P16: FALSE | Q16: TRUE | S16: QC101100405 | T16: qeep_perfect_spray_200ml | U16: qeep_perfect_spray_200ml | V16: qeep_perfect_spray_200ml | W16: qeep_perfect_spray_200ml | Y16: qeep_perfect_spray_200ml | AA16: 377788941 | AB16: 2018960887 | AC16: 4315768672 | AD16: 99000115784 | AF16: QEEP-SOLEVSP | AH16: Спрей солевой для объема волос, ,qeep, 200 мл | AI16: Спрей для объема и укладки волос с фиксацией | AJ16: Спрей для волос солевой для объема и укладки волос с фиксацией qeep 200 мл | AK16: Спрей для объема и укладки волос с фиксацией, прикорневой объем волос qeep, 200 мл | AL16: Спрей для волос солевой для объема и укладки волос с фиксацией, qeep, 200 мл | AN16: Спрей для волос солевой для объема и укладки волос с фиксацией qeep 200 мл | AP16: https://www.wildberries.ru/catalog/377788941/detail.aspx | AQ16: https://www.ozon.ru/product/2018960887 | AR16: https://market.yandex.ru/card/sprey-dlya-obyema-i-ukladki-volos-s-fiksatsiyey-qeep-200-ml/4315768672?businessId=8291477&clid=8291477&model_id=1103677448&distr_type=8&pp=605 | AU16: https://mm.ru/product/sprej-dlya-volos-5898539?skuId=13170083 | AW16: Спреи | AX16: Спрей для волос солевой для объема и укладки волос с фиксацией qeep 200 мл | AY16: товары для красоты / косметика, парфюмерия и уход / уход за волосами / для укладки / лаки и спреи | AZ16: Уход для волос | BB16: Спреи | BD16: Мария | BE16: Кристина | BF16: Анна Пирогова | BG16: Екатерина Доможирова | BH16: Екатерина Доможирова | BI16: Екатерина Доможирова | BL16: 4670020498420 | BM16: 3305900009 | BN16: ДС | BO16: https://drive.google.com/drive/folders/1tkb0VjzFG6nTETD90FvT27TX2vLzgDjy | BP16: без ЧЗ | BS16: Вода очищенная, поливинилпирролидон, соль морская, мочевина, carepol 99, натрия гидроокись, молочная кислота, парфюмерная композиция, ПЭГ-40 гидрогенезированное касторовое масло, гидролизат кератина, Д-пантенол, феноксиэтанол, этилгексилглицерин, экстракт розмарина, экстракт орхидеи, твин 20. | BU16: хорошо встряхнуть флакон перед применением. Распылить на волосы, распределить руками по длине. Придайте волосам нужную форму своими руками. Дать волосам высохнуть естественным путём или с помощью фена. Не смывать. При необходимости повторить. | BW16: хранят при температуре не ниже 5˚С и не выше 25˚ Не допускается хранить продукцию под непосредственным воздействием солнечного света и вблизи отопительных приборов. | BX16: 200 | BY16: мл | CA16: 24 месяца | CB16: 24 месяца | CC16: https://docs.google.com/document/d/1as7qSPL_FDh8Gb9PLz5CNARde-H9drK_5pJMeQf_GK8/edit?tab=t.0 | CM16: =IFERROR(VLOOKUP(B16,CC!A:D,4,0)," ") -> 99.5 | CN16: ООО ПКФ Две линии (Алтэя) | CP16: Мария Чуйкова +7 (3854) 30-30-87 https://productaltai.com/ www.dvelinii.com моб., WhatsApp 8-903-948-3450 Алтайский край, г. Бийск, ул.Социалистическая д.11, стр. 1 | CQ16: 90 | CS16: 5 | CT16: нет | CY16: FALSE | CZ16: FALSE | DA16: FALSE | DB16: FALSE | DJ16: 5 | DK16: 16 | DL16: 5 | DM16: 400 | DN16: 0.228
A17: Биг-Л | B17: qeep_dlyarostavolos_100ml | C17: qeep | D17: Актуальный | E17: Внимание, Цена ВБ | F17: Спрей для роста и от выпадения волос ,qeep, 100 мл | G17: Косметика | H17: Волосы | K17: TRUE | L17: TRUE | M17: TRUE | N17: TRUE | O17: TRUE | P17: TRUE | Q17: FALSE | S17: QC101100406 | T17: qeep_dlyarostavolos_100ml | U17: qeep_dlyarostavolos_100ml | V17: qeep_dlyarostavolos_100ml | W17: qeep_dlyarostavolos_100ml | X17: qeep_dlyarostavolos_100ml | AA17: 449423638 | AB17: 2354324278 | AC17: 4909516637 | AD17: 99000115954 | AE17: MPL494786 | AH17: Спрей для роста и от выпадения волос ,qeep, 100 мл | AI17: Спрей сыворотка для роста волос | AJ17: Спрей для волос, для роста и от выпадения волос qeep 100 мл | AK17: Спрей для роста и от выпадения волос, сыворотка для роста волос активатор qeep 100 мл | AL17: спрей для волос, для роста и от выпадения волос, qeep, 100 мл | AM17: Спрей для волос, для роста и от выпадения волос | AP17: https://www.wildberries.ru/catalog/449423638/detail.aspx | AQ17: https://www.ozon.ru/product/2354324278 | AR17: https://market.yandex.ru/card/sprey-dlya-rosta-i-ot-vypadeniya-volos-qeep-100-ml/4480600215?businessId=8291477&clid=8291477&model_id=4909516636&distr_type=8&pp=605 | AS17: https://goldapple.ru/catalogsearch/result?q=99000115954 | AT17: https://www.letu.ru/product/qeep-sprei-dlya-volos-dlya-rosta-i-ot-vypadeniya-volos/175700153 | AW17: Сыворотки | AX17: Спрей для волос, для роста и от выпадения волос qeep 100 мл | AY17: товары для красоты / косметика, парфюмерия и уход / уход за волосами / маски и сыворотки | AZ17: Уход для волос | BA17: Уход за волосами >> Уход за волосами >> Сыворотка для ухода за волосами | BD17: Мария | BE17: Кристина | BF17: Анна Пирогова | BG17: Екатерина Доможирова | BH17: Екатерина Доможирова | BI17: Екатерина Доможирова | BL17: 4603320465434 | BM17: 3305900009 | BN17: ЕАЭС N RU Д-RU.РА03.В.29743/25 от 10.04.2025 по 10.04.2030 | BO17: https://drive.google.com/drive/folders/1ejD8pLP3trBa83tKqhil3_9DZnl-zh1B | BP17: без ЧЗ | BS17: Aqua, Niacinamide, Hydroxyethyl Urea, Glycerin, Rosemary Extract, Acetyl Tetrapeptide-3, Capsicum Annuum Extract, D-Panthenol, Phenoxyethanol, PEG-40 Hydrogenated Castor Oil, Fragrance, Glycolic Acid, Oleanolic acid, 1,2-Hexanediol, Ethylhexylglycerin, Hexamethylindanopyran, Hexyl Cinnamal, Tetramethyl Acetyloctahydronaphthalenes, Pinene, D-Limonene | BU17: Встряхните флакон и равномерно распылить средство на сухую или влажную кожу головы, разделяя волосы на проборы. Провести легкий массаж. Средство не загрязняет кожу головы и не требует смывания. Рекомендуется для регулярного использования. | BW17: при температуре от 0 до 25 oС | BX17: 100 | BY17: мл | CA17: 36 месяцев | CB17: 36 месяцев | CC17: https://docs.google.com/document/d/12STKI-NMYfL1xbAqJUqIbh1TKTru8BF48TrgEiod520/edit?tab=t.0 | CG17: 46071 | CH17: https://disk.yandex.ru/d/uHOU2gc2rR089A | CM17: =IFERROR(VLOOKUP(B17,CC!A:D,4,0)," ") -> 135.47 | CN17: ООО «Марвел 420049, Республика Татарстан, г Казань, ул Павлюхина, д. 99б, помещ. 1027. | CO17: Эйвон Бьюти | CP17: 79196215060 Евгений | CQ17: 60 | CS17: 3 | CT17: нет | CY17: FALSE | CZ17: FALSE | DA17: FALSE | DB17: FALSE | DJ17: 9 | DK17: 13 | DL17: 9 | DM17: 1053 | DN17: 0.15
A18: Биг-Л | B18: qeep_hairspray_200ml | C18: qeep | D18: Актуальный | E18: Внимание, небольшой остаток держим | F18: Спрей термозащита для волос 17 в 1 ,qeep, 200 мл | G18: Косметика | H18: Волосы | K18: TRUE | L18: TRUE | M18: TRUE | N18: TRUE | O18: FALSE | P18: TRUE | Q18: FALSE | S18: QC101100407 | T18: qeep_hairspray_200ml | U18: qeep_hairspray_200ml | V18: qeep_hairspray_200ml | X18: qeep_hairspray_200ml | AA18: 268884161 | AB18: 1729383128 | AC18: 103578859652 | AE18: MPL405943 | AH18: Спрей термозащита для волос 17 в 1 ,qeep, 200 мл | AI18: Спрей для волос многофункциональный с кератином | AJ18: Спрей термозащита для волос 17 в 1 многофункциональный с кератином qeep 200 мл | AK18: Спрей для волос 17 в 1 многофункциональный с кератином qeep 200 мл | AM18: Спрей для волос 17 в 1 многофункциональный с кератином | AP18: https://www.wildberries.ru/catalog/268884161/detail.aspx | AQ18: https://www.ozon.ru/product/1729383128 | AR18: https://market.yandex.ru/card/sprey-dlya-volos-mnogofunktsionalnyy-s-keratinom-qeep-200-ml/103578859652?businessId=8291477&clid=8291477&model_id=1103677448&distr_type=8&pp=605 | AT18: https://www.letu.ru/product/qeep-sprei-dlya-volos-17-v-1-mnogofunktsionalnyi-s-keratinom/168000614?sort=default&open=ingredient&hide=expectedEffect | AW18: Спреи | AX18: Спрей термозащита для волос 17 в 1 многофункциональный с кератином qeep 200 мл | AY18: товары для красоты / косметика, парфюмерия и уход / уход за волосами / для укладки / лаки и спреи | BA18: Уход за волосами >> Уход за волосами >> Спрей для ухода за волосами | BD18: Мария | BE18: Кристина | BF18: Анна Пирогова | BG18: Екатерина Доможирова | BH18: Екатерина Доможирова | BI18: Екатерина Доможирова | BL18: 4670020498024 | BM18: 3305900009 | BN18: ДС | BO18: https://drive.google.com/drive/folders/1D9_9YHYClR7hdKWe5YPLWdcJy578H-4u | BP18: без ЧЗ | BS18: Aqua, Amodimethicone, Cetearyl Alcohol, Glycerin, Cetrimonium Chloride, Trideceth-12, Ceteareth 20, Polyquaternium-37, Behentrimonium Chloride, Lysine, Histidine, Arginine, Aspartic Acid, Threonine, Serine, Glutamic Acid, Proline, Glycine, Alanine, Valine, Methionine, Isoleucine, Leucine, Tyrosine, Phenylalanine, Cysteine, Sodium PCA, Glucose, Urea, Allantoin, Lactic Acid, Oenothera Biennis Oil, Retinyl Palmitate, Tocopheryl Acetate, Panthenol, Hydrolyzed Keratin, Hydrolysed Silk, Argania Spinosa Kernel Oil, PEG-7 Glyceryl Cocoate, Potassium Sorbate, Sodium Benzoate, Gluconolactone, Calcium Gluconate, PEG-40 Hydrogenated Castor Oil, Benzoic Acid, Dehydroacetic Acid, Parfum, Phenoxyethanol, Ethylhexylglycerin. | BU18: перед применением встряхните флакон. Нанесите средство на чистые и подсушенные волосы на расстоянии 10-20 см в необходимом количестве, распределите по длине волос. Приступите к укладке волос. | BW18: хранят при температуре не ниже 5˚С и не выше 25˚ Не допускается хранить продукцию под непосредственным воздействием солнечного света и вблизи отопительных приборов. | BX18: 200 | BY18: мл | CA18: 2 года | CB18: 24 месяца | CC18: https://docs.google.com/document/d/10J8C2tL_Ttlb0h2oWm5GtXjXdwtwyf_qKWKopwZQzFg/edit | CM18: =IFERROR(VLOOKUP(B18,CC!A:D,4,0)," ") -> 111.6 | CN18: ООО ПКФ Две линии (Алтэя) | CP18: Мария Чуйкова +7 (3854) 30-30-87 https://productaltai.com/ www.dvelinii.com моб., WhatsApp 8-903-948-3450 Алтайский край, г. Бийск, ул.Социалистическая д.11, стр. 1 | CQ18: 90 | CS18: 5 | CT18: нет | CY18: FALSE | CZ18: FALSE | DA18: FALSE | DB18: FALSE | DJ18: 4 | DK18: 18 | DL18: 4 | DM18: 288 | DN18: 0.23
A19: Биг-Л | B19: qeep_gummy_d3_60 | C19: qeep | D19: Под вопросом | E19: КЗ Внешка | F19: БАД Д3 мармеладки ,qeep, 60 штук | G19: БАДы | H19: Детские витамины | K19: TRUE | L19: TRUE | M19: TRUE | N19: TRUE | O19: TRUE | P19: FALSE | Q19: FALSE | S19: QB101100420 | T19: qeep_gummy_d3_60 | U19: qeep_gummy_d3_60 | V19: qeep_gummy_d3_60 | W19: qeep_gummy_d3_60 | AA19: 432821274 | AB19: 2214705163 | AC19: 4476305013 | AD19: 99000117740 | AH19: БАД Д3 мармеладки ,qeep, 60 штук | AI19: Витамин Д3 для детей жевательный | AJ19: Витамины для детей витамин Д3 жевательные мармеладки qeep 60 штук | AK19: Витамин Д3 для детей жевательный qeep 60 мармеладок, витамишки | AL19: витамины для детей витамин д3 жевательные мармеладки qeep со вкусом вишни 60 штук | AP19: https://www.wildberries.ru/catalog/432821274/detail.aspx | AQ19: https://www.ozon.ru/product/2214705163 | AR19: https://market.yandex.ru/card/vitamin-d3-dlya-detey-zhevatelnyy-qeep-60-marmeladok/4476305013?businessId=8291477&clid=8291477&model_id=1947049801&distr_type=8&pp=605 | AS19: https://goldapple.ru/catalogsearch/result?q=99000117740 | AW19: БАДы | AX19: Витамины для детей витамин Д3 жевательные мармеладки qeep 60 штук | AY19: аптека / витамины, минералы, добавки | AZ19: Бады витамины | BD19: Света | BE19: Семен | BF19: Анна Пирогова | BG19: Екатерина Доможирова | BH19: Екатерина Доможирова | BI19: Екатерина Доможирова | BL19: 4640332830317 | BM19: 2106909808 | BN19: AM.01.01.01.003.R.000594.08.23 от 17.08.2023 г. | BO19: https://drive.google.com/drive/folders/1jZ4eqgWNd8vmt2FebMgnvRLrkJrCvx9w | BP19: ЧЗ | BS19: патока, сахар, вода, желатин, носитель – глицерин, глазирователь (содержит глазирователи: воск карнаубский, воск пчелиный белый, антиокислитель – альфа-токоферол), регулятор кислотности – лимонная кислота, холекальциферол, жир молочный, ароматизатор натуральный «Вишня» | BU19: детям старше 3 лет и взрослым по 1 пастилке в день, разжевывая после еды. | BV19: индивидуальная непереносимость компонентов, беременность, кормление грудью, нарушения углеводного обмена (в том числе сахарный диабет). Перед применением рекомендуется проконсультироваться с врачом. Перед применением БАД детьми необходимо проконсультироваться с врачом-педиатром. Детям до 14 лет принимать БАД по согласованию и под наблюдением врача-педиатра. | BW19: в сухом, защищенном от воздействия прямых солнечных лучей и недоступном для детей месте при температуре не выше +25°С. | BX19: 60 | BY19: штук | CA19: 2 года | CB19: 24 месяца | CC19: https://docs.google.com/document/d/1IAHvVzgeKSqo1-9G60Q4yjs42ezg6WvRovlxkChGLZQ/edit?tab=t.0 | CM19: =IFERROR(VLOOKUP(B19,CC!A:D,4,0)," ") -> 220 | CN19: ООО ПК "Битра" | CP19: Михалева Галина тел. 495/988-93-50 доб.120 моб./whatsapp+7 916-905-60-40 Mikhalevabitra@yandex.ru | CQ19: 90 | CS19: 1 | CT19: нет | CY19: FALSE | CZ19: FALSE | DA19: FALSE | DB19: FALSE | DJ19: 7 | DK19: 13 | DL19: 7 | DM19: 637 | DN19: 0.235
A20: Биг-Л | B20: qeepomega_kids | C20: qeep | D20: Вывод | F20: БАД Омега 3 для детей 540 мг ,qeep, 90 капсул | G20: БАДы | H20: Детские витамины | K20: TRUE | L20: TRUE | M20: TRUE | N20: FALSE | O20: FALSE | P20: FALSE | Q20: FALSE | S20: QB101100475 | T20: qeepomega_kids | U20: qeepomega_kids | AA20: 138757897 | AB20: 809466646 | AH20: БАД Омега 3 для детей 540 мг ,qeep, 90 капсул | AI20: Омега 3 для детей с витамином Д и Е для иммунитета и роста | AJ20: Омега 3 витамины для детей 540 мг Qeep 90 капсул | AP20: https://www.wildberries.ru/catalog/138757897/detail.aspx | AQ20: https://www.ozon.ru/product/809466646 | AW20: БАДы | AX20: Омега 3 витамины для детей 540 мг Qeep 90 капсул | BD20: Света | BE20: Семен | BF20: Анна Пирогова | BG20: Екатерина Доможирова | BH20: Екатерина Доможирова | BI20: Екатерина Доможирова | BL20: 2253874668540 4620153900611 | BM20: 3504009000 | BN20: RU.77.99.11.003.R.003248.09.19 от 10.09.2019 г. | BO20: https://drive.google.com/drive/folders/1hjNWvHCJR_wfGIdgHTvU153navLEZsF2 | BP20: ЧЗ | BS20: рыбий жир, капсула желатиновая (желатин, глицерин, картофельный крахмал, фруктоза), кремния диоксид (носитель), натуральный ароматизатор «малина и травы», витамин Е (токоферола ацетат), ликопин (или бета-каротин) (краситель), антиокислитель «Гриндокс», витамин D3 (холекальциферол). | BU20: детям с 3х лет и взрослым по 1-2 капсулы 2 раза в день во время еды (разжевать). Продолжительность приема 1 месяц. При необходимости прием можно повторить в течение года. | BV20: индивидуальная непереносимость компонентов. Перед применением рекомендуется проконсультироваться с врачом, перед применением БАД детьми рекомендуется проконсультироваться с врачом-педиатром. | BW20: В недоступном для детей месте при температуре не выше 25°С. | BX20: 90 | BY20: таблеток | CA20: 2 года | CB20: 24 месяца | CF20: https://drive.google.com/drive/u/0/folders/10ZcNddpKKbQ2OW4wt_06WNYC5-1fTDJ1 | CM20: =IFERROR(VLOOKUP(B20,CC!A:D,4,0)," ") -> 336.44 | CN20: ООО «Сибфармконтракт», Россия, 634034, г. Томск, ул. Нахимова 8, стр. 11. | CS20: 10 | CT20: нет | CY20: FALSE | CZ20: FALSE | DA20: FALSE | DB20: FALSE | DJ20: 10 | DK20: 6 | DL20: 10 | DM20: 600 | DN20: 0.09
A21: Биг-Л | B21: qeep_gummy_magn_60 | C21: qeep | D21: Под вопросом | E21: Выяснить какой продукт | F21: БАД магний для детей мармеладки ,qeep, 60 штук | G21: БАДы | H21: Детский витамины | K21: TRUE | L21: TRUE | M21: TRUE | N21: TRUE | O21: TRUE | P21: FALSE | Q21: FALSE | S21: QB101100460 | T21: qeep_gummy_magn_60 | U21: qeep_gummy_magn_60 | V21: qeep_gummy_magn_60 | W21: qeep_gummy_magn_60 | AA21: 293062934 | AB21: 1773856028 | AC21: 103665495848 | AD21: 99000117794 | AH21: БАД магний для детей мармеладки ,qeep, 60 штук | AI21: Витамины для детей магний цитрат жевательные мармеладки | AJ21: Витамины для детей магний цитрат жевательные мармеладки qeep 60 штук | AK21: Витамины для детей магний цитрат жевательные мармеладки, мармеладные мишки qeep 60 штук | AL21: витамины для детей магний цитрат жевательные мармеладки qeep со вкусом ягодного микса 60 штук | AP21: https://www.wildberries.ru/catalog/293062934/detail.aspx | AQ21: https://www.ozon.ru/product/1773856028 | AR21: https://market.yandex.ru/card/vitaminy-dlya-detey-magniy-tsitrat-zhevatelnyye-marmeladki-qeep-60-shtuk/103665495848?businessId=8291477&clid=8291477&model_id=1947049801&distr_type=8&pp=605 | AS21: https://goldapple.ru/catalogsearch/result?q=99000117794 | AW21: БАДы | AX21: Витамины для детей магний цитрат жевательные мармеладки qeep 60 штук | AY21: аптека / витамины, минералы, добавки | AZ21: Бады витамины | BD21: Света | BE21: Семен | BF21: Анна Пирогова | BG21: Екатерина Доможирова | BH21: Екатерина Доможирова | BI21: Екатерина Доможирова | BL21: 4640346711336 | BM21: 2106909808 | BN21: AM.01.07.01.003.R.000302.03.24 от 11.03.2024 | BO21: https://drive.google.com/drive/folders/18RmLZdwskR-wJY5i0_FQQ25ZkllrDPc- | BP21: ЧЗ | BS21: магний цитрат, желатин, лимонная кислота - регулятор кислотности, натуральный ароматизатор "Ягодный микс", концентрат сока черной моркови – краситель, растительное масло (содержит карнаубский воск – глазирователь). глюкозный сироп, сахар. На предприятии используется сырье, содержащее продукты переработки молока, рыбы, ракообразных и сои. | BU21: детям старше 3-х лет и взрослым принимать по 1 пастилке в день во время еды. Не превышать рекомендуемую дозировку. | BV21: индивидуальная непереносимость компонентов, беременность, кормление грудью, нарушения углеводного обмена (в том числе сахарный диабет). Перед применением рекомендуется проконсультироваться с врачом. Перед применением БАД детьми необходимо проконсультироваться с врачом-педиатром. Детям до 14 лет принимать БАД по согласованию и под наблюдением врача-педиатра. | BW21: хранить в сухом, защищенном от попадания прямых солнечных лучей и недоступном для детей месте, при температуре от +5°С до +25°С и относительной влажности воздуха не более 75%. | BX21: 60 | BY21: шт | CA21: 18 месяцев | CB21: 18 месяцев | CC21: https://docs.google.com/document/d/1hFyhMnyjIC7Qb4t82VGmf3vdwfGg8itrcmm5MVkbmJM/edit?tab=t.0 | CM21: =IFERROR(VLOOKUP(B21,CC!A:D,4,0)," ") -> 228 | CN21: ООО "НУТРИЛЕНТ" | CP21: Анна Панкова @AnnaPankovaUKIZ | CQ21: 60 | CS21: 3 | CT21: нет | CY21: FALSE | CZ21: FALSE | DA21: FALSE | DB21: FALSE | DJ21: 11 | DK21: 5 | DL21: 11 | DM21: 605 | DN21: 0.165
A22: Биг-Л | B22: qeep_gummy_c_60 | C22: qeep | D22: Под вопросом | E22: КЗ Внешка | F22: БАД витамин С для детей мармеладки ,qeep, 60 штук | G22: БАДы | H22: Детский витамины | K22: TRUE | L22: TRUE | M22: TRUE | N22: TRUE | O22: TRUE | P22: FALSE | Q22: FALSE | S22: QB101100408 | T22: qeep_gummy_c_60 | U22: qeep_gummy_c_60 | V22: qeep_gummy_c_60 | W22: qeep_gummy_c_60 | AA22: 432841134 | AB22: 2214748873 | AC22: 4476310330 | AD22: 99000117739 | AH22: БАД витамин С для детей мармеладки ,qeep, 60 штук | AI22: Витамин С для детей жевательный | AJ22: Витамины для детей витамин с жевательные мармеладки qeep 60 штук | AK22: Витамин С для детей жевательный qeep 60 жевательных мармеладок, витамишки | AL22: витамины для детей витамин с жевательные мармеладки qeep со вкусом апельсина 60 штук | AP22: https://www.wildberries.ru/catalog/432841134/detail.aspx | AQ22: https://www.ozon.ru/product/2214748873 | AR22: https://market.yandex.ru/card/vitamin-s-dlya-detey-zhevatelnyy-qeep-60-zhevatelnykh-marmeladok/4476310330?businessId=8291477&clid=8291477&model_id=1947049801&distr_type=8&pp=605 | AS22: https://goldapple.ru/catalogsearch/result?q=99000117739 | AW22: БАДы | AX22: Витамины для детей витамин с жевательные мармеладки qeep 60 штук | AY22: аптека / витамины, минералы, добавки | AZ22: Бады витамины | BD22: Света | BE22: Семен | BF22: Анна Пирогова | BG22: Екатерина Доможирова | BH22: Екатерина Доможирова | BI22: Екатерина Доможирова | BL22: 4640332830300 | BM22: 2106909808 | BN22: AM.01.01.01.003.R.000584.08.23 от 15.08.2023 г. | BO22: https://drive.google.com/drive/folders/1-Pgr3i2_OqiWQSo8yCWIZcaUHTKtWguF | BP22: ЧЗ | BS22: патока, сахар, вода, желатин, носитель – глицерин, L-аскорбиновая кислота, глазирователь (содержит глазирователи: воск карнаубский и воск пчелиный белый, антиокислитель – альфа-токоферол), жир молочный; ароматизатор натуральный «Апельсин», краситель натуральный | BU22: детям старше 3 лет по 1 пастилке в день, взрослым по 1-2 пастилки в день, разжевывая после еды. | BV22: индивидуальная непереносимость компонентов, беременность, кормление грудью, нарушения углеводного обмена (в том числе сахарный диабет). Перед применением рекомендуется проконсультироваться с врачом. Перед применением БАД детьми необходимо проконсультироваться с врачом-педиатром. Детям до 14 лет принимать БАД по согласованию и под наблюдением врача-педиатра. | BW22: в сухом, защищенном от воздействия прямых солнечных лучей и недоступном для детей месте при температуре не выше +25°С. | BX22: 60 | BY22: штук | CA22: 2 года | CB22: 24 месяца | CC22: https://docs.google.com/document/d/1R65c50N_ld9jmDvK87XlIizSVB2GfnPinCtxjVCxlBU/edit?tab=t.0 | CM22: =IFERROR(VLOOKUP(B22,CC!A:D,4,0)," ") -> 220 | CN22: ООО ПК "Битра" | CP22: Михалева Галина тел. 495/988-93-50 доб.120 моб./whatsapp+7 916-905-60-40 Mikhalevabitra@yandex.ru | CQ22: 90 | CS22: 1 | CT22: нет | CY22: FALSE | CZ22: FALSE | DA22: FALSE | DB22: FALSE | DJ22: 7 | DK22: 13 | DL22: 7 | DM22: 637 | DN22: 0.227
A23: Биг-Л | B23: harly_pawsoap_500ml | C23: Harly | D23: Актуальный | F23: Мыло для лап собак ,Harly, 500 мл | G23: Косметика для животных | H23: Для лап | K23: TRUE | L23: TRUE | M23: TRUE | N23: TRUE | O23: FALSE | P23: FALSE | Q23: FALSE | S23: HC101100406 | T23: harly_pawsoap_500ml | U23: harly_pawsoap_500ml | V23: harly_pawsoap_500ml | AA23: 307874530 | AB23: 1828993605 | AC23: 103724222997 | AH23: Мыло для лап собак ,Harly, 500 мл | AI23: Мыло для лап собак с пантенолом и коллоидным серебром | AJ23: Мыло для лап собак с пантенолом и коллоидным серебром Harly 500 мл | AK23: Мыло для лап собак с пантенолом и коллоидным серебром Harly 500 мл | AP23: https://www.wildberries.ru/catalog/307874530/detail.aspx | AQ23: https://www.ozon.ru/product/1828993605 | AR23: https://market.yandex.ru/card/mylo-dlya-lap-sobak-s-pantenolom-i-kolloidnym-serebrom-harly-500-ml/103724222997?businessId=8291477&clid=8291477&model_id=944504526&distr_type=8&pp=605 | AW23: Мыло для животных | AX23: Мыло для лап собак с пантенолом и коллоидным серебром Harly 500 мл | AY23: товары для животных / косметика и гигиена / средства для уборки за животными | BD23: Алексей | BE23: Семен | BF23: Анна Пирогова | BG23: Екатерина Доможирова | BH23: Екатерина Доможирова | BI23: Екатерина Доможирова | BL23: 4673767781190 | BM23: 3307900008 | BN23: ДС | BO23: https://drive.google.com/drive/folders/1YcoxDfDh4ruJhBG56E2T7u94bh1w79DC | BP23: без ЧЗ | BS23: Water (Aqua), Sodium Laureth Sulfate, Cocamidopropyl Betaine, Glycerin, D-Panthenol, Cocamide DEA, Parfum, Citric Acid, Methylchloroisothiazolinone, Methylisothiazolinone, Colloidal Silver. | BU23: нанесите небольшое количество мыла на влажные руки, вспеньте, очистите образовавшейся пеной лапки питомца, смоченные водой. После тщательно смойте пену теплой водой. Рекомендуется после мытья обработать лапки воском для лап. Можно использовать для щенков от 6 месяцев. | BW23: при температуре от 0 до 25 oС | BX23: 500 | BY23: мл | CA23: 2 года | CB23: 24 месяца | CC23: https://docs.google.com/document/d/1_eSJtZO0eUrwiF0HDADKHQOq_usuoSpYtxP_JdmcIGk/edit?tab=t.0 | CG23: 46080 | CH23: https://disk.yandex.ru/d/Xz_B17SiYOGjpw | CM23: =IFERROR(VLOOKUP(B23,CC!A:D,4,0)," ") -> 92.75 | CN23: ООО "Батискаф" | CP23: Адель 8 962 557 2689 | CQ23: 45 | CS23: 3 | CT23: нет | CY23: FALSE | CZ23: FALSE | DA23: FALSE | DB23: FALSE | DJ23: 16 | DK23: 7 | DL23: 16 | DM23: 1792 | DN23: 0.551
A24: Биг-Л | B24: harly_pawprotector_30ml | C24: Harly | D24: Вывод | F24: Воск для лап ,Harly, 30 мл | G24: Косметика для животных | H24: Для лап | K24: TRUE | L24: TRUE | M24: TRUE | N24: FALSE | O24: FALSE | P24: FALSE | Q24: FALSE | S24: HC101100400 | T24: harly_pawprotector_30ml | U24: harly_pawprotector_30ml | AA24: 276247301 | AB24: 1745032627 | AH24: Воск для лап ,Harly, 30 мл | AI24: Воск для лап собак и кошек защитный | AJ24: Воск для лапок собак и кошек защитный Harly 30 мл | AP24: https://www.wildberries.ru/catalog/276247301/detail.aspx | AQ24: https://www.ozon.ru/product/1745032627 | AW24: Воск для лап | AX24: Воск для лапок собак и кошек защитный Harly 30 мл | BD24: Алексей | BE24: Семен | BF24: Анна Пирогова | BG24: Екатерина Доможирова | BH24: Екатерина Доможирова | BI24: Екатерина Доможирова | BL24: 4657786831579 | BN24: ДС | BP24: без ЧЗ | BS24: Масло семян гелиантуса однолетнего, Пчелиный воск, Вазелин, Пальмовое масло, Воск из отрубей риса (Oriza sativa), Коллоидное серебро, Ланолин, Микрокристаллический воск, гидрогенизированное растительное масло, гидрогенизированная пальмовая кислота, Стеарилстеарат, глицерилмоностеарат, Стеариновая кислота, Полисорбат 80, Олеат сорбитана, Ароматизатор, бутилгидрокситолуол. | BU24: нанесите средство на подушечки лап животных перед прогулкой, давая составу подсохнуть в течение минуты. После прогулки сотрите воск салфеткой и смойте остатки продукта теплой водой. | BW24: Температура хранения: от +5°C до +25°C. | BX24: 30 | BY24: мл | CA24: 1 год | CB24: 12 месяцев | CC24: https://docs.google.com/document/d/1KgCVfJkmpvVcN800fh2ozy8rpk8wfHp7o3jwNbMaPTk/edit?tab=t.0 | CM24: =IFERROR(VLOOKUP(B24,CC!A:D,4,0)," ") -> 181 | CN24: ООО «М9 Фарм» 445043, Самарская обл, Тольятти г, Южное шоссе, влд. 14 стр.3, помещение 31, 32. | CP24: Дмитрий +7 960 841 9108 | CQ24: 90 | CS24: 3 | CT24: нет | CY24: FALSE | CZ24: FALSE | DA24: FALSE | DB24: FALSE | DJ24: 3 | DK24: 7 | DL24: 3 | DM24: 63 | DN24: 0.071
A25: Биг-Л | B25: qeep_berberine_60caps | C25: qeep | D25: Актуальный | F25: БАД Берберин 500 мг ,qeep, 60 капсул | G25: БАДы | H25: Женские | K25: TRUE | L25: TRUE | M25: TRUE | N25: TRUE | O25: TRUE | P25: FALSE | Q25: FALSE | S25: QB101100405 | T25: qeep_berberine_60caps | U25: qeep_berberine_60caps | V25: qeep_berberine_60caps | W25: qeep_berberine_60caps | AA25: 198421782 | AB25: 1361997453 | AC25: 102650853073 | AD25: 99000118637 | AH25: БАД Берберин 500 мг ,qeep, 60 капсул | AI25: Берберин БАД для контроля сахара и жиросжигатель холестерина | AJ25: Берберин 500 мг Qeep 60 капсул | AK25: Берберин 500 мг капсулы для похудения и контроля аппетита Qeep 60 капсул | AL25: берберин 500 мг qeep 60 капсул | AP25: https://www.wildberries.ru/catalog/198421782/detail.aspx | AQ25: https://www.ozon.ru/product/1361997453 | AR25: https://market.yandex.ru/card/berberin-500-mg-qeep-60-kapsul/103374785698?businessId=8291477&clid=8291477&model_id=1826260757&distr_type=8&pp=605 | AS25: https://goldapple.ru/catalogsearch/result?q=99000118637 | AW25: БАДы | AX25: Берберин 500 мг Qeep 60 капсул | AY25: аптека / витамины, минералы, добавки | AZ25: Бады витамины | BD25: Света | BE25: Семен | BF25: Анна Пирогова | BG25: Екатерина Доможирова | BH25: Екатерина Доможирова | BI25: Екатерина Доможирова | BL25: 4630205148199 | BM25: 2106909808 | BN25: AM.01.01.01.003.R.000809.11.23 от 09.11.2023 | BO25: https://drive.google.com/drive/folders/1yXjmu5hDb-Pz71Rz8yc1YcRLpSpxr7Mh | BP25: ЧЗ | BS25: экстракт плодов барбариса, пиридоксин гидрохлорида (витамин В6), стеарат кальция, кремний диоксид коллоидный (АЭРОСИЛ@), твёрдая желатиновая капсула. | BU25: взрослым по 1 капсуле 1 раз в день. Продолжительность приёма: 1 месяц. При необходимости повторить. | BV25: индивидуальная непереносимость компонентов продукта, беременность, кормление грудью. Продукт не рекомендуется принимать детям до 18 лет. Перед применением проконсультироваться с врачом. | BW25: хранить в сухом, недоступном для детей месте, при температуре от +5 °С до +25 °С. | BX25: 60 | BY25: капсул | CA25: 2 года | CB25: 24 месяца | CC25: https://docs.google.com/document/d/1iR2ypw2bjgV0t5WgfvrEJygn4BKVz3hCoykhvJp9KKc/edit?usp=sharing | CM25: =IFERROR(VLOOKUP(B25,CC!A:D,4,0)," ") -> 293 | CN25: ООО «Жива Продукт ПРО». 350062, Россия, Краснодарский край, город Краснодар, улица Казбекская, дом 17, кв. (оф.) 85 | CP25: Магамадов Ибрагим e-mail: ima@dzivaproduct.ru сайт: www.dzivaproduct.ru сот.тел. +7-967-660-1277(доступен WhatsApp) | CQ25: 60 | CS25: 5 | CT25: да | CY25: FALSE | CZ25: FALSE | DA25: FALSE | DB25: FALSE | DJ25: 11 | DK25: 5 | DL25: 11 | DM25: 605 | DN25: 0.087
A26: Биг-Л | B26: qeepinositol | C26: qeep | D26: Актуальный | F26: БАД Мио Инозитол 820 мг ,qeep, 60 капсул | G26: БАДы | H26: Женские | K26: TRUE | L26: TRUE | M26: TRUE | N26: TRUE | O26: TRUE | P26: FALSE | Q26: FALSE | S26: QB101100466 | T26: qeepinositol | U26: qeepinositol | V26: qeepinositol | W26: qeepinositol | AA26: 142963712 | AB26: 835603195 | AC26: 101948470526 | AD26: 99000121336 | AH26: БАД Мио Инозитол 820 мг ,qeep, 60 капсул | AI26: Инозитол витамины для женщин 821 мг | AJ26: Мио Инозитол 820 мг Qeep 60 капсул | AK26: Мио Инозитол витамины для женского здоровья и баланс гормонов 820 мг Qeep 60 капсул | AL26: мио инозитол 820 мг qeep 60 капсул | AP26: https://www.wildberries.ru/catalog/142963712/detail.aspx | AQ26: https://www.ozon.ru/product/835603195 | AR26: https://market.yandex.ru/card/mio-inozitol-820-mg-qeep-60-kapsul/101948470526?businessId=8291477&clid=8291477&model_id=1111706245&distr_type=8&pp=605 | AS26: https://goldapple.ru/catalogsearch/result?q=99000121336 | AW26: БАДы | AX26: Мио Инозитол 820 мг Qeep 60 капсул | AY26: аптека / витамины, минералы, добавки | AZ26: Бады витамины | BD26: Алексей | BE26: Семен | BF26: Анна Пирогова | BG26: Екатерина Доможирова | BH26: Екатерина Доможирова | BI26: Екатерина Доможирова | BL26: 4603335715654 | BM26: 3504009000 | BN26: RU.77.99.88.003.R.001844.06.22 от 01.06.2022 | BO26: https://drive.google.com/drive/folders/1SbDMn90SltH25aZ7xTxoAGf0JGRDj0Wa | BP26: ЧЗ | BS26: Мио-инозитол, антислеживающий агент тальк пищевой, антислеживающий агент магниевая соль стеариновой кислоты, капсула (желатин, краситель диоксид титана) | BU26: взрослым по 3 капсулы в день во время еды в течение одного месяца, при необходимости прием можно продлить. | BV26: Противопоказания: индивидуальная непереносимость компонентов продукта, беременность, кормление грудью, язвенная болезнь желудка и двенадцатиперстной кишки, гиперацидный гастрит, заболевание печени. Перед применением проконсультироваться с врачом. | BW26: Хранить в сухом недоступном для детей месте при температуре не выше 25◦С. | BX26: 60 | BY26: капсул | CA26: 2 года | CB26: 24 месяца | CC26: https://docs.google.com/document/d/1FHRHavRBDdi2gKFjBn9bjWsFAdIYSnUhNR4TwF87PzA/edit?usp=sharing | CF26: https://drive.google.com/drive/u/0/folders/1CqK8xLB_9LpFcd6o_xx5XGicVfEsIJXA | CG26: 46043 | CH26: https://disk.yandex.ru/d/Y1y6LE7lT5p4ew | CM26: =IFERROR(VLOOKUP(B26,CC!A:D,4,0)," ") -> 164 | CN26: ООО "ЮНИЭКО" 115201 Москва 1й Варшавский проезд 2с26 | CP26: Максим Тарасов <mt@uni-eco.com> 8 909 452 6848 | CS26: 1 | CT26: нет | CY26: FALSE | CZ26: FALSE | DA26: FALSE | DB26: FALSE | DJ26: 11 | DK26: 4 | DL26: 11 | DM26: 484 | DN26: 0.062
A27: Биг-Л | B27: qeep_ByeBye_fat_Prebiotics | C27: qeep | D27: Вывод | E27: Старый артикул | F27: БАД Набор Байфет и пробиотики | K27: TRUE | L27: TRUE | M27: TRUE | N27: FALSE | O27: FALSE | P27: FALSE | Q27: FALSE | S27: QB101100525 | T27: qeep_ByeBye_fat_Prebiotics | U27: qeep_ByeBye_fat_Prebiotics | AA27: 167680087 | AB27: 1099614303 | AH27: БАД Набор Байфет и пробиотики | AI27: Жиросжигатель для похудения + пребиотики | AJ27: Жиросжигатель для похудения + Пробиотики для взрослых Qeep 60+30 капсул | AP27: https://www.wildberries.ru/catalog/167680087/detail.aspx | AQ27: https://www.ozon.ru/product/1099614303 | AW27: Жиросжигатели | AX27: Жиросжигатель для похудения + Пробиотики для взрослых Qeep 60+30 капсул | BF27: Анна Пирогова | BG27: Екатерина Доможирова | BH27: Екатерина Доможирова | BI27: Екатерина Доможирова | BL27: 2038121297342 | BM27: 2106909808 | BP27: ЧЗ | BS27: Экстракт гарцинии камбоджийская, L-Карнитин L-Тартрат, микрокристаллическая целлюлоза (носитель), экстракт лимонника, экстракт зелёного чая, пиколинат хрома, яблочный уксус, стеарат кальция, пиколинат цинка, экстракт клюквы. | BU27: взрослым по 1 капсуле 3 раза в день после еды. | BV27: индивидуальная непереносимость компонентов продукта, беременность, кормление грудью. Перед применением проконсультироваться с врачом. | BW27: хранить в сухом, недоступном для детей месте, при температуре от +5 °С до +25 °С. | BX27: 60 | BY27: капсул | CM27: =IFERROR(VLOOKUP(B27,CC!A:D,4,0)," ") -> 477.54 | CQ27: 90 | CS27: 4 | CT27: нет | CY27: FALSE | CZ27: FALSE | DA27: FALSE | DB27: FALSE | DJ27: =IFERROR(VLOOKUP($B27,'Лист4'!$D:$AI,27,0)," ") | DK27: =IFERROR(VLOOKUP($B27,'Лист4'!$D:$AI,28,0)," ") | DL27: =IFERROR(VLOOKUP($B27,'Лист4'!$D:$AI,29,0)," ") | DM27: =IFERROR(DJ27*DK27*DL27," ") -> 0 | DN27: =IFERROR(VLOOKUP($B27,'Лист4'!$D:$AI,32,0)," ")
A28: Биг-Л | B28: qeep_melatonin2mg_90tabs | C28: qeep | D28: Вывод | E28: Запрес продажи в РФ | F28: БАД Мелатонин 90 таблеток | K28: TRUE | L28: TRUE | M28: TRUE | N28: FALSE | O28: FALSE | P28: FALSE | Q28: FALSE | S28: QB101100517 | T28: qeep_melatonin2mg_90tabs | U28: qeep_melatonin2mg_90tabs | AA28: 188493994 | AB28: 1283138723 | AH28: БАД Мелатонин 90 таблеток | AI28: Мелатонин для сна БАД таблетки Melatonin 2 mg 90 шт | AJ28: Мелатонин 2 мг Qeep 90 таблеток | AP28: https://www.wildberries.ru/catalog/188493994/detail.aspx | AQ28: https://www.ozon.ru/product/1283138723 | AW28: БАДы | AX28: Мелатонин 2 мг Qeep 90 таблеток | BF28: Анна Пирогова | BG28: Екатерина Доможирова | BH28: Екатерина Доможирова | BI28: Екатерина Доможирова | BL28: 4630205146119 | BM28: 2106909808 | BN28: AM.01.01.01.003.R.000645.09.23 от 08.09.2023 г. | BP28: ЧЗ | BS28: Мелатонин (из растительного сырья), носители: мальтодекстрин, микрокристаллическая целлюлоза, стеарат кальция, кремний диоксид коллоидный (АЭРОСИЛ@). | BU28: взрослым по 1 таблетке в день в вечернее время | BV28: индивидуальная непереносимость компонентов продукта, беременность, кормление грудью. Продукт не рекомендуется принимать детям до 18 лет. Перед применением проконсультироваться с врачом. | BW28: хранить в сухом, недоступном для детей месте, при температуре от +5 °С до +25 °С. | BX28: 90 | BY28: таблеток | CA28: 2 года | CB28: 24 месяца | CC28: https://docs.google.com/document/d/1eaOslcbNtStwAj8-U1YvP6ric478pka_5bO-d1TsLTA/edit?usp=sharing | CF28: https://drive.google.com/drive/u/0/folders/1uMtKkkJJyhrEKETZWyeSNFEJWFJOvqI2 | CM28: =IFERROR(VLOOKUP(B28,CC!A:D,4,0)," ") -> 160 | CN28: ООО «Жива Продукт ПРО». 350062, Россия, Краснодарский край, город Краснодар, улица Казбекская, дом 17, кв. (оф.) 85 | CP28: Магамадов Ибрагим e-mail: ima@dzivaproduct.ru сайт: www.dzivaproduct.ru сот.тел. +7-967-660-1277(доступен WhatsApp) | CQ28: 60 | CS28: 5 | CT28: да | CY28: FALSE | CZ28: FALSE | DA28: FALSE | DB28: FALSE | DJ28: =IFERROR(VLOOKUP($B28,'Лист4'!$D:$AI,27,0)," ") -> 4 | DK28: =IFERROR(VLOOKUP($B28,'Лист4'!$D:$AI,28,0)," ") -> 7 | DL28: =IFERROR(VLOOKUP($B28,'Лист4'!$D:$AI,29,0)," ") -> 4 | DM28: =IFERROR(DJ28*DK28*DL28," ") -> 112 | DN28: =IFERROR(VLOOKUP($B28,'Лист4'!$D:$AI,32,0)," ") -> 0.05
A29: Биг-Л | B29: qeep_biomelatonin_60caps | C29: qeep | D29: Вывод | E29: Запрес продажи в РФ | F29: БАД Биомелатонин 60 капсул | K29: TRUE | L29: TRUE | M29: TRUE | N29: FALSE | O29: FALSE | P29: FALSE | Q29: FALSE | S29: QB101100518 | T29: qeep_biomelatonin_60caps | U29: qeep_biomelatonin_60caps | AA29: 188602690 | AB29: 1283143901 | AH29: БАД Биомелатонин 60 капсул | AI29: Мелатонин для сна от бессонницы БАД Bio Melatonin | AJ29: БАД успокоительный комплекс, Омега 3 696 мг Qeep 60 капсул | AP29: https://www.wildberries.ru/catalog/188602690/detail.aspx | AQ29: https://www.ozon.ru/product/1283143901 | AW29: БАДы | AX29: БАД успокоительный комплекс, Омега 3 696 мг Qeep 60 капсул | BF29: Анна Пирогова | BG29: Екатерина Доможирова | BH29: Екатерина Доможирова | BI29: Екатерина Доможирова | BL29: 4620153905661 | BM29: 2106909808 | BN29: RU.77.99.11.003.R.000811.03.23 от 23.03.2023 г. | BP29: ЧЗ | BS29: шлемника байкальского экстракт, лаванды цветков экстракт, коэнзим Q10, рыбный жир, капсула желатиновая (желатин, глицерин (агент влагоудерживающий), кремния диоксид аморфный (носитель), смесь токоферолов (антиокислитель). | BU29: взрослым по 1 капсуле вечером с последним приемом пищи. Продолжительность приема 1 месяц. При необходимости прием можно повторить. | BV29: индивидуальная непереносимость компонентов, беременность и кормление грудью. Перед применением рекомендуется проконсультироваться с врачом. | BW29: хранить в недоступном для детей месте, при температуре от +15 ºС до +25 ºС и относительной влажности воздуха не более 60%. | BX29: 60 | BY29: капсул | CA29: 2 года | CB29: 24 месяца | CC29: https://docs.google.com/document/d/17xTFJTIdvIexPXUmuln5X_o7MW0jlfWQDJROJNhuel8/edit?usp=sharing | CF29: https://drive.google.com/drive/u/0/folders/1EJ4tf05-m9tdvTI4jcyzXPrkyCyQU7uY | CM29: =IFERROR(VLOOKUP(B29,CC!A:D,4,0)," ") -> 355.96 | CN29: ООО «Сибфармконтракт» | CP29: Анастасия Лапина тел: 8(3822)556092 (доб. 258), 426792 E-mail: lapina@artlife.ru Skype: live:e18940191d9f1027 634034 г.Томск ул Нахимова 8/2 а/я 358 | CQ29: 90 | CS29: 10 | CT29: нет | CY29: FALSE | CZ29: FALSE | DA29: FALSE | DB29: FALSE | DJ29: =IFERROR(VLOOKUP($B29,'Лист4'!$D:$AI,27,0)," ") -> 4 | DK29: =IFERROR(VLOOKUP($B29,'Лист4'!$D:$AI,28,0)," ") -> 7 | DL29: =IFERROR(VLOOKUP($B29,'Лист4'!$D:$AI,29,0)," ") -> 4 | DM29: =IFERROR(DJ29*DK29*DL29," ") -> 112 | DN29: =IFERROR(VLOOKUP($B29,'Лист4'!$D:$AI,32,0)," ") -> 0.05
A30: Биг-Л | B30: qeep_enzyme_80g | C30: qeep | D30: Актуальный | F30: БАД Коэнзим | G30: Косметика | H30: Лицо | K30: TRUE | L30: TRUE | M30: TRUE | N30: TRUE | O30: FALSE | P30: TRUE | Q30: FALSE | S30: QB101100519 | T30: qeep_enzyme_80g | U30: qeep_enzyme_80g | V30: qeep_enzyme_80g | X30: qeep_enzyme_80g | AA30: 549551191 | AB30: 2921727205 | AC30: 4693953993 | AE30: MPL536234 | AH30: БАД Коэнзим | AI30: Энзимная пудра для умывания лица и тела | AJ30: Энзимная пудра для умывания лица и тела | AK30: Энзимная пудра для умывания лица и тела, с энзимами из папайи для всех типов кожи, пилинг для лица, 80 гр | AM30: Энзимная пудра для умывания лица и тела | AP30: https://www.wildberries.ru/catalog/549551191/detail.aspx | AQ30: https://www.ozon.ru/product/2921727205 | AR30: https://market.yandex.ru/card/enzimnaya-pudra-dlya-umyvaniya-litsa-i-tela/4693953993?businessId=8291477&clid=8291477&model_id=1243169397&distr_type=8&pp=605 | AT30: https://www.letu.ru/product/qeep-enzimnaya-pudra-dlya-umyvaniya-litsa-i-tela/177800329?sort=default&open=ingredient%7EcleanBeauty&hide=expectedEffect%7EnotContain%7EskinTypes | AW30: Пудры | AX30: Энзимная пудра для умывания лица и тела | AY30: товары для красоты / косметика, парфюмерия и уход / уход за лицом / очищение и снятие макияжа / средства для умывания | BA30: Уход за лицом >> Средства для умывания >> Пудра для умывания | BE30: Кристина | BF30: Анна Пирогова | BG30: Екатерина Доможирова | BH30: Екатерина Доможирова | BI30: Екатерина Доможирова | BL30: 4670020499243 | BN30: ДС | BO30: https://drive.google.com/drive/folders/1sMpHVVo7fru69JaemeaE4lTRbQomIz9y | BP30: без ЧЗ | BS30: Corn Starch, Sodium Cocoyl Isethionate, Kaolin, Parfum, Papain, Allantoin, Camellia Sinensis Leaf Extract, Salicylic acid, Аcrylic Рolymer, Inulin, Geraniol, Limonene. | BU30: небольшое количество пудры насыпать в смоченную водой ладонь. Вспенить средство и массажными движениями нанести на влажную кожу лица и шеи, избегая области вокруг глаз. Смыть водой. | BW30: в сухом, защищенном от воздействия прямых солнечных лучей и недоступном для детей месте при температуре не выше +25°С. | BX30: 80 | BY30: г | CA30: 2 года | CB30: 24 месяца | CC30: https://docs.google.com/document/d/1c965KEqR4_me16b5rMZlKygryHIZkneAeU-V2WS00CU/edit?tab=t.0 | CM30: =IFERROR(VLOOKUP(B30,CC!A:D,4,0)," ") -> 119 | CN30: ООО ПКФ Две линии (Алтэя) | CP30: Мария Чуйкова +7 (3854) 30-30-87 https://productaltai.com/ www.dvelinii.com моб., WhatsApp 8-903-948-3450 Алтайский край, г. Бийск, ул.Социалистическая д.11, стр. 1 | CS30: 5 | CT30: нет | CY30: FALSE | CZ30: FALSE | DA30: FALSE | DB30: FALSE | DJ30: =IFERROR(VLOOKUP($B30,'Лист4'!$D:$AI,27,0)," ") -> 5 | DK30: =IFERROR(VLOOKUP($B30,'Лист4'!$D:$AI,28,0)," ") -> 14 | DL30: =IFERROR(VLOOKUP($B30,'Лист4'!$D:$AI,29,0)," ") -> 5 | DM30: =IFERROR(DJ30*DK30*DL30," ") -> 350 | DN30: =IFERROR(VLOOKUP($B30,'Лист4'!$D:$AI,32,0)," ") -> 0.099
A31: Биг-Л | B31: qeep_retinolcream_50ml | C31: qeep | D31: Актуальный | F31: Крем для лица Retinol с ретинолом 0,5% | G31: Косметика | H31: Лицо | K31: TRUE | L31: TRUE | M31: TRUE | N31: TRUE | O31: FALSE | P31: TRUE | Q31: TRUE | S31: QB101100520 | T31: qeep_retinolcream_50ml | U31: qeep_retinolcream_50ml | V31: qeep_retinolcream_50ml | X31: qeep_retinolcream_50ml | Y31: qeep_retinolcream_50ml | AA31: 549611709 | AB31: 2921798266 | AC31: 4695750936 | AE31: MPL536223 | AF31: QEEP-RETINL5 | AH31: Крем для лица Retinol с ретинолом 0,5% | AI31: Крем для Лица с Липосомальным Ретинолом 0.5% | AJ31: Крем для Лица с Липосомальным Ретинолом 0.5% | AK31: Крем для лица с липосомальным ретинолом 0.5%, антивозрастной крем, сыворотка для лица от морщин Ретинол, 50 мл | AM31: Крем для Лица с Липосомальным Ретинолом 0.5% | AN31: Крем для Лица с Липосомальным Ретинолом 0.5% | AP31: https://www.wildberries.ru/catalog/549611709/detail.aspx | AQ31: https://www.ozon.ru/product/2921798266 | AR31: https://market.yandex.ru/card/krem-dlya-litsa-s-liposomalnym-retinolom-05/4695750936?businessId=8291477&clid=8291477&model_id=1453951928&distr_type=8&pp=605 | AT31: https://www.letu.ru/product/qeep-krem-dlya-litsa-s-liposomalnym-retinolom-0-5-/178100057?sort=default&open=ingredient%7EcleanBeauty&hide=expectedEffect%7EnotContain%7EskinTypes | AU31: https://mm.ru/product/krem-dlya-lica-s-liposomalnym-retinolom-5898608?skuId=13170183 | AW31: Кремы | AX31: Крем для Лица с Липосомальным Ретинолом 0.5% | AY31: товары для красоты / косметика, парфюмерия и уход / уход за лицом / кремы и сыворотки / средства для ухода за лицом | BA31: Уход за лицом >> Крем для лица >> Уход за лицом | BB31: Кремы для лица | BD31: Мария | BE31: Кристина | BF31: Анна Пирогова | BG31: Екатерина Доможирова | BH31: Екатерина Доможирова | BI31: Екатерина Доможирова | BL31: 4660417421520 | BN31: ДС | BO31: https://drive.google.com/drive/folders/1q2apvTtvQEh0yeNpyR4Csa1wlhvTiKVX | BP31: без ЧЗ | BS31: Aqua, Isopropyl Palmitate, Acrylamide/Sodium Acrylate Copolymer, Niacinamide, Urea, Squalane, Helianthus, Annuus (Sunflower) Seed Oil, Mineral Oil, Cyclopentasiloxane, Caprylic/Capric Triglyceride, Acrylates/C10-30 Alkyl Acrylate Crosspolymer, Tocopheryl Acetate, Lecithin, Retinol, Phospholipids, Dimethiconol, Panthenol, Trideceth-6, C11-13 Isoparaffin, Colloidal Gold, BHT, Tetrasodium Glutamate Diacetate, Sodium Hydroxide, Phenoxyethanol, Ethylhexylglycerin, Parfum, Geraniol, Linalool. | BU31: небольшое количество крема распределить между ладоней. Нанести на сухую кожу лица. Сделать мягкий массаж. Если выпользуетесь ретинолом впервые, начните с 2-3 раз в неделю и постепенно увеличивайте частоту применений. Пользуясь ретинолом, защищайте кожу от солнца кремом с SPF 30 и больше. | BW31: хранить в сухом недоступном для света месте при температуре от +5 ℃ до +25 ℃. | BX31: 50 | BY31: мл | CA31: 36 месяцев | CB31: 36 месяцев | CC31: https://docs.google.com/document/d/1ITo_sEFvRnQaUKCL19D-_sR4a_h15UPCo037S5gShLs/edit?tab=t.0 | CG31: 46071 | CH31: https://disk.yandex.ru/d/iO_TaD7U2A8-rw/18.02.2026 | CM31: =IFERROR(VLOOKUP(B31,CC!A:D,4,0)," ") -> 92.82 | CN31: Восток-плюс | CP31: Дмитрий | CQ31: 45 | CS31: 1 | CT31: нет | CY31: FALSE | CZ31: FALSE | DA31: FALSE | DB31: FALSE | DJ31: =IFERROR(VLOOKUP($B31,'Лист4'!$D:$AI,27,0)," ") -> 3 | DK31: =IFERROR(VLOOKUP($B31,'Лист4'!$D:$AI,28,0)," ") -> 11 | DL31: =IFERROR(VLOOKUP($B31,'Лист4'!$D:$AI,29,0)," ") -> 3 | DM31: =IFERROR(DJ31*DK31*DL31," ") -> 99 | DN31: =IFERROR(VLOOKUP($B31,'Лист4'!$D:$AI,32,0)," ") -> 0.064
A32: Биг-Л | B32: qeep_inositol1500mg_60caps | C32: qeep | D32: Актуальный | F32: БАД Инозитол 1500 мг | G32: БАДы | H32: Женские | K32: TRUE | L32: TRUE | M32: TRUE | N32: TRUE | O32: FALSE | P32: FALSE | Q32: FALSE | S32: QB101100521 | T32: qeep_inositol1500mg_60caps | U32: qeep_inositol1500mg_60caps | V32: qeep_inositol1500mg_60caps | AA32: 559173569 | AB32: 2946850815 | AC32: 4737110307 | AH32: БАД Инозитол 1500 мг | AI32: Инозитол витамины для женщин 1500 мг | AJ32: Мио Инозитол 1500 мг Qeep 60 капсул | AK32: Мио Инозитол витамины для женского здоровья , баланс гормонов 1500 мг Qeep 60 капсул | AP32: https://www.wildberries.ru/catalog/559173569/detail.aspx | AQ32: https://www.ozon.ru/product/2946850815 | AR32: https://market.yandex.ru/card/mio-inozitol-1500-mg-qeep-60-kapsul/4737110307?businessId=8291477&clid=8291477&model_id=1111706245&distr_type=8&pp=605 | AW32: БАДы | AX32: Мио Инозитол 1500 мг Qeep 60 капсул | AY32: аптека / витамины, минералы, добавки | BD32: Алексей | BE32: Семен | BF32: Анна Пирогова | BG32: Екатерина Доможирова | BH32: Екатерина Доможирова | BI32: Екатерина Доможирова | BL32: 4630263906380 | BN32: AM.01.11.01.003.R.000430.07.24 от 26.07.2024 | BO32: https://drive.google.com/drive/folders/1tJn-U5-4SUwDVUMhCm0kivRx5EnuKk0S | BP32: ЧЗ | BS32: инозитол, оболочка капсулы (желатин), агент антислеживающий магниевая соль стеариновой кислоты, агент антислеживающий кремния диоксид, фолиевая кислота (витамин В9). | BU32: взрослым принимать по 2 капсулы 1 раз в день во время еды. Продолжительность приема: 1 месяц. При необходимости прием можно повторить. | BV32: индивидуальная непереносимость компонентов продукта. Перед применением рекомендуется проконсультироваться с врачом. Не превышать установленную рекомендуемую дозу. | BW32: в сухом, защищенном от прямых солнечных лучей и недоступном для детей месте при температуре от +5 до +25° С | BX32: 60 | BY32: капс | CA32: 2 года | CB32: 24 месяца | CC32: https://docs.google.com/document/d/1Nqifi53A5eDt5AMOmmlHJBPbM8QPakcsGrHCvS6La7g/edit?tab=t.0 | CG32: 46043 | CH32: https://disk.yandex.ru/d/1ndXL8wYq_YmVg | CM32: =IFERROR(VLOOKUP(B32,CC!A:D,4,0)," ") -> 199 | CN32: ООО "ЮНИЭКО" | CP32: Елена | CS32: 1 | CT32: нет | CY32: FALSE | CZ32: FALSE | DA32: FALSE | DB32: FALSE | DJ32: =IFERROR(VLOOKUP($B32,'Лист4'!$D:$AI,27,0)," ") -> 5 | DK32: =IFERROR(VLOOKUP($B32,'Лист4'!$D:$AI,28,0)," ") -> 11 | DL32: =IFERROR(VLOOKUP($B32,'Лист4'!$D:$AI,29,0)," ") -> 5 | DM32: =IFERROR(DJ32*DK32*DL32," ") -> 275 | DN32: =IFERROR(VLOOKUP($B32,'Лист4'!$D:$AI,32,0)," ") -> 0.82
A33: Биг-Л | B33: harly_pawprotector_50ml | C33: Harly | D33: Актуальный | F33: Воск для лап для собак и кошек 50 мл | G33: Косметика для животных | H33: Для лап | K33: TRUE | L33: TRUE | M33: TRUE | N33: TRUE | O33: TRUE | P33: TRUE | Q33: FALSE | S33: HC101100411 | T33: harly_pawprotector_50ml | U33: harly_pawprotector_50ml | V33: harly_pawprotector_50ml | AA33: 559225020 | AB33: 1503121227 | AC33: 4728326400 | AH33: Воск для лап для собак и кошек 50 мл | AI33: Воск для лап собак и кошек защитный | AJ33: Шампунь для собак и кошек с кондиционером, 500 мл | AK33: Шампунь для собак и кошек с кондиционером, универсальный шампунь для животных 500 мл | AP33: https://www.wildberries.ru/catalog/559225020/detail.aspx | AQ33: https://www.ozon.ru/product/1503121227 | AR33: https://market.yandex.ru/card/shampun-dlya-sobak-i-koshek-s-konditsionerom-500-ml/103397002661?businessId=8291477&clid=8291477&model_id=965085250&distr_type=8&pp=605 | AW33: Шампуни для животных | AX33: Шампунь для собак и кошек с кондиционером, 500 мл | AY33: товары для животных / косметика и гигиена | BD33: Алексей | BE33: Семен | BF33: Анна Пирогова | BG33: Екатерина Доможирова | BH33: Екатерина Доможирова | BI33: Екатерина Доможирова | BL33: 4670207150202; 4657786831487 | BN33: ДС | BO33: https://drive.google.com/drive/folders/1_QPjS9mJZl1HeJQYZvxo5r41lee-IUVq | BP33: без ЧЗ | BS33: то же самое, что и 30 мл | BU33: нанесите средство на подушечки лап животных перед прогулкой, давая составу подсохнуть в течение минуты. После прогулки сотрите воск салфеткой и смойте остатки продукта теплой водой. | BW33: Температура хранения: от +5°C до +25°C. | BX33: 50 | BY33: мл | CA33: 2 года | CB33: 24 месяца | CC33: то же самое, что и 30 мл | CM33: =IFERROR(VLOOKUP(B33,CC!A:D,4,0)," ") -> 185.4 | CN33: ООО «М9 Фарм» 445043, Самарская обл, Тольятти г, Южное шоссе, влд. 14 стр.3, помещение 31, 32. | CS33: 3 | CT33: нет | CY33: FALSE | CZ33: FALSE | DA33: FALSE | DB33: FALSE | DJ33: =IFERROR(VLOOKUP($B33,'Лист4'!$D:$AI,27,0)," ") -> 5 | DK33: =IFERROR(VLOOKUP($B33,'Лист4'!$D:$AI,28,0)," ") -> 11 | DL33: =IFERROR(VLOOKUP($B33,'Лист4'!$D:$AI,29,0)," ") -> 5 | DM33: =IFERROR(DJ33*DK33*DL33," ") -> 275 | DN33: =IFERROR(VLOOKUP($B33,'Лист4'!$D:$AI,32,0)," ") -> 0.081
A34: Биг-Л | B34: qeep_probioticdetox_60caps | C34: qeep | D34: Актуальный | E34: КЗ Внешка | F34: БАД Пробиотик детокс | G34: БАДы | H34: ЖКТ | K34: TRUE | L34: TRUE | M34: TRUE | N34: TRUE | O34: FALSE | P34: FALSE | Q34: FALSE | S34: QB101100523 | T34: qeep_probioticdetox_60caps | U34: qeep_probioticdetox_60caps | V34: qeep_probioticdetox_60caps | AA34: 568667310 | AB34: 3010994519 | AC34: 4737198096 | AH34: БАД Пробиотик детокс | AI34: Пробиотик и пребиотик для кишечника взрослым | AJ34: Пробиотики для взрослых qeep Probiotic Detox, 60 капсул | AK34: Пробиотики для взрослых, восстановление микрофлоры qeep Probiotic Detox, 60 капсул | AP34: https://www.wildberries.ru/catalog/568667310/detail.aspx | AQ34: https://www.ozon.ru/product/3010994519 | AR34: https://market.yandex.ru/card/probiotiki-dlya-vzroslykh-vosstanovleniye-mikroflory-qeep-probiotic-detox-60-kapsul/4737198096?businessId=8291477&clid=8291477&model_id=696148335&distr_type=8&pp=605 | AW34: Комплексные пищевые добавки | AX34: Пробиотики для взрослых qeep Probiotic Detox, 60 капсул | AY34: аптека / витамины, минералы, добавки | BD34: Света | BE34: Семен | BF34: Анна Пирогова | BG34: Екатерина Доможирова | BH34: Екатерина Доможирова | BI34: Екатерина Доможирова | BL34: 4657796830517 | BM34: 2106909808 | BN34: ДС | BO34: https://drive.google.com/drive/folders/1zKli08gC7aQQz0moHj-M5xlo3KGR6t-7 | BP34: без ЧЗ | BS34: Lactobacillus acidophilus, Bifidobacterium lactis, Lactobacillus rhamnosus, Lactobacillus plantarum, Bifidobacterium longum, Bifidobacterium breve, Lactobacillus casei, Lactobacillus salivarius, стеарат магния и диоксид кремния (антислеживающие агенты), целлюлоза микрокристаллическая (носитель), гидроксипропилметилцеллюлоза (оболочка). | BU34: взрослым по 1 капсуле 1 раз в сутки во время еды во второй половине дня. Продолжительность приема: 30 дней. При необходимости прием можно повторить. | BV34: индивидуальная непереносимость компонентов, беременность, кормление грудью. Перед применением рекомендуется проконсультироваться с врачом. | BW34: хранить в сухом, защищенном от прямых солнечных лучей и недоступном для детей месте, при температуре не выше 25°С. | BX34: 60 | BY34: капс | CA34: 2 года | CB34: 24 месяца | CC34: https://docs.google.com/document/d/1D18PC_n37C59tahp-aWwfDTYcMsxYgE6ImIIoDSCzHI/edit?tab=t.0 | CG34: 46058 | CH34: https://disk.yandex.ru/d/PryAeo5LcSBWJw | CM34: =IFERROR(VLOOKUP(B34,CC!A:D,4,0)," ") -> 147.33 | CN34: НПК Биосинергия | CP34: Янина 89516200810 | CS34: 10 | CT34: нет | CY34: FALSE | CZ34: FALSE | DA34: FALSE | DB34: FALSE | DJ34: =IFERROR(VLOOKUP($B34,'Лист4'!$D:$AI,27,0)," ") -> 5 | DK34: =IFERROR(VLOOKUP($B34,'Лист4'!$D:$AI,28,0)," ") -> 5 | DL34: =IFERROR(VLOOKUP($B34,'Лист4'!$D:$AI,29,0)," ") -> 5 | DM34: =IFERROR(DJ34*DK34*DL34," ") -> 125 | DN34: =IFERROR(VLOOKUP($B34,'Лист4'!$D:$AI,32,0)," ") -> 0.05
A35: Биг-Л | B35: qeep_zma_120caps_v2 | C35: qeep | D35: Актуальный | E35: Цена ВБ | F35: БАД ZMA 120 капсул | G35: БАДы | H35: Спорт | K35: TRUE | L35: TRUE | M35: TRUE | N35: TRUE | O35: FALSE | P35: FALSE | Q35: FALSE | S35: QB101100524 | T35: qeep_zma_120caps_v2 | U35: qeep_zma_120caps_v2 | V35: qeep_zma_120caps_v2 | AA35: 588937927 | AB35: 3044876607 | AC35: 4737102558 | AH35: БАД ZMA 120 капсул | AI35: ZMA – комплекс для бустера тестостерона | AJ35: ZMA тестостерон для мужчин Цинк + Магний + Аспарагиновая Кислота + В6 Qeep Экдистерон 120 капсул | AK35: ZMA тестостерон для мужчин Цинк + Магний + Аспарагиновая Кислота + В6 Qeep Экдистерон 120 капсул | AP35: https://www.wildberries.ru/catalog/588937927/detail.aspx | AQ35: https://www.ozon.ru/product/3044876607 | AR35: https://market.yandex.ru/card/zma-testosteron-dlya-muzhchin-tsink--magniy--asparaginovaya-kislota--v6-qeep-ekdisteron-120-kapsul/4737102558?businessId=8291477&clid=8291477&model_id=925062646&distr_type=8&pp=605 | AW35: Бустеры тестостерона | AX35: ZMA тестостерон для мужчин Цинк + Магний + Аспарагиновая Кислота + В6 Qeep Экдистерон 120 капсул | AY35: спорт и отдых / тренажеры и фитнес / спортивное питание / тестостероновые бустеры | BD35: Алексей | BE35: Семен | BF35: Анна Пирогова | BG35: Екатерина Доможирова | BH35: Екатерина Доможирова | BI35: Екатерина Доможирова | BL35: 4627102679765 | BM35: 2106909808 | BN35: AM.01.11.01.003.R.000356.06.24 от 04.06.2024 | BO35: https://drive.google.com/drive/folders/1rV8K5p1fq6qOIW7VD0lGtibqmVER_wvl | BP35: ЧЗ | BS35: магния цитрат, микрокристаллическая целлюлоза (агент антислеживающий), желатин*, цитрат цинка, аспарагиновая кислота, витамин В6 (пиридоксина гидрохлорид). | BU35: взрослым по 1 капсуле в день во время еды. | BV35: индивидуальная непереносимость компонентов продукта, беременность, кормление грудью. Перед применением рекомендуется проконсультироваться с врачом. | BW35: хранить в сухом, защищенном от прямых солнечных лучей, недоступном для детей месте, при температуре от +5°С до 25 °С и относительной влажности воздуха не более 75%. | BX35: 120 | BY35: капс | CA35: 2 года | CB35: 24 месяца | CC35: https://docs.google.com/document/d/1Pql-dvczOf-_ICvb7bpO4To-neBst-RQ2vw-bPcx6HI/edit?tab=t.0 | CM35: =IFERROR(VLOOKUP(B35,CC!A:D,4,0)," ") -> 196.22 | CN35: ООО "Лайфавит" | CP35: Артем (гендир) +7 916 602 5268 | CS35: 1 | CT35: нет | CY35: FALSE | CZ35: FALSE | DA35: FALSE | DB35: FALSE | DJ35: =IFERROR(VLOOKUP($B35,'Лист4'!$D:$AI,27,0)," ") -> 6 | DK35: =IFERROR(VLOOKUP($B35,'Лист4'!$D:$AI,28,0)," ") -> 11 | DL35: =IFERROR(VLOOKUP($B35,'Лист4'!$D:$AI,29,0)," ") -> 6 | DM35: =IFERROR(DJ35*DK35*DL35," ") -> 396 | DN35: =IFERROR(VLOOKUP($B35,'Лист4'!$D:$AI,32,0)," ") -> 0.133
A36: Биг-Л | B36: harly_salmonoil_250ml | C36: Harly | D36: Актуальный | F36: Масло лосося для собак и кошек 250 мл | G36: Корма и Кормовые добавки | H36: Лососевое масло | K36: TRUE | L36: TRUE | M36: TRUE | N36: TRUE | O36: FALSE | P36: FALSE | Q36: FALSE | S36: HB101100410 | T36: harly_salmonoil_250ml | U36: harly_salmonoil_250ml | V36: harly_salmonoil_250ml | AA36: 617717249 | AB36: 3106984552 | AC36: 4764708144 | AH36: Масло лосося для собак и кошек 250 мл | AI36: Лососевое масло для собак и кошек | AJ36: Лососевое масло для собак и кошек Harly 250 мл | AK36: Лососевое масло для собак и кошек, с маслом лосося, рыбий жир, Омега 3 для животных, Harly 250 мл | AP36: https://www.wildberries.ru/catalog/617717249/detail.aspx | AQ36: https://www.ozon.ru/product/3106984552 | AR36: https://market.yandex.ru/card/lososevoye-maslo-dlya-sobak-i-koshek-s-maslom-lososya-rybiy-zhir-omega-3-dlya-zhivotnykh-harly-250-ml/4764708144?businessId=8291477&clid=8291477&model_id=838121044&distr_type=8&pp=605 | AW36: Витамины и добавки для животных | AX36: Лососевое масло для собак и кошек Harly 250 мл | AY36: товары для животных / ветаптека / витамины для животных и птиц / витамины для животных и птиц | BD36: Алексей | BE36: Семен | BF36: Анна Пирогова | BG36: Екатерина Доможирова | BH36: Екатерина Доможирова | BI36: Екатерина Доможирова | BL36: 4620290621356 | BM36: 2309109000 | BN36: РОСС RU Д-RU.РА01.В.08426/25 от 18.03.2025 по 17.03.2030 | BO36: https://drive.google.com/drive/folders/1mWkENWzV8LFCasWOb9Z2fVT4g_8zzLup | BP36: ЧЗ | BS36: 100% натуральное масло лосося | BU36: Одно нажатие 1,15 г на каждые 5 кг веса животного. | BW36: хранить в прохладном, защищенном от света месте (в летний период не выше 30 °С). Вскрытый флакон хранить в холодильнике при температуре от + 4 °С до +8 °С. | BX36: 250 | BY36: мл | CA36: 12 месяцев | CB36: 12 месяцев | CC36: то же самое, что и 250 мл | CG36: 46044 | CH36: https://disk.yandex.ru/d/ZObw08ht-L3EKg | CM36: =IFERROR(VLOOKUP(B36,CC!A:D,4,0)," ") -> 278 | CN36: ООО Терра-пласт | CP36: Гордиенко Евгения Степановна (812)748-22-25(доб.101) +7(962)689-06-49 stm@gkfavorite.ru | CQ36: 60 | CS36: 2 | CT36: нет | CY36: FALSE | CZ36: FALSE | DA36: FALSE | DB36: FALSE | DJ36: =IFERROR(VLOOKUP($B36,'Лист4'!$D:$AI,27,0)," ") -> 7 | DK36: =IFERROR(VLOOKUP($B36,'Лист4'!$D:$AI,28,0)," ") -> 17 | DL36: =IFERROR(VLOOKUP($B36,'Лист4'!$D:$AI,29,0)," ") -> 7 | DM36: =IFERROR(DJ36*DK36*DL36," ") -> 833 | DN36: =IFERROR(VLOOKUP($B36,'Лист4'!$D:$AI,32,0)," ") -> 0.236
A37: Биг-Л | B37: qeep_chlorophyll_500ml_v2 | C37: qeep | D37: Актуальный | F37: БАД Хлорофилл 500 мл | G37: БАДы | H37: ЖКТ | K37: TRUE | L37: TRUE | M37: TRUE | N37: TRUE | O37: FALSE | P37: FALSE | Q37: FALSE | S37: QB101100515 | T37: qeep_chlorophyll_500ml_v2 | U37: qeep_chlorophyll_500ml_v2 | V37: qeep_chlorophyll_500ml_v2 | AA37: 165592674 | AB37: 3108027348 | AC37: 102055263406 | AH37: БАД Хлорофилл 500 мл | AI37: Хлорофилл жидкий со вкусом мяты БАД Chlorophyll, 500 мл | AJ37: БАД Chlorophyll, 500 мл Жидкий хлорофилл со вкусом мяты, 500мл | AK37: Хлорофилл жидкий пищевой со вкусом мяты, детокс и похудение, выводит токсины, Chlorophyll 500 мл | AP37: https://www.wildberries.ru/catalog/165592674/detail.aspx | AQ37: https://www.ozon.ru/product/3108027348 | AR37: https://market.yandex.ru/card/bad-chlorophyll-500-ml-zhidkiy-khlorofill-so-vkusom-myaty-500ml/4787246513?businessId=8291477&clid=8291477&model_id=1826260757&distr_type=8&pp=605 | AW37: БАДы | AX37: БАД Chlorophyll, 500 мл Жидкий хлорофилл со вкусом мяты, 500мл | AY37: аптека / витамины, минералы, добавки | BD37: Света | BE37: Семен | BF37: Анна Пирогова | BG37: Екатерина Доможирова | BH37: Екатерина Доможирова | BI37: Екатерина Доможирова | BL37: 4630205142852 | BM37: 2106909808 | BN37: AM.01.01.01.003.R.000759.11.24 | BO37: https://drive.google.com/drive/folders/1ldsojot3L5fpXNicn_hj4PzJwj0hpgp8 | BP37: ЧЗ | BS37: столовая минеральная вода, краситель: медный комплекс хлорофилла, регулятор кислотности лимонная кислота, эфирное масло мяты, консерванты: сорбат калия. | BU37: взрослым принимать 25 мл 1 раз в день смешав со 100 мл тёплой воды или любым напитком во время приема пищи. | BW37: хранить в сухом, защищённом от прямых солнечных лучей и недоступном для детей месте при температуре от +5 °С до + 25 °С. | BX37: 500 | BY37: мл | CA37: 12 месяцев | CC37: https://docs.google.com/document/d/104ULlyOAuV1IDK64Sv8iDI3_Bj64t1baZTUGBsWJfz4/edit?tab=t.0 | CG37: 46062 | CH37: https://disk.yandex.ru/d/VLjP4IaPPTLyzQ | CM37: =IFERROR(VLOOKUP(B37,CC!A:D,4,0)," ") -> 400 | CN37: ООО «Жива Продукт ПРО». 350062, Россия, Краснодарский край, город Краснодар, улица Казбекская, дом 17, кв. (оф.) 85 | CP37: Магамадов Ибрагим e-mail: ima@dzivaproduct.ru сайт: www.dzivaproduct.ru сот.тел. +7-967-660-1277(доступен WhatsApp) | CQ37: 60 | CS37: 5 | CT37: да | CY37: FALSE | CZ37: FALSE | DA37: FALSE | DB37: FALSE | DJ37: =IFERROR(VLOOKUP($B37,'Лист4'!$D:$AI,27,0)," ") -> 6 | DK37: =IFERROR(VLOOKUP($B37,'Лист4'!$D:$AI,28,0)," ") -> 21 | DL37: =IFERROR(VLOOKUP($B37,'Лист4'!$D:$AI,29,0)," ") -> 6 | DM37: =IFERROR(DJ37*DK37*DL37," ") -> 756 | DN37: =IFERROR(VLOOKUP($B37,'Лист4'!$D:$AI,32,0)," ") -> 0.576
A38: Биг-Л | B38: qeep_spf50_50ml | C38: qeep | D38: Актуальный | F38: Крем SPF 50 солнцезащитный 50 мл | G38: Косметика | H38: Лицо | K38: TRUE | L38: TRUE | M38: TRUE | N38: TRUE | O38: FALSE | P38: FALSE | Q38: FALSE | S38: QC101100414 | T38: qeep_spf50_50ml | U38: qeep_spf50_50ml | V38: qeep_spf50_50ml | AA38: 681199239 | AB38: 3190972100 | AC38: 4824577371 | AH38: Крем SPF 50 солнцезащитный 50 мл | AI38: Крем солнцезащитный SPF 50 для лица, 50 мл | AJ38: Крем солнцезащитный SPF 50 для лица, 50 мл | AK38: Солнцезащитный крем SPF 50 для лица, увлажняющий крем от загара с спф, 50мл | AP38: https://www.wildberries.ru/catalog/681199239/detail.aspx | AQ38: https://www.ozon.ru/product/3190972100 | AR38: https://market.yandex.ru/card/krem-solntsezashchitnyy-spf-50-dlya-litsa-50-ml/4824577371?businessId=8291477&clid=8291477&model_id=1581702225&distr_type=8&pp=605 | AW38: Кремы | AX38: Крем солнцезащитный SPF 50 для лица, 50 мл | AY38: товары для красоты / косметика, парфюмерия и уход / уход за лицом / загар и защита от солнца | BD38: Мария | BE38: Кристина | BF38: Анна Пирогова | BG38: Екатерина Доможирова | BH38: Екатерина Доможирова | BI38: Екатерина Доможирова | BL38: 4660417421773 | BN38: ДС | BO38: https://drive.google.com/drive/folders/1GcFduMhHSQj_HtTQiHBS8B-cdpu5Eyhz | BP38: ЧЗ | BS38: Deionized Water, Methylene Bis-Benzotriazolyl Tetramethylbutylphenol, Diethylamino Hydroxybenzoyl Hexyl Benzoate, Ceto Stearyl Alcohol, Isoamyl laurate, Hyaluronic Acid, Sodium acrylates copolymer (and) Lecithin, Green Tea Leaf Extract, Glycerin, Glycerol monostearate, Glyceryl Stearate, Ceteareth-20, Ceteareth-12, Cetearyl Alcohol, Cetyl Palmitate, Bis-Ethylhexyloxyphenol Methoxyphenyl Triazine, Phenoxyethanol, Ethylhexylglycerin, Divinyldimethicone, Ethylhexyl Triazone, Coenzyme Q10, Coenzyme Q10, Disodium edta, , Ceramides Complex CR/Water, Pentylene Glycol, Phospholipids, Sphingolipids, Niacinamide, Tapioca Starch, Sodium Polyacrylate, Panthenol, Butyrospermum Parkii, Prunus Amygdalus Dulcis Oil, CI 17200, Parfum | BU38: необходимое количество распределите на коже лёгкими массажными движениями. | BW38: хранить в сухом недоступном для света месте при температуре от +5 ℃ до +25 ℃. | BX38: 50 | BY38: мл | CA38: 3 года | CB38: 36 месяца | CC38: https://docs.google.com/document/d/1_ZRzckXpOl9Dc9S0bk4Sbj69ercMb3ffBIya-yui4XI/edit?tab=t.0 | CM38: =IFERROR(VLOOKUP(B38,CC!A:D,4,0)," ") -> 130 | CN38: Восток-плюс | CP38: Дмитрий | CQ38: 45 | CS38: 1 | CT38: нет | CY38: FALSE | CZ38: FALSE | DA38: FALSE | DB38: FALSE | DJ38: =IFERROR(VLOOKUP($B38,'Лист4'!$D:$AI,27,0)," ") -> 1 | DK38: =IFERROR(VLOOKUP($B38,'Лист4'!$D:$AI,28,0)," ") -> 1 | DL38: =IFERROR(VLOOKUP($B38,'Лист4'!$D:$AI,29,0)," ") -> 1 | DM38: =IFERROR(DJ38*DK38*DL38," ") -> 1 | DN38: =IFERROR(VLOOKUP($B38,'Лист4'!$D:$AI,32,0)," ") -> 1
A39: Биг-Л | B39: qeep_retinolcream1_50ml | C39: qeep | D39: Актуальный | F39: Крем для лица Retinol с ретинолом 1%, 50 мл | G39: Косметика | H39: Лицо | K39: TRUE | L39: TRUE | M39: TRUE | N39: TRUE | O39: FALSE | P39: FALSE | Q39: FALSE | S39: QC101100412 | T39: qeep_retinolcream1_50ml | U39: qeep_retinolcream1_50ml | V39: qeep_retinolcream1_50ml | AA39: 687712933 | AB39: 3219081694 | AC39: 4842304692 | AH39: Крем для лица Retinol с ретинолом 1%, 50 мл | AI39: Крем для Лица с Липосомальным Ретинолом 1% | AJ39: Крем для Лица с Липосомальным Ретинолом 1% | AK39: Крем для лица с липосомальным ретинолом 1%, антивозрастной крем, сыворотка для лица от морщин, Ретинол, 50 мл | AP39: https://www.wildberries.ru/catalog/687712933/detail.aspx | AQ39: https://www.ozon.ru/product/3219081694 | AR39: https://market.yandex.ru/card/krem-dlya-litsa-s-liposomalnym-retinolom-1/4842304692?businessId=8291477&clid=8291477&model_id=1453951928&distr_type=8&pp=605 | AW39: Кремы | AX39: Крем для Лица с Липосомальным Ретинолом 1% | AY39: товары для красоты / косметика, парфюмерия и уход / уход за лицом / кремы и сыворотки / средства для ухода за лицом | BD39: Мария | BE39: Кристина | BF39: Анна Пирогова | BG39: Екатерина Доможирова | BH39: Екатерина Доможирова | BI39: Екатерина Доможирова | BL39: 4660417421780 | BN39: ДС | BP39: ЧЗ | BS39: Aqua, Isopropyl Palmitate, Acrylamide/Sodium Acrylate Copolymer, Niacinamide, Urea, Squalane, Helianthus, Annuus (Sunflower) Seed Oil, Mineral Oil, Cyclopentasiloxane, Caprylic/Capric Triglyceride, Acrylates/C10-30 Alkyl Acrylate Crosspolymer, Tocopheryl Acetate, Lecithin, Retinol, Phospholipids, Dimethiconol, Panthenol, Trideceth-6, C11-13 Isoparaffin, Colloidal Gold, BHT, Tetrasodium Glutamate Diacetate, Sodium Hydroxide, Phenoxyethanol, Ethylhexylglycerin, Parfum, Geraniol, Linalool. | BU39: небольшое количество крема распределить между ладоней. Нанести на сухую кожу лица. Сделать мягкий массаж. Если выпользуетесь ретинолом впервые, начните с 2-3 раз в неделю и постепенно увеличивайте частоту применений. Пользуясь ретинолом, защищайте кожу от солнца кремом с SPF 30 и больше. | BW39: хранить в сухом недоступном для света месте при температуре от +5 ℃ до +25 ℃. | BX39: 50 | BY39: мл | CA39: 36 месяцев | CB39: 36 месяцев | CC39: https://docs.google.com/document/d/19loz_S6MoghRtwGPBPaBA67dYGaqjoNVU0hzqH3ehCs/edit?tab=t.0 | CG39: 46071 | CH39: https://disk.yandex.ru/d/kWCbF653aZ0amQ | CM39: =IFERROR(VLOOKUP(B39,CC!A:D,4,0)," ") -> 99.73 | CN39: Восток-плюс | CP39: Дмитрий | CQ39: 45 | CS39: 1 | CT39: нет | CY39: FALSE | CZ39: FALSE | DA39: FALSE | DB39: FALSE | DJ39: =IFERROR(VLOOKUP($B39,'Лист4'!$D:$AI,27,0)," ") -> 1 | DK39: =IFERROR(VLOOKUP($B39,'Лист4'!$D:$AI,28,0)," ") -> 1 | DL39: =IFERROR(VLOOKUP($B39,'Лист4'!$D:$AI,29,0)," ") -> 1 | DM39: =IFERROR(DJ39*DK39*DL39," ") -> 1 | DN39: =IFERROR(VLOOKUP($B39,'Лист4'!$D:$AI,32,0)," ") -> 1
A40: Биг-Л | B40: qeep_retinolcream15_50ml | C40: qeep | D40: Актуальный | F40: Крем для лица Retinol с ретинолом 1,5%, 50 мл | G40: Косметика | H40: Лицо | K40: TRUE | L40: TRUE | M40: TRUE | N40: TRUE | O40: FALSE | P40: FALSE | Q40: FALSE | S40: QC101100413 | T40: qeep_retinolcream15_50ml | U40: qeep_retinolcream15_50ml | V40: qeep_retinolcream15_50ml | AA40: 692599189 | AB40: 3220730122 | AC40: 4842314518 | AH40: Крем для лица Retinol с ретинолом 1,5%, 50 мл | AI40: Крем для Лица с Липосомальным Ретинолом 1.5% | AJ40: Крем для Лица с Липосомальным Ретинолом 1.5% | AK40: Крем для лица с липосомальным ретинолом 1.5%, сыворотка для лица от морщин, антивозрастной крем, Ретинол, 50 мл | AP40: https://www.wildberries.ru/catalog/692599189/detail.aspx | AQ40: https://www.ozon.ru/product/3220730122 | AR40: https://market.yandex.ru/card/krem-dlya-litsa-s-liposomalnym-retinolom-15/4842314518?businessId=8291477&clid=8291477&model_id=1453951928&distr_type=8&pp=605 | AW40: Кремы | AX40: Крем для Лица с Липосомальным Ретинолом 1.5% | AY40: товары для красоты / косметика, парфюмерия и уход / уход за лицом / кремы и сыворотки / средства для ухода за лицом | BD40: Мария | BE40: Кристина | BF40: Анна Пирогова | BG40: Екатерина Доможирова | BH40: Екатерина Доможирова | BI40: Екатерина Доможирова | BL40: 4660417421742 | BN40: ДС | BP40: ЧЗ | BS40: Aqua, Isopropyl Palmitate, Acrylamide/Sodium Acrylate Copolymer, Niacinamide, Urea, Squalane, Helianthus, Annuus (Sunflower) Seed Oil, Mineral Oil, Cyclopentasiloxane, Caprylic/Capric Triglyceride, Acrylates/C10-30 Alkyl Acrylate Crosspolymer, Tocopheryl Acetate, Lecithin, Retinol, Phospholipids, Dimethiconol, Panthenol, Trideceth-6, C11-13 Isoparaffin, Colloidal Gold, BHT, Tetrasodium Glutamate Diacetate, Sodium Hydroxide, Phenoxyethanol, Ethylhexylglycerin, Parfum, Geraniol, Linalool. | BU40: небольшое количество крема распределить между ладоней. Нанести на сухую кожу лица. Сделать мягкий массаж. Если выпользуетесь ретинолом впервые, начните с 2-3 раз в неделю и постепенно увеличивайте частоту применений. Пользуясь ретинолом, защищайте кожу от солнца кремом с SPF 30 и больше. | BW40: хранить в сухом недоступном для света месте при температуре от +5 ℃ до +25 ℃. | BX40: 50 | BY40: мл | CA40: 36 месяцев | CB40: 36 месяцев | CC40: https://docs.google.com/document/d/1MAA6ZzERRG3dnphO-1JyLfa2yb4d8I9nH72L7T3jQzg/edit?tab=t.0 | CG40: 46071 | CM40: =IFERROR(VLOOKUP(B40,CC!A:D,4,0)," ") -> 104.83 | CN40: Восток-плюс | CP40: Дмитрий | CQ40: 45 | CS40: 1 | CT40: нет | CY40: FALSE | CZ40: FALSE | DA40: FALSE | DB40: FALSE | DJ40: =IFERROR(VLOOKUP($B40,'Лист4'!$D:$AI,27,0)," ") -> 1 | DK40: =IFERROR(VLOOKUP($B40,'Лист4'!$D:$AI,28,0)," ") -> 1 | DL40: =IFERROR(VLOOKUP($B40,'Лист4'!$D:$AI,29,0)," ") -> 1 | DM40: =IFERROR(DJ40*DK40*DL40," ") -> 1 | DN40: =IFERROR(VLOOKUP($B40,'Лист4'!$D:$AI,32,0)," ") -> 1
A41: Биг-Л | B41: qeep_biotin_10000_60caps | C41: qeep | D41: Актуальный | E41: Фокус + КЗ | F41: Биотин 10000 мкг ,qeep, 60 капсул | G41: БАДы | H41: Женские | K41: TRUE | L41: TRUE | M41: TRUE | N41: TRUE | O41: TRUE | P41: FALSE | Q41: FALSE | S41: QB101100509 | T41: qeep_biotin_10000_60caps | U41: qeep_biotin_10000_60caps | V41: qeep_biotin_10000_60caps | W41: qeep_biotin_10000_60caps | AA41: 311795896 | AB41: 1773394130 | AC41: 103665479999 | AD41: 99000117795 | AH41: Биотин 10000 мкг ,qeep, 60 капсул | AI41: Биотин 10000 мкг витамины для волос и ногтей Biotin | AJ41: Биотин 10000 мкг Qeep 60 капсул | AK41: Биотин 10000 мкг для здоровья кожи, волос, ногтей Qeep 60 капсул | AL41: биотин 10000 мкг qeep 60 капсул | AP41: https://www.wildberries.ru/catalog/311795896/detail.aspx | AQ41: https://www.ozon.ru/product/1773394130 | AR41: https://market.yandex.ru/card/biotin-10000-mkg-qeep-60-kapsul/103665479999?businessId=8291477&clid=8291477&model_id=838753782&distr_type=8&pp=605 | AS41: https://goldapple.ru/catalogsearch/result?q=99000117795 | AW41: Комплексные пищевые добавки | AX41: Биотин 10000 мкг Qeep 60 капсул | AY41: аптека / витамины, минералы, добавки | AZ41: Бады витамины | BD41: Света | BE41: Семен | BF41: Анна Пирогова | BG41: Екатерина Доможирова | BH41: Екатерина Доможирова | BI41: Екатерина Доможирова | BL41: 4670227416890 | BN41: ЕАЭС N RU Д-RU.РА03.В.41003/23 от 21.04.2023 до 19.04.2026 | BO41: https://drive.google.com/drive/folders/1z8D3umXCI2M6KCJyeirlPDZ2j20UoYfG | BP41: без ЧЗ | BS41: биотин, микрокристаллическая целлюлоза (носитель), капсула целлюлозная. | BU41: взрослым принимать по 1 капсуле 1 раз в день, вне приема пищи. Продолжительность приема: 1 месяц. | BV41: индивидуальная непереносимость компонентов продукта, беременность, кормление грудью. Перед применением проконсультироваться с врачом. | BW41: хранить в сухом, защищённом от прямых солнечных лучей и недоступном для детей месте при температуре от +5 °С до + 25 °С. | BX41: 60 | BY41: шт | CA41: 2 года | CB41: 24 месяца | CC41: https://docs.google.com/document/d/13hyDvniBc4P4K1GrV4sx8EJIsQ3I-GOIthGYpRptuHg/edit?usp=sharing | CM41: =IFERROR(VLOOKUP(B41,CC!A:D,4,0)," ") -> 220 | CN41: ООО «Жива Продукт ПРО». 350062, Россия, Краснодарский край, город Краснодар, улица Казбекская, дом 17, кв. (оф.) 85 | CP41: Магамадов Ибрагим e-mail: ima@dzivaproduct.ru сайт: www.dzivaproduct.ru сот.тел. +7-967-660-1277(доступен WhatsApp) | CQ41: 60 | CS41: 5 | CT41: да | CY41: FALSE | CZ41: FALSE | DA41: FALSE | DB41: FALSE | DJ41: =IFERROR(VLOOKUP($B41,'Лист4'!$D:$AI,27,0)," ") -> 12 | DK41: =IFERROR(VLOOKUP($B41,'Лист4'!$D:$AI,28,0)," ") -> 6 | DL41: =IFERROR(VLOOKUP($B41,'Лист4'!$D:$AI,29,0)," ") -> 12 | DM41: =IFERROR(DJ41*DK41*DL41," ") -> 864 | DN41: =IFERROR(VLOOKUP($B41,'Лист4'!$D:$AI,32,0)," ") -> 0.074
A42: Биг-Л | B42: qeep_pqq_30caps | C42: qeep | D42: Актуальный | F42: PQQ Q10 Витамины для сердца ,qeep, 30 капсул | G42: БАДы | H42: Женские | K42: TRUE | L42: TRUE | M42: TRUE | N42: TRUE | O42: TRUE | P42: FALSE | Q42: FALSE | S42: QB101100514 | T42: qeep_pqq_30caps | U42: qeep_pqq_30caps | V42: qeep_pqq_30caps | W42: qeep_pqq_30caps | AA42: 302436449 | AB42: 1785810392 | AC42: 103689767957 | AD42: 99000117793 | AH42: PQQ Q10 Витамины для сердца ,qeep, 30 капсул | AI42: PQQ + Q10 Витамины для сердца и сосудов | AJ42: PQQ Q10 Витамины для сердца и сосудов qeep 30 капсул | AK42: PQQ Q10 Витамины для сердца и сосудов комплекс витаминов для сердца qeep 30 капсул | AL42: pqq q10 витамины для сердца и сосудов qeep 30 капсул | AP42: https://www.wildberries.ru/catalog/302436449/detail.aspx | AQ42: https://www.ozon.ru/product/1785810392 | AR42: https://market.yandex.ru/card/koenzim-q10-vitaminy-dlya-serdtsa-i-sosudov-qeep-30-kapsul/103689767957?businessId=8291477&clid=8291477&model_id=1268975231&distr_type=8&pp=605 | AW42: Комплексные пищевые добавки | AX42: PQQ Q10 Витамины для сердца и сосудов qeep 30 капсул | AY42: аптека / витамины, минералы, добавки | AZ42: БАДы и витамины | BD42: Алексей | BE42: Семен | BF42: Анна Пирогова | BG42: Екатерина Доможирова | BH42: Екатерина Доможирова | BI42: Екатерина Доможирова | BL42: 4680162842876 | BM42: 2914698000 | BN42: ЕАЭС N RU Д-RU.РА10.В.31748/24 от 08.11.2024 по 07.11.2029 | BO42: https://drive.google.com/drive/folders/1hPlN19xPrlRyphMqsWwBx67MXsHQJSce | BP42: без ЧЗ | BS42: астаксантин, глутатион, коэнзим Q10 (убихинон), пирролохинолинхинона динатриевая соль, микрокристаллическая целлюлоза (носитель), магния стеарат (антислеживающий агент); желатин – оболочка капсулы. | BU42: По 1-2 капсуле в день во время еды. Для приготовления порции напитка содержимое капсулы смешивают с водой комнатной температуры. Продолжительность приема – 1 месяц. При необходимости прием можно повторить. Перед применением рекомендуется проконсультироваться с врачом | BV42: Индивидуальная непереносимость компонентов, беременность, кормление грудью, возраст до 18 лет. | BW42: хранить в сухом, защищенном от попадания прямых солнечных лучей, недоступном для детей месте, при температуре не выше +25 °С. | BX42: 30 | BY42: шт | CA42: 2 года | CB42: 24 месяца | CC42: https://docs.google.com/document/d/1jvekMTUpAs6HSt_spJB0RedxivbBxQB_stcPrNSUEHk/edit?tab=t.0 | CM42: =IFERROR(VLOOKUP(B42,CC!A:D,4,0)," ") -> 490 | CN42: НПК Миламед | CP42: Юлия Шаврина РФ, г. Пермь, ул. Монастырская д. 61 оф. 600 Тел.: +7 (342) 248 38 70 доб 14 E-mail: uk_shavrina@milapharma.ru | CQ42: 90 | CS42: 7 | CT42: нет | CY42: FALSE | CZ42: FALSE | DA42: FALSE | DB42: FALSE | DJ42: =IFERROR(VLOOKUP($B42,'Лист4'!$D:$AI,27,0)," ") -> 9 | DK42: =IFERROR(VLOOKUP($B42,'Лист4'!$D:$AI,28,0)," ") -> 4 | DL42: =IFERROR(VLOOKUP($B42,'Лист4'!$D:$AI,29,0)," ") -> 9 | DM42: =IFERROR(DJ42*DK42*DL42," ") -> 324 | DN42: =IFERROR(VLOOKUP($B42,'Лист4'!$D:$AI,32,0)," ") -> 0.043
A43: Биг-Л | B43: qeep_biopurin_60caps | C43: qeep | D43: Актуальный | F43: Биопурин от подагры ,qeep, 60 капсул | G43: БАДы | H43: Женские | K43: TRUE | L43: TRUE | M43: TRUE | N43: TRUE | O43: FALSE | P43: FALSE | Q43: FALSE | S43: QB101100508 | T43: qeep_biopurin_60caps | U43: qeep_biopurin_60caps | V43: qeep_biopurin_60caps | AA43: 337468231 | AB43: 1884226546 | AC43: 103812558261 | AH43: Биопурин от подагры ,qeep, 60 капсул | AI43: Биопурин от подагры для суставов 60 капсул | AJ43: Комплексная пищевая добавка "Биопурин", от подагры для суставов qeep 60 капсул | AK43: Биопурин от подагры для суставов, комплекс для здоровья суставов qeep 60 капсул | AP43: https://www.wildberries.ru/catalog/337468231/detail.aspx | AQ43: https://www.ozon.ru/product/1884226546 | AR43: https://market.yandex.ru/card/biopurin-ot-podagry-dlya-sustavov-qeep-60-kapsul/103812558261?businessId=8291477&clid=8291477&model_id=973159540&distr_type=8&pp=605 | AW43: Комплексные пищевые добавки | AX43: Комплексная пищевая добавка "Биопурин", от подагры для суставов qeep 60 капсул | AY43: спорт и отдых / тренажеры и фитнес / спортивное питание / препараты для укрепления связок и суставов | BD43: Света | BE43: Семен | BF43: Анна Пирогова | BG43: Екатерина Доможирова | BH43: Екатерина Доможирова | BI43: Екатерина Доможирова | BL43: 4610030634050 | BN43: ЕАЭС N RU Д-RU.РА11.В.10611/24 от 03.12.2024 по 02.12.2029 | BO43: https://drive.google.com/drive/folders/1hP-3TexPulE2xNhZ0KlXzCHc8aIJ2ux7 | BP43: без ЧЗ | BS43: экстракт мартинии душистой, экстракт хвоща, экстракт чистотела, экстракт босвелии, экстракт корня солодки, агент антислёживающий: диоксид кремния аморфный, агент антислёживающий: магниевая соль стеариновой кислоты, оболочка капсулы белого цвета (желатин, краситель оксид цинка), целлюлоза микрокристаллическая. | BU43: взрослым по 1 капсуле 2 раза в день во время еды. | BV43: индивидуальная непереносимость компонентов продукта, беременность, кормление грудью. Перед применением рекомендуется проконсультироваться с врачом. | BW43: хранить в сухом, защищенном от попадания прямых солнечных лучей, недоступном для детей месте, при температуре не выше +25 °С. | BX43: 60 | BY43: шт | CA43: 2 года | CB43: 24 месяца | CC43: https://docs.google.com/document/d/13YTmPCWXCsDtYIPf6uCLMEQ31B-h9-WRJ5gKLA_hAFg/edit?tab=t.0 | CM43: =IFERROR(VLOOKUP(B43,CC!A:D,4,0)," ") -> 182.97 | CN43: ООО "ЗдравФарм" | CP43: Оксана, 7 966 345 2873 | CQ43: 90 | CS43: 1 | CT43: нет | CY43: FALSE | CZ43: FALSE | DA43: FALSE | DB43: FALSE | DJ43: =IFERROR(VLOOKUP($B43,'Лист4'!$D:$AI,27,0)," ") -> 5 | DK43: =IFERROR(VLOOKUP($B43,'Лист4'!$D:$AI,28,0)," ") -> 9 | DL43: =IFERROR(VLOOKUP($B43,'Лист4'!$D:$AI,29,0)," ") -> 5 | DM43: =IFERROR(DJ43*DK43*DL43," ") -> 225 | DN43: =IFERROR(VLOOKUP($B43,'Лист4'!$D:$AI,32,0)," ") -> 0.047
A44: Биг-Л | B44: qeep_bcomplex_90caps | C44: qeep | D44: Вывод | E44: Неконкурентная цена | F44: БАД Витамины группы B ,qeep, 90 капсул | G44: БАДы | H44: Женские | K44: TRUE | L44: TRUE | M44: TRUE | N44: TRUE | O44: FALSE | P44: FALSE | Q44: FALSE | S44: QB101100411 | T44: qeep_bcomplex_90caps | U44: qeep_bcomplex_90caps | V44: qeep_bcomplex_90caps | AA44: 206020100 | AB44: 1408084489 | AH44: БАД Витамины группы B ,qeep, 90 капсул | AI44: Комплекс БАДы из 7 витаминов группы B | AJ44: Витамины группы B Qeep 90 капсул | AP44: https://www.wildberries.ru/catalog/206020100/detail.aspx | AQ44: https://www.ozon.ru/product/1408084489 | AW44: БАДы | AX44: Витамины группы B Qeep 90 капсул | BD44: Света | BE44: Семен | BF44: Анна Пирогова | BG44: Екатерина Доможирова | BH44: Екатерина Доможирова | BI44: Екатерина Доможирова | BL44: 4620153906576 | BM44: 2106909808 | BN44: RU.77.99.11.003.R.001885.07.23 от 18.07.2023 г. | BO44: https://drive.google.com/drive/folders/12NLK4M-zsS_xNSg_z9brf6p0g7tOFi-w | BP44: ЧЗ | BS44: витамин В3 (никотинамид), витамин В5 (пантотенат кальция), кальциевая соль стеариновой кислоты (агент антислеживающий), кремния диоксид (агент антислеживающий), витамин В6 (пиридоксина гидрохлорид), витамин В1 (тиамина гидрохлорид), витамин В2 (рибофлавин), витамин В9 (L-метилфолат кальция), витамин Н (биотин), витамин В12 (метилкобаламин). целлюлоза микрокристаллическая (носитель), парааминобензойная кислота, крахмал картофельный (носитель), капсула желатиновая (желатин (носитель), глицерин (агент влагоудерживающий)), | BU44: взрослым принимать внутрь по 1 капсуле в день во время еды. Продолжительность приема - 1 месяц. При необходимости прием БАД можно повторить. | BV44: индивидуальная непереносимость компонентов продукта, беременность, кормление грудью. Перед применением рекомендуется проконсультироваться с врачом. | BW44: хранить в сухом, защищенном от попадания прямых солнечных лучей, недоступном для детей месте, при температуре не выше +25 °С. | BX44: 90 | BY44: капсул | CA44: 2 года | CB44: 24 месяца | CC44: https://docs.google.com/document/d/1gKWYWK8CR0ynPcSLie6iQAJD1n0kQ3YKkTGHmbWGNRo/edit?usp=sharing | CM44: =IFERROR(VLOOKUP(B44,CC!A:D,4,0)," ") -> 220.77 | CN44: ООО «Сибфармконтракт» | CP44: Анастасия Лапина тел: 8(3822)556092 (доб. 258), 426792 E-mail: lapina@artlife.ru Skype: live:e18940191d9f1027 634034 г.Томск ул Нахимова 8/2 а/я 358 | CQ44: 90 | CS44: 10 | CT44: нет | CY44: FALSE | CZ44: FALSE | DA44: FALSE | DB44: FALSE | DJ44: =IFERROR(VLOOKUP($B44,'Лист4'!$D:$AI,27,0)," ") -> 4 | DK44: =IFERROR(VLOOKUP($B44,'Лист4'!$D:$AI,28,0)," ") -> 9 | DL44: =IFERROR(VLOOKUP($B44,'Лист4'!$D:$AI,29,0)," ") -> 4 | DM44: =IFERROR(DJ44*DK44*DL44," ") -> 144 | DN44: =IFERROR(VLOOKUP($B44,'Лист4'!$D:$AI,32,0)," ") -> 0.062
A45: Биг-Л | B45: qeep_perfectwoman_60caps | C45: qeep | D45: Актуальный | E45: Фокус + КЗ | F45: БАД Витамины для женщин ,qeep, 60 капсул | G45: БАДы | H45: Женские | K45: TRUE | L45: TRUE | M45: TRUE | N45: TRUE | O45: TRUE | P45: FALSE | Q45: FALSE | S45: QB101100412 | T45: qeep_perfectwoman_60caps | U45: qeep_perfectwoman_60caps | V45: qeep_perfectwoman_60caps | W45: qeep_perfectwoman_60caps | AA45: 216488606 | AB45: 1500211407 | AC45: 103398256606 | AD45: 99000118341 | AH45: БАД Витамины для женщин ,qeep, 60 капсул | AI45: Комплекс витаминов и минералов БАД с коллагеном | AJ45: Витамины для женщин Qeep 60 капсул | AK45: Витамины для женщин, комплекс витаминов и минералов с коллагеном Qeep 60 капсул | AL45: витамины для женщин qeep 60 капсул | AP45: https://www.wildberries.ru/catalog/216488606/detail.aspx | AQ45: https://www.ozon.ru/product/1500211407 | AR45: https://market.yandex.ru/card/vitaminy-dlya-zhenshchin-qeep-60-kapsul/103398256606?businessId=8291477&clid=8291477&model_id=1111706245&distr_type=8&pp=605 | AW45: БАДы | AX45: Витамины для женщин Qeep 60 капсул | AY45: аптека / витамины, минералы, добавки | AZ45: БАДы и витамины | BD45: Света | BE45: Семен | BF45: Анна Пирогова | BG45: Екатерина Доможирова | BH45: Екатерина Доможирова | BI45: Екатерина Доможирова | BL45: 4680162842333 | BM45: 2106909808 | BN45: RU.77.99.11.003.R.001764.07.23 от 11.07.2023 | BO45: https://drive.google.com/drive/folders/1uTF3PrNOTzgxxcX3uhJ5NATQKzjzaT2t | BP45: ЧЗ | BS45: микрокристаллическая целлюлоза (носитель), желатин (оболочка капсулы), витаминный премикс (лактоза (носитель), L-аскорбат натрия, никотинамид, D-альфа-токоферола ацетат, пантотенат кальция, рибофлавин, пиридоксина гидрохлорид, тиамина мононитрат, ретинола ацетат, фолиевая кислота, D-биотин, холекальциферол, цианокобаламин), метилсульфонилметан, экстракты побегов бамбука, листьев крапивы двудомной, травы хвоща полевого, коллаген гидролизованный говяжий, экстракты цветков клевера лугового, корневищ дикого ямса, меди глюконат. | BU45: Взрослым по 1 капсуле 2 раза в день непосредственно после еды. Продолжительность приема – 1 месяц. | BV45: индивидуальная непереносимость компонентов продукта, беременность, кормление грудью. Перед применением рекомендуется проконсультироваться с врачом. | BW45: хранить в сухом, защищенном от попадания прямых солнечных лучей, недоступном для детей месте, при температуре не выше +25 °С. | BX45: 60 | BY45: капсул | CA45: 2 года | CB45: 24 месяца | CC45: https://docs.google.com/document/d/1QA90Z-gegoCS_9yMWQSy4k5MWVkDIWvVx5oPSvbSSkw/edit?usp=sharing | CM45: =IFERROR(VLOOKUP(B45,CC!A:D,4,0)," ") -> 250 | CN45: НПК Миламед | CP45: Юлия Шаврина РФ, г. Пермь, ул. Монастырская д. 61 оф. 600 Тел.: +7 (342) 248 38 70 доб 14 E-mail: uk_shavrina@milapharma.ru | CQ45: 90 | CS45: 7 | CT45: нет | CY45: FALSE | CZ45: FALSE | DA45: FALSE | DB45: FALSE | DJ45: =IFERROR(VLOOKUP($B45,'Лист4'!$D:$AI,27,0)," ") -> 5 | DK45: =IFERROR(VLOOKUP($B45,'Лист4'!$D:$AI,28,0)," ") -> 9 | DL45: =IFERROR(VLOOKUP($B45,'Лист4'!$D:$AI,29,0)," ") -> 5 | DM45: =IFERROR(DJ45*DK45*DL45," ") -> 225 | DN45: =IFERROR(VLOOKUP($B45,'Лист4'!$D:$AI,32,0)," ") -> 0.062
A46: Биг-Л | B46: qeepantioxy | C46: qeep | D46: Актуальный | E46: ПОСТАВКА | F46: БАД Дигидрокверцетин ,qeep, 30 капсул | G46: БАДы | H46: Женские | K46: TRUE | L46: TRUE | M46: TRUE | N46: TRUE | O46: FALSE | P46: FALSE | Q46: FALSE | S46: QB101100424 | T46: qeepantioxy | U46: qeepantioxy | V46: qeepantioxy | AA46: 91969061 | AB46: 650452213 | AC46: 101805120670 | AH46: БАД Дигидрокверцетин ,qeep, 30 капсул | AI46: Дигидрокверцетин с комплексом витаминов А С Е | AJ46: Дигидрокверцетин + Витамин А, С, Е 25 мг Qeep 30 капсул | AK46: Дигидрокверцетин + Витамин А, С, Е витамины для женщин 25 мг Qeep 30 капсул | AP46: https://www.wildberries.ru/catalog/91969061/detail.aspx | AQ46: https://www.ozon.ru/product/650452213 | AR46: https://market.yandex.ru/card/digidrokvertsetin--vitamin-a-s-ye-25-mg-qeep-30-kapsul/101805120670?businessId=8291477&clid=8291477&model_id=1111706245&distr_type=8&pp=605 | AW46: БАДы | AX46: Дигидрокверцетин + Витамин А, С, Е 25 мг Qeep 30 капсул | AY46: аптека / витамины, минералы, добавки | BD46: Выведено | BE46: Семен | BF46: Анна Пирогова | BG46: Екатерина Доможирова | BH46: Екатерина Доможирова | BI46: Екатерина Доможирова | BL46: 4630040228506 | BM46: 2106909808 | BN46: RU.77.99.88.003.R.000885.03.20 | BP46: ЧЗ | BS46: масло виноградной косточки, капсула желатиновая (желатин, глицерин), витамин С (аскорбил пальмитат), лавитол (дигидрокверцетин), витамин Е (токоферола ацетат), витамин А (ретинола пальмитат), антиокислитель гриндокс (аскорбилпальмитат, натуральный концентрат смеси токоферолов, лецитин, рапсовое масло). | BU46: взрослым по 1 капсуле в день во время еды. Продолжительность приёма 1 месяц. | BV46: индивидуальная непереносимость компонентов, беременность и кормление грудью. Перед применением рекомендуется проконсультироваться с врачом. | BW46: Хранить в недоступном для детей месте, при температуре от 15 до 25ºС и относительной влажности воздуха не более 60%. | BX46: 30 | BY46: капсул | CA46: 2 года/ 730 | CB46: 24 месяца | CC46: https://drive.google.com/drive/u/0/folders/1SFz8_HQVxubQNufAu82-e2JnaongccTm | CF46: https://drive.google.com/drive/u/0/folders/1SFz8_HQVxubQNufAu82-e2JnaongccTm | CM46: =IFERROR(VLOOKUP(B46,CC!A:D,4,0)," ") -> 144.55 | CN46: ООО «Сибфармконтракт» "Анастасия Лапина тел: 8(3822)556092 (доб. 258), 426792 E-mail: lapina@artlife.ru Skype: live:e18940191d9f1027 634034 г.Томск ул Нахимова 8/2 а/я 358 " | CP46: Анастасия Лапина тел: 8(3822)556092 (доб. 258), 426792 E-mail: lapina@artlife.ru Skype: live:e18940191d9f1027 634034 г.Томск ул Нахимова 8/2 а/я 358 | CS46: 10 | CT46: нет | CY46: FALSE | CZ46: FALSE | DA46: FALSE | DB46: FALSE | DJ46: =IFERROR(VLOOKUP($B46,'Лист4'!$D:$AI,27,0)," ") -> 9 | DK46: =IFERROR(VLOOKUP($B46,'Лист4'!$D:$AI,28,0)," ") -> 5 | DL46: =IFERROR(VLOOKUP($B46,'Лист4'!$D:$AI,29,0)," ") -> 9 | DM46: =IFERROR(DJ46*DK46*DL46," ") -> 405 | DN46: =IFERROR(VLOOKUP($B46,'Лист4'!$D:$AI,32,0)," ") -> 0.049
A47: Биг-Л | B47: qeep_si_beauty_90caps | C47: qeep | D47: Перезапуск | E47: Пересмотреть позиционирование - воронка | F47: БАД Кремний 35 мг ,qeep, 90 капсул | G47: БАДы | H47: Женские | K47: TRUE | L47: TRUE | M47: TRUE | N47: TRUE | O47: TRUE | P47: FALSE | Q47: FALSE | S47: QB101100456 | T47: qeep_si_beauty_90caps | U47: qeep_si_beauty_90caps | V47: qeep_si_beauty_90caps | W47: qeep_si_beauty_90caps | AA47: 206027291 | AB47: 1408116280 | AC47: 103398260189 | AD47: 99000118641 | AH47: БАД Кремний 35 мг ,qeep, 90 капсул | AI47: Кремний, биотин, гиалуроновая кислота | AJ47: Кремний 35 мг Qeep 90 капсул | AK47: Кремний с гиалуроновой кислотой, витамины для кожи, волос и ногтей 35 мг Qeep 90 капсул | AL47: кремний 35 мг qeep 90 капсул | AP47: https://www.wildberries.ru/catalog/206027291/detail.aspx | AQ47: https://www.ozon.ru/product/1408116280 | AR47: https://market.yandex.ru/card/kremniy-35-mg-qeep-90-kapsul/103398260189?businessId=8291477&clid=8291477&model_id=838753782&distr_type=8&pp=605 | AS47: https://goldapple.ru/catalogsearch/result?q=99000118641 | AW47: Комплексные пищевые добавки | AX47: Кремний 35 мг Qeep 90 капсул | AY47: аптека / витамины, минералы, добавки | AZ47: Бады витамины | BD47: Света | BE47: Семен | BF47: Анна Пирогова | BG47: Екатерина Доможирова | BH47: Екатерина Доможирова | BI47: Екатерина Доможирова | BL47: 4620153906644 | BM47: 2106909808 | BN47: RU.77.99.32.003.R.003779.11.22 от 01.11.2022 г. | BO47: https://drive.google.com/drive/folders/1I551mOcieiloH0nGEV4x905NSikzHmB- | BP47: ЧЗ | BS47: хвоща травы экстракт, капсула разъёмная твердая желатиновая (желатин (носитель), глицерин (агент влагоудерживающий)), крахмал картофельный (носитель), бамбука экстракт, витамин С (аскорбиновая кислота), крапивы листа экстракт, гиалуроновая кислота, винограда косточек экстракт, кальциевая соль стеариновой кислоты (агент антислеживающий), кремния диоксид (агент антислеживающий), витамин Н (биотин). | BU47: взрослым по 1 капсуле в день во время еды. | BV47: индивидуальная непереносимость компонентов продукта, беременность, кормление грудью. Перед применением рекомендуется проконсультироваться с врачом. | BW47: хранить в сухом, защищенном от попадания прямых солнечных лучей, недоступном для детей месте, при температуре не выше +25 °С. | BX47: 90 | BY47: капсул | CA47: 2 года | CB47: 24 месяца | CC47: https://docs.google.com/document/d/1SLVMaKVgZB6hCS4R172IbAFGfwyfLUSUqXl3Y0BCyrM/edit?usp=sharing | CM47: =IFERROR(VLOOKUP(B47,CC!A:D,4,0)," ") -> 443.21 | CN47: ООО «Сибфармконтракт» | CP47: Анастасия Лапина тел: 8(3822)556092 (доб. 258), 426792 E-mail: lapina@artlife.ru Skype: live:e18940191d9f1027 634034 г.Томск ул Нахимова 8/2 а/я 358 | CQ47: 90 | CS47: 10 | CT47: нет | CY47: FALSE | CZ47: FALSE | DA47: FALSE | DB47: FALSE | DJ47: =IFERROR(VLOOKUP($B47,'Лист4'!$D:$AI,27,0)," ") -> 6 | DK47: =IFERROR(VLOOKUP($B47,'Лист4'!$D:$AI,28,0)," ") -> 5 | DL47: =IFERROR(VLOOKUP($B47,'Лист4'!$D:$AI,29,0)," ") -> 6 | DM47: =IFERROR(DJ47*DK47*DL47," ") -> 180 | DN47: =IFERROR(VLOOKUP($B47,'Лист4'!$D:$AI,32,0)," ") -> 0.08
A48: Биг-Л | B48: qoenzyme | C48: qeep | D48: Актуальный | F48: БАД Коэнзим q10 30 мг ,qeep, 30 капсул | G48: БАДы | H48: Женские | K48: TRUE | L48: TRUE | M48: TRUE | N48: TRUE | O48: FALSE | P48: FALSE | Q48: FALSE | S48: QB101100454 | T48: qoenzyme | U48: qoenzyme | V48: qoenzyme | AA48: 90343752 | AB48: 616948885 | AC48: 101824298336 | AH48: БАД Коэнзим q10 30 мг ,qeep, 30 капсул | AI48: Коэнзим q10 капсулы 30 шт | AJ48: Коэнзим q10 30 мг Qeep 30 капсул | AK48: Коэнзим q10, для молодости, сердца, энергии + витамины группы В, 30 мг Qeep 30 капсул | AP48: https://www.wildberries.ru/catalog/90343752/detail.aspx | AQ48: https://www.ozon.ru/product/616948885 | AW48: БАДы | AX48: Коэнзим q10 30 мг Qeep 30 капсул | AY48: аптека / витамины, минералы, добавки | BD48: Света | BE48: Семен | BF48: Анна Пирогова | BG48: Екатерина Доможирова | BH48: Екатерина Доможирова | BI48: Екатерина Доможирова | BL48: 4630040228346 | BM48: 2106909808 | BN48: RU.77.99.88.003.Е.003181.09.19 от 05.09.2019 г. | BP48: ЧЗ | BS48: оливковое масло нерафинированное, витамин В3 (никотинамид), кверцетин, коэнзим Q10, витамин В5 (пантотенат кальция), витамин В6 (пиридоксина гидрохлорид), витамин В1 (тиамина мононитрат), витамин В2 (рибофлавин), витамин В9 (фолиевая кислота), витамин Н (биотин), витамин В12 (цианокобаламин). Вспомогательные вещества: капсула желатиновая (желатин, глицерин агент влагоудерживающий, сорбит агент влагоудерживающий), кремния диоксид (носитель), антиокислитель гриндокс (аскорбилпальмитат, натуральный концентрат смеси токоферолов, лецитин, рапсовое масло). | BU48: взрослым по 1 капсуле 1-2 раза в день во время еды. Продолжительность приёма 1 месяц. | BV48: индивидуальная непереносимость компонентов, беременность и кормление грудью. Перед применением рекомендуется проконсультироваться с врачом. | BW48: в недоступном для детей месте, при температуре от +15 до +25ºС и относительной влажности воздуха не более 60%. | BX48: 30 | BY48: шт | CA48: 2 года/ 730 | CB48: 24 месяца | CC48: https://drive.google.com/drive/u/0/folders/1xTYWZ7bYXSRSlW4kuRn83L9-D20CJ21r | CF48: https://drive.google.com/drive/u/0/folders/1xTYWZ7bYXSRSlW4kuRn83L9-D20CJ21r | CM48: =IFERROR(VLOOKUP(B48,CC!A:D,4,0)," ") -> 145.8 | CN48: ООО «Сибфармконтракт», Россия, 634034, г. Томск, ул. Нахимова 8, стр. 11. | CP48: Анастасия Лапина тел: 8(3822)556092 (доб. 258), 426792 E-mail: lapina@artlife.ru Skype: live:e18940191d9f1027 634034 г.Томск ул Нахимова 8/2 а/я 358 | CS48: 10 | CT48: нет | CY48: FALSE | CZ48: FALSE | DA48: FALSE | DB48: FALSE | DJ48: =IFERROR(VLOOKUP($B48,'Лист4'!$D:$AI,27,0)," ") -> 10 | DK48: =IFERROR(VLOOKUP($B48,'Лист4'!$D:$AI,28,0)," ") -> 5 | DL48: =IFERROR(VLOOKUP($B48,'Лист4'!$D:$AI,29,0)," ") -> 10 | DM48: =IFERROR(DJ48*DK48*DL48," ") -> 500 | DN48: =IFERROR(VLOOKUP($B48,'Лист4'!$D:$AI,32,0)," ") -> 0.1
A49: Биг-Л | B49: qeep_chrom250_60caps | C49: qeep | D49: Актуальный | E49: Фокус + КЗ | F49: БАД Пиколинат хрома ,qeep, 60 капсул | G49: БАДы | H49: Женские | K49: TRUE | L49: TRUE | M49: TRUE | N49: TRUE | O49: TRUE | P49: FALSE | Q49: FALSE | S49: QB101100476 | T49: qeep_chrom250_60caps | U49: qeep_chrom250_60caps | V49: qeep_chrom250_60caps | W49: qeep_chrom250_60caps | AA49: 417262785 | AB49: 2168454928 | AC49: 4476682176 | AD49: 99000117796 | AH49: БАД Пиколинат хрома ,qeep, 60 капсул | AI49: Пиколинат хрома БАД таблетки для похудения | AJ49: Пиколинат хрома БАД таблетки для похудения | AK49: Пиколинат хрома БАД таблетки для похудения, уменьшение аппетита, снижение веса 60 капсул | AL49: пиколинат хрома бад таблетки для похудения qeep | AP49: https://www.wildberries.ru/catalog/417262785/detail.aspx | AQ49: https://www.ozon.ru/product/2168454928 | AR49: https://market.yandex.ru/card/pikolinat-khroma-bad-tabletki-dlya-pokhudeniya/4476682176?businessId=8291477&clid=8291477&model_id=1268975231&distr_type=8&pp=605 | AS49: https://goldapple.ru/catalogsearch/result?q=99000117796 | AW49: БАДы | AX49: Пиколинат хрома БАД таблетки для похудения | AY49: аптека / витамины, минералы, добавки | AZ49: Бады витамины | BD49: Света | BE49: Семен | BF49: Анна Пирогова | BG49: Екатерина Доможирова | BH49: Екатерина Доможирова | BI49: Екатерина Доможирова | BL49: 4607025204626 | BN49: RU.77.99.11.003.R.001919.07.23 от 17.07.2023 | BO49: https://drive.google.com/drive/folders/1LkfMjci_czH6GixoPga3xpWIKlfPLlQL | BP49: ЧЗ | BS49: микрокристаллическая целлюлоза (Е460, носитель), хрома пиколинат, оболочка капсулы: желатин. | BU49: Взрослым принимать по 1 капсуле 1 раз в день, во время еды. Продолжительность приема - 1 месяц. При необходимости прием можно повторить через месяц. | BV49: Индивидуальная непереносимость компонентов. | BW49: В недоступном для детей месте при температуре не выше 25°С. | BX49: 60 | BY49: капс | CA49: 2 года | CB49: 24 месяца | CC49: https://docs.google.com/document/d/15LyNRSZoQgW_dbJXEk_7ukUNxtR741jLIcuSXlytGKQ/edit?tab=t.0 | CG49: 46101 | CH49: https://disk.yandex.ru/d/C9uy9DshaJOETw | CM49: =IFERROR(VLOOKUP(B49,CC!A:D,4,0)," ") -> 136.8 | CN49: ООО «Витамер», 117623, РФ, г. Москва, вн.тер.г. муниципальный округ Южное Бутово, ул. 2-я Мелитопольская, д.19, к.2, кв.57. Адрес производства: 601144, РФ, Владимирская обл., г. Петушки, ул. Совхозная, д. 11 | CP49: Светлана Румянцева <svetlana.rumyanceva@list.ru> Контактный телефон 8(495) 625-51-15. | CQ49: 60 | CS49: 1 | CT49: нет | CY49: FALSE | CZ49: FALSE | DA49: FALSE | DB49: FALSE | DJ49: =IFERROR(VLOOKUP($B49,'Лист4'!$D:$AI,27,0)," ") -> 6 | DK49: =IFERROR(VLOOKUP($B49,'Лист4'!$D:$AI,28,0)," ") -> 10 | DL49: =IFERROR(VLOOKUP($B49,'Лист4'!$D:$AI,29,0)," ") -> 6 | DM49: =IFERROR(DJ49*DK49*DL49," ") -> 360 | DN49: =IFERROR(VLOOKUP($B49,'Лист4'!$D:$AI,32,0)," ") -> 0.035
A50: Биг-Л | B50: qeep_iron40mg_60caps | C50: qeep | D50: Актуальный | E50: Фокус + КЗ | F50: БАД Железо хелат ,qeep, 60 капсул | G50: БАДы | H50: Женские | K50: TRUE | L50: TRUE | M50: TRUE | N50: TRUE | O50: TRUE | P50: FALSE | Q50: FALSE | S50: QB101100433 | T50: qeep_iron40mg_60caps | U50: qeep_iron40mg_60caps | V50: qeep_iron40mg_60caps | W50: qeep_iron40mg_60caps | AA50: 266214623 | AB50: 1713242647 | AC50: 103555039362 | AD50: 99000121328 | AH50: БАД Железо хелат ,qeep, 60 капсул | AI50: Железо хелат витамины, 60 капсул | AJ50: Железо хелат витамины qeep, 60 капсул | AK50: Железо хелат витамины qeep, витаминный комплекс для женщин 60 капсул | AL50: железо хелат витамины qeep, 60 капсул | AP50: https://www.wildberries.ru/catalog/266214623/detail.aspx | AQ50: https://www.ozon.ru/product/1713242647 | AR50: https://market.yandex.ru/card/zhelezo-khelat-vitaminy-qeep-60-kapsul/103555039362?businessId=8291477&clid=8291477&model_id=1111706245&distr_type=8&pp=605 | AS50: https://goldapple.ru/catalogsearch/result?q=99000121328 | AW50: БАДы | AX50: Железо хелат витамины qeep, 60 капсул | AY50: аптека / витамины, минералы, добавки | AZ50: Бады витамины | BD50: Света | BE50: Семен | BF50: Анна Пирогова | BG50: Екатерина Доможирова | BH50: Екатерина Доможирова | BI50: Екатерина Доможирова | BL50: 4670227414926 | BM50: 2106909808 | BN50: AM.01.01.01.003.R.000361.07.22 от 29.07.2022 г. | BO50: https://drive.google.com/drive/folders/1kkqEKShoipkjwyLesaxgdZcbQzF1QaIn | BP50: ЧЗ | BS50: бисглицинат железа, микрокристаллическая целлюлоза (носитель), капсула целлюлозная. | BU50: взрослым по 1 капсуле в любое время дня. Продолжительность приёма: 1 месяц. При необходимости повторить. | BV50: индивидуальная непереносимость компонентов продукта, беременность, кормление грудью. Перед применением проконсультироваться с врачом. | BW50: хранить в сухом, недоступном для детей месте, при температуре от +5 °С до +25 °С. | BX50: 60 | BY50: капсул | CA50: 2 года | CB50: 24 месяца | CC50: https://docs.google.com/document/d/1iHFOdSKWC-0jKOZLzM1EK9MGfF3PctiGyZlOGzqK0oI/edit | CG50: 46059 | CH50: https://disk.yandex.ru/d/82yJwBqzvyIE9w | CM50: =IFERROR(VLOOKUP(B50,CC!A:D,4,0)," ") -> 261 | CN50: ООО «Жива Продукт ПРО». 350062, Россия, Краснодарский край, город Краснодар, улица Казбекская, дом 17, кв. (оф.) 85 | CP50: Магамадов Ибрагим e-mail: ima@dzivaproduct.ru сайт: www.dzivaproduct.ru сот.тел. +7-967-660-1277(доступен WhatsApp) | CQ50: 60 | CS50: 5 | CT50: да | CY50: FALSE | CZ50: FALSE | DA50: FALSE | DB50: FALSE | DJ50: =IFERROR(VLOOKUP($B50,'Лист4'!$D:$AI,27,0)," ") -> 11 | DK50: =IFERROR(VLOOKUP($B50,'Лист4'!$D:$AI,28,0)," ") -> 6 | DL50: =IFERROR(VLOOKUP($B50,'Лист4'!$D:$AI,29,0)," ") -> 11 | DM50: =IFERROR(DJ50*DK50*DL50," ") -> 726 | DN50: =IFERROR(VLOOKUP($B50,'Лист4'!$D:$AI,32,0)," ") -> 0.069
A51: Биг-Л | B51: qeep_climafem_60caps | C51: qeep | D51: Вывод | E51: Пересмотреть позиционирование | F51: БАД при климаксе Climafem ,qeep, 60 капсул | G51: БАДы | H51: Женские | K51: TRUE | L51: TRUE | M51: TRUE | N51: TRUE | O51: FALSE | P51: FALSE | Q51: FALSE | S51: QB101100479 | T51: qeep_climafem_60caps | U51: qeep_climafem_60caps | V51: qeep_climafem_60caps | AA51: 271680783 | AB51: 1738941767 | AC51: 4295610520 | AH51: БАД при климаксе Climafem ,qeep, 60 капсул | AI51: Комплекс витаминов от климакса и приливов Климафем | AJ51: Комплекс витаминов для женского здоровья от климакса и приливов Climafem qeep 60 капсул | AK51: Комплекс витаминов для женского здоровья от климакса и приливов Climafem qeep 60 капсул | AP51: https://www.wildberries.ru/catalog/271680783/detail.aspx | AQ51: https://www.ozon.ru/product/1738941767 | AR51: https://market.yandex.ru/card/kompleks-vitaminov-ot-klimaksa-i-prilivov-climafem-qeep-60-kapsul/103589261760?businessId=8291477&clid=8291477&model_id=1826260757&distr_type=8&pp=605 | AW51: БАДы | AX51: Комплекс витаминов для женского здоровья от климакса и приливов Climafem qeep 60 капсул | AY51: аптека / витамины, минералы, добавки | BD51: Света | BE51: Семен | BF51: Анна Пирогова | BG51: Екатерина Доможирова | BH51: Екатерина Доможирова | BI51: Екатерина Доможирова | BL51: 4610030631868 | BM51: 2106909808 | BN51: AM.01.06.01.003.R.000199.05.24 от 16.05.2024 г. | BP51: ЧЗ | BS51: экстракт цимицифуги, экстракт сои, экстракт травы пустырника, магниевая соль стеариновой кислоты, диоксид кремния аморфный, витамин В9 (фолиевая кислота), оболочка капсулы белого цвета (желатин, оксид цинка), целлюлоза микрокристаллическая | BU51: взрослым по 1 капсуле 2 раза в день во время еды. | BV51: индивидуальная непереносимость компонентов продукта, беременность, кормление грудью. Перед применением рекомендуется проконсультироваться с врачом. | BW51: хранить в сухом, недоступном для детей месте, при температуре от +5 °С до +25 °С. | BX51: 60 | BY51: капсул | CA51: 2 года | CB51: 24 месяца | CC51: https://docs.google.com/document/d/1N9vH076zUFnzarQva1zuDXMEr1ij0XS-dfLaDMB7cm8/edit | CM51: =IFERROR(VLOOKUP(B51,CC!A:D,4,0)," ") -> 174.15 | CN51: ООО "ЗдравФарм" | CP51: Оксана, 7 966 345 2873 | CQ51: 90 | CS51: 1 | CT51: нет | CY51: FALSE | CZ51: FALSE | DA51: FALSE | DB51: FALSE | DJ51: =IFERROR(VLOOKUP($B51,'Лист4'!$D:$AI,27,0)," ") -> 4 | DK51: =IFERROR(VLOOKUP($B51,'Лист4'!$D:$AI,28,0)," ") -> 8 | DL51: =IFERROR(VLOOKUP($B51,'Лист4'!$D:$AI,29,0)," ") -> 4 | DM51: =IFERROR(DJ51*DK51*DL51," ") -> 128 | DN51: =IFERROR(VLOOKUP($B51,'Лист4'!$D:$AI,32,0)," ") -> 0.045
A52: Биг-Л | B52: qeepprobiotics | C52: qeep | D52: Актуальный | F52: БАД Пробиотики ,qeep, 30 капсул | G52: БАДы | H52: ЖКТ | K52: TRUE | L52: TRUE | M52: TRUE | N52: TRUE | O52: TRUE | P52: FALSE | Q52: FALSE | S52: QB101100484 | T52: qeepprobiotics | U52: qeepprobiotics | V52: qeepprobiotics | W52: qeepprobiotics | AA52: 91969350 | AB52: 650348972 | AC52: 101871358737 | AD52: 99000122455 | AH52: БАД Пробиотики ,qeep, 30 капсул | AI52: Пробиотик и пребиотик для кишечника взрослым | AJ52: Пробиотики и пребиотики для взрослых 570 мг Qeep 30 капсул | AK52: Пробиотики + пребиотики для взрослых, восстановление микрофлоры 570 мг Qeep 30 капсул | AL52: пробиотики для взрослых 570 мг qeep 30 капсул | AP52: https://www.wildberries.ru/catalog/91969350/detail.aspx | AQ52: https://www.ozon.ru/product/650348972 | AW52: БАДы | AX52: Пробиотики и пребиотики для взрослых 570 мг Qeep 30 капсул | AY52: аптека / лекарственные препараты / средства для пищеварения | AZ52: Бады витамины | BD52: Света | BE52: Семен | BF52: Анна Пирогова | BG52: Екатерина Доможирова | BH52: Екатерина Доможирова | BI52: Екатерина Доможирова | BL52: 4630040228322 | BM52: 2106909808 | BN52: AM.01.06.01.003.R.000233.12.21 от 01.12.2021 | BO52: https://drive.google.com/drive/folders/1661ysU66VNch6pumNtNg5KYosvH9FmJ3 | BP52: ЧЗ | BS52: биомасса бактерий селективная сухая BB-Bf серии «Панбиом» («Panbiom») (Bifidobacterium bifidum ARTB-187), биомасса бактерий селективная сухая LB-Pl серии «Панбиом» («Panbiom») (Lactobacillus plantarum ARTB-135), биомасса бактерий селективная сухая PR-Frd серии «Панбиом» («Panbiom») (Propionibacterium freudenreichii ARTB-137), инулин, «Метафул (Metafull)» (комбуча концентрат, биомасса гидролизованная «УЛЬТРАЛИЗАТ ПЕПТИДНЫЙ» BB-Bf Bifidobacterium bifidum (ARTB-187), BB-Ad Bifidobacterium adolescentis (ARTB-127), BB-An Bifidobacterium animalis (ARTB-128), BB-Ln Bifidobacterium longum (ARTB-184), BB-Br Bifidobacterium breve (ARTB-129), BB-If Bifidobacterium infantis (ARTB-189), LB-Ac Lactobacillus acidophilus (ARTB-130), LB-Ac Lactobacillus acidophilus (ARTB-177), LB-Pl Lactobacillus plantarum (ARTB-135), LB-Pl Lactobacillus plantarum (ARTB-175), LB-Bg Lactobacillus delbrueckii subsp.bulgaricus (ARTB-131), LB-Sl Lactobacillus salivarius (ARTB-136), LB-Sl Lactobacillus salivarius (ARTB-142), LB-Rm Lactobacillus rhamnosus (ARTB-183), LB-Rm Lactobacillus rhamnosus (ARTB-180), LB-Hl Lactobacillus helveticus (ARTB-133), LB-Hl Lactobacillus helveticus (ARTB-174), гуммиарабик, молочная кислота, мальтодекстрин, гуаровая камедь (галактоманнан), ксантановая камедь (глюкоманнан)). Вспомогательные вещества: капсула твердая разъёмная желатиновая (желатин (носитель), глицерин (агент влагоудерживающий)), антислеживатели: кальция стеарат, кремния диоксид. | BU52: взрослым по 1 капсуле 1-3 раза в день во время еды. Продолжительность приема 1 месяц. | BV52: индивидуальная непереносимость компонентов, беременность и кормление грудью. Перед применением рекомендуется проконсультироваться с врачом. | BW52: хранить в недоступном для детей месте, при температуре не выше 25⁰С и относительной влажности воздуха не более 60%. | BX52: 30 | BY52: шт | CA52: 2 года/ 730 | CB52: 24 месяца | CC52: https://docs.google.com/document/d/1yJnbPgyY1nI_AZn2Dmtl7cgOBhxhIx79k-xpm7o3Sc8/edit?tab=t.0 | CG52: 46062 | CH52: https://disk.yandex.ru/d/tGCqfZO9dbek0Q | CM52: =IFERROR(VLOOKUP(B52,CC!A:D,4,0)," ") -> 155.15 | CN52: ООО «Сибфармконтракт», Россия, 634034, г. Томск, ул. Нахимова 8, стр. 11. | CP52: Анастасия Лапина тел: 8(3822)556092 (доб. 258), 426792 E-mail: lapina@artlife.ru Skype: live:e18940191d9f1027 634034 г.Томск ул Нахимова 8/2 а/я 358 | CS52: 10 | CT52: нет | CY52: FALSE | CZ52: FALSE | DA52: FALSE | DB52: FALSE | DJ52: =IFERROR(VLOOKUP($B52,'Лист4'!$D:$AI,27,0)," ") -> 2 | DK52: =IFERROR(VLOOKUP($B52,'Лист4'!$D:$AI,28,0)," ") -> 10 | DL52: =IFERROR(VLOOKUP($B52,'Лист4'!$D:$AI,29,0)," ") -> 2 | DM52: =IFERROR(DJ52*DK52*DL52," ") -> 40 | DN52: =IFERROR(VLOOKUP($B52,'Лист4'!$D:$AI,32,0)," ") -> 0.05
A53: Биг-Л | B53: qeep_Antiparasite_60caps | C53: qeep | D53: Вывод | E53: Пробуем КЗ | F53: БАД Антипаразитарный комплекс ,qeep, 60 капсул | G53: БАДы | H53: ЖКТ | K53: TRUE | L53: TRUE | M53: TRUE | N53: TRUE | O53: FALSE | P53: FALSE | Q53: FALSE | S53: QB101100403 | T53: qeep_Antiparasite_60caps | U53: qeep_Antiparasite_60caps | V53: qeep_Antiparasite_60caps | AA53: 193123880 | AB53: 1323353605 | AC53: 102621786592 | AH53: БАД Антипаразитарный комплекс ,qeep, 60 капсул | AI53: Антипаразитарный комплекс БАД травяной сбор | AJ53: Антипаразитарный комплекс Qeep 60 капсул | AK53: Антипаразитарный комплекс от паразитов и глистов Qeep 60 капсул | AP53: https://www.wildberries.ru/catalog/193123880/detail.aspx | AQ53: https://www.ozon.ru/product/1323353605 | AR53: https://market.yandex.ru/card/antiparazitarnyy-kompleks-qeep-kaps/103614885657?businessId=8291477&clid=8291477&model_id=44495663&distr_type=8&pp=605 | AW53: Травяные сборы | AX53: Антипаразитарный комплекс Qeep 60 капсул | AY53: аптека / витамины, минералы, добавки | BD53: Алексей | BE53: Семен | BF53: Анна Пирогова | BG53: Екатерина Доможирова | BH53: Екатерина Доможирова | BI53: Екатерина Доможирова | BL53: 4670142965350 | BM53: 2106909808 | BN53: AM.01.11.01.003.R.000306.08.23 от 25.08.2023 г. | BO53: https://drive.google.com/drive/folders/1KNEwUbAoNj_n5iSZjupqnxJbiF715hxT | BP53: ЧЗ | BS53: экстракты концентрированные сухие коры осины обыкновенной (Populus tremula L.), цветков пижмы обыкновенной (Tanacetum vulgare L.), травы тысячелистника обыкновенного (Achillea millefolium L.), травы зверобоя продырявленного (Hypericum perforatum L.), перегородок грецкого ореха (Juglans regia L.), цветков бессмертника песчаного (Helichrysum arenarium L.), крахмал кукурузный, стеарат кальция. | BU53: взрослым принимать по 2 капсулы 3 раза в день во время еды. Продолжительность приема: 10 дней. При необходимости прием можно повторить. | BV53: индивидуальная непереносимость компонентов продукта, беременность, кормление грудью. | BW53: хранить при температуре от 0 ºС до +25 ºС и относительной влажности воздуха не более 75%, в защищенном от света и недоступном для детей месте. | BX53: 60 | BY53: капсул | CA53: 3 года | CB53: 36 месяца | CC53: https://docs.google.com/document/d/1BgASHF8aR4NOXw1SFN33xvmAXN4kEDtRAcVUF6XGb0o/edit?usp=sharing | CM53: =IFERROR(VLOOKUP(B53,CC!A:D,4,0)," ") -> 240 | CN53: ООО «Биолит», 634055, Россия, г. Томск, пр. Академический, д. 4, стр. 3. | CP53: Алексей Ребитва Руководитель отдела продаж ООО «Биолит» e-mail: rav@biolit.info тел. моб. +7-913-889-20-51 | CQ53: 60 | CS53: 10 | CT53: нет | CY53: FALSE | CZ53: FALSE | DA53: FALSE | DB53: FALSE | DJ53: =IFERROR(VLOOKUP($B53,'Лист4'!$D:$AI,27,0)," ") -> 8 | DK53: =IFERROR(VLOOKUP($B53,'Лист4'!$D:$AI,28,0)," ") -> 11 | DL53: =IFERROR(VLOOKUP($B53,'Лист4'!$D:$AI,29,0)," ") -> 8 | DM53: =IFERROR(DJ53*DK53*DL53," ") -> 704 | DN53: =IFERROR(VLOOKUP($B53,'Лист4'!$D:$AI,32,0)," ") -> 0.06
A54: Биг-Л | B54: qeep_betain_60caps | C54: qeep | D54: Вывод | E54: Неконкурентный товар | F54: БАД Бетаин 600 мг ,qeep, 60 капсул | G54: БАДы | H54: ЖКТ | K54: TRUE | L54: TRUE | M54: TRUE | N54: TRUE | O54: TRUE | P54: FALSE | Q54: FALSE | S54: QB101100406 | T54: qeep_betain_60caps | U54: qeep_betain_60caps | V54: qeep_betain_60caps | W54: qeep_betain_60caps | AA54: 169963867 | AB54: 1101330936 | AC54: 102626043690 | AD54: 99000118639 | AH54: БАД Бетаин 600 мг ,qeep, 60 капсул | AI54: Бетаин Гидрохлорид БАД для печени и кишечника | AJ54: Бетаин 600 мг Qeep 60 капсул | AK54: Бетаин для печени и кишечника 600 мг. для пищеварения Qeep 60 капсул | AL54: бетаин 600 мг qeep 60 капсул | AP54: https://www.wildberries.ru/catalog/169963867/detail.aspx | AQ54: https://www.ozon.ru/product/1101330936 | AR54: https://market.yandex.ru/card/betain-600-mg-qeep-60-kapsul/103374785701?businessId=8291477&clid=8291477&model_id=1826260757&distr_type=8&pp=605 | AW54: БАДы | AX54: Бетаин 600 мг Qeep 60 капсул | AY54: аптека / витамины, минералы, добавки | AZ54: БАДы и витамины | BD54: Света | BE54: Семен | BF54: Анна Пирогова | BG54: Екатерина Доможирова | BH54: Екатерина Доможирова | BI54: Екатерина Доможирова | BL54: 4627150924015 4660401460016 4660401460054 | BM54: 2106909808 | BN54: AM.01.01.01.003.R.000335.05.23 от 04.05.2023 г. | BO54: https://drive.google.com/drive/folders/1fCnfdV2Eo5L84etkpz_GlEQbBCbEq5HA | BP54: ЧЗ | BS54: бетаин гидрохлорид, стеарат кальция, твёрдая желатиновая капсула. | BU54: Взрослым по 1 капсуле в день. | BV54: индивидуальная непереносимость компонентов продукта, беременность, кормление грудью. Продукт не рекомендуется принимать детям до 18 лет. Перед применением проконсультироваться с врачом. | BW54: хранить в сухом, недоступном для детей месте, при температуре от +5 °С до +25 °С. | BX54: 60 | BY54: капсул | CA54: 2 года | CB54: 24 месяца | CC54: https://docs.google.com/document/d/1btMLoKjGiPiNbhwZ2f6qDmBwM2xegs1lppoz6n2azxw/edit | CF54: https://drive.google.com/drive/u/0/folders/1MG-BzuApIlExV8-3nD7wX6WFiSm3kP14 | CM54: =IFERROR(VLOOKUP(B54,CC!A:D,4,0)," ") -> 268 | CN54: ООО «Жива Продукт ПРО». 350062, Россия, Краснодарский край, город Краснодар, улица Казбекская, дом 17, кв. (оф.) 85 | CP54: Джанета | CQ54: 60 | CS54: 5 | CT54: да | CY54: FALSE | CZ54: FALSE | DA54: FALSE | DB54: FALSE | DJ54: =IFERROR(VLOOKUP($B54,'Лист4'!$D:$AI,27,0)," ") -> 5 | DK54: =IFERROR(VLOOKUP($B54,'Лист4'!$D:$AI,28,0)," ") -> 15 | DL54: =IFERROR(VLOOKUP($B54,'Лист4'!$D:$AI,29,0)," ") -> 5 | DM54: =IFERROR(DJ54*DK54*DL54," ") -> 375 | DN54: =IFERROR(VLOOKUP($B54,'Лист4'!$D:$AI,32,0)," ") -> 0.088
A55: Биг-Л | B55: qeep_livercomplex_60caps | C55: qeep | D55: Вывод | E55: Узкий рынок | F55: БАД Расторопша для печени ,qeep, 60 капсул | G55: БАДы | H55: ЖКТ | K55: TRUE | L55: TRUE | M55: TRUE | N55: TRUE | O55: FALSE | P55: FALSE | Q55: FALSE | S55: QB101100487 | T55: qeep_livercomplex_60caps | U55: qeep_livercomplex_60caps | V55: qeep_livercomplex_60caps | AA55: 161526543 | AB55: 985677823 | AC55: 4997621076 | AH55: БАД Расторопша для печени ,qeep, 60 капсул | AI55: БАД qeep Liver Complex, 60 капсул Природный гепатопротектор | AJ55: Расторопша для печени 600 мг Qeep 60 капсул | AK55: Расторопша, витамины для защиты печени 600 мг Qeep 60 капсул | AP55: https://www.wildberries.ru/catalog/161526543/detail.aspx | AQ55: https://www.ozon.ru/product/985677823 | AW55: БАДы | AX55: Расторопша для печени 600 мг Qeep 60 капсул | AY55: аптека / витамины, минералы, добавки | BD55: Света | BE55: Семен | BF55: Анна Пирогова | BG55: Екатерина Доможирова | BH55: Екатерина Доможирова | BI55: Екатерина Доможирова | BL55: 4670142964537 | BM55: 2106909808 | BN55: AM.01.01.01.003.R.000372.08.22 от 01.08.2022 г. | BO55: https://drive.google.com/drive/folders/1f4jOvNo9bbNfeCqj9rVDFqtxQaZ_OOTi | BP55: ЧЗ | BS55: экстракты концентрированные сухие травы солянки холмовой (Salsola collina Pall), расторопши пятнистой (Sílybum marianum), травы овса посевного молочной спелости (Avena sativa), крахмал кукурузный, стеарат кальция | BU55: взрослым по 1 капсуле 2 раза в день во время еды. Перед применением рекомендуется проконсультироваться с врачом. Продолжительность приема: 30 дней. При необходимости прием можно повторить. | BV55: индивидуальная непереносимость компонентов продукта, беременность, кормление грудью. | BW55: хранить при температуре от 0 ºС до +25ºС и относительной влажности воздуха не более 75%, в защищенном от света и недоступном для детей месте. | BX55: 60 | BY55: капсул | CA55: 2 года | CB55: 24 месяца | CC55: https://docs.google.com/document/d/1u4s30Tp4BCPPO9U3tTIxjOOGRR_1kc3nNCCYXEN0oU4/edit?usp=sharing | CF55: https://drive.google.com/drive/u/0/folders/1sL3txEX1OSsv1WQ0PP1X_zYsx82wBbYE | CM55: =IFERROR(VLOOKUP(B55,CC!A:D,4,0)," ") -> 235 | CN55: ООО «Биолит», 634055, Россия, г. Томск, пр. Академический, д. 4, стр. 3. | CP55: Алексей Ребитва Руководитель отдела продаж ООО «Биолит» e-mail: rav@biolit.info тел. моб. +7-913-889-20-51 | CQ55: 60 | CS55: 10 | CT55: нет | CY55: FALSE | CZ55: FALSE | DA55: FALSE | DB55: FALSE | DJ55: =IFERROR(VLOOKUP($B55,'Лист4'!$D:$AI,27,0)," ") -> 10 | DK55: =IFERROR(VLOOKUP($B55,'Лист4'!$D:$AI,28,0)," ") -> 5 | DL55: =IFERROR(VLOOKUP($B55,'Лист4'!$D:$AI,29,0)," ") -> 10 | DM55: =IFERROR(DJ55*DK55*DL55," ") -> 500 | DN55: =IFERROR(VLOOKUP($B55,'Лист4'!$D:$AI,32,0)," ") -> 0.063
A56: Биг-Л | B56: harly_toothpaste_50ml | C56: Harly | D56: Актуальный | F56: Паста зубная для собак и кошек, Harly, 50 мл | G56: Косметика для животных | H56: Зубная паста | K56: TRUE | L56: TRUE | M56: TRUE | N56: TRUE | O56: FALSE | P56: FALSE | Q56: FALSE | S56: HC101100401 | T56: harly_toothpaste_50ml | U56: harly_toothpaste_50ml | V56: harly_toothpaste_50ml | AA56: 494708852 | AB56: 2686479094 | AC56: 4602254449 | AH56: Паста зубная для собак и кошек, Harly, 50 мл | AI56: Зубная паста для собак и кошек | AJ56: Зубная паста для собак и кошек | AK56: Зубная паста для собак и кошек, гель для полости рта домашних животных, Harly 50 мл | AP56: https://www.wildberries.ru/catalog/494708852/detail.aspx | AQ56: https://www.ozon.ru/product/2686479094 | AR56: https://market.yandex.ru/card/zubnaya-pasta-dlya-sobak-i-koshek/4602254449?businessId=8291477&clid=8291477&model_id=1353065860&distr_type=8&pp=605 | AW56: Пасты для животных | AX56: Зубная паста для собак и кошек | AY56: товары для животных / косметика и гигиена / средства для ухода за ротовой полостью животных | BD56: Алексей | BE56: Кристина | BF56: Анна Пирогова | BG56: Екатерина Доможирова | BH56: Екатерина Доможирова | BI56: Екатерина Доможирова | BL56: 4620290621325 | BN56: Отказное письмо № ОП/11-0028 от 06.11.2024 г. | BO56: https://drive.google.com/drive/folders/1x8BA-mv8v_o4slyl7SBR7GKpEqah_Wck | BP56: ЧЗ | BS56: вода, глицерин, гидроксиэтилцеллюлоза, ПЭГ 40, гидрогенизированное касторовое масло, ПЭГ-400 полиэтиленгликоль, аллантоин, экстракт прополиса, экстракт ромашки, экстракт коры дуба, пропиленгликоль, хлорид натрия, субтилизин, глюкозооксидаза, д-пантенол, сорбат калия | BT56: 46044 | BU56: з | BW56: хранить в сухом, защищенном от света месте, при температуре от -15 °С до +20 °С. | BX56: 50 | BY56: мл | CA56: 36 месяцев | CB56: 36 месяцев | CC56: https://docs.google.com/document/d/1Sz0LP9aVbdQfEU2WMRCtI-DDfLzGptLZvgLBIQURHDM/edit?tab=t.0 | CG56: 46044 | CH56: https://disk.yandex.ru/d/lxnlqd1t71Uaig | CM56: =IFERROR(VLOOKUP(B56,CC!A:D,4,0)," ") -> 116 | CN56: ООО Терра-пласт | CP56: Гордиенко Евгения Степановна (812)748-22-25(доб.101) +7(962)689-06-49 stm@gkfavorite.ru | CQ56: 60 | CS56: 2 | CT56: нет | CY56: FALSE | CZ56: FALSE | DA56: FALSE | DB56: FALSE | DJ56: =IFERROR(VLOOKUP($B56,'Лист4'!$D:$AI,27,0)," ") -> 4 | DK56: =IFERROR(VLOOKUP($B56,'Лист4'!$D:$AI,28,0)," ") -> 41 | DL56: =IFERROR(VLOOKUP($B56,'Лист4'!$D:$AI,29,0)," ") -> 4 | DM56: =IFERROR(DJ56*DK56*DL56," ") -> 656 | DN56: =IFERROR(VLOOKUP($B56,'Лист4'!$D:$AI,32,0)," ") -> 0.061
A57: Биг-Л | B57: qeep_omega_3_1620_90caps | C57: qeep | D57: Актуальный | F57: БАД Омега 1620 мг ,qeep, 90 капсул | G57: БАДы | H57: Иммунитет | K57: TRUE | L57: TRUE | M57: TRUE | N57: TRUE | O57: TRUE | P57: FALSE | Q57: FALSE | S57: QB101100473 | T57: qeep_omega_3_1620_90caps | U57: qeep_omega_3_1620_90caps | V57: qeep_omega_3_1620_90caps | W57: qeep_omega_3_1620_90caps | AA57: 161948275 | AB57: 989542196 | AC57: 102071901773 | AD57: 99000118638 | AH57: БАД Омега 1620 мг ,qeep, 90 капсул | AI57: Омега 3 рыбий жир в капсулах 1620 мг omega 3 | AJ57: Омега 3 1620 мг EPA 792 мг DHA 528 мг Qeep 90 капсул | AK57: Омега 3 Рыбий жир из Исландии, для сердца 1620 мг EPA 792 мг DHA 528 мг Qeep 90 капсул | AL57: омега 3 1620 мг epa 792 мг dha 528 мг qeep 90 капсул | AP57: https://www.wildberries.ru/catalog/161948275/detail.aspx | AQ57: https://www.ozon.ru/product/989542196 | AR57: https://market.yandex.ru/card/omega-3-1620-mg-epa-792-mg-dha-528-mg-qeep-90-kapsul/103262837664?businessId=8291477&clid=8291477&model_id=1885081753&distr_type=8&pp=605 | AS57: https://goldapple.ru/catalogsearch/result?q=99000118638 | AW57: БАДы | AX57: Омега 3 1620 мг EPA 792 мг DHA 528 мг Qeep 90 капсул | AY57: аптека / витамины, минералы, добавки | AZ57: Бады витамины | BD57: Света | BE57: Семен | BF57: Анна Пирогова | BG57: Екатерина Доможирова | BH57: Екатерина Доможирова | BI57: Екатерина Доможирова | BL57: 4620153902592 | BM57: 2106909808 | BN57: AM.01.48.01.003.Е.000045.04.19 | BO57: https://drive.google.com/drive/folders/1ySrfx_k1dHppSCuT11-UWd1OHtg3JaGD | BP57: ЧЗ | BS57: рыбий жир, капсула желатиновая (желатин (носитель), глицерин (агент влагоудерживающий)), витамин Е (антиокислитель). | BU57: принимать взрослым и детям с трех лет во время еды в течение 1 месяца (по рекомендации специалиста доза может быть увеличена) по 1- 2 капсулы в день. | BV57: индивидуальная непереносимость компонентов, беременность и кормление грудью. Перед применением рекомендуется проконсультироваться с врачом. | BW57: в недоступном для детей месте, при температуре от +15 до +25ºС и относительной влажности воздуха не более 60%. | BX57: 90 | BY57: капсул | CA57: 2 года | CB57: 24 месяца | CC57: https://docs.google.com/document/d/1oxB4dKuqGO9RKMs4QSRRjOY9q4PgUGd8OrGUfAbbA9Y/edit?tab=t.0 | CF57: https://drive.google.com/drive/u/0/folders/1YYRoKT7rU8dhG1zHTW4AyaJkpbdYipaV | CM57: =IFERROR(VLOOKUP(B57,CC!A:D,4,0)," ") -> 475.01 | CN57: ООО «Сибфармконтракт», Россия, 634034, г. Томск, ул. Нахимова 8, стр. 11. | CP57: Анастасия Лапина тел: 8(3822)556092 (доб. 258), 426792 E-mail: lapina@artlife.ru Skype: live:e18940191d9f1027 634034 г.Томск ул Нахимова 8/2 а/я 358 | CQ57: 90 | CS57: 10 | CT57: нет | CY57: FALSE | CZ57: FALSE | DA57: FALSE | DB57: FALSE | DJ57: =IFERROR(VLOOKUP($B57,'Лист4'!$D:$AI,27,0)," ") -> 6 | DK57: =IFERROR(VLOOKUP($B57,'Лист4'!$D:$AI,28,0)," ") -> 11 | DL57: =IFERROR(VLOOKUP($B57,'Лист4'!$D:$AI,29,0)," ") -> 6 | DM57: =IFERROR(DJ57*DK57*DL57," ") -> 396 | DN57: =IFERROR(VLOOKUP($B57,'Лист4'!$D:$AI,32,0)," ") -> 0.176
A58: Биг-Л | B58: qeep_nac_90caps | C58: qeep | D58: Актуальный | E58: Цена | F58: NAC комплекс от ОРВИ ,qeep, 90 капсул | G58: БАДы | H58: Иммунитет | K58: TRUE | L58: TRUE | M58: TRUE | N58: TRUE | O58: TRUE | P58: FALSE | Q58: FALSE | S58: QB101100513 | T58: qeep_nac_90caps | U58: qeep_nac_90caps | V58: qeep_nac_90caps | W58: qeep_nac_90caps | AA58: 240166228 | AB58: 1613724697 | AC58: 103396767624 | AD58: 99000118345 | AH58: NAC комплекс от ОРВИ ,qeep, 90 капсул | AI58: Витамины для иммунитета NAC, комплекс от ОРВИ 90 капсул | AJ58: Витамины для иммунитета NAC, комплекс от ОРВИ qeep 90 капсул | AK58: Витамины для иммунитета NAC, комплекс от ОРВИ, Комплекс НАК N-ацетилцистеин qeep 90 капсул | AL58: витамины для иммунитета nac, комплекс от орви qeep 90 капсул | AP58: https://www.wildberries.ru/catalog/240166228/detail.aspx | AQ58: https://www.ozon.ru/product/1613724697 | AR58: https://market.yandex.ru/card/vitaminy-dlya-immuniteta-nac-kompleks-ot-orvi-90-kapsul/103396767624?businessId=8291477&clid=8291477&model_id=1280856904&distr_type=8&pp=605 | AS58: https://goldapple.ru/catalogsearch/result?q=99000118345 | AW58: Комплексные пищевые добавки | AX58: Витамины для иммунитета NAC, комплекс от ОРВИ qeep 90 капсул | AY58: аптека / витамины, минералы, добавки | AZ58: Бады витамины | BD58: Алексей | BE58: Семен | BF58: Анна Пирогова | BG58: Екатерина Доможирова | BH58: Екатерина Доможирова | BI58: Екатерина Доможирова | BL58: 4670227414018 | BM58: 2106909808 | BN58: ЕАЭС N RU Д-RU.РА01.В.18739/24 от 19.01.2024 до 16.01.2027 | BO58: https://drive.google.com/drive/folders/1NTwwpvMvYatlgVwisT2gXZIbKZscs9LS | BP58: без ЧЗ | BS58: N-Ацетил L-Цистеин, носители: микрокристаллическая целлюлоза, твёрдая желатиновая капсула. | BU58: взрослым принимать по 1 капсуле 2 раза в день. | BV58: индивидуальная непереносимость компонентов продукта, беременность, кормление грудью. Перед применением проконсультироваться с врачом. | BW58: хранить при температуре от 0 ºС до +25ºС и относительной влажности воздуха не более 75%, в защищенном от света и недоступном для детей месте. | BX58: 90 | BY58: капсул | CA58: 2 года | CB58: 24 месяца | CC58: https://docs.google.com/document/d/17vMGodUH7Jw1G3-QJzBkrGHB_tV4WW7o0BQWlmeKG94/edit | CM58: =IFERROR(VLOOKUP(B58,CC!A:D,4,0)," ") -> 427 | CN58: ООО «Жива Продукт ПРО». 350062, Россия, Краснодарский край, город Краснодар, улица Казбекская, дом 17, кв. (оф.) 85 | CP58: Магамадов Ибрагим e-mail: ima@dzivaproduct.ru сайт: www.dzivaproduct.ru сот.тел. +7-967-660-1277(доступен WhatsApp) | CQ58: 60 | CS58: 5 | CT58: да | CY58: FALSE | CZ58: FALSE | DA58: FALSE | DB58: FALSE | DJ58: =IFERROR(VLOOKUP($B58,'Лист4'!$D:$AI,27,0)," ") -> 6 | DK58: =IFERROR(VLOOKUP($B58,'Лист4'!$D:$AI,28,0)," ") -> 12 | DL58: =IFERROR(VLOOKUP($B58,'Лист4'!$D:$AI,29,0)," ") -> 6 | DM58: =IFERROR(DJ58*DK58*DL58," ") -> 432 | DN58: =IFERROR(VLOOKUP($B58,'Лист4'!$D:$AI,32,0)," ") -> 0.122
A59: Биг-Л | B59: qeep_omega3_180caps | C59: qeep | D59: Вывод | E59: Сокращение товарной матрицы | F59: БАД Омега 1320 мг ,qeep, 180 капсул | G59: БАДы | H59: Иммунитет | K59: TRUE | L59: TRUE | M59: TRUE | N59: TRUE | O59: FALSE | P59: FALSE | Q59: FALSE | S59: QB101100470 | T59: qeep_omega3_180caps | U59: qeep_omega3_180caps | V59: qeep_omega3_180caps | AA59: 228331343 | AB59: 1566735886 | AC59: 103824496894 | AH59: БАД Омега 1320 мг ,qeep, 180 капсул | AI59: Витамины омега 3 omega рыбий жир БАД | AJ59: Омега 3 1320 мг EPA 627 мг DHA 465 мг Qeep 180 капсул | AK59: Омега 3 рыбий жир 1320 мг EPA 627 мг DHA 465 мг Qeep витамины 180 капсул | AP59: https://www.wildberries.ru/catalog/228331343/detail.aspx | AQ59: https://www.ozon.ru/product/1566735886 | AR59: https://market.yandex.ru/card/omega-3-1320-mg-epa-627-mg-dha-465-mg-qeep-180-kapsul/103398260192?businessId=8291477&clid=8291477&model_id=1826260757&distr_type=8&pp=605 | AW59: БАДы | AX59: Омега 3 1320 мг EPA 627 мг DHA 465 мг Qeep 180 капсул | AY59: аптека / витамины, минералы, добавки | BD59: Выведено | BE59: Семен | BF59: Анна Пирогова | BG59: Екатерина Доможирова | BH59: Екатерина Доможирова | BI59: Екатерина Доможирова | BL59: 4640233110730 | BM59: 2106909808 | BN59: AM.01.08.01.003.R.000005.12.22 от 28.12.2022г. | BO59: https://drive.google.com/drive/folders/1uv1bxc8fyEFxLMBZ_r9wPp_TYOyi4eao | BP59: ЧЗ | BS59: Рыбий жир, компоненты капсулы (вода, желатин, глицерин пищевой, сорбитол, сорбат калия). | BU59: принимать по 3 капсулы 2 раза в день во время еды, запивая обильным количеством воды. | BV59: индивидуальная непереносимость компонентов, беременность, кормление грудью, лица в возрасте до 18 лет. Перед применением рекомендуется проконсультироваться с врачом. Не превышать установленную рекомендуемую дозу. Биологически активная добавка к пище не должна употребляться в качестве замены пищи. | BW59: хранить в сухом, защищенном от прямых солнечных лучей и недоступном для детей месте при температуре от 0°С до 25°С и относительной влажности не более 75%. | BX59: 180 | BY59: капсул | CA59: 2 года | CB59: 24 месяца | CC59: https://docs.google.com/document/d/1sNYhRYgYetttE-UId3DBP-2BYgQpyfVTYys-zo8hTnY/edit?usp=sharing | CM59: =IFERROR(VLOOKUP(B59,CC!A:D,4,0)," ") -> 271 | CN59: ООО «Биофарм». Юридический адрес: Россия, 127015, г. Москва, улица Вятская, д.49, стр.2, помещение 11, комната 8. (адрес производства: 143080, Московская область, Одинцовский район, п. ВНИИССОК, ул. Селекционная, д.14, Россия) | CP59: Татьяна +7 985 083-04-64 | CQ59: 90 | CT59: нет | CY59: FALSE | CZ59: FALSE | DA59: FALSE | DB59: FALSE | DJ59: =IFERROR(VLOOKUP($B59,'Лист4'!$D:$AI,27,0)," ") -> 11 | DK59: =IFERROR(VLOOKUP($B59,'Лист4'!$D:$AI,28,0)," ") -> 6 | DL59: =IFERROR(VLOOKUP($B59,'Лист4'!$D:$AI,29,0)," ") -> 11 | DM59: =IFERROR(DJ59*DK59*DL59," ") -> 726 | DN59: =IFERROR(VLOOKUP($B59,'Лист4'!$D:$AI,32,0)," ") -> 0.149
A60: Биг-Л | B60: qeep_sodium_ascorbate_90caps | C60: qeep | D60: Актуальный | F60: БАД Витамин С ,qeep, 90 капсул | G60: БАДы | H60: Иммунитет | K60: TRUE | L60: TRUE | M60: TRUE | N60: TRUE | O60: FALSE | P60: FALSE | Q60: FALSE | S60: QB101100409 | T60: qeep_sodium_ascorbate_90caps | U60: qeep_sodium_ascorbate_90caps | V60: qeep_sodium_ascorbate_90caps | AA60: 176110909 | AB60: 1181035529 | AC60: 102621619721 | AH60: БАД Витамин С ,qeep, 90 капсул | AI60: Витамин C аскорбат натрия капсулы 500 мг | AJ60: Витамин С 500 мг Qeep 90 капсул | AK60: Витамин С 500 мг комплекс для иммунитета и сердца Qeep 90 капсул | AP60: https://www.wildberries.ru/catalog/176110909/detail.aspx | AQ60: https://www.ozon.ru/product/1181035529 | AR60: https://market.yandex.ru/card/vitamin-s-500-mg-qeep-90-kapsul/103374785702?businessId=8291477&clid=8291477&model_id=1826260757&distr_type=8&pp=605 | AW60: БАДы | AX60: Витамин С 500 мг Qeep 90 капсул | AY60: аптека / витамины, минералы, добавки | BD60: Света | BE60: Семен | BF60: Анна Пирогова | BG60: Екатерина Доможирова | BH60: Екатерина Доможирова | BI60: Екатерина Доможирова | BL60: 4607025203049 | BM60: 2106909808 | BN60: RU.77.99.11.003.R.000404.02.23 от 17.02.2023г. | BO60: https://drive.google.com/drive/folders/11V47raeGUzjMoy3mBCMqpcGPyba8nnqr | BP60: ЧЗ | BS60: Аскорбат натрия, микрокристаллическая целлюлоза (Е460, носитель); оболочка капсулы: желатин (КРС) | BU60: Взрослым по 1 капсуле в день во время еды. Продолжительность приёма - 1 месяц. При необходимости прием можно повторить. | BV60: Индивидуальная непереносимость компонентов. | BW60: В недоступном для детей месте при температуре не выше 25°С. Места реализации определяются национальным законодательством государств-членов Евразийского экономического союза. | BX60: 90 | BY60: капсул | CA60: 2 года | CB60: 24 месяца | CC60: https://docs.google.com/document/d/1mJnYdPfr-00wh_Cf1g4i-ezp1qy74IHnLRtvjZay0EU/edit?usp=sharing | CF60: https://drive.google.com/drive/u/0/folders/1tF08U9AEt4IHcBEywiAv2OOoFnPmhIPt | CM60: =IFERROR(VLOOKUP(B60,CC!A:D,4,0)," ") -> 232.3 | CN60: ООО «Витамер», 117623, РФ, г. Москва, вн.тер.г. муниципальный округ Южное Бутово, ул. 2-я Мелитопольская, д.19, к.2, кв.57. Адрес производства: 601144, РФ, Владимирская обл., г. Петушки, ул. Совхозная, д. 11 | CP60: Светлана Румянцева <svetlana.rumyanceva@list.ru> Контактный телефон 8(495) 625-51-15. | CQ60: 60 | CS60: 1 | CT60: нет | CY60: FALSE | CZ60: FALSE | DA60: FALSE | DB60: FALSE | DJ60: =IFERROR(VLOOKUP($B60,'Лист4'!$D:$AI,27,0)," ") -> 9 | DK60: =IFERROR(VLOOKUP($B60,'Лист4'!$D:$AI,28,0)," ") -> 5 | DL60: =IFERROR(VLOOKUP($B60,'Лист4'!$D:$AI,29,0)," ") -> 9 | DM60: =IFERROR(DJ60*DK60*DL60," ") -> 405 | DN60: =IFERROR(VLOOKUP($B60,'Лист4'!$D:$AI,32,0)," ") -> 0.086
A61: Биг-Л | B61: qeepcurcumin_500mg_60caps | C61: qeep | D61: Актуальный | F61: БАД Куркумин ,qeep, 60 капсул | G61: БАДы | H61: Иммунитет | K61: TRUE | L61: TRUE | M61: TRUE | N61: TRUE | O61: TRUE | P61: FALSE | Q61: FALSE | S61: QB101100458 | T61: qeepcurcumin_500mg_60caps | U61: qeepcurcumin_500mg_60caps | V61: qeepcurcumin_500mg_60caps | W61: qeepcurcumin_500mg_60caps | AA61: 148382531 | AB61: 881205774 | AC61: 101975171797 | AD61: 99000122833 | AH61: БАД Куркумин ,qeep, 60 капсул | AI61: Куркумин в капсулах для иммунитета curcumin БАД | AJ61: Куркумин 500 мг Qeep 60 капсул | AK61: Куркумин в капсулах для иммунитета, антиоксидант 500 мг Qeep 60 капсул | AL61: куркумин 500 мг qeep 60 капсул | AP61: https://www.wildberries.ru/catalog/148382531/detail.aspx | AQ61: https://www.ozon.ru/product/881205774 | AR61: https://market.yandex.ru/card/kurkumin-500-mg-qeep-60-kapsul/103262837666?businessId=8291477&clid=8291477&model_id=1826260757&distr_type=8&pp=605 | AS61: https://goldapple.ru/catalogsearch/result?q=99000122833 | AW61: БАДы | AX61: Куркумин 500 мг Qeep 60 капсул | AY61: аптека / витамины, минералы, добавки | AZ61: Бады витамины | BD61: Света | BE61: Семен | BF61: Анна Пирогова | BG61: Екатерина Доможирова | BH61: Екатерина Доможирова | BI61: Екатерина Доможирова | BL61: 4670110184271 | BM61: 2106909808 | BN61: AM.01.07.01.003.R.000474.05.22 от 23.05.2022 г. | BP61: ЧЗ | BS61: действующее вещество: куркумы экстракт; вспомогательные вещества: диоксид кремния, желатин говяжий (для капсул). | BU61: принимайте продукт по одной порции (1 капсула) 1 раз в день во время приема пищи, или в соответствии с вашей индивидуальной программой питания или рекомендациями врача. | BV61: Противопоказания: индивидуальная непереносимость компонентов, беременность и кормление грудью. Перед применением рекомендуется проконсультироваться с врачом. | BW61: хранить в сухом прохладном, защищенном от попадания прямых солнечных лучей и недоступном для детей месте, при температуре не выше 25°С. После вскрытия упаковку хранить плотно закрытой при тех же условиях | BX61: 60 | BY61: капсул | CA61: 2 года/ 730 | CB61: 24 месяца | CC61: Куркумин 500 мг - Google Документы | CF61: https://drive.google.com/drive/u/0/folders/1aAcjmCFwzpgtMDcdeunmIMrPjgb2xDfI | CM61: =IFERROR(VLOOKUP(B61,CC!A:D,4,0)," ") -> 190 | CN61: ООО Арсенал Атлета, 443535, Россия, Самарская область, Волжский муниципальный район, сельское поселение Лопатино, село Лопатино, улица Мира, здание 16/8, офис 1, тел.: +7 (902) 580 30 82, e-mail: yozavod@gmail.com. | CP61: Галина Кулагина <pm4.yozavod@gmail.com> +7 963 117-27-73 | CT61: нет | CY61: FALSE | CZ61: FALSE | DA61: FALSE | DB61: FALSE | DJ61: =IFERROR(VLOOKUP($B61,'Лист4'!$D:$AI,27,0)," ") -> 4 | DK61: =IFERROR(VLOOKUP($B61,'Лист4'!$D:$AI,28,0)," ") -> 7 | DL61: =IFERROR(VLOOKUP($B61,'Лист4'!$D:$AI,29,0)," ") -> 4 | DM61: =IFERROR(DJ61*DK61*DL61," ") -> 112 | DN61: =IFERROR(VLOOKUP($B61,'Лист4'!$D:$AI,32,0)," ") -> 0.1
A62: Биг-Л | B62: qeep_D3_30ml | C62: qeep | D62: Актуальный | F62: БАД Д3 Капли ,qeep, 30 мл | G62: БАДы | H62: Иммунитет | K62: TRUE | L62: TRUE | M62: TRUE | N62: TRUE | O62: TRUE | P62: FALSE | Q62: FALSE | S62: QB101100423 | T62: qeep_D3_30ml | U62: qeep_D3_30ml | V62: qeep_D3_30ml | W62: qeep_D3_30ml | AA62: 157382017 | AB62: 945003764 | AC62: 102019832737 | AD62: 99000121335 | AH62: БАД Д3 Капли ,qeep, 30 мл | AI62: БАДы Витамин д3 жидкий в каплях 500 ME | AJ62: Витамин Д3 Капли 500 ME Qeep 30 мл | AK62: Витамин Д3 для укрепления иммунитета Капли 500 ME Qeep 30 мл | AL62: витамин д3 капли 500 me qeep 30 мл | AP62: https://www.wildberries.ru/catalog/157382017/detail.aspx | AQ62: https://www.ozon.ru/product/945003764 | AR62: https://market.yandex.ru/card/vitamin-d3-kapli-500-me-qeep-30-ml/102019832737?businessId=8291477&clid=8291477&model_id=1111672191&distr_type=8&pp=605 | AS62: https://goldapple.ru/catalogsearch/result?q=99000121335 | AW62: БАДы | AX62: Витамин Д3 Капли 500 ME Qeep 30 мл | AY62: аптека / витамины, минералы, добавки | AZ62: Бады витамины | BD62: Света | BE62: Семен | BF62: Анна Пирогова | BG62: Екатерина Доможирова | BH62: Екатерина Доможирова | BI62: Екатерина Доможирова | BL62: 4670142964339 | BM62: 2106909808 | BN62: AM.01.01.01.003.R.000293.07.22 от 04.07.2022 г. | BO62: https://drive.google.com/drive/folders/1nyCK7KtfFdw6ATDyZiUsp-8R_xsvasJf | BP62: ЧЗ | BS62: холекальциферол (витамин D3), масло МСТ (триглицериды среднецепочечные кокосового масла), ароматизатор натуральный «банан», смесь витамина Е (токоферолов) и витамина С (аскорбил пальмитата) - (антиокислитель). | BU62: взрослым и детям с 3-х лет по 1 капле (500 МЕ) в день во время еды или согласно рекомендациям врача. Продолжительность приема: 1-2 месяца. | BV62: индивидуальная непереносимость компонентов. Перед применением рекомендуется проконсультироваться с врачом. Перед применением БАД детьми – с врачом-педиатром. | BW62: при температуре не выше +25ºС и относительной влажности воздуха не более 75%, в защищенном от света и недоступном для детей месте. | BX62: 30 | BY62: мл | CA62: 2 года | CB62: 24 месяца | CC62: https://docs.google.com/document/d/1hdoargGeFe62QqxLQUBOx5Z2xpT5_QvdJVdO0bKjvuk/edit?usp=sharing | CF62: https://drive.google.com/drive/u/0/folders/1vImWk9rrF-f6StlS6U_aqB6fqN73ffMB | CM62: =IFERROR(VLOOKUP(B62,CC!A:D,4,0)," ") -> 265 | CN62: ООО «Биолит», 634055, Россия, г. Томск, пр. Академический, д. 4, стр. 3. | CP62: Алексей Ребитва Руководитель отдела продаж ООО «Биолит» e-mail: rav@biolit.info тел. моб. +7-913-889-20-51 | CQ62: 60 | CS62: 10 | CT62: нет | CY62: FALSE | CZ62: FALSE | DA62: FALSE | DB62: FALSE | DJ62: =IFERROR(VLOOKUP($B62,'Лист4'!$D:$AI,27,0)," ") -> 11 | DK62: =IFERROR(VLOOKUP($B62,'Лист4'!$D:$AI,28,0)," ") -> 3 | DL62: =IFERROR(VLOOKUP($B62,'Лист4'!$D:$AI,29,0)," ") -> 11 | DM62: =IFERROR(DJ62*DK62*DL62," ") -> 363 | DN62: =IFERROR(VLOOKUP($B62,'Лист4'!$D:$AI,32,0)," ") -> 0.087
A63: Биг-Л | B63: qeepzinc | C63: qeep | D63: Актуальный | E63: КЗ | F63: БАД Цинк хелат ,qeep, 90 таблеток | G63: БАДы | H63: Иммунитет | K63: TRUE | L63: TRUE | M63: TRUE | N63: TRUE | O63: FALSE | P63: FALSE | Q63: FALSE | S63: QB101100503 | T63: qeepzinc | U63: qeepzinc | V63: qeepzinc | AA63: 138758948 | AB63: 814824220 | AC63: 101948497015 | AH63: БАД Цинк хелат ,qeep, 90 таблеток | AI63: Цинк хелат бисглицинат, бад для укрепления иммунитета | AJ63: Цинк хелат 25 мг Qeep 90 таблеток | AK63: Цинк хелат 25 мг комплекс для кожи, волос и ногтей Qeep 90 таблеток | AP63: https://www.wildberries.ru/catalog/138758948/detail.aspx | AQ63: https://www.ozon.ru/product/814824220 | AR63: https://market.yandex.ru/card/tsink-khelat-25-mg-qeep-90-tabletok/101948497015?businessId=8291477&clid=8291477&model_id=838753782&distr_type=8&pp=605 | AW63: БАДы | AX63: Цинк хелат 25 мг Qeep 90 таблеток | AY63: аптека / витамины, минералы, добавки | BD63: Света | BE63: Семен | BF63: Анна Пирогова | BG63: Екатерина Доможирова | BH63: Екатерина Доможирова | BI63: Екатерина Доможирова | BL63: 4607025202875 | BM63: 3504009000 | BN63: RU.77.99.11.003.R.003861.10.21 от 28.10.2021 | BP63: ЧЗ | BS63: МКЦ (наполнитель), цинка бисглицинат, кальция стеарат (антислеживающий агент), аэросил (антислеживающий агент). | BU63: взрослым по 1 таблетке 1 раз в день во время еды. Продолжительность приёма - 1 месяц. При необходимости прием можно повторить. | BV63: индивидуальная непереносимость компонентов, беременность и кормление грудью. Перед применением рекомендуется проконсультироваться с врачом. | BW63: В недоступном для детей месте при температуре не выше 25°С. | BX63: 90 | BY63: таблеток | CA63: 2 года | CB63: 24 месяца | CC63: https://docs.google.com/document/d/1V53-Zl8DYEAmao39JYKuOjznb2bYtKbB0kr7sWdpYbE/edit?tab=t.0 | CF63: https://drive.google.com/drive/u/0/folders/1ReycPg9FGytMZyyRTX9heQK-zrjw-yWX | CG63: 46101 | CH63: https://disk.yandex.ru/d/uDHcYb7tZ1TpXQ | CM63: =IFERROR(VLOOKUP(B63,CC!A:D,4,0)," ") -> 169.09 | CN63: ООО «Витамер», 117623, РФ, г. Москва, вн.тер.г. муниципальный округ Южное Бутово, ул. 2-я Мелитопольская, д.19, к.2, кв.57. Адрес производства: 601144, РФ, Владимирская обл., г. Петушки, ул. Совхозная, д. 11 | CP63: Светлана Румянцева <svetlana.rumyanceva@list.ru> Контактный телефон 8(495) 625-51-15. | CS63: 1 | CT63: нет | CY63: FALSE | CZ63: FALSE | DA63: FALSE | DB63: FALSE | DJ63: =IFERROR(VLOOKUP($B63,'Лист4'!$D:$AI,27,0)," ") -> 9 | DK63: =IFERROR(VLOOKUP($B63,'Лист4'!$D:$AI,28,0)," ") -> 6 | DL63: =IFERROR(VLOOKUP($B63,'Лист4'!$D:$AI,29,0)," ") -> 9 | DM63: =IFERROR(DJ63*DK63*DL63," ") -> 486 | DN63: =IFERROR(VLOOKUP($B63,'Лист4'!$D:$AI,32,0)," ") -> 0.05
A64: Биг-Л | B64: qeep_omega369_90caps | C64: qeep | D64: Перезапуск | F64: БАД Омега 3 6 9 ,qeep, 90 капсул | G64: БАДы | H64: Иммунитет | K64: TRUE | L64: TRUE | M64: TRUE | N64: TRUE | O64: FALSE | P64: FALSE | Q64: FALSE | S64: QB101100474 | T64: qeep_omega369_90caps | U64: qeep_omega369_90caps | V64: qeep_omega369_90caps | AA64: 165252790 | AB64: 1032695400 | AC64: 102054330150 | AH64: БАД Омега 3 6 9 ,qeep, 90 капсул | AI64: Омега 3, 6, 9 БАД витаминный комплекс | AJ64: Омега 3 6 9 Qeep 90 капсул | AK64: Омега 3-6-9 для укрепления иммунитета, комплекс витаминов для всей семьи Qeep 90 капсул | AP64: https://www.wildberries.ru/catalog/165252790/detail.aspx | AQ64: https://www.ozon.ru/product/1032695400 | AW64: БАДы | AX64: Омега 3 6 9 Qeep 90 капсул | AY64: аптека / витамины, минералы, добавки | BD64: Семен | BE64: Семен | BF64: Анна Пирогова | BG64: Екатерина Доможирова | BH64: Екатерина Доможирова | BI64: Екатерина Доможирова | BL64: 4670167253043 | BM64: 2106909808 | BN64: RU.77.99.32.003.R.003955.12.23 от 29.12.2023 | BO64: https://drive.google.com/drive/folders/1moRzguS5Ptx9hhgAKcigDTHgVdJci-MP | BP64: ЧЗ | BS64: рыбий жир, масло огуречника, масло льняное, альфа-токоферола ацетат, оболочка капсулы (желатин, загуститель – глицерин, вода). | BU64: взрослым и детям старше 14 лет по 3 капсулы в день во время еды. Продолжительность приема – 1 месяц. По рекомендации врача прием можно повторить. | BV64: индивидуальная непереносимость компонентов продукта, беременность, кормление грудью. | BW64: в недоступном для детей месте, при температуре не выше +25ºС и относительной влажности воздуха не более 60%. | BX64: 90 | BY64: капсул | CA64: 2 года | CB64: 24 месяца | CC64: https://docs.google.com/document/d/1YAjgc4ouJahRJNquY38BHuWLmBBqVs178XgnWcVwip0/edit | CF64: https://drive.google.com/drive/u/0/folders/1YYRoKT7rU8dhG1zHTW4AyaJkpbdYipaV | CM64: =IFERROR(VLOOKUP(B64,CC!A:D,4,0)," ") -> 321.07 | CN64: ООО "Нутрилент" | CP64: Кирилл Трофимов trofimov.k@nutrilent.ru 89626843328 | CQ64: 60 | CS64: 3 | CT64: нет | CY64: FALSE | CZ64: FALSE | DA64: FALSE | DB64: FALSE | DJ64: =IFERROR(VLOOKUP($B64,'Лист4'!$D:$AI,27,0)," ") -> 6 | DK64: =IFERROR(VLOOKUP($B64,'Лист4'!$D:$AI,28,0)," ") -> 11 | DL64: =IFERROR(VLOOKUP($B64,'Лист4'!$D:$AI,29,0)," ") -> 6 | DM64: =IFERROR(DJ64*DK64*DL64," ") -> 396 | DN64: =IFERROR(VLOOKUP($B64,'Лист4'!$D:$AI,32,0)," ") -> 0.2
A65: Биг-Л | B65: qeep_d3k2_5000ME_120tabs | C65: qeep | D65: Актуальный | E65: Проверить, можно ли? | F65: БАД Д3 5000 ME К2 ,qeep, 120 таблеток | G65: БАДы | H65: Иммунитет | K65: TRUE | L65: TRUE | M65: TRUE | N65: TRUE | O65: TRUE | P65: FALSE | Q65: FALSE | S65: QB101100419 | T65: qeep_d3k2_5000ME_120tabs | U65: qeep_d3k2_5000ME_120tabs | V65: qeep_d3k2_5000ME_120tabs | W65: qeep_d3k2_5000ME_120tabs | AA65: 209196024 | AB65: 1499949331 | AC65: 103398256605 | AD65: 99000121333 | AH65: БАД Д3 5000 ME К2 ,qeep, 120 таблеток | AI65: Витамин д3 к2 комплекс для иммунитета | AJ65: Витамин Д3 5000 ME К2 12,5 мкг Qeep 120 таблеток | AK65: Витамин Д3 5000 для иммунитета, костей ME К2 12,5 мкг Qeep 120 таблеток | AL65: витамин д3 5000 me к2 12,5 мкг qeep 120 таблеток | AP65: https://www.wildberries.ru/catalog/209196024/detail.aspx | AQ65: https://www.ozon.ru/product/1499949331 | AR65: https://market.yandex.ru/card/vitamin-d3-5000-me-k2-125-mkg-qeep-120-tabletok/103398256605?businessId=8291477&clid=8291477&model_id=1111672191&distr_type=8&pp=605 | AS65: https://goldapple.ru/catalogsearch/result?q=99000121333 | AW65: БАДы | AX65: Витамин Д3 5000 ME К2 12,5 мкг Qeep 120 таблеток | AY65: аптека / витамины, минералы, добавки | AZ65: Бады витамины | BD65: Света | BE65: Семен | BF65: Анна Пирогова | BG65: Екатерина Доможирова | BH65: Екатерина Доможирова | BI65: Екатерина Доможирова | BL65: 4630205149011 | BM65: 2106909808 | BN65: AM.01.01.01.003.R.000393.05.23 от 26.05.2023 г | BO65: https://drive.google.com/drive/folders/1Ff011wv7rQ4F7-IgqVQmiO7I_ZhEFkeB | BP65: ЧЗ | BS65: холекальциферол, менахинон-7, носители: микрокристаллическая целлюлоза, мальтодекстрин, стеарат кальция (Е470), кремний диоксид коллоидный (Е 551) (АЭРОСИЛ@). | BU65: принимать взрослым по ¼ таблетки в день в первой половине дня. | BV65: индивидуальная непереносимость компонентов, беременность, кормление грудью, лица в возрасте до 18 лет. Перед применением рекомендуется проконсультироваться с врачом. Не превышать установленную рекомендуемую дозу. Биологически активная добавка к пище не должна употребляться в качестве замены пищи. | BW65: хранить в сухом, защищенном от прямых солнечных лучей и недоступном для детей месте при температуре от 0°С до 25°С и относительной влажности не более 75%. | BX65: 120 | BY65: таблеток | CA65: 2 года | CB65: 24 месяца | CC65: https://docs.google.com/document/d/1H-we0rrrX46oFlO6fhgJkMhJgqJLYSYleX3SUFyg8y0/edit | CM65: =IFERROR(VLOOKUP(B65,CC!A:D,4,0)," ") -> 190 | CN65: ООО «Жива Продукт ПРО». 350062, Россия, Краснодарский край, город Краснодар, улица Казбекская, дом 17, кв. (оф.) 85 | CP65: Магамадов Ибрагим e-mail: ima@dzivaproduct.ru сайт: www.dzivaproduct.ru сот.тел. +7-967-660-1277(доступен WhatsApp) | CQ65: 60 | CS65: 5 | CT65: да | CY65: FALSE | CZ65: FALSE | DA65: FALSE | DB65: FALSE | DJ65: =IFERROR(VLOOKUP($B65,'Лист4'!$D:$AI,27,0)," ") -> 4 | DK65: =IFERROR(VLOOKUP($B65,'Лист4'!$D:$AI,28,0)," ") -> 9 | DL65: =IFERROR(VLOOKUP($B65,'Лист4'!$D:$AI,29,0)," ") -> 4 | DM65: =IFERROR(DJ65*DK65*DL65," ") -> 144 | DN65: =IFERROR(VLOOKUP($B65,'Лист4'!$D:$AI,32,0)," ") -> 0.062
A66: Биг-Л | B66: qeep_D3_2000ME_120caps | C66: qeep | D66: Актуальный | F66: БАД Д3 2000 МЕ ,qeep, 120 капсул | G66: БАДы | H66: Иммунитет | K66: TRUE | L66: TRUE | M66: TRUE | N66: TRUE | O66: TRUE | P66: FALSE | Q66: FALSE | S66: QB101100418 | T66: qeep_D3_2000ME_120caps | U66: qeep_D3_2000ME_120caps | V66: qeep_D3_2000ME_120caps | W66: qeep_D3_2000ME_120caps | AA66: 196519115 | AB66: 1342066127 | AC66: 102621875416 | AD66: 99000121327 | AH66: БАД Д3 2000 МЕ ,qeep, 120 капсул | AI66: Витамин Д 3 БАД в капсулах D3 2000 ме 120 шт | AJ66: Витамин Д3 2000 МЕ 120 капсул | AK66: Витамин Д3 2000 МЕ для иммунитета и укрепления организма 120 капсул | AL66: витамин д3 2000 ме 120 капсул | AP66: https://www.wildberries.ru/catalog/196519115/detail.aspx | AQ66: https://www.ozon.ru/product/1342066127 | AR66: https://market.yandex.ru/card/vitamin-d3-2000-me-120-kapsul/103374785697?businessId=8291477&clid=8291477&model_id=1826260757&distr_type=8&pp=605 | AW66: БАДы | AX66: Витамин Д3 2000 МЕ 120 капсул | AY66: аптека / витамины, минералы, добавки | AZ66: Бады витамины | BD66: Света | BE66: Семен | BF66: Анна Пирогова | BG66: Екатерина Доможирова | BH66: Екатерина Доможирова | BI66: Екатерина Доможирова | BL66: 4630205145730 | BM66: 2106909808 | BN66: AM.01.01.01.003.R.000129.04.22 от 15.04.2022 г. | BO66: https://drive.google.com/drive/folders/1uNAsNA4oVTOq2LtvWwLXiSjLMH4BX0SI | BP66: ЧЗ | BS66: масляный раствор витамина D3 (среднецепочечные триглицериды или кукурузное масло, антиокислитель – альфа-токоферол, холекальциферол (витамин D3)), масло растительное рафинированное, оболочка капсулы (желатин, агент влагоудерживающий – глицерин, вода очищенная, загуститель – каррагинан), антиокислитель – смесь токоферолов. | BU66: взрослым по 1 капсуле в день во время еды. Продолжительность приёма: 1 месяц. При необходимости повторить. | BV66: индивидуальная непереносимость компонентов продукта, беременность, кормление грудью. Перед применением проконсультироваться с врачом. | BW66: хранить в сухом, недоступном для детей месте, при температуре от +5 °С до +25 °С. | BX66: 120 | BY66: капсул | CA66: 3 года | CB66: 36 месяца | CC66: https://docs.google.com/document/d/1FLCC9-RkT8OIyTIbAX7ko8SLL5xaNgJ5Ahl9-jivg-Y/edit | CM66: =IFERROR(VLOOKUP(B66,CC!A:D,4,0)," ") -> 191 | CN66: ООО «Жива Продукт ПРО». 350062, Россия, Краснодарский край, город Краснодар, улица Казбекская, дом 17, кв. (оф.) 85 | CP66: Магамадов Ибрагим e-mail: ima@dzivaproduct.ru сайт: www.dzivaproduct.ru сот.тел. +7-967-660-1277(доступен WhatsApp) | CQ66: 60 | CS66: 5 | CT66: да | CY66: FALSE | CZ66: FALSE | DA66: FALSE | DB66: FALSE | DJ66: =IFERROR(VLOOKUP($B66,'Лист4'!$D:$AI,27,0)," ") -> 4 | DK66: =IFERROR(VLOOKUP($B66,'Лист4'!$D:$AI,28,0)," ") -> 9 | DL66: =IFERROR(VLOOKUP($B66,'Лист4'!$D:$AI,29,0)," ") -> 4 | DM66: =IFERROR(DJ66*DK66*DL66," ") -> 144 | DN66: =IFERROR(VLOOKUP($B66,'Лист4'!$D:$AI,32,0)," ") -> 0.062
A67: Биг-Л | B67: qeepcurcumin | C67: qeep | D67: Актуальный | F67: БАД Куркумин 130 мг ,qeep, 60 капсул | G67: БАДы | H67: Иммунитет | K67: TRUE | L67: TRUE | M67: TRUE | N67: TRUE | O67: TRUE | P67: FALSE | Q67: FALSE | S67: QB101100457 | T67: qeepcurcumin | U67: qeepcurcumin | V67: qeepcurcumin | W67: qeepcurcumin | AA67: 91969213 | AB67: 650726667 | AC67: 101805130270 | AD67: 99000119614 | AH67: БАД Куркумин 130 мг ,qeep, 60 капсул | AI67: Куркумин в капсулах для иммунитета curcumin БАД | AJ67: Куркумин 130 мг Qeep 60 капсул | AK67: Куркумин с пиперином (биоперином) для иммунитета 130 мг Qeep 60 капсул | AL67: куркумин 130 мг qeep 60 капсул | AP67: https://www.wildberries.ru/catalog/91969213/detail.aspx | AQ67: https://www.ozon.ru/product/650726667 | AR67: https://market.yandex.ru/card/kurkumin-130-mg-qeep-60-kapsul/102210720237?businessId=8291477&clid=8291477&model_id=1826260757&distr_type=8&pp=605 | AW67: БАДы | AX67: Куркумин 130 мг Qeep 60 капсул | AY67: аптека / витамины, минералы, добавки | AZ67: БАДы и витамины | BD67: Света | BE67: Семен | BF67: Анна Пирогова | BG67: Екатерина Доможирова | BH67: Екатерина Доможирова | BI67: Екатерина Доможирова | BL67: 4630040228513 | BM67: 2106909808 | BN67: RU.77.99.11.003.R.000532.02.21 | BP67: ЧЗ | BS67: масло зародышей пшеницы, капсула желатиновая (желатин (носитель), глицерин (агент влагоудерживающий)), кишечнорастворимая оболочка капсулы (колликут (носитель), трикальций фосфат (носитель), кальциевая соль стеариновой кислоты (агент антислеживающий), поливинилпирролидон (загуститель), красители: оксид железа жёлтый, оксид железа красный), куркумы экстракт, диоксид кремния (носитель), биоперин (экстракт чёрного перца), антиокислитель «Гриндокс 539» (аскорбилпальмитат, натуральные токоферолы, лецитин, рапсовое масло). | BU67: взрослым по 1 капсуле 2 раза в день во время еды. Продолжительность приема 1 месяц. При необходимости прием можно повторить. | BV67: индивидуальная непереносимость компонентов, беременность и кормление грудью. Перед применением рекомендуется проконсультироваться с врачом. | BW67: в недоступном для детей месте, при температуре от 15 до 25 ºС и относительной влажности воздуха не более 60%. | BX67: 60 | BY67: шт | CA67: 2 года/ 730 | CB67: 24 месяца | CC67: https://docs.google.com/document/d/1rStD9LfL8-lXmrG3ZPI5ROlPQ0F8vM2gcY5G8YsGYYU/edit?usp=sharing | CF67: https://drive.google.com/drive/u/0/folders/1EWl76TX-ujF2rrg9uGzYgfUiQRWYoFhB | CM67: =IFERROR(VLOOKUP(B67,CC!A:D,4,0)," ") -> 236.59 | CN67: ООО «Сибфармконтракт», Россия, 634034, г. Томск, ул. Нахимова 8, стр. 11. По заказу (организация, уполномоченная принимать претензии от потребителя): ООО «Биг-Л», 127473, Россия, г. Москва, Переулок Самотёчный 1-й, д. 15, cтр. 1, этаж подвал № 0, помещ. I, ком. 1, офис 1, | CP67: Анастасия Лапина тел: 8(3822)556092 (доб. 258), 426792 E-mail: lapina@artlife.ru Skype: live:e18940191d9f1027 634034 г.Томск ул Нахимова 8/2 а/я 358 | CS67: 10 | CT67: нет | CY67: FALSE | CZ67: FALSE | DA67: FALSE | DB67: FALSE | DJ67: =IFERROR(VLOOKUP($B67,'Лист4'!$D:$AI,27,0)," ") -> 5 | DK67: =IFERROR(VLOOKUP($B67,'Лист4'!$D:$AI,28,0)," ") -> 9 | DL67: =IFERROR(VLOOKUP($B67,'Лист4'!$D:$AI,29,0)," ") -> 5 | DM67: =IFERROR(DJ67*DK67*DL67," ") -> 225 | DN67: =IFERROR(VLOOKUP($B67,'Лист4'!$D:$AI,32,0)," ") -> 0.073
A68: Биг-Л | B68: qeep_vitaminA_90caps | C68: qeep | D68: Вывод | E68: Узкий рынок | F68: БАД Витамин А 10000 МЕ ,qeep, 90 капсул | G68: БАДы | H68: Иммунитет | K68: TRUE | L68: TRUE | M68: TRUE | N68: TRUE | O68: TRUE | P68: FALSE | Q68: FALSE | S68: QB101100407 | T68: qeep_vitaminA_90caps | U68: qeep_vitaminA_90caps | V68: qeep_vitaminA_90caps | W68: qeep_vitaminA_90caps | AA68: 221232387 | AB68: 1539152458 | AC68: 103398256607 | AD68: 99000118343 | AH68: БАД Витамин А 10000 МЕ ,qeep, 90 капсул | AI68: Витамин А 10000 МЕ | AJ68: Витамин А 10000 МЕ Qeep 90 капсул | AK68: Витамин А 10000 МЕ, витамины для кожи, глаз и красоты Qeep 90 капсул | AL68: витамин а 10000 ме qeep 90 капсул | AP68: https://www.wildberries.ru/catalog/221232387/detail.aspx | AQ68: https://www.ozon.ru/product/1539152458 | AR68: https://market.yandex.ru/card/vitamin-a-10000-me-qeep-90-kapsul/103398256607?businessId=8291477&clid=8291477&model_id=838753782&distr_type=8&pp=605 | AW68: БАДы | AX68: Витамин А 10000 МЕ Qeep 90 капсул | AY68: аптека / витамины, минералы, добавки | AZ68: БАДы и витамины | BD68: Света | BE68: Семен | BF68: Анна Пирогова | BG68: Екатерина Доможирова | BH68: Екатерина Доможирова | BI68: Екатерина Доможирова | BL68: 4670227412809 | BM68: 2106909808 | BN68: AM.01.04.01.003.R.000138.08.23 от 01.08.2023 г. | BO68: https://drive.google.com/drive/folders/1_ynF5VJKS5hkP0AnYAzDsSbtn4cLVINv | BP68: ЧЗ | BS68: ретинола пальмитат (витамин А), подсолнечное масло , оболочка (желатин (халяль), глицерин (загуститель), вода). | BU68: принимать по 1 капсуле 1 раз в день во время еды, запивая обильным количеством воды. Продолжительность приема: не менее 2 месяцев. При необходимости прием можно повторить. | BV68: индивидуальная непереносимость компонентов, беременность и кормление грудью. Перед применением рекомендуется проконсультироваться с врачом. | BW68: хранить в сухом, недоступном для детей месте, при температуре от +5 °С до +25 °С. | BX68: 90 | BY68: капсул | CA68: 2 года | CB68: 24 месяца | CC68: https://docs.google.com/document/d/1mfpemUGhIQRQEuoZ32gQ2rCwimfFTw4Xca3WX3j3_rE/edit?usp=sharing | CM68: =IFERROR(VLOOKUP(B68,CC!A:D,4,0)," ") -> 190 | CN68: ООО «Жива Продукт ПРО». 350062, Россия, Краснодарский край, город Краснодар, улица Казбекская, дом 17, кв. (оф.) 85 | CP68: Магамадов Ибрагим e-mail: ima@dzivaproduct.ru сайт: www.dzivaproduct.ru сот.тел. +7-967-660-1277(доступен WhatsApp) | CQ68: 60 | CS68: 5 | CT68: да | CY68: FALSE | CZ68: FALSE | DA68: FALSE | DB68: FALSE | DJ68: =IFERROR(VLOOKUP($B68,'Лист4'!$D:$AI,27,0)," ") -> 5 | DK68: =IFERROR(VLOOKUP($B68,'Лист4'!$D:$AI,28,0)," ") -> 5 | DL68: =IFERROR(VLOOKUP($B68,'Лист4'!$D:$AI,29,0)," ") -> 5 | DM68: =IFERROR(DJ68*DK68*DL68," ") -> 125 | DN68: =IFERROR(VLOOKUP($B68,'Лист4'!$D:$AI,32,0)," ") -> 0.058
A69: Биг-Л | B69: harly_ear_drops | C69: Harly | D69: Актуальный | F69: Капли ушные для собак и кошек, Harly, 10 мл | G69: Косметика для животных | H69: Капли и лосьоны | K69: TRUE | L69: TRUE | M69: TRUE | N69: TRUE | O69: FALSE | P69: FALSE | Q69: FALSE | S69: HC101100404 | T69: harly_ear_drops | U69: harly_ear_drops | V69: harly_ear_drops | AA69: 232451654 | AB69: 1580754644 | AC69: 103397002660 | AH69: Капли ушные для собак и кошек, Harly, 10 мл | AI69: Ушные капли от бактерий и паразитов для собак и кошек | AJ69: Ушные капли для чистки ушей собак и кошек Harly | AK69: Ушные капли для чистки ушей собак и кошек, лосьон для ушей животных Harly 10 мл. | AP69: https://www.wildberries.ru/catalog/232451654/detail.aspx | AQ69: https://www.ozon.ru/product/1580754644 | AR69: https://market.yandex.ru/card/ushnyye-kapli-dlya-chistki-ushey-sobak-i-koshek-harly/103397002660?businessId=8291477&clid=8291477&model_id=973176873&distr_type=8&pp=605 | AW69: Капли для животных | AX69: Ушные капли для чистки ушей собак и кошек Harly | AY69: товары для животных / косметика и гигиена / средства для ухода за животными | BD69: Алексей | BE69: Кристина | BF69: Анна Пирогова | BG69: Екатерина Доможирова | BH69: Екатерина Доможирова | BI69: Екатерина Доможирова | BL69: 4605543012839 | BM69: 3004900002 | BN69: 101-КС/177 от 12.02.2024 | BO69: https://drive.google.com/drive/folders/1aiTWi4fH9Tu-9saz_vCQ_noHCVaBPg3B | BP69: меркурий | BS69: фитокомплекс, являющийся водным извлечением из растительного сырья: пижмы обыкновенной цветков, чабреца травы, душицы обыкновенной травы, полыни горькой травы, фиалки травы, клевера лугового (красного) цветков, бузины черной цветков, коровяка травы, сосны обыкновенной почек, чеснока; сосны масло эфирное; полиэтилен_x0002_гликоль низкомолекулярный (ПЭГ-400). | BU69: Перед применением средство рекомендуется нагреть до комнатной температуры, поместив флакон капельницу в теплую воду. Тампоном, смоченным средством, тщательно очистить ушные раковины от поверхностных корок и струпьев. Закапать в каждое ухо по 3-5 капель: - кошкам, собакам мелких пород по 3 капли, - средним собакам по 4 капли, - крупным собакам по 5 капель. Обработку проводят до полного очищения ушной раковины. | BW69: Хранить при температуре от 0 до 25 ºС. | BX69: 10 | BY69: мл | CA69: 2 года | CB69: 24 месяца | CC69: https://docs.google.com/document/d/1GdCWCyPa4bcipNFAIH4NvwAVmBhk2ovQZCl96DiCB6g/edit | CM69: =IFERROR(VLOOKUP(B69,CC!A:D,4,0)," ") -> 55.98 | CN69: ООО "ВЕДА" | CP69: Дмитрий Алексеев / Dmitry Alekseev Коммерческий директор ООО "ВЕДА Вет-Фарм" / Commercial Director VEDA Vet-Farm +7-919-766-6452 dmitriy.alexeev@vedaved.ru | CQ69: 30 | CS69: 1 | CT69: нет | CY69: FALSE | CZ69: FALSE | DA69: FALSE | DB69: FALSE | DJ69: =IFERROR(VLOOKUP($B69,'Лист4'!$D:$AI,27,0)," ") -> 8 | DK69: =IFERROR(VLOOKUP($B69,'Лист4'!$D:$AI,28,0)," ") -> 4 | DL69: =IFERROR(VLOOKUP($B69,'Лист4'!$D:$AI,29,0)," ") -> 8 | DM69: =IFERROR(DJ69*DK69*DL69," ") -> 256 | DN69: =IFERROR(VLOOKUP($B69,'Лист4'!$D:$AI,32,0)," ") -> 0.026
A70: Биг-Л | B70: harly_eye_lotion | C70: Harly | D70: Актуальный | F70: Лосьон для глаз собак и кошек ,Harly, 100 мл | G70: Косметика для животных | H70: Капли и лосьоны | K70: TRUE | L70: TRUE | M70: TRUE | N70: TRUE | O70: FALSE | P70: FALSE | Q70: FALSE | S70: HC101100405 | T70: harly_eye_lotion | U70: harly_eye_lotion | V70: harly_eye_lotion | AA70: 385728241 | AB70: 2022703709 | AC70: 4335656072 | AH70: Лосьон для глаз собак и кошек ,Harly, 100 мл | AI70: Лосьон для глаз собак и кошек очищающий | AJ70: Лосьон для глаз собак и кошек очищающий Harly 100 мл | AK70: Лосьон для глаз собак и кошек очищающий, глазные очищающие капли для животных Harly 100 мл | AP70: https://www.wildberries.ru/catalog/385728241/detail.aspx | AQ70: https://www.ozon.ru/product/2022703709 | AR70: https://market.yandex.ru/card/loson-dlya-glaz-sobak-i-koshek-ochishchayushchiy-harly-100-ml/4335656072?businessId=8291477&clid=8291477&model_id=973176873&distr_type=8&pp=605 | AW70: Лосьоны для животных | AX70: Лосьон для глаз собак и кошек очищающий Harly 100 мл | AY70: товары для животных / косметика и гигиена / средства для ухода за животными | BD70: Алексей | BE70: Семен | BF70: Анна Пирогова | BG70: Екатерина Доможирова | BH70: Екатерина Доможирова | BI70: Екатерина Доможирова | BL70: 4680201379691 | BM70: 3307900008 | BN70: Отказное письмо № ОП/11-0028 от 06.11.2024 | BO70: https://drive.google.com/drive/folders/1RduJO02y0QEdXb8BjVojXxZmne38XFVi | BP70: ЧЗ | BS70: вода, глицерин, экстракт ромашки лекарственной, пропиленгликоль, борная кислота, аллантоин, таурин, янтарная кислота, метилпарабен, этилпарабен. | BU70: нагрейте флакон до температуры тела животного и тщательно встряхните. Смочите ватный тампон небольшим количеством препарата и обработайте область вокруг глаз, по направлению от наружного угла глаза к внутреннему, аккуратно устраняя выделения. Повторите обработку уже очищенного глаза чистым ватным тампоном в том же порядке. | BW70: хранить в сухом, защищенном от света месте, при температуре -15 до +25С. | BX70: 100 | BY70: мл | CA70: 36 месяцев | CB70: 36 месяцев | CC70: https://docs.google.com/document/d/17PwOoGHqPHI6M5ganvilfBiDnw2ISH5rbEckpD3GaQw/edit?tab=t.0 | CF70: https://disk.yandex.ru/d/QgMX7JJSA0ZCdg | CG70: 46044 | CM70: =IFERROR(VLOOKUP(B70,CC!A:D,4,0)," ") -> 108 | CN70: ООО Терра-пласт | CP70: Гордиенко Евгения Степановна (812)748-22-25(доб.101) +7(962)689-06-49 stm@gkfavorite.ru | CQ70: 60 | CS70: 2 | CT70: нет | CY70: FALSE | CZ70: FALSE | DA70: FALSE | DB70: FALSE | DJ70: =IFERROR(VLOOKUP($B70,'Лист4'!$D:$AI,27,0)," ") -> 4 | DK70: =IFERROR(VLOOKUP($B70,'Лист4'!$D:$AI,28,0)," ") -> 16 | DL70: =IFERROR(VLOOKUP($B70,'Лист4'!$D:$AI,29,0)," ") -> 4 | DM70: =IFERROR(DJ70*DK70*DL70," ") -> 256 | DN70: =IFERROR(VLOOKUP($B70,'Лист4'!$D:$AI,32,0)," ") -> 0.126
A71: Биг-Л | B71: qeep_liqCollagen_apple_14shots | C71: qeep | D71: Вывод | F71: БАД Коллаген жидкий ,qeep, яблоко 14 шотов по 25 мл | G71: БАДы | H71: Коллаген | K71: TRUE | L71: TRUE | M71: TRUE | N71: TRUE | O71: FALSE | P71: FALSE | Q71: FALSE | S71: QB101100446 | T71: qeep_liqCollagen_apple_14shots | U71: qeep_liqCollagen_apple_14shots | V71: qeep_liqCollagen_apple_14shots | AA71: 228329542 | AB71: 1563742020 | AC71: 103397906852 | AH71: БАД Коллаген жидкий ,qeep, яблоко 14 шотов по 25 мл | AI71: Коллаген жидкий говяжий | AJ71: Коллаген жидкий говяжий 5000 мг Qeep яблоко 14 шотов по 25 мл | AK71: Коллаген жидкий говяжий 5000 мг Qeep яблоко 14 шотов по 25 мл | AP71: https://www.wildberries.ru/catalog/228329542/detail.aspx | AQ71: https://www.ozon.ru/product/1563742020 | AR71: https://market.yandex.ru/card/kollagen-zhidkiy-govyazhiy-5000-mg-qeep-yabloko-14-shotov-po-25-ml/103397906852?businessId=8291477&showOriginalKmEmptyOffer=1&ogV=-10 | AW71: Добавки для суставов и связок | AX71: Коллаген жидкий говяжий 5000 мг Qeep яблоко 14 шотов по 25 мл | AY71: спорт и отдых / тренажеры и фитнес / спортивное питание / препараты для укрепления связок и суставов | BD71: Выведено | BE71: Семен | BF71: Анна Пирогова | BG71: Екатерина Доможирова | BH71: Екатерина Доможирова | BI71: Екатерина Доможирова | BL71: 4670227410591 | BM71: 2106909808 | BN71: AM.01.01.01.003.R.000931.12.23 от 28.12.2023 г | BP71: ЧЗ | BS71: гидролизованный говяжий коллаген, гиалуроновая кислота, витаминный комплекс (аскорбиновая кислота, dl-a-токоферол, ниацин, ретинол ацетат, кальций пантотенат, холекальцеферол, пиридоксин гидрохлорид, тиамин мононитрат, рибофлавин, фолиевая кислота, биотин, цианокобаламин), подготовленная столовая вода, лимонная кислота, консерванты | BU71: взрослым принимать 25 мл 1 раз в день. Продолжительность приёма: 1 месяц. При необходимости повторить. | BV71: индивидуальная непереносимость компонентов продукта, беременность, кормление грудью. Продукт не рекомендуется принимать детям до 18 лет. Перед применением проконсультироваться с врачом. | BW71: хранить в сухом, недоступном для детей месте, при температуре от +5 °С до +25 °С. | BX71: 14 | BY71: мл | CA71: 18 месяцев | CB71: 18 месяцев | CC71: https://docs.google.com/document/d/1TdX7bOpUzizlnYsgpZjEVStPU6vGcEkVmx0izqrKJlM/edit?usp=sharing | CM71: =IFERROR(VLOOKUP(B71,CC!A:D,4,0)," ") -> 820 | CN71: ООО «Жива Продукт ПРО». 350062, Россия, Краснодарский край, город Краснодар, улица Казбекская, дом 17, кв. (оф.) 85 | CP71: Магамадов Ибрагим e-mail: ima@dzivaproduct.ru сайт: www.dzivaproduct.ru сот.тел. +7-967-660-1277(доступен WhatsApp) | CQ71: 60 | CS71: 5 | CT71: да | CY71: FALSE | CZ71: FALSE | DA71: FALSE | DB71: FALSE | DJ71: =IFERROR(VLOOKUP($B71,'Лист4'!$D:$AI,27,0)," ") -> 15 | DK71: =IFERROR(VLOOKUP($B71,'Лист4'!$D:$AI,28,0)," ") -> 12 | DL71: =IFERROR(VLOOKUP($B71,'Лист4'!$D:$AI,29,0)," ") -> 15 | DM71: =IFERROR(DJ71*DK71*DL71," ") -> 2700 | DN71: =IFERROR(VLOOKUP($B71,'Лист4'!$D:$AI,32,0)," ") -> 0.542
A72: Биг-Л | B72: qeep_liqCollagen_orange_14shots | C72: qeep | D72: Вывод | F72: БАД Коллаген жидкий ,qeep, апельсин 14 шотов по 25 мл | G72: БАДы | H72: Коллаген | K72: TRUE | L72: TRUE | M72: TRUE | N72: TRUE | O72: FALSE | P72: FALSE | Q72: FALSE | S72: QB101100444 | T72: qeep_liqCollagen_orange_14shots | U72: qeep_liqCollagen_orange_14shots | V72: qeep_liqCollagen_orange_14shots | AA72: 228329661 | AB72: 1563742059 | AC72: 103397906851 | AH72: БАД Коллаген жидкий ,qeep, апельсин 14 шотов по 25 мл | AI72: Коллаген жидкий говяжий | AJ72: Коллаген жидкий говяжий 5000 мг Qeep апельсин 14 шотов по 25 мл | AK72: Коллаген жидкий говяжий 5000 мг Qeep апельсин 14 шотов по 25 мл | AP72: https://www.wildberries.ru/catalog/228329661/detail.aspx | AQ72: https://www.ozon.ru/product/1563742059 | AR72: https://market.yandex.ru/card/kollagen-zhidkiy-govyazhiy-5000-mg-qeep-apelsin-14-shotov-po-25-ml/103397906851?businessId=8291477&showOriginalKmEmptyOffer=1&ogV=-10 | AW72: Добавки для суставов и связок | AX72: Коллаген жидкий говяжий 5000 мг Qeep апельсин 14 шотов по 25 мл | AY72: спорт и отдых / тренажеры и фитнес / спортивное питание / препараты для укрепления связок и суставов | BD72: Выведено | BE72: Семен | BF72: Анна Пирогова | BG72: Екатерина Доможирова | BH72: Екатерина Доможирова | BI72: Екатерина Доможирова | BL72: 4670227410614 | BM72: 2106909808 | BN72: AM.01.01.01.003.R.000931.12.23 от 28.12.2023 г | BP72: ЧЗ | BS72: гидролизованный говяжий коллаген, гиалуроновая кислота, витаминный комплекс (аскорбиновая кислота,dl-a-токоферол, ниацин, ретинол ацетат, кальций пантотенат, холекальцеферол, пиридоксин гидрохлорид, тиамин мононитрат, рибофлавин, фолиевая кислота, биотин, цианокобаламин), подготовленная столовая вода, лимонная кислота, консерванты | BU72: взрослым принимать 25 мл 1 раз в день. Продолжительность приёма: 1 месяц. При необходимости повторить. | BV72: индивидуальная непереносимость компонентов продукта, беременность, кормление грудью. Продукт не рекомендуется принимать детям до 18 лет. Перед применением проконсультироваться с врачом. | BW72: хранить в сухом, недоступном для детей месте, при температуре от +5 °С до +25 °С. | BX72: 14 | BY72: мл | CA72: 18 месяцев | CB72: 18 месяцев | CC72: https://docs.google.com/document/d/1TdX7bOpUzizlnYsgpZjEVStPU6vGcEkVmx0izqrKJlM/edit?usp=sharing | CM72: =IFERROR(VLOOKUP(B72,CC!A:D,4,0)," ") -> 820 | CN72: ООО «Жива Продукт ПРО». 350062, Россия, Краснодарский край, город Краснодар, улица Казбекская, дом 17, кв. (оф.) 85 | CP72: Магамадов Ибрагим e-mail: ima@dzivaproduct.ru сайт: www.dzivaproduct.ru сот.тел. +7-967-660-1277(доступен WhatsApp) | CQ72: 60 | CS72: 5 | CT72: да | CY72: FALSE | CZ72: FALSE | DA72: FALSE | DB72: FALSE | DJ72: =IFERROR(VLOOKUP($B72,'Лист4'!$D:$AI,27,0)," ") -> 15 | DK72: =IFERROR(VLOOKUP($B72,'Лист4'!$D:$AI,28,0)," ") -> 12 | DL72: =IFERROR(VLOOKUP($B72,'Лист4'!$D:$AI,29,0)," ") -> 15 | DM72: =IFERROR(DJ72*DK72*DL72," ") -> 2700 | DN72: =IFERROR(VLOOKUP($B72,'Лист4'!$D:$AI,32,0)," ") -> 0.542
A73: Биг-Л | B73: qeepcollagen | C73: qeep | D73: Вывод | F73: БАД Коллаген с Гиалуроновой Кислотой ,qeep, 60 капсул | G73: БАДы | H73: Коллаген | K73: TRUE | L73: TRUE | M73: TRUE | N73: TRUE | O73: FALSE | P73: FALSE | Q73: FALSE | S73: QB101100451 | T73: qeepcollagen | U73: qeepcollagen | V73: qeepcollagen | AA73: 90476399 | AB73: 616963626 | AC73: 101824298337 | AH73: БАД Коллаген с Гиалуроновой Кислотой ,qeep, 60 капсул | AI73: Коллаген капсулы с Гиалуроном и витамином C бад для волос | AJ73: Коллаген I и III типа с Витамином С и Гиалуроновой Кислотой Qeep 60 капсул | AK73: Коллаген I и III типа с Витамином С и Гиалуроновой Кислотой Qeep 60 капсул | AP73: https://www.wildberries.ru/catalog/90476399/detail.aspx | AQ73: https://www.ozon.ru/product/616963626 | AR73: https://market.yandex.ru/card/kollagen-i-i-iii-tipa-s-vitaminom-s-i-gialuronovoy-kislotoy-qeep-60-kapsul/101824298337?businessId=8291477&clid=8291477&model_id=1111517446&distr_type=8&pp=605 | AW73: БАДы | AX73: Коллаген I и III типа с Витамином С и Гиалуроновой Кислотой Qeep 60 капсул | AY73: аптека / витамины, минералы, добавки | BD73: Света | BE73: Семен | BF73: Анна Пирогова | BG73: Екатерина Доможирова | BH73: Екатерина Доможирова | BI73: Екатерина Доможирова | BL73: 4630040228285 | BM73: 2106909808 | BN73: AM.01.06.01.003.R.000121.10.19 от 30.10.2019 г. | BP73: ЧЗ | BS73: коллаген гидролизованный, мумиё алтайское, глюкозамина сульфат, витамин С (аскорбиновая кислота), натрия гиалуронат, дигидрокверцетин, березовый экстракт. Вспомогательные вещества: целлюлоза микрокристаллическая (носитель), капсула желатиновая (желатин, глицерин), антислеживатели: кальция стеарат, кремния диоксид. | BU73: взрослым по 1 капсуле 2 раза в день во время еды. Курс приема 1 месяц. | BV73: индивидуальная непереносимость компонентов, беременность и кормление грудью. Перед применением рекомендуется проконсультироваться с врачом. | BW73: в недоступном для детей месте, при температуре не выше +25ºС и относительной влажности воздуха не более 60%. | BX73: 60 | BY73: шт | CA73: 2 года/ 730 | CB73: 24 месяца | CC73: https://drive.google.com/drive/u/0/folders/1vOiIY1XsOr2O40QbZVdluwtxKotRe-0N | CF73: https://drive.google.com/drive/u/0/folders/1vOiIY1XsOr2O40QbZVdluwtxKotRe-0N | CM73: =IFERROR(VLOOKUP(B73,CC!A:D,4,0)," ") -> 225.54 | CN73: "ООО «Сибфармконтракт», Россия, 634034, г. Томск, ул. Нахимова 8, стр. 11. По заказу (организация, уполномоченная принимать претензии от потребителя): ООО «Биг-Л», 127473, Россия, г. Москва, Переулок Самотёчный 1-й, д. 15, cтр. 1, этаж подвал № 0, помещ. I, ком. 1, офис 1," | CP73: Анастасия Лапина тел: 8(3822)556092 (доб. 258), 426792 E-mail: lapina@artlife.ru Skype: live:e18940191d9f1027 634034 г.Томск ул Нахимова 8/2 а/я 358 | CS73: 10 | CT73: нет | CY73: FALSE | CZ73: FALSE | DA73: FALSE | DB73: FALSE | DJ73: =IFERROR(VLOOKUP($B73,'Лист4'!$D:$AI,27,0)," ") -> 10 | DK73: =IFERROR(VLOOKUP($B73,'Лист4'!$D:$AI,28,0)," ") -> 5 | DL73: =IFERROR(VLOOKUP($B73,'Лист4'!$D:$AI,29,0)," ") -> 10 | DM73: =IFERROR(DJ73*DK73*DL73," ") -> 500 | DN73: =IFERROR(VLOOKUP($B73,'Лист4'!$D:$AI,32,0)," ") -> 0.059
A74: Биг-Л | B74: qeep_liqCollagen_rspbry_14shots | C74: qeep | D74: Вывод | F74: БАД Коллаген жидкий ,qeep, малина 14 шотов по 25 мл | G74: БАДы | H74: Коллаген | K74: TRUE | L74: TRUE | M74: TRUE | N74: TRUE | O74: FALSE | P74: FALSE | Q74: FALSE | S74: QB101100445 | T74: qeep_liqCollagen_rspbry_14shots | U74: qeep_liqCollagen_rspbry_14shots | V74: qeep_liqCollagen_rspbry_14shots | AA74: 228329662 | AB74: 1563742150 | AC74: 103397906850 | AH74: БАД Коллаген жидкий ,qeep, малина 14 шотов по 25 мл | AI74: Коллаген жидкий говяжий | AJ74: Коллаген жидкий говяжий 5000 мг Qeep малина 14 шотов по 25 мл | AK74: Коллаген жидкий говяжий 5000 мг Qeep малина 14 шотов по 25 мл | AP74: https://www.wildberries.ru/catalog/228329662/detail.aspx | AQ74: https://www.ozon.ru/product/1563742150 | AR74: https://market.yandex.ru/card/kollagen-zhidkiy-govyazhiy-5000-mg-qeep-malina-14-shotov-po-25-ml/103397906850?businessId=8291477&showOriginalKmEmptyOffer=1&ogV=-10 | AW74: Добавки для суставов и связок | AX74: Коллаген жидкий говяжий 5000 мг Qeep малина 14 шотов по 25 мл | AY74: спорт и отдых / тренажеры и фитнес / спортивное питание / препараты для укрепления связок и суставов | BD74: Выведено | BE74: Семен | BF74: Анна Пирогова | BG74: Екатерина Доможирова | BH74: Екатерина Доможирова | BI74: Екатерина Доможирова | BL74: 4670227410607 | BM74: 2106909808 | BN74: AM.01.01.01.003.R.000931.12.23 от 28.12.2023 г | BP74: ЧЗ | BS74: гидролизованный говяжий коллаген, гиалуроновая кислота, витаминный комплекс (аскорбиновая кислота,dl-a-токоферол, ниацин, ретинол ацетат, кальций пантотенат, холекальцеферол, пиридоксин гидрохлорид, тиамин мононитрат, рибофлавин, фолиевая кислота, биотин, цианокобаламин), подготовленная столовая вода, лимонная кислота, консерванты | BU74: взрослым принимать 25 мл 1 раз в день. Продолжительность приёма: 1 месяц. При необходимости повторить. | BV74: индивидуальная непереносимость компонентов продукта, беременность, кормление грудью. Продукт не рекомендуется принимать детям до 18 лет. Перед применением проконсультироваться с врачом. | BW74: хранить в сухом, недоступном для детей месте, при температуре от +5 °С до +25 °С. | BX74: 14 | BY74: мл | CA74: 18 месяцев | CB74: 18 месяцев | CC74: https://docs.google.com/document/d/1TdX7bOpUzizlnYsgpZjEVStPU6vGcEkVmx0izqrKJlM/edit?usp=sharing | CM74: =IFERROR(VLOOKUP(B74,CC!A:D,4,0)," ") -> 820 | CN74: ООО «Жива Продукт ПРО». 350062, Россия, Краснодарский край, город Краснодар, улица Казбекская, дом 17, кв. (оф.) 85 | CP74: Магамадов Ибрагим e-mail: ima@dzivaproduct.ru сайт: www.dzivaproduct.ru сот.тел. +7-967-660-1277(доступен WhatsApp) | CQ74: 60 | CS74: 5 | CT74: да | CY74: FALSE | CZ74: FALSE | DA74: FALSE | DB74: FALSE | DJ74: =IFERROR(VLOOKUP($B74,'Лист4'!$D:$AI,27,0)," ") -> 15 | DK74: =IFERROR(VLOOKUP($B74,'Лист4'!$D:$AI,28,0)," ") -> 12 | DL74: =IFERROR(VLOOKUP($B74,'Лист4'!$D:$AI,29,0)," ") -> 15 | DM74: =IFERROR(DJ74*DK74*DL74," ") -> 2700 | DN74: =IFERROR(VLOOKUP($B74,'Лист4'!$D:$AI,32,0)," ") -> 0.542
